Workbook

Sheet Control de Cambios
D3: LEVANTAMIENTO DE MESA DE SERVICIOS
D5: Caracterización y Diagnóstico de Mesas de Servicio Operación Actual | G5: Fecha: 2026/07/03
D6: Versión: | E6: 1.0 | G6: Clasificación: Interna
B9: Elaboró | D9: Revisó | F9: Aprobó
B10: Natalia Zartha Junior Architect
B11: Fecha | D11: Fecha | F11: Fecha
B12: 46206
B14: Fecha | C14: Versión | D14: Descripción
B15: 2026/07/03 | C15: 1 | D15: Versión inicial; levantamiento de información actual de las mesas de servicio
C16: 2
C17: 3
C18: 4
C19: 5

Sheet Instrucciones
D2: LECCIONES APRENDIDAS — MESA DE SERVICIOS DE NUEVA GENERACIÓN
D4: Esta herramienta permite caracterizar la mesa de servicios actual en todas sus dimensiones para diseñar el futuro servicio Gen Next | F4: Fecha: 2026/07/03
D5: Versión: 1.0 | F5: Clasificación: Interna
B8: AGENDA DE LA SESIÓN DE LECCIONES APRENDIDAS (~60 minutos)
B9: # | C9: BLOQUE | D9: TIEMPO | E9: DESCRIPCIÓN
B10: ① | C10: INFORMACIÓN GENERAL | D10: 5 min | E10: Registrar datos básicos de la mesa: cliente, nombre del servicio, líder, ubicación, modalidad, contrato, herramientas y participantes.
B11: ② | C11: IDENTIFICAR NIVEL DE MADUREZ ACTUAL | D11: 5 min | E11: Identificar el nivel de madurez actual de la mesa de servicio de TI en una escala N0–N5, identificando el punto de partida operativo.
B12: ③ | C12: 17 PRÁCTICAS ITIL v4 + DIMENSIONES | D12: 5 min | E12: Revisar el cumplimiento de las prácticas ITIL v4 por las 4 dimensiones: organización/personas, información/tecnología, socios/proveedores y valor/mejora.
B13: ④ | C13: VOLUMETRÍA Y KPIs OPERATIVOS | D13: 5 min | E13: Levantar métricas operativas clave: volumen de tickets, FCR, SLA, backlog, tiempos de atención, escalamiento y desempeño general.
B14: ④b | C14: ④b DISTRIBUCIÓN DE INCIDENTES POR CATEGORÍA | D14: 5 min | E14: Analizar la distribución de incidentes por categoría para identificar patrones, servicios críticos, causas recurrentes y oportunidades de mejora.
B15: ⑤ | C15: EXPERIENCIA DEL USUARIO — XLA / DEX | D15: 5 min | E15: Evaluar la experiencia del usuario final mediante indicadores XLA/DEX, satisfacción, percepción del servicio, puntos de dolor y canales de atención.
B16: ⑥ | C16: DOLORES CRÍTICOS DE LA MESA (D1–D22) | D16: 5 min | E16: Identificar y priorizar los dolores críticos de la mesa, su impacto operativo, evidencias disponibles y nivel de urgencia para intervención.
B17: ⑦ | C17: ROTACIÓN Y TALENTO | D17: 5 min | E17: Revisar rotación, perfiles críticos, capacidades del equipo, clima laboral, brechas de conocimiento y necesidades de formación.
B18: ⑧ | C18: TECNOLOGÍA Y HERRAMIENTAS | D18: 5 min | E18: Evaluar herramientas tecnológicas actuales: ITSM, monitoreo, autoservicio, base de conocimiento, automatización, integraciones y reportes.
B19: ⑨ | C19: MODELO ECONÓMICO ACTUAL | D19: 5 min | E19: Analizar el modelo económico actual: FTEs, costos, esquema contractual, capacidad instalada, eficiencia operativa y posibles oportunidades de optimización.
B20: ⑩ | C20: VISIÓN PARA EL NUEVO SERVICIO — ¿QUÉ DEBERÍA CAMBIAR? | D20: 5 min | E20: Definir la visión objetivo del nuevo servicio: cambios esperados, capacidades Gen Next, automatización, experiencia deseada y prioridades de transformación.
B21: ⑪ | C21: CASOS DE EXITO | D21: 5 min | E21: Documentar casos de éxito, buenas prácticas, aprendizajes reutilizables y elementos que deben conservarse o escalarse en el nuevo modelo.
B23: ESCALA DE MADUREZ — N0 a N5
B24: NIVEL | C24: NOMBRE | D24: DESCRIPCIÓN
B25: N0 | C25: Reactivo / Sin estructura | D25: No existe proceso formal. Todo es manual y reactivo. Sin CMDB ni catálogo.
B26: N1 | C26: Inicial / Ad hoc/ Operación reactiva | D26: Procesos básicos documentados. Herramientas mínimas. Cumplimiento inconsistente.
B27: N2 | C27: Definido / Organización funcional | D27: Procesos ITIL definidos y seguidos. Métricas básicas (SLA (Service Level Agreement), FCR (Fondo de Capital Riesgo)). Equipo estable.
B28: N3 | C28: Gestionado / Gestión por servicios | D28: Métricas avanzadas. Automatización parcial. Gestión proactiva de problemas.
B29: N4 | C29: Optimizado / Gestión integrada | D29: Autoservicio maduro. IA/ML básico. XLA (Experience Level Agreement) medidos. Mejora continua activa.
B30: N5 | C30: Innovador / Diferenciador | D30: IA generativa, predicción, hiper-automatización. Referente del sector.
B32: LEYENDA DE RESPUESTAS — PRÁCTICAS ITIL
B33: RESPUESTA | C33: SIGNIFICADO | D33: COLOR | E33: PUNTAJE
B34: Sí | C34: Cumplimiento completo y documentado | D34: 1F7A4D | E34: 1.0
B35: Parcial | C35: Cumplimiento parcial o en proceso | D35: E07B26 | E35: 0.5
B36: No | C36: No existe o no se cumple | D36: C0392B | E36: 0.0
B37: N/A | C37: No aplica a esta mesa | D37: D9D9D9 | E37: —

Sheet Dashboard
C2: DASHBOARD — MESA DE SERVICIOS DE NUEVA GENERACIÓN | I2: Fecha: 2026/07/03 Clasificación: Interna
C3: Resumen consolidado · Julio 2026 · PersonalSoft
C5: Versión: 1.0
B7: RESUMEN POR MESA DE SERVICIOS — 12 MESAS
B8: MESA | C8: Nivel Madurez | D8: Score Prácticas | E8: FCR (%) | F8: SLA (%) | G8: NPS | H8: FTEs | I8: Dolores Activos | J8: Prioridad Global | K8: Estado
B9: SURA Cotizadores | C9: ='SURA Cotizadores'!C12 -> N2 | D9: =IFERROR('SURA Cotizadores'!E56,0) -> 0.52941176 | E9: =IFERROR('SURA Cotizadores'!C66,0) -> N/D | F9: =IFERROR('SURA Cotizadores'!C68,0) -> 0.7 | G9: =IFERROR('SURA Cotizadores'!C86,0) -> 0 | H9: =IFERROR('SURA Cotizadores'!C72,0) -> 8 | I9: =IF(OR('SURA Cotizadores'!C99="Sí",'SURA Cotizadores'!C99="Si"),1,IF('SURA Cotizadores'!C99="Parcial",0.5,0))+IF(OR('SURA Cotizadores'!C100="Sí",'SURA Cotizadores'!C100="Si"),1,IF('SURA Cotizadores'!C100="Parcial",0.5,0))+IF(OR('SURA Cotizadores'!C101="Sí",'SURA Cotizadores'!C101="Si"),1,IF('SURA Cotizadores'!C101="Parcial",0.5,0))+IF(OR('SURA Cotizadores'!C102="Sí",'SURA Cotizadores'!C102="Si"),1,IF('SURA Cotizadores'!C102="Parcial",0.5,0))+IF(OR('SURA Cotizadores'!C103="Sí",'SURA Cotizadores'!C103="Si"),1,IF('SURA Cotizadores'!C103="Parcial",0.5,0))+IF(OR('SURA Cotizadores'!C104="Sí",'SURA Cotizadores'!C104="Si"),1,IF('SURA Cotizadores'!C104="Parcial",0.5,0))+IF(OR('SURA Cotizadores'!C105="Sí",'SURA Cotizadores'!C105="Si"),1,IF('SURA Cotizadores'!C105="Parcial",0.5,0))+IF(OR('SURA Cotizadores'!C106="Sí",'SURA Cotizadores'!C106="Si"),1,IF('SURA Cotizadores'!C106="Parcial",0.5,0))+IF(OR('SURA Cotizadores'!C107="Sí",'SURA Cotizadores'!C107="Si"),1,IF('SURA Cotizadores'!C107="Parcial",0.5,0))+IF(OR('SURA Cotizadores'!C108="Sí",'SURA Cotizadores'!C108="Si"),1,IF('SURA Cotizadores'!C108="Parcial",0.5,0))+IF(OR('SURA Cotizadores'!C109="Sí",'SURA Cotizadores'!C109="Si"),1,IF('SURA Cotizadores'!C109="Parcial",0.5,0))+IF(OR('SURA Cotizadores'!C110="Sí",'SURA Cotizadores'!C110="Si"),1,IF('SURA Cotizadores'!C110="Parcial",0.5,0))+IF(OR('SURA Cotizadores'!C111="Sí",'SURA Cotizadores'!C111="Si"),1,IF('SURA Cotizadores'!C111="Parcial",0.5,0))+IF(OR('SURA Cotizadores'!C112="Sí",'SURA Cotizadores'!C112="Si"),1,IF('SURA Cotizadores'!C112="Parcial",0.5,0))+IF(OR('SURA Cotizadores'!C113="Sí",'SURA Cotizadores'!C113="Si"),1,IF('SURA Cotizadores'!C113="Parcial",0.5,0))+IF(OR('SURA Cotizadores'!C114="Sí",'SURA Cotizadores'!C114="Si"),1,IF('SURA Cotizadores'!C114="Parcial",0.5,0))+IF(OR('SURA Cotizadores'!C115="Sí",'SURA Cotizadores'!C115="Si"),1,IF('SURA Cotizadores'!C115="Parcial",0.5,0))+IF(OR('SURA Cotizadores'!C116="Sí",'SURA Cotizadores'!C116="Si"),1,IF('SURA Cotizadores'!C116="Parcial",0.5,0))+IF(OR('SURA Cotizadores'!C117="Sí",'SURA Cotizadores'!C117="Si"),1,IF('SURA Cotizadores'!C117="Parcial",0.5,0))+IF(OR('SURA Cotizadores'!C118="Sí",'SURA Cotizadores'!C118="Si"),1,IF('SURA Cotizadores'!C118="Parcial",0.5,0))+IF(OR('SURA Cotizadores'!C119="Sí",'SURA Cotizadores'!C119="Si"),1,IF('SURA Cotizadores'!C119="Parcial",0.5,0))+IF(OR('SURA Cotizadores'!C120="Sí",'SURA Cotizadores'!C120="Si"),1,IF('SURA Cotizadores'!C120="Parcial",0.5,0))+IF(OR('SURA Cotizadores'!C121="Sí",'SURA Cotizadores'!C121="Si"),1,IF('SURA Cotizadores'!C121="Parcial",0.5,0)) -> 13 | J9: =IF(D9<30%,"Alta",IF(D9<60%,"Media","Baja")) -> Media | K9: =IF(D9=0,"Pendiente",IF(D9>=70%,"Fuerte",IF(D9>=40%,"En desarrollo","Crítica"))) -> En desarrollo
B10: SURA Digital Venta | C10: ='SURA Digital Venta'!C13 -> N2 | D10: =IFERROR('SURA Digital Venta'!E57,0) -> 0.55882353 | E10: =IFERROR('SURA Digital Venta'!C67,0) -> N/D | F10: =IFERROR('SURA Digital Venta'!C69,0) -> 0.74 | G10: =IFERROR('SURA Digital Venta'!C90,0) -> 0 | H10: =IFERROR('SURA Digital Venta'!C73,0) -> 2 | I10: =IF(OR('SURA Digital Venta'!C100="Sí",'SURA Digital Venta'!C100="Si"),1,IF('SURA Digital Venta'!C100="Parcial",0.5,0))+IF(OR('SURA Digital Venta'!C101="Sí",'SURA Digital Venta'!C101="Si"),1,IF('SURA Digital Venta'!C101="Parcial",0.5,0))+IF(OR('SURA Digital Venta'!C102="Sí",'SURA Digital Venta'!C102="Si"),1,IF('SURA Digital Venta'!C102="Parcial",0.5,0))+IF(OR('SURA Digital Venta'!C103="Sí",'SURA Digital Venta'!C103="Si"),1,IF('SURA Digital Venta'!C103="Parcial",0.5,0))+IF(OR('SURA Digital Venta'!C104="Sí",'SURA Digital Venta'!C104="Si"),1,IF('SURA Digital Venta'!C104="Parcial",0.5,0))+IF(OR('SURA Digital Venta'!C105="Sí",'SURA Digital Venta'!C105="Si"),1,IF('SURA Digital Venta'!C105="Parcial",0.5,0))+IF(OR('SURA Digital Venta'!C106="Sí",'SURA Digital Venta'!C106="Si"),1,IF('SURA Digital Venta'!C106="Parcial",0.5,0))+IF(OR('SURA Digital Venta'!C107="Sí",'SURA Digital Venta'!C107="Si"),1,IF('SURA Digital Venta'!C107="Parcial",0.5,0))+IF(OR('SURA Digital Venta'!C108="Sí",'SURA Digital Venta'!C108="Si"),1,IF('SURA Digital Venta'!C108="Parcial",0.5,0))+IF(OR('SURA Digital Venta'!C109="Sí",'SURA Digital Venta'!C109="Si"),1,IF('SURA Digital Venta'!C109="Parcial",0.5,0))+IF(OR('SURA Digital Venta'!C110="Sí",'SURA Digital Venta'!C110="Si"),1,IF('SURA Digital Venta'!C110="Parcial",0.5,0))+IF(OR('SURA Digital Venta'!C111="Sí",'SURA Digital Venta'!C111="Si"),1,IF('SURA Digital Venta'!C111="Parcial",0.5,0))+IF(OR('SURA Digital Venta'!C112="Sí",'SURA Digital Venta'!C112="Si"),1,IF('SURA Digital Venta'!C112="Parcial",0.5,0))+IF(OR('SURA Digital Venta'!C113="Sí",'SURA Digital Venta'!C113="Si"),1,IF('SURA Digital Venta'!C113="Parcial",0.5,0))+IF(OR('SURA Digital Venta'!C114="Sí",'SURA Digital Venta'!C114="Si"),1,IF('SURA Digital Venta'!C114="Parcial",0.5,0))+IF(OR('SURA Digital Venta'!C115="Sí",'SURA Digital Venta'!C115="Si"),1,IF('SURA Digital Venta'!C115="Parcial",0.5,0))+IF(OR('SURA Digital Venta'!C116="Sí",'SURA Digital Venta'!C116="Si"),1,IF('SURA Digital Venta'!C116="Parcial",0.5,0))+IF(OR('SURA Digital Venta'!C117="Sí",'SURA Digital Venta'!C117="Si"),1,IF('SURA Digital Venta'!C117="Parcial",0.5,0))+IF(OR('SURA Digital Venta'!C118="Sí",'SURA Digital Venta'!C118="Si"),1,IF('SURA Digital Venta'!C118="Parcial",0.5,0))+IF(OR('SURA Digital Venta'!C119="Sí",'SURA Digital Venta'!C119="Si"),1,IF('SURA Digital Venta'!C119="Parcial",0.5,0))+IF(OR('SURA Digital Venta'!C120="Sí",'SURA Digital Venta'!C120="Si"),1,IF('SURA Digital Venta'!C120="Parcial",0.5,0))+IF(OR('SURA Digital Venta'!C121="Sí",'SURA Digital Venta'!C121="Si"),1,IF('SURA Digital Venta'!C121="Parcial",0.5,0)) -> 12.5 | J10: =IF(D10<30%,"Alta",IF(D10<60%,"Media","Baja")) -> Media | K10: =IF(D10=0,"Pendiente",IF(D10>=70%,"Fuerte",IF(D10>=40%,"En desarrollo","Crítica"))) -> En desarrollo
B11: SURA Automatizacion | C11: ='SURA Automatizacion'!C13 -> N2 | D11: =IFERROR('SURA Automatizacion'!E57,0) -> 0.61764706 | E11: =IFERROR('SURA Automatizacion'!C67,0) -> N/D | F11: =IFERROR('SURA Automatizacion'!C69,0) -> 0.98 | G11: =IFERROR('SURA Automatizacion'!C90,0) -> 0 | H11: =IFERROR('SURA Automatizacion'!C73,0) -> 6 | I11: =IF(OR('SURA Automatizacion'!C100="Sí",'SURA Automatizacion'!C100="Si"),1,IF('SURA Automatizacion'!C100="Parcial",0.5,0))+IF(OR('SURA Automatizacion'!C101="Sí",'SURA Automatizacion'!C101="Si"),1,IF('SURA Automatizacion'!C101="Parcial",0.5,0))+IF(OR('SURA Automatizacion'!C102="Sí",'SURA Automatizacion'!C102="Si"),1,IF('SURA Automatizacion'!C102="Parcial",0.5,0))+IF(OR('SURA Automatizacion'!C103="Sí",'SURA Automatizacion'!C103="Si"),1,IF('SURA Automatizacion'!C103="Parcial",0.5,0))+IF(OR('SURA Automatizacion'!C104="Sí",'SURA Automatizacion'!C104="Si"),1,IF('SURA Automatizacion'!C104="Parcial",0.5,0))+IF(OR('SURA Automatizacion'!C105="Sí",'SURA Automatizacion'!C105="Si"),1,IF('SURA Automatizacion'!C105="Parcial",0.5,0))+IF(OR('SURA Automatizacion'!C106="Sí",'SURA Automatizacion'!C106="Si"),1,IF('SURA Automatizacion'!C106="Parcial",0.5,0))+IF(OR('SURA Automatizacion'!C107="Sí",'SURA Automatizacion'!C107="Si"),1,IF('SURA Automatizacion'!C107="Parcial",0.5,0))+IF(OR('SURA Automatizacion'!C108="Sí",'SURA Automatizacion'!C108="Si"),1,IF('SURA Automatizacion'!C108="Parcial",0.5,0))+IF(OR('SURA Automatizacion'!C109="Sí",'SURA Automatizacion'!C109="Si"),1,IF('SURA Automatizacion'!C109="Parcial",0.5,0))+IF(OR('SURA Automatizacion'!C110="Sí",'SURA Automatizacion'!C110="Si"),1,IF('SURA Automatizacion'!C110="Parcial",0.5,0))+IF(OR('SURA Automatizacion'!C111="Sí",'SURA Automatizacion'!C111="Si"),1,IF('SURA Automatizacion'!C111="Parcial",0.5,0))+IF(OR('SURA Automatizacion'!C112="Sí",'SURA Automatizacion'!C112="Si"),1,IF('SURA Automatizacion'!C112="Parcial",0.5,0))+IF(OR('SURA Automatizacion'!C113="Sí",'SURA Automatizacion'!C113="Si"),1,IF('SURA Automatizacion'!C113="Parcial",0.5,0))+IF(OR('SURA Automatizacion'!C114="Sí",'SURA Automatizacion'!C114="Si"),1,IF('SURA Automatizacion'!C114="Parcial",0.5,0))+IF(OR('SURA Automatizacion'!C115="Sí",'SURA Automatizacion'!C115="Si"),1,IF('SURA Automatizacion'!C115="Parcial",0.5,0))+IF(OR('SURA Automatizacion'!C116="Sí",'SURA Automatizacion'!C116="Si"),1,IF('SURA Automatizacion'!C116="Parcial",0.5,0))+IF(OR('SURA Automatizacion'!C117="Sí",'SURA Automatizacion'!C117="Si"),1,IF('SURA Automatizacion'!C117="Parcial",0.5,0))+IF(OR('SURA Automatizacion'!C118="Sí",'SURA Automatizacion'!C118="Si"),1,IF('SURA Automatizacion'!C118="Parcial",0.5,0))+IF(OR('SURA Automatizacion'!C119="Sí",'SURA Automatizacion'!C119="Si"),1,IF('SURA Automatizacion'!C119="Parcial",0.5,0))+IF(OR('SURA Automatizacion'!C120="Sí",'SURA Automatizacion'!C120="Si"),1,IF('SURA Automatizacion'!C120="Parcial",0.5,0))+IF(OR('SURA Automatizacion'!C121="Sí",'SURA Automatizacion'!C121="Si"),1,IF('SURA Automatizacion'!C121="Parcial",0.5,0)) -> 11 | J11: =IF(D11<30%,"Alta",IF(D11<60%,"Media","Baja")) -> Baja | K11: =IF(D11=0,"Pendiente",IF(D11>=70%,"Fuerte",IF(D11>=40%,"En desarrollo","Crítica"))) -> En desarrollo
B12: SURA Canales Masivos | C12: ='SURA Canales Masivos'!C13 -> N2 | D12: =IFERROR('SURA Canales Masivos'!E57,0) -> 0.58823529 | E12: =IFERROR('SURA Canales Masivos'!C67,0) -> 0 | F12: =IFERROR('SURA Canales Masivos'!C69,0) -> 0.72 | G12: =IFERROR('SURA Canales Masivos'!C90,0) -> 0 | H12: =IFERROR('SURA Canales Masivos'!C73,0) -> 1 | I12: =IF(OR('SURA Canales Masivos'!C100="Sí",'SURA Canales Masivos'!C100="Si"),1,IF('SURA Canales Masivos'!C100="Parcial",0.5,0))+IF(OR('SURA Canales Masivos'!C101="Sí",'SURA Canales Masivos'!C101="Si"),1,IF('SURA Canales Masivos'!C101="Parcial",0.5,0))+IF(OR('SURA Canales Masivos'!C102="Sí",'SURA Canales Masivos'!C102="Si"),1,IF('SURA Canales Masivos'!C102="Parcial",0.5,0))+IF(OR('SURA Canales Masivos'!C103="Sí",'SURA Canales Masivos'!C103="Si"),1,IF('SURA Canales Masivos'!C103="Parcial",0.5,0))+IF(OR('SURA Canales Masivos'!C104="Sí",'SURA Canales Masivos'!C104="Si"),1,IF('SURA Canales Masivos'!C104="Parcial",0.5,0))+IF(OR('SURA Canales Masivos'!C105="Sí",'SURA Canales Masivos'!C105="Si"),1,IF('SURA Canales Masivos'!C105="Parcial",0.5,0))+IF(OR('SURA Canales Masivos'!C106="Sí",'SURA Canales Masivos'!C106="Si"),1,IF('SURA Canales Masivos'!C106="Parcial",0.5,0))+IF(OR('SURA Canales Masivos'!C107="Sí",'SURA Canales Masivos'!C107="Si"),1,IF('SURA Canales Masivos'!C107="Parcial",0.5,0))+IF(OR('SURA Canales Masivos'!C108="Sí",'SURA Canales Masivos'!C108="Si"),1,IF('SURA Canales Masivos'!C108="Parcial",0.5,0))+IF(OR('SURA Canales Masivos'!C109="Sí",'SURA Canales Masivos'!C109="Si"),1,IF('SURA Canales Masivos'!C109="Parcial",0.5,0))+IF(OR('SURA Canales Masivos'!C110="Sí",'SURA Canales Masivos'!C110="Si"),1,IF('SURA Canales Masivos'!C110="Parcial",0.5,0))+IF(OR('SURA Canales Masivos'!C111="Sí",'SURA Canales Masivos'!C111="Si"),1,IF('SURA Canales Masivos'!C111="Parcial",0.5,0))+IF(OR('SURA Canales Masivos'!C112="Sí",'SURA Canales Masivos'!C112="Si"),1,IF('SURA Canales Masivos'!C112="Parcial",0.5,0))+IF(OR('SURA Canales Masivos'!C113="Sí",'SURA Canales Masivos'!C113="Si"),1,IF('SURA Canales Masivos'!C113="Parcial",0.5,0))+IF(OR('SURA Canales Masivos'!C114="Sí",'SURA Canales Masivos'!C114="Si"),1,IF('SURA Canales Masivos'!C114="Parcial",0.5,0))+IF(OR('SURA Canales Masivos'!C115="Sí",'SURA Canales Masivos'!C115="Si"),1,IF('SURA Canales Masivos'!C115="Parcial",0.5,0))+IF(OR('SURA Canales Masivos'!C116="Sí",'SURA Canales Masivos'!C116="Si"),1,IF('SURA Canales Masivos'!C116="Parcial",0.5,0))+IF(OR('SURA Canales Masivos'!C117="Sí",'SURA Canales Masivos'!C117="Si"),1,IF('SURA Canales Masivos'!C117="Parcial",0.5,0))+IF(OR('SURA Canales Masivos'!C118="Sí",'SURA Canales Masivos'!C118="Si"),1,IF('SURA Canales Masivos'!C118="Parcial",0.5,0))+IF(OR('SURA Canales Masivos'!C119="Sí",'SURA Canales Masivos'!C119="Si"),1,IF('SURA Canales Masivos'!C119="Parcial",0.5,0))+IF(OR('SURA Canales Masivos'!C120="Sí",'SURA Canales Masivos'!C120="Si"),1,IF('SURA Canales Masivos'!C120="Parcial",0.5,0))+IF(OR('SURA Canales Masivos'!C121="Sí",'SURA Canales Masivos'!C121="Si"),1,IF('SURA Canales Masivos'!C121="Parcial",0.5,0)) -> 13 | J12: =IF(D12<30%,"Alta",IF(D12<60%,"Media","Baja")) -> Media | K12: =IF(D12=0,"Pendiente",IF(D12>=70%,"Fuerte",IF(D12>=40%,"En desarrollo","Crítica"))) -> En desarrollo
B13: BCO COES Integracion | C13: ='BCO COES Integracion'!C13 -> N1 | D13: =IFERROR('BCO COES Integracion'!E58,0) -> 0.73529412 | E13: =IFERROR('BCO COES Integracion'!C68,0) -> Pendiente revisar líderes técnicos | F13: =IFERROR('BCO COES Integracion'!C70,0) -> No aplica SLA- ANS del Banco y de COES | G13: =IFERROR('BCO COES Integracion'!C91,0) -> 0 | H13: =IFERROR('BCO COES Integracion'!C74,0) -> 7 | I13: =IF(OR('BCO COES Integracion'!C101="Sí",'BCO COES Integracion'!C101="Si"),1,IF('BCO COES Integracion'!C101="Parcial",0.5,0))+IF(OR('BCO COES Integracion'!C102="Sí",'BCO COES Integracion'!C102="Si"),1,IF('BCO COES Integracion'!C102="Parcial",0.5,0))+IF(OR('BCO COES Integracion'!C103="Sí",'BCO COES Integracion'!C103="Si"),1,IF('BCO COES Integracion'!C103="Parcial",0.5,0))+IF(OR('BCO COES Integracion'!C104="Sí",'BCO COES Integracion'!C104="Si"),1,IF('BCO COES Integracion'!C104="Parcial",0.5,0))+IF(OR('BCO COES Integracion'!C105="Sí",'BCO COES Integracion'!C105="Si"),1,IF('BCO COES Integracion'!C105="Parcial",0.5,0))+IF(OR('BCO COES Integracion'!C106="Sí",'BCO COES Integracion'!C106="Si"),1,IF('BCO COES Integracion'!C106="Parcial",0.5,0))+IF(OR('BCO COES Integracion'!C107="Sí",'BCO COES Integracion'!C107="Si"),1,IF('BCO COES Integracion'!C107="Parcial",0.5,0))+IF(OR('BCO COES Integracion'!C108="Sí",'BCO COES Integracion'!C108="Si"),1,IF('BCO COES Integracion'!C108="Parcial",0.5,0))+IF(OR('BCO COES Integracion'!C109="Sí",'BCO COES Integracion'!C109="Si"),1,IF('BCO COES Integracion'!C109="Parcial",0.5,0))+IF(OR('BCO COES Integracion'!C110="Sí",'BCO COES Integracion'!C110="Si"),1,IF('BCO COES Integracion'!C110="Parcial",0.5,0))+IF(OR('BCO COES Integracion'!C111="Sí",'BCO COES Integracion'!C111="Si"),1,IF('BCO COES Integracion'!C111="Parcial",0.5,0))+IF(OR('BCO COES Integracion'!C112="Sí",'BCO COES Integracion'!C112="Si"),1,IF('BCO COES Integracion'!C112="Parcial",0.5,0))+IF(OR('BCO COES Integracion'!C113="Sí",'BCO COES Integracion'!C113="Si"),1,IF('BCO COES Integracion'!C113="Parcial",0.5,0))+IF(OR('BCO COES Integracion'!C114="Sí",'BCO COES Integracion'!C114="Si"),1,IF('BCO COES Integracion'!C114="Parcial",0.5,0))+IF(OR('BCO COES Integracion'!C115="Sí",'BCO COES Integracion'!C115="Si"),1,IF('BCO COES Integracion'!C115="Parcial",0.5,0))+IF(OR('BCO COES Integracion'!C116="Sí",'BCO COES Integracion'!C116="Si"),1,IF('BCO COES Integracion'!C116="Parcial",0.5,0))+IF(OR('BCO COES Integracion'!C117="Sí",'BCO COES Integracion'!C117="Si"),1,IF('BCO COES Integracion'!C117="Parcial",0.5,0))+IF(OR('BCO COES Integracion'!C118="Sí",'BCO COES Integracion'!C118="Si"),1,IF('BCO COES Integracion'!C118="Parcial",0.5,0))+IF(OR('BCO COES Integracion'!C119="Sí",'BCO COES Integracion'!C119="Si"),1,IF('BCO COES Integracion'!C119="Parcial",0.5,0))+IF(OR('BCO COES Integracion'!C120="Sí",'BCO COES Integracion'!C120="Si"),1,IF('BCO COES Integracion'!C120="Parcial",0.5,0))+IF(OR('BCO COES Integracion'!C121="Sí",'BCO COES Integracion'!C121="Si"),1,IF('BCO COES Integracion'!C121="Parcial",0.5,0))+IF(OR('BCO COES Integracion'!C122="Sí",'BCO COES Integracion'!C122="Si"),1,IF('BCO COES Integracion'!C122="Parcial",0.5,0)) -> 9.5 | J13: =IF(D13<30%,"Alta",IF(D13<60%,"Media","Baja")) -> Baja | K13: =IF(D13=0,"Pendiente",IF(D13>=70%,"Fuerte",IF(D13>=40%,"En desarrollo","Crítica"))) -> Fuerte
B14: BCO COES Datos | C14: ='BCO COES Datos'!#REF! -> #REF! | D14: =IFERROR('BCO COES Datos'!E58,0) -> 0.73529412 | E14: =IFERROR('BCO COES Datos'!C68,0) -> Pendiente revisar líderes técnicos | F14: =IFERROR('BCO COES Datos'!C70,0) -> No aplica SLA- ANS del Banco y de COES | G14: =IFERROR('BCO COES Datos'!C91,0) -> 0 | H14: =IFERROR('BCO COES Datos'!C74,0) -> 7 | I14: =IF(OR('BCO COES Datos'!C101="Sí",'BCO COES Datos'!C101="Si"),1,IF('BCO COES Datos'!C101="Parcial",0.5,0))+IF(OR('BCO COES Datos'!C102="Sí",'BCO COES Datos'!C102="Si"),1,IF('BCO COES Datos'!C102="Parcial",0.5,0))+IF(OR('BCO COES Datos'!C103="Sí",'BCO COES Datos'!C103="Si"),1,IF('BCO COES Datos'!C103="Parcial",0.5,0))+IF(OR('BCO COES Datos'!C104="Sí",'BCO COES Datos'!C104="Si"),1,IF('BCO COES Datos'!C104="Parcial",0.5,0))+IF(OR('BCO COES Datos'!C105="Sí",'BCO COES Datos'!C105="Si"),1,IF('BCO COES Datos'!C105="Parcial",0.5,0))+IF(OR('BCO COES Datos'!C106="Sí",'BCO COES Datos'!C106="Si"),1,IF('BCO COES Datos'!C106="Parcial",0.5,0))+IF(OR('BCO COES Datos'!C107="Sí",'BCO COES Datos'!C107="Si"),1,IF('BCO COES Datos'!C107="Parcial",0.5,0))+IF(OR('BCO COES Datos'!C108="Sí",'BCO COES Datos'!C108="Si"),1,IF('BCO COES Datos'!C108="Parcial",0.5,0))+IF(OR('BCO COES Datos'!C109="Sí",'BCO COES Datos'!C109="Si"),1,IF('BCO COES Datos'!C109="Parcial",0.5,0))+IF(OR('BCO COES Datos'!C110="Sí",'BCO COES Datos'!C110="Si"),1,IF('BCO COES Datos'!C110="Parcial",0.5,0))+IF(OR('BCO COES Datos'!C111="Sí",'BCO COES Datos'!C111="Si"),1,IF('BCO COES Datos'!C111="Parcial",0.5,0))+IF(OR('BCO COES Datos'!C112="Sí",'BCO COES Datos'!C112="Si"),1,IF('BCO COES Datos'!C112="Parcial",0.5,0))+IF(OR('BCO COES Datos'!C113="Sí",'BCO COES Datos'!C113="Si"),1,IF('BCO COES Datos'!C113="Parcial",0.5,0))+IF(OR('BCO COES Datos'!C114="Sí",'BCO COES Datos'!C114="Si"),1,IF('BCO COES Datos'!C114="Parcial",0.5,0))+IF(OR('BCO COES Datos'!C115="Sí",'BCO COES Datos'!C115="Si"),1,IF('BCO COES Datos'!C115="Parcial",0.5,0))+IF(OR('BCO COES Datos'!C116="Sí",'BCO COES Datos'!C116="Si"),1,IF('BCO COES Datos'!C116="Parcial",0.5,0))+IF(OR('BCO COES Datos'!C117="Sí",'BCO COES Datos'!C117="Si"),1,IF('BCO COES Datos'!C117="Parcial",0.5,0))+IF(OR('BCO COES Datos'!C118="Sí",'BCO COES Datos'!C118="Si"),1,IF('BCO COES Datos'!C118="Parcial",0.5,0))+IF(OR('BCO COES Datos'!C119="Sí",'BCO COES Datos'!C119="Si"),1,IF('BCO COES Datos'!C119="Parcial",0.5,0))+IF(OR('BCO COES Datos'!C120="Sí",'BCO COES Datos'!C120="Si"),1,IF('BCO COES Datos'!C120="Parcial",0.5,0))+IF(OR('BCO COES Datos'!C121="Sí",'BCO COES Datos'!C121="Si"),1,IF('BCO COES Datos'!C121="Parcial",0.5,0))+IF(OR('BCO COES Datos'!C122="Sí",'BCO COES Datos'!C122="Si"),1,IF('BCO COES Datos'!C122="Parcial",0.5,0)) -> 9.5 | J14: =IF(D14<30%,"Alta",IF(D14<60%,"Media","Baja")) -> Baja | K14: =IF(D14=0,"Pendiente",IF(D14>=70%,"Fuerte",IF(D14>=40%,"En desarrollo","Crítica"))) -> Fuerte
B15: BCO Soporte | C15: ='BCO Soporte'!C13 -> N1 | D15: =IFERROR('BCO Soporte'!E58,0) -> 0.73529412 | E15: =IFERROR('BCO Soporte'!C68,0) -> Pendiente revisar líderes técnicos | F15: =IFERROR('BCO Soporte'!C70,0) -> No aplica SLA- ANS del Banco y de COES | G15: =IFERROR('BCO Soporte'!C91,0) -> 0 | H15: =IFERROR('BCO Soporte'!C74,0) -> 13 | I15: =IF(OR('BCO Soporte'!C102="Sí",'BCO Soporte'!C102="Si"),1,IF('BCO Soporte'!C102="Parcial",0.5,0))+IF(OR('BCO Soporte'!C103="Sí",'BCO Soporte'!C103="Si"),1,IF('BCO Soporte'!C103="Parcial",0.5,0))+IF(OR('BCO Soporte'!C104="Sí",'BCO Soporte'!C104="Si"),1,IF('BCO Soporte'!C104="Parcial",0.5,0))+IF(OR('BCO Soporte'!C105="Sí",'BCO Soporte'!C105="Si"),1,IF('BCO Soporte'!C105="Parcial",0.5,0))+IF(OR('BCO Soporte'!C106="Sí",'BCO Soporte'!C106="Si"),1,IF('BCO Soporte'!C106="Parcial",0.5,0))+IF(OR('BCO Soporte'!C107="Sí",'BCO Soporte'!C107="Si"),1,IF('BCO Soporte'!C107="Parcial",0.5,0))+IF(OR('BCO Soporte'!C108="Sí",'BCO Soporte'!C108="Si"),1,IF('BCO Soporte'!C108="Parcial",0.5,0))+IF(OR('BCO Soporte'!C109="Sí",'BCO Soporte'!C109="Si"),1,IF('BCO Soporte'!C109="Parcial",0.5,0))+IF(OR('BCO Soporte'!C110="Sí",'BCO Soporte'!C110="Si"),1,IF('BCO Soporte'!C110="Parcial",0.5,0))+IF(OR('BCO Soporte'!C111="Sí",'BCO Soporte'!C111="Si"),1,IF('BCO Soporte'!C111="Parcial",0.5,0))+IF(OR('BCO Soporte'!C112="Sí",'BCO Soporte'!C112="Si"),1,IF('BCO Soporte'!C112="Parcial",0.5,0))+IF(OR('BCO Soporte'!C113="Sí",'BCO Soporte'!C113="Si"),1,IF('BCO Soporte'!C113="Parcial",0.5,0))+IF(OR('BCO Soporte'!C114="Sí",'BCO Soporte'!C114="Si"),1,IF('BCO Soporte'!C114="Parcial",0.5,0))+IF(OR('BCO Soporte'!C115="Sí",'BCO Soporte'!C115="Si"),1,IF('BCO Soporte'!C115="Parcial",0.5,0))+IF(OR('BCO Soporte'!C116="Sí",'BCO Soporte'!C116="Si"),1,IF('BCO Soporte'!C116="Parcial",0.5,0))+IF(OR('BCO Soporte'!C117="Sí",'BCO Soporte'!C117="Si"),1,IF('BCO Soporte'!C117="Parcial",0.5,0))+IF(OR('BCO Soporte'!C118="Sí",'BCO Soporte'!C118="Si"),1,IF('BCO Soporte'!C118="Parcial",0.5,0))+IF(OR('BCO Soporte'!C119="Sí",'BCO Soporte'!C119="Si"),1,IF('BCO Soporte'!C119="Parcial",0.5,0))+IF(OR('BCO Soporte'!C120="Sí",'BCO Soporte'!C120="Si"),1,IF('BCO Soporte'!C120="Parcial",0.5,0))+IF(OR('BCO Soporte'!C121="Sí",'BCO Soporte'!C121="Si"),1,IF('BCO Soporte'!C121="Parcial",0.5,0))+IF(OR('BCO Soporte'!C123="Sí",'BCO Soporte'!C123="Si"),1,IF('BCO Soporte'!C123="Parcial",0.5,0)) -> 9 | J15: =IF(D15<30%,"Alta",IF(D15<60%,"Media","Baja")) -> Baja | K15: =IF(D15=0,"Pendiente",IF(D15>=70%,"Fuerte",IF(D15>=40%,"En desarrollo","Crítica"))) -> Fuerte
B16: BCO COES Emma | C16: ='BCO COES Emma'!C13 -> N1 | D16: =IFERROR('BCO COES Emma'!E58,0) -> 0.73529412 | E16: =IFERROR('BCO COES Emma'!C68,0) -> 0 | F16: =IFERROR('BCO COES Emma'!C70,0) -> No aplica SLA- ANS del Banco y de COES | G16: =IFERROR('BCO COES Emma'!C91,0) -> 0 | H16: =IFERROR('BCO COES Emma'!C74,0) -> 4 | I16: =IF(OR('BCO COES Emma'!C101="Sí",'BCO COES Emma'!C101="Si"),1,IF('BCO COES Emma'!C101="Parcial",0.5,0))+IF(OR('BCO COES Emma'!C102="Sí",'BCO COES Emma'!C102="Si"),1,IF('BCO COES Emma'!C102="Parcial",0.5,0))+IF(OR('BCO COES Emma'!C103="Sí",'BCO COES Emma'!C103="Si"),1,IF('BCO COES Emma'!C103="Parcial",0.5,0))+IF(OR('BCO COES Emma'!C104="Sí",'BCO COES Emma'!C104="Si"),1,IF('BCO COES Emma'!C104="Parcial",0.5,0))+IF(OR('BCO COES Emma'!C105="Sí",'BCO COES Emma'!C105="Si"),1,IF('BCO COES Emma'!C105="Parcial",0.5,0))+IF(OR('BCO COES Emma'!C106="Sí",'BCO COES Emma'!C106="Si"),1,IF('BCO COES Emma'!C106="Parcial",0.5,0))+IF(OR('BCO COES Emma'!C107="Sí",'BCO COES Emma'!C107="Si"),1,IF('BCO COES Emma'!C107="Parcial",0.5,0))+IF(OR('BCO COES Emma'!C108="Sí",'BCO COES Emma'!C108="Si"),1,IF('BCO COES Emma'!C108="Parcial",0.5,0))+IF(OR('BCO COES Emma'!C109="Sí",'BCO COES Emma'!C109="Si"),1,IF('BCO COES Emma'!C109="Parcial",0.5,0))+IF(OR('BCO COES Emma'!C110="Sí",'BCO COES Emma'!C110="Si"),1,IF('BCO COES Emma'!C110="Parcial",0.5,0))+IF(OR('BCO COES Emma'!C111="Sí",'BCO COES Emma'!C111="Si"),1,IF('BCO COES Emma'!C111="Parcial",0.5,0))+IF(OR('BCO COES Emma'!C112="Sí",'BCO COES Emma'!C112="Si"),1,IF('BCO COES Emma'!C112="Parcial",0.5,0))+IF(OR('BCO COES Emma'!C113="Sí",'BCO COES Emma'!C113="Si"),1,IF('BCO COES Emma'!C113="Parcial",0.5,0))+IF(OR('BCO COES Emma'!C114="Sí",'BCO COES Emma'!C114="Si"),1,IF('BCO COES Emma'!C114="Parcial",0.5,0))+IF(OR('BCO COES Emma'!C115="Sí",'BCO COES Emma'!C115="Si"),1,IF('BCO COES Emma'!C115="Parcial",0.5,0))+IF(OR('BCO COES Emma'!C116="Sí",'BCO COES Emma'!C116="Si"),1,IF('BCO COES Emma'!C116="Parcial",0.5,0))+IF(OR('BCO COES Emma'!C117="Sí",'BCO COES Emma'!C117="Si"),1,IF('BCO COES Emma'!C117="Parcial",0.5,0))+IF(OR('BCO COES Emma'!C118="Sí",'BCO COES Emma'!C118="Si"),1,IF('BCO COES Emma'!C118="Parcial",0.5,0))+IF(OR('BCO COES Emma'!C119="Sí",'BCO COES Emma'!C119="Si"),1,IF('BCO COES Emma'!C119="Parcial",0.5,0))+IF(OR('BCO COES Emma'!C120="Sí",'BCO COES Emma'!C120="Si"),1,IF('BCO COES Emma'!C120="Parcial",0.5,0))+IF(OR('BCO COES Emma'!C121="Sí",'BCO COES Emma'!C121="Si"),1,IF('BCO COES Emma'!C121="Parcial",0.5,0))+IF(OR('BCO COES Emma'!C122="Sí",'BCO COES Emma'!C122="Si"),1,IF('BCO COES Emma'!C122="Parcial",0.5,0)) -> 9.5 | J16: =IF(D16<30%,"Alta",IF(D16<60%,"Media","Baja")) -> Baja | K16: =IF(D16=0,"Pendiente",IF(D16>=70%,"Fuerte",IF(D16>=40%,"En desarrollo","Crítica"))) -> Fuerte
B17: BCO Emma Iseries | C17: ='BCO Emma Iseries'!C13 -> N1 | D17: =IFERROR('BCO Emma Iseries'!E58,0) -> 0.73529412 | E17: =IFERROR('BCO Emma Iseries'!C68,0) -> 0 | F17: =IFERROR('BCO Emma Iseries'!C70,0) -> No aplica SLA- ANS del Banco y de COES | G17: =IFERROR('BCO Emma Iseries'!C91,0) -> 0 | H17: =IFERROR('BCO Emma Iseries'!C74,0) -> 1 | I17: =IF(OR('BCO Emma Iseries'!C101="Sí",'BCO Emma Iseries'!C101="Si"),1,IF('BCO Emma Iseries'!C101="Parcial",0.5,0))+IF(OR('BCO Emma Iseries'!C102="Sí",'BCO Emma Iseries'!C102="Si"),1,IF('BCO Emma Iseries'!C102="Parcial",0.5,0))+IF(OR('BCO Emma Iseries'!C103="Sí",'BCO Emma Iseries'!C103="Si"),1,IF('BCO Emma Iseries'!C103="Parcial",0.5,0))+IF(OR('BCO Emma Iseries'!C104="Sí",'BCO Emma Iseries'!C104="Si"),1,IF('BCO Emma Iseries'!C104="Parcial",0.5,0))+IF(OR('BCO Emma Iseries'!C105="Sí",'BCO Emma Iseries'!C105="Si"),1,IF('BCO Emma Iseries'!C105="Parcial",0.5,0))+IF(OR('BCO Emma Iseries'!C106="Sí",'BCO Emma Iseries'!C106="Si"),1,IF('BCO Emma Iseries'!C106="Parcial",0.5,0))+IF(OR('BCO Emma Iseries'!C107="Sí",'BCO Emma Iseries'!C107="Si"),1,IF('BCO Emma Iseries'!C107="Parcial",0.5,0))+IF(OR('BCO Emma Iseries'!C108="Sí",'BCO Emma Iseries'!C108="Si"),1,IF('BCO Emma Iseries'!C108="Parcial",0.5,0))+IF(OR('BCO Emma Iseries'!C109="Sí",'BCO Emma Iseries'!C109="Si"),1,IF('BCO Emma Iseries'!C109="Parcial",0.5,0))+IF(OR('BCO Emma Iseries'!C110="Sí",'BCO Emma Iseries'!C110="Si"),1,IF('BCO Emma Iseries'!C110="Parcial",0.5,0))+IF(OR('BCO Emma Iseries'!C111="Sí",'BCO Emma Iseries'!C111="Si"),1,IF('BCO Emma Iseries'!C111="Parcial",0.5,0))+IF(OR('BCO Emma Iseries'!C112="Sí",'BCO Emma Iseries'!C112="Si"),1,IF('BCO Emma Iseries'!C112="Parcial",0.5,0))+IF(OR('BCO Emma Iseries'!C113="Sí",'BCO Emma Iseries'!C113="Si"),1,IF('BCO Emma Iseries'!C113="Parcial",0.5,0))+IF(OR('BCO Emma Iseries'!C114="Sí",'BCO Emma Iseries'!C114="Si"),1,IF('BCO Emma Iseries'!C114="Parcial",0.5,0))+IF(OR('BCO Emma Iseries'!C115="Sí",'BCO Emma Iseries'!C115="Si"),1,IF('BCO Emma Iseries'!C115="Parcial",0.5,0))+IF(OR('BCO Emma Iseries'!C116="Sí",'BCO Emma Iseries'!C116="Si"),1,IF('BCO Emma Iseries'!C116="Parcial",0.5,0))+IF(OR('BCO Emma Iseries'!C117="Sí",'BCO Emma Iseries'!C117="Si"),1,IF('BCO Emma Iseries'!C117="Parcial",0.5,0))+IF(OR('BCO Emma Iseries'!C118="Sí",'BCO Emma Iseries'!C118="Si"),1,IF('BCO Emma Iseries'!C118="Parcial",0.5,0))+IF(OR('BCO Emma Iseries'!C119="Sí",'BCO Emma Iseries'!C119="Si"),1,IF('BCO Emma Iseries'!C119="Parcial",0.5,0))+IF(OR('BCO Emma Iseries'!C120="Sí",'BCO Emma Iseries'!C120="Si"),1,IF('BCO Emma Iseries'!C120="Parcial",0.5,0))+IF(OR('BCO Emma Iseries'!C121="Sí",'BCO Emma Iseries'!C121="Si"),1,IF('BCO Emma Iseries'!C121="Parcial",0.5,0))+IF(OR('BCO Emma Iseries'!C122="Sí",'BCO Emma Iseries'!C122="Si"),1,IF('BCO Emma Iseries'!C122="Parcial",0.5,0)) -> 2 | J17: =IF(D17<30%,"Alta",IF(D17<60%,"Media","Baja")) -> Baja | K17: =IF(D17=0,"Pendiente",IF(D17>=70%,"Fuerte",IF(D17>=40%,"En desarrollo","Crítica"))) -> Fuerte
B18: AES | C18: =AES!C13 -> N1 | D18: =IFERROR(AES!E57,0) -> 0.29411765 | E18: =IFERROR(AES!C62,0) -> 0 | F18: =IFERROR(AES!C64,0) -> 0 | G18: =IFERROR(AES!C85,0) -> 0 | H18: =IFERROR(AES!C11,0) -> 4 | I18: =ChartData!AT12 -> 7 | J18: =IF(D18<30%,"Alta",IF(D18<60%,"Media","Baja")) -> Alta | K18: =IF(D18=0,"Pendiente",IF(D18>=70%,"Fuerte",IF(D18>=40%,"En desarrollo","Crítica"))) -> Crítica
B19: XM | C19: =XM!C13 -> N2 | D19: =IFERROR(XM!E57,0) -> 0.5 | E19: =IFERROR(XM!C68,0) -> 0 | F19: =IFERROR(XM!C70,0) -> 0 | G19: =IFERROR(XM!C91,0) -> 0 | H19: =IFERROR(XM!C11,0) -> 4 | I19: =ChartData!AT13 -> 16 | J19: =IF(D19<30%,"Alta",IF(D19<60%,"Media","Baja")) -> Media | K19: =IF(D19=0,"Pendiente",IF(D19>=70%,"Fuerte",IF(D19>=40%,"En desarrollo","Crítica"))) -> En desarrollo
B20: MEDICARTE | C20: =MEDICARTE!C13 -> 0 | D20: =IFERROR(MEDICARTE!E57,0) -> 0 | E20: =IFERROR(MEDICARTE!C62,0) -> 0 | F20: =IFERROR(MEDICARTE!C64,0) -> 0 | G20: =IFERROR(MEDICARTE!C85,0) -> 0 | H20: =IFERROR(MEDICARTE!C11,0) -> 0 | I20: =ChartData!AT14 -> 1 | J20: =IF(D20<30%,"Alta",IF(D20<60%,"Media","Baja")) -> Alta | K20: =IF(D20=0,"Pendiente",IF(D20>=70%,"Fuerte",IF(D20>=40%,"En desarrollo","Crítica"))) -> Pendiente
B22: ESTADÍSTICAS DE CONSOLIDADO
B23: Promedio Score Prácticas ITIL: | E23: =AVERAGE(D9:D19) -> 0.61497326
B24: Score Mínimo: | E24: =MIN(D9:D19) -> 0.29411765
B25: Score Máximo: | E25: =MAX(D9:D19) -> 0.73529412
B26: Total FTEs evaluados: | E26: =SUM(H9:H19) -> 57
B27: Mesas evaluadas: | E27: =COUNTA(B9:B19) -> 11
B28: Mesas pendientes / sin datos: | E28: =COUNTIF(K9:K19,"Pendiente") -> 0
B31: SEMÁFORO DE MADUREZ — ESTADO POR MESA
B32: MESA | C32: Nivel | D32: Descripción del Nivel | E32: Score Prácticas | F32: Fortaleza Identificada | G32: Brecha Principal | H32: Acción Recomendada Mesas de Nueva Generación
B33: =B9 -> SURA Cotizadores | C33: =C9 -> N2 | D33: {=_xlfn.SWITCH(C33,"N0","Reactivo / Sin estructura","N1","Inicial / Ad hoc","N2","Definido","N3","Gestionado","N4","Optimizado","N5","Innovador / Diferenciador","— Por definir")} -> Definido | E33: =D9 -> 0.52941176 | F33: =IF(E33>=70%,"Buenas prácticas ITIL consolidadas",IF(E33>=40%,"Base operativa existente","Información o práctica incompleta")) -> Base operativa existente | G33: =IF(E33<40%,"Bajo cumplimiento / datos pendientes",IF(E33<70%,"Estandarización y medición","Escalamiento a automatización")) -> Estandarización y medición | H33: =IF(E33<40%,"Completar levantamiento y priorizar quick wins",IF(E33<70%,"Formalizar procesos, métricas y gobierno","Escalar autoservicio, analítica e IA")) -> Formalizar procesos, métricas y gobierno
B34: =B10 -> SURA Digital Venta | C34: =C10 -> N2 | D34: {=_xlfn.SWITCH(C34,"N0","Reactivo / Sin estructura","N1","Inicial / Ad hoc","N2","Definido","N3","Gestionado","N4","Optimizado","N5","Innovador / Diferenciador","— Por definir")} -> Definido | E34: =D10 -> 0.55882353 | F34: =IF(E34>=70%,"Buenas prácticas ITIL consolidadas",IF(E34>=40%,"Base operativa existente","Información o práctica incompleta")) -> Base operativa existente | G34: =IF(E34<40%,"Bajo cumplimiento / datos pendientes",IF(E34<70%,"Estandarización y medición","Escalamiento a automatización")) -> Estandarización y medición | H34: =IF(E34<40%,"Completar levantamiento y priorizar quick wins",IF(E34<70%,"Formalizar procesos, métricas y gobierno","Escalar autoservicio, analítica e IA")) -> Formalizar procesos, métricas y gobierno
B35: =B11 -> SURA Automatizacion | C35: =C11 -> N2 | D35: {=_xlfn.SWITCH(C35,"N0","Reactivo / Sin estructura","N1","Inicial / Ad hoc","N2","Definido","N3","Gestionado","N4","Optimizado","N5","Innovador / Diferenciador","— Por definir")} -> Definido | E35: =D11 -> 0.61764706 | F35: =IF(E35>=70%,"Buenas prácticas ITIL consolidadas",IF(E35>=40%,"Base operativa existente","Información o práctica incompleta")) -> Base operativa existente | G35: =IF(E35<40%,"Bajo cumplimiento / datos pendientes",IF(E35<70%,"Estandarización y medición","Escalamiento a automatización")) -> Estandarización y medición | H35: =IF(E35<40%,"Completar levantamiento y priorizar quick wins",IF(E35<70%,"Formalizar procesos, métricas y gobierno","Escalar autoservicio, analítica e IA")) -> Formalizar procesos, métricas y gobierno
B36: =B12 -> SURA Canales Masivos | C36: =C12 -> N2 | D36: {=_xlfn.SWITCH(C36,"N0","Reactivo / Sin estructura","N1","Inicial / Ad hoc","N2","Definido","N3","Gestionado","N4","Optimizado","N5","Innovador / Diferenciador","— Por definir")} -> Definido | E36: =D12 -> 0.58823529 | F36: =IF(E36>=70%,"Buenas prácticas ITIL consolidadas",IF(E36>=40%,"Base operativa existente","Información o práctica incompleta")) -> Base operativa existente | G36: =IF(E36<40%,"Bajo cumplimiento / datos pendientes",IF(E36<70%,"Estandarización y medición","Escalamiento a automatización")) -> Estandarización y medición | H36: =IF(E36<40%,"Completar levantamiento y priorizar quick wins",IF(E36<70%,"Formalizar procesos, métricas y gobierno","Escalar autoservicio, analítica e IA")) -> Formalizar procesos, métricas y gobierno
B37: =B13 -> BCO COES Integracion | C37: =C13 -> N1 | D37: {=_xlfn.SWITCH(C37,"N0","Reactivo / Sin estructura","N1","Inicial / Ad hoc","N2","Definido","N3","Gestionado","N4","Optimizado","N5","Innovador / Diferenciador","— Por definir")} -> Inicial / Ad hoc | E37: =D13 -> 0.73529412 | F37: =IF(E37>=70%,"Buenas prácticas ITIL consolidadas",IF(E37>=40%,"Base operativa existente","Información o práctica incompleta")) -> Buenas prácticas ITIL consolidadas | G37: =IF(E37<40%,"Bajo cumplimiento / datos pendientes",IF(E37<70%,"Estandarización y medición","Escalamiento a automatización")) -> Escalamiento a automatización | H37: =IF(E37<40%,"Completar levantamiento y priorizar quick wins",IF(E37<70%,"Formalizar procesos, métricas y gobierno","Escalar autoservicio, analítica e IA")) -> Escalar autoservicio, analítica e IA
B38: =B14 -> BCO COES Datos | C38: =C14 -> #REF! | D38: {=_xlfn.SWITCH(C38,"N0","Reactivo / Sin estructura","N1","Inicial / Ad hoc","N2","Definido","N3","Gestionado","N4","Optimizado","N5","Innovador / Diferenciador","— Por definir")} -> #REF! | E38: =D14 -> 0.73529412 | F38: =IF(E38>=70%,"Buenas prácticas ITIL consolidadas",IF(E38>=40%,"Base operativa existente","Información o práctica incompleta")) -> Buenas prácticas ITIL consolidadas | G38: =IF(E38<40%,"Bajo cumplimiento / datos pendientes",IF(E38<70%,"Estandarización y medición","Escalamiento a automatización")) -> Escalamiento a automatización | H38: =IF(E38<40%,"Completar levantamiento y priorizar quick wins",IF(E38<70%,"Formalizar procesos, métricas y gobierno","Escalar autoservicio, analítica e IA")) -> Escalar autoservicio, analítica e IA
B39: =B15 -> BCO Soporte | C39: =C15 -> N1 | D39: {=_xlfn.SWITCH(C39,"N0","Reactivo / Sin estructura","N1","Inicial / Ad hoc","N2","Definido","N3","Gestionado","N4","Optimizado","N5","Innovador / Diferenciador","— Por definir")} -> Inicial / Ad hoc | E39: =D15 -> 0.73529412 | F39: =IF(E39>=70%,"Buenas prácticas ITIL consolidadas",IF(E39>=40%,"Base operativa existente","Información o práctica incompleta")) -> Buenas prácticas ITIL consolidadas | G39: =IF(E39<40%,"Bajo cumplimiento / datos pendientes",IF(E39<70%,"Estandarización y medición","Escalamiento a automatización")) -> Escalamiento a automatización | H39: =IF(E39<40%,"Completar levantamiento y priorizar quick wins",IF(E39<70%,"Formalizar procesos, métricas y gobierno","Escalar autoservicio, analítica e IA")) -> Escalar autoservicio, analítica e IA
B40: =B16 -> BCO COES Emma | C40: =C16 -> N1 | D40: {=_xlfn.SWITCH(C40,"N0","Reactivo / Sin estructura","N1","Inicial / Ad hoc","N2","Definido","N3","Gestionado","N4","Optimizado","N5","Innovador / Diferenciador","— Por definir")} -> Inicial / Ad hoc | E40: =D16 -> 0.73529412 | F40: =IF(E40>=70%,"Buenas prácticas ITIL consolidadas",IF(E40>=40%,"Base operativa existente","Información o práctica incompleta")) -> Buenas prácticas ITIL consolidadas | G40: =IF(E40<40%,"Bajo cumplimiento / datos pendientes",IF(E40<70%,"Estandarización y medición","Escalamiento a automatización")) -> Escalamiento a automatización | H40: =IF(E40<40%,"Completar levantamiento y priorizar quick wins",IF(E40<70%,"Formalizar procesos, métricas y gobierno","Escalar autoservicio, analítica e IA")) -> Escalar autoservicio, analítica e IA
B41: =B17 -> BCO Emma Iseries | C41: =C17 -> N1 | D41: {=_xlfn.SWITCH(C41,"N0","Reactivo / Sin estructura","N1","Inicial / Ad hoc","N2","Definido","N3","Gestionado","N4","Optimizado","N5","Innovador / Diferenciador","— Por definir")} -> Inicial / Ad hoc | E41: =D17 -> 0.73529412 | F41: =IF(E41>=70%,"Buenas prácticas ITIL consolidadas",IF(E41>=40%,"Base operativa existente","Información o práctica incompleta")) -> Buenas prácticas ITIL consolidadas | G41: =IF(E41<40%,"Bajo cumplimiento / datos pendientes",IF(E41<70%,"Estandarización y medición","Escalamiento a automatización")) -> Escalamiento a automatización | H41: =IF(E41<40%,"Completar levantamiento y priorizar quick wins",IF(E41<70%,"Formalizar procesos, métricas y gobierno","Escalar autoservicio, analítica e IA")) -> Escalar autoservicio, analítica e IA
B42: =B18 -> AES | C42: =C18 -> N1 | D42: {=_xlfn.SWITCH(C42,"N0","Reactivo / Sin estructura","N1","Inicial / Ad hoc","N2","Definido","N3","Gestionado","N4","Optimizado","N5","Innovador / Diferenciador","— Por definir")} -> Inicial / Ad hoc | E42: =D18 -> 0.29411765 | F42: =IF(E42>=70%,"Buenas prácticas ITIL consolidadas",IF(E42>=40%,"Base operativa existente","Información o práctica incompleta")) -> Información o práctica incompleta | G42: =IF(E42<40%,"Bajo cumplimiento / datos pendientes",IF(E42<70%,"Estandarización y medición","Escalamiento a automatización")) -> Bajo cumplimiento / datos pendientes | H42: =IF(E42<40%,"Completar levantamiento y priorizar quick wins",IF(E42<70%,"Formalizar procesos, métricas y gobierno","Escalar autoservicio, analítica e IA")) -> Completar levantamiento y priorizar quick wins
B43: =B19 -> XM | C43: =C19 -> N2 | D43: {=_xlfn.SWITCH(C43,"N0","Reactivo / Sin estructura","N1","Inicial / Ad hoc","N2","Definido","N3","Gestionado","N4","Optimizado","N5","Innovador / Diferenciador","— Por definir")} -> Definido | E43: =D19 -> 0.5 | F43: =IF(E43>=70%,"Buenas prácticas ITIL consolidadas",IF(E43>=40%,"Base operativa existente","Información o práctica incompleta")) -> Base operativa existente | G43: =IF(E43<40%,"Bajo cumplimiento / datos pendientes",IF(E43<70%,"Estandarización y medición","Escalamiento a automatización")) -> Estandarización y medición | H43: =IF(E43<40%,"Completar levantamiento y priorizar quick wins",IF(E43<70%,"Formalizar procesos, métricas y gobierno","Escalar autoservicio, analítica e IA")) -> Formalizar procesos, métricas y gobierno
B45: DOLORES ACTIVOS POR MESA — D1–D23 (✓=Sí · ~=Parcial)
B46: DOLOR | C46: SURA Cotiz. | D46: SURA Venta D. | E46: SURA Autom. | F46: SURA Canales | G46: BCO COES Int. | H46: BCO Datos | I46: BCO Soporte | J46: BCO Emma | K46: BCO Iseries | L46: AES | M46: XM | N46: MEDICARTE | O46: TOTAL
B47: D1 | C47: =IF(OR('SURA Cotizadores'!C99="Sí",'SURA Cotizadores'!C99="Si"),"✓",IF('SURA Cotizadores'!C99="Parcial","~","")) -> ~ | D47: =IF(OR('SURA Digital Venta'!C100="Sí",'SURA Digital Venta'!C100="Si"),"✓",IF('SURA Digital Venta'!C100="Parcial","~","")) -> ~ | E47: =IF(OR('SURA Automatizacion'!C100="Sí",'SURA Automatizacion'!C100="Si"),"✓",IF('SURA Automatizacion'!C100="Parcial","~","")) -> ~ | F47: =IF(OR('SURA Canales Masivos'!C100="Sí",'SURA Canales Masivos'!C100="Si"),"✓",IF('SURA Canales Masivos'!C100="Parcial","~","")) -> ~ | G47: =IF(OR('BCO COES Integracion'!C101="Sí",'BCO COES Integracion'!C101="Si"),"✓",IF('BCO COES Integracion'!C101="Parcial","~","")) -> ~ | H47: =IF(OR('BCO COES Datos'!C101="Sí",'BCO COES Datos'!C101="Si"),"✓",IF('BCO COES Datos'!C101="Parcial","~","")) -> ~ | I47: =IF(OR('BCO Soporte'!C102="Sí",'BCO Soporte'!C102="Si"),"✓",IF('BCO Soporte'!C102="Parcial","~","")) | J47: =IF(OR('BCO COES Emma'!C101="Sí",'BCO COES Emma'!C101="Si"),"✓",IF('BCO COES Emma'!C101="Parcial","~","")) -> ~ | K47: =IF(OR('BCO Emma Iseries'!C101="Sí",'BCO Emma Iseries'!C101="Si"),"✓",IF('BCO Emma Iseries'!C101="Parcial","~","")) | L47: =IF(OR(AES!C98="Sí",AES!C98="Si"),"✓",IF(AES!C98="Parcial","~","")) | M47: =IF(OR(XM!C100="Sí",XM!C100="Si"),"✓",IF(XM!C100="Parcial","~","")) -> ~ | N47: =IF(OR(MEDICARTE!C101="Sí",MEDICARTE!C101="Si"),"✓",IF(MEDICARTE!C101="Parcial","~","")) | O47: =COUNTIF(C47:N47,"✓")+0.5*COUNTIF(C47:N47,"~") -> 4
B48: D2 | C48: =IF(OR('SURA Cotizadores'!C100="Sí",'SURA Cotizadores'!C100="Si"),"✓",IF('SURA Cotizadores'!C100="Parcial","~","")) -> ✓ | D48: =IF(OR('SURA Digital Venta'!C101="Sí",'SURA Digital Venta'!C101="Si"),"✓",IF('SURA Digital Venta'!C101="Parcial","~","")) -> ✓ | E48: =IF(OR('SURA Automatizacion'!C101="Sí",'SURA Automatizacion'!C101="Si"),"✓",IF('SURA Automatizacion'!C101="Parcial","~","")) | F48: =IF(OR('SURA Canales Masivos'!C101="Sí",'SURA Canales Masivos'!C101="Si"),"✓",IF('SURA Canales Masivos'!C101="Parcial","~","")) -> ✓ | G48: =IF(OR('BCO COES Integracion'!C102="Sí",'BCO COES Integracion'!C102="Si"),"✓",IF('BCO COES Integracion'!C102="Parcial","~","")) | H48: =IF(OR('BCO COES Datos'!C102="Sí",'BCO COES Datos'!C102="Si"),"✓",IF('BCO COES Datos'!C102="Parcial","~","")) | I48: =IF(OR('BCO Soporte'!C103="Sí",'BCO Soporte'!C103="Si"),"✓",IF('BCO Soporte'!C103="Parcial","~","")) -> ~ | J48: =IF(OR('BCO COES Emma'!C102="Sí",'BCO COES Emma'!C102="Si"),"✓",IF('BCO COES Emma'!C102="Parcial","~","")) | K48: =IF(OR('BCO Emma Iseries'!C102="Sí",'BCO Emma Iseries'!C102="Si"),"✓",IF('BCO Emma Iseries'!C102="Parcial","~","")) | L48: =IF(OR(AES!C99="Sí",AES!C99="Si"),"✓",IF(AES!C99="Parcial","~","")) | M48: =IF(OR(XM!C101="Sí",XM!C101="Si"),"✓",IF(XM!C101="Parcial","~","")) | N48: =IF(OR(MEDICARTE!C102="Sí",MEDICARTE!C102="Si"),"✓",IF(MEDICARTE!C102="Parcial","~","")) | O48: =COUNTIF(C48:N48,"✓")+0.5*COUNTIF(C48:N48,"~") -> 3.5
B49: D3 | C49: =IF(OR('SURA Cotizadores'!C101="Sí",'SURA Cotizadores'!C101="Si"),"✓",IF('SURA Cotizadores'!C101="Parcial","~","")) -> ✓ | D49: =IF(OR('SURA Digital Venta'!C102="Sí",'SURA Digital Venta'!C102="Si"),"✓",IF('SURA Digital Venta'!C102="Parcial","~","")) -> ✓ | E49: =IF(OR('SURA Automatizacion'!C102="Sí",'SURA Automatizacion'!C102="Si"),"✓",IF('SURA Automatizacion'!C102="Parcial","~","")) -> ✓ | F49: =IF(OR('SURA Canales Masivos'!C102="Sí",'SURA Canales Masivos'!C102="Si"),"✓",IF('SURA Canales Masivos'!C102="Parcial","~","")) -> ✓ | G49: =IF(OR('BCO COES Integracion'!C103="Sí",'BCO COES Integracion'!C103="Si"),"✓",IF('BCO COES Integracion'!C103="Parcial","~","")) -> ~ | H49: =IF(OR('BCO COES Datos'!C103="Sí",'BCO COES Datos'!C103="Si"),"✓",IF('BCO COES Datos'!C103="Parcial","~","")) -> ~ | I49: =IF(OR('BCO Soporte'!C104="Sí",'BCO Soporte'!C104="Si"),"✓",IF('BCO Soporte'!C104="Parcial","~","")) | J49: =IF(OR('BCO COES Emma'!C103="Sí",'BCO COES Emma'!C103="Si"),"✓",IF('BCO COES Emma'!C103="Parcial","~","")) -> ~ | K49: =IF(OR('BCO Emma Iseries'!C103="Sí",'BCO Emma Iseries'!C103="Si"),"✓",IF('BCO Emma Iseries'!C103="Parcial","~","")) | L49: =IF(OR(AES!C100="Sí",AES!C100="Si"),"✓",IF(AES!C100="Parcial","~","")) | M49: =IF(OR(XM!C102="Sí",XM!C102="Si"),"✓",IF(XM!C102="Parcial","~","")) -> ✓ | N49: =IF(OR(MEDICARTE!C103="Sí",MEDICARTE!C103="Si"),"✓",IF(MEDICARTE!C103="Parcial","~","")) | O49: =COUNTIF(C49:N49,"✓")+0.5*COUNTIF(C49:N49,"~") -> 6.5
B50: D4 | C50: =IF(OR('SURA Cotizadores'!C102="Sí",'SURA Cotizadores'!C102="Si"),"✓",IF('SURA Cotizadores'!C102="Parcial","~","")) -> ~ | D50: =IF(OR('SURA Digital Venta'!C103="Sí",'SURA Digital Venta'!C103="Si"),"✓",IF('SURA Digital Venta'!C103="Parcial","~","")) -> ~ | E50: =IF(OR('SURA Automatizacion'!C103="Sí",'SURA Automatizacion'!C103="Si"),"✓",IF('SURA Automatizacion'!C103="Parcial","~","")) -> ~ | F50: =IF(OR('SURA Canales Masivos'!C103="Sí",'SURA Canales Masivos'!C103="Si"),"✓",IF('SURA Canales Masivos'!C103="Parcial","~","")) -> ~ | G50: =IF(OR('BCO COES Integracion'!C104="Sí",'BCO COES Integracion'!C104="Si"),"✓",IF('BCO COES Integracion'!C104="Parcial","~","")) | H50: =IF(OR('BCO COES Datos'!C104="Sí",'BCO COES Datos'!C104="Si"),"✓",IF('BCO COES Datos'!C104="Parcial","~","")) | I50: =IF(OR('BCO Soporte'!C105="Sí",'BCO Soporte'!C105="Si"),"✓",IF('BCO Soporte'!C105="Parcial","~","")) | J50: =IF(OR('BCO COES Emma'!C104="Sí",'BCO COES Emma'!C104="Si"),"✓",IF('BCO COES Emma'!C104="Parcial","~","")) | K50: =IF(OR('BCO Emma Iseries'!C104="Sí",'BCO Emma Iseries'!C104="Si"),"✓",IF('BCO Emma Iseries'!C104="Parcial","~","")) | L50: =IF(OR(AES!C101="Sí",AES!C101="Si"),"✓",IF(AES!C101="Parcial","~","")) -> ~ | M50: =IF(OR(XM!C103="Sí",XM!C103="Si"),"✓",IF(XM!C103="Parcial","~","")) -> ~ | N50: =IF(OR(MEDICARTE!C104="Sí",MEDICARTE!C104="Si"),"✓",IF(MEDICARTE!C104="Parcial","~","")) | O50: =COUNTIF(C50:N50,"✓")+0.5*COUNTIF(C50:N50,"~") -> 3
B51: D5 | C51: =IF(OR('SURA Cotizadores'!C103="Sí",'SURA Cotizadores'!C103="Si"),"✓",IF('SURA Cotizadores'!C103="Parcial","~","")) | D51: =IF(OR('SURA Digital Venta'!C104="Sí",'SURA Digital Venta'!C104="Si"),"✓",IF('SURA Digital Venta'!C104="Parcial","~","")) | E51: =IF(OR('SURA Automatizacion'!C104="Sí",'SURA Automatizacion'!C104="Si"),"✓",IF('SURA Automatizacion'!C104="Parcial","~","")) | F51: =IF(OR('SURA Canales Masivos'!C104="Sí",'SURA Canales Masivos'!C104="Si"),"✓",IF('SURA Canales Masivos'!C104="Parcial","~","")) | G51: =IF(OR('BCO COES Integracion'!C105="Sí",'BCO COES Integracion'!C105="Si"),"✓",IF('BCO COES Integracion'!C105="Parcial","~","")) | H51: =IF(OR('BCO COES Datos'!C105="Sí",'BCO COES Datos'!C105="Si"),"✓",IF('BCO COES Datos'!C105="Parcial","~","")) | I51: =IF(OR('BCO Soporte'!C106="Sí",'BCO Soporte'!C106="Si"),"✓",IF('BCO Soporte'!C106="Parcial","~","")) | J51: =IF(OR('BCO COES Emma'!C105="Sí",'BCO COES Emma'!C105="Si"),"✓",IF('BCO COES Emma'!C105="Parcial","~","")) | K51: =IF(OR('BCO Emma Iseries'!C105="Sí",'BCO Emma Iseries'!C105="Si"),"✓",IF('BCO Emma Iseries'!C105="Parcial","~","")) | L51: =IF(OR(AES!C102="Sí",AES!C102="Si"),"✓",IF(AES!C102="Parcial","~","")) | M51: =IF(OR(XM!C104="Sí",XM!C104="Si"),"✓",IF(XM!C104="Parcial","~","")) | N51: =IF(OR(MEDICARTE!C105="Sí",MEDICARTE!C105="Si"),"✓",IF(MEDICARTE!C105="Parcial","~","")) | O51: =COUNTIF(C51:N51,"✓")+0.5*COUNTIF(C51:N51,"~") -> 0
B52: D6 | C52: =IF(OR('SURA Cotizadores'!C104="Sí",'SURA Cotizadores'!C104="Si"),"✓",IF('SURA Cotizadores'!C104="Parcial","~","")) -> ~ | D52: =IF(OR('SURA Digital Venta'!C105="Sí",'SURA Digital Venta'!C105="Si"),"✓",IF('SURA Digital Venta'!C105="Parcial","~","")) -> ~ | E52: =IF(OR('SURA Automatizacion'!C105="Sí",'SURA Automatizacion'!C105="Si"),"✓",IF('SURA Automatizacion'!C105="Parcial","~","")) -> ~ | F52: =IF(OR('SURA Canales Masivos'!C105="Sí",'SURA Canales Masivos'!C105="Si"),"✓",IF('SURA Canales Masivos'!C105="Parcial","~","")) -> ~ | G52: =IF(OR('BCO COES Integracion'!C106="Sí",'BCO COES Integracion'!C106="Si"),"✓",IF('BCO COES Integracion'!C106="Parcial","~","")) | H52: =IF(OR('BCO COES Datos'!C106="Sí",'BCO COES Datos'!C106="Si"),"✓",IF('BCO COES Datos'!C106="Parcial","~","")) | I52: =IF(OR('BCO Soporte'!C107="Sí",'BCO Soporte'!C107="Si"),"✓",IF('BCO Soporte'!C107="Parcial","~","")) | J52: =IF(OR('BCO COES Emma'!C106="Sí",'BCO COES Emma'!C106="Si"),"✓",IF('BCO COES Emma'!C106="Parcial","~","")) | K52: =IF(OR('BCO Emma Iseries'!C106="Sí",'BCO Emma Iseries'!C106="Si"),"✓",IF('BCO Emma Iseries'!C106="Parcial","~","")) | L52: =IF(OR(AES!C103="Sí",AES!C103="Si"),"✓",IF(AES!C103="Parcial","~","")) -> ~ | M52: =IF(OR(XM!C105="Sí",XM!C105="Si"),"✓",IF(XM!C105="Parcial","~","")) -> ~ | N52: =IF(OR(MEDICARTE!C106="Sí",MEDICARTE!C106="Si"),"✓",IF(MEDICARTE!C106="Parcial","~","")) | O52: =COUNTIF(C52:N52,"✓")+0.5*COUNTIF(C52:N52,"~") -> 3
B53: D7 | C53: =IF(OR('SURA Cotizadores'!C105="Sí",'SURA Cotizadores'!C105="Si"),"✓",IF('SURA Cotizadores'!C105="Parcial","~","")) -> ~ | D53: =IF(OR('SURA Digital Venta'!C106="Sí",'SURA Digital Venta'!C106="Si"),"✓",IF('SURA Digital Venta'!C106="Parcial","~","")) -> ✓ | E53: =IF(OR('SURA Automatizacion'!C106="Sí",'SURA Automatizacion'!C106="Si"),"✓",IF('SURA Automatizacion'!C106="Parcial","~","")) -> ✓ | F53: =IF(OR('SURA Canales Masivos'!C106="Sí",'SURA Canales Masivos'!C106="Si"),"✓",IF('SURA Canales Masivos'!C106="Parcial","~","")) -> ~ | G53: =IF(OR('BCO COES Integracion'!C107="Sí",'BCO COES Integracion'!C107="Si"),"✓",IF('BCO COES Integracion'!C107="Parcial","~","")) | H53: =IF(OR('BCO COES Datos'!C107="Sí",'BCO COES Datos'!C107="Si"),"✓",IF('BCO COES Datos'!C107="Parcial","~","")) | I53: =IF(OR('BCO Soporte'!C108="Sí",'BCO Soporte'!C108="Si"),"✓",IF('BCO Soporte'!C108="Parcial","~","")) -> ~ | J53: =IF(OR('BCO COES Emma'!C107="Sí",'BCO COES Emma'!C107="Si"),"✓",IF('BCO COES Emma'!C107="Parcial","~","")) | K53: =IF(OR('BCO Emma Iseries'!C107="Sí",'BCO Emma Iseries'!C107="Si"),"✓",IF('BCO Emma Iseries'!C107="Parcial","~","")) | L53: =IF(OR(AES!C104="Sí",AES!C104="Si"),"✓",IF(AES!C104="Parcial","~","")) | M53: =IF(OR(XM!C106="Sí",XM!C106="Si"),"✓",IF(XM!C106="Parcial","~","")) -> ✓ | N53: =IF(OR(MEDICARTE!C107="Sí",MEDICARTE!C107="Si"),"✓",IF(MEDICARTE!C107="Parcial","~","")) | O53: =COUNTIF(C53:N53,"✓")+0.5*COUNTIF(C53:N53,"~") -> 4.5
B54: D8 | C54: =IF(OR('SURA Cotizadores'!C106="Sí",'SURA Cotizadores'!C106="Si"),"✓",IF('SURA Cotizadores'!C106="Parcial","~","")) -> ~ | D54: =IF(OR('SURA Digital Venta'!C107="Sí",'SURA Digital Venta'!C107="Si"),"✓",IF('SURA Digital Venta'!C107="Parcial","~","")) -> ~ | E54: =IF(OR('SURA Automatizacion'!C107="Sí",'SURA Automatizacion'!C107="Si"),"✓",IF('SURA Automatizacion'!C107="Parcial","~","")) -> ~ | F54: =IF(OR('SURA Canales Masivos'!C107="Sí",'SURA Canales Masivos'!C107="Si"),"✓",IF('SURA Canales Masivos'!C107="Parcial","~","")) -> ~ | G54: =IF(OR('BCO COES Integracion'!C108="Sí",'BCO COES Integracion'!C108="Si"),"✓",IF('BCO COES Integracion'!C108="Parcial","~","")) -> ~ | H54: =IF(OR('BCO COES Datos'!C108="Sí",'BCO COES Datos'!C108="Si"),"✓",IF('BCO COES Datos'!C108="Parcial","~","")) -> ~ | I54: =IF(OR('BCO Soporte'!C109="Sí",'BCO Soporte'!C109="Si"),"✓",IF('BCO Soporte'!C109="Parcial","~","")) -> ~ | J54: =IF(OR('BCO COES Emma'!C108="Sí",'BCO COES Emma'!C108="Si"),"✓",IF('BCO COES Emma'!C108="Parcial","~","")) -> ~ | K54: =IF(OR('BCO Emma Iseries'!C108="Sí",'BCO Emma Iseries'!C108="Si"),"✓",IF('BCO Emma Iseries'!C108="Parcial","~","")) | L54: =IF(OR(AES!C105="Sí",AES!C105="Si"),"✓",IF(AES!C105="Parcial","~","")) | M54: =IF(OR(XM!C107="Sí",XM!C107="Si"),"✓",IF(XM!C107="Parcial","~","")) -> ✓ | N54: =IF(OR(MEDICARTE!C108="Sí",MEDICARTE!C108="Si"),"✓",IF(MEDICARTE!C108="Parcial","~","")) | O54: =COUNTIF(C54:N54,"✓")+0.5*COUNTIF(C54:N54,"~") -> 5
B55: D9 | C55: =IF(OR('SURA Cotizadores'!C107="Sí",'SURA Cotizadores'!C107="Si"),"✓",IF('SURA Cotizadores'!C107="Parcial","~","")) -> ✓ | D55: =IF(OR('SURA Digital Venta'!C108="Sí",'SURA Digital Venta'!C108="Si"),"✓",IF('SURA Digital Venta'!C108="Parcial","~","")) -> ✓ | E55: =IF(OR('SURA Automatizacion'!C108="Sí",'SURA Automatizacion'!C108="Si"),"✓",IF('SURA Automatizacion'!C108="Parcial","~","")) -> ✓ | F55: =IF(OR('SURA Canales Masivos'!C108="Sí",'SURA Canales Masivos'!C108="Si"),"✓",IF('SURA Canales Masivos'!C108="Parcial","~","")) -> ✓ | G55: =IF(OR('BCO COES Integracion'!C109="Sí",'BCO COES Integracion'!C109="Si"),"✓",IF('BCO COES Integracion'!C109="Parcial","~","")) -> ~ | H55: =IF(OR('BCO COES Datos'!C109="Sí",'BCO COES Datos'!C109="Si"),"✓",IF('BCO COES Datos'!C109="Parcial","~","")) -> ~ | I55: =IF(OR('BCO Soporte'!C110="Sí",'BCO Soporte'!C110="Si"),"✓",IF('BCO Soporte'!C110="Parcial","~","")) -> ~ | J55: =IF(OR('BCO COES Emma'!C109="Sí",'BCO COES Emma'!C109="Si"),"✓",IF('BCO COES Emma'!C109="Parcial","~","")) -> ~ | K55: =IF(OR('BCO Emma Iseries'!C109="Sí",'BCO Emma Iseries'!C109="Si"),"✓",IF('BCO Emma Iseries'!C109="Parcial","~","")) | L55: =IF(OR(AES!C106="Sí",AES!C106="Si"),"✓",IF(AES!C106="Parcial","~","")) -> ~ | M55: =IF(OR(XM!C108="Sí",XM!C108="Si"),"✓",IF(XM!C108="Parcial","~","")) -> ~ | N55: =IF(OR(MEDICARTE!C109="Sí",MEDICARTE!C109="Si"),"✓",IF(MEDICARTE!C109="Parcial","~","")) | O55: =COUNTIF(C55:N55,"✓")+0.5*COUNTIF(C55:N55,"~") -> 7
B56: D10 | C56: =IF(OR('SURA Cotizadores'!C108="Sí",'SURA Cotizadores'!C108="Si"),"✓",IF('SURA Cotizadores'!C108="Parcial","~","")) -> ~ | D56: =IF(OR('SURA Digital Venta'!C109="Sí",'SURA Digital Venta'!C109="Si"),"✓",IF('SURA Digital Venta'!C109="Parcial","~","")) -> ~ | E56: =IF(OR('SURA Automatizacion'!C109="Sí",'SURA Automatizacion'!C109="Si"),"✓",IF('SURA Automatizacion'!C109="Parcial","~","")) -> ~ | F56: =IF(OR('SURA Canales Masivos'!C109="Sí",'SURA Canales Masivos'!C109="Si"),"✓",IF('SURA Canales Masivos'!C109="Parcial","~","")) -> ~ | G56: =IF(OR('BCO COES Integracion'!C110="Sí",'BCO COES Integracion'!C110="Si"),"✓",IF('BCO COES Integracion'!C110="Parcial","~","")) -> ~ | H56: =IF(OR('BCO COES Datos'!C110="Sí",'BCO COES Datos'!C110="Si"),"✓",IF('BCO COES Datos'!C110="Parcial","~","")) -> ~ | I56: =IF(OR('BCO Soporte'!C111="Sí",'BCO Soporte'!C111="Si"),"✓",IF('BCO Soporte'!C111="Parcial","~","")) | J56: =IF(OR('BCO COES Emma'!C110="Sí",'BCO COES Emma'!C110="Si"),"✓",IF('BCO COES Emma'!C110="Parcial","~","")) -> ~ | K56: =IF(OR('BCO Emma Iseries'!C110="Sí",'BCO Emma Iseries'!C110="Si"),"✓",IF('BCO Emma Iseries'!C110="Parcial","~","")) | L56: =IF(OR(AES!C107="Sí",AES!C107="Si"),"✓",IF(AES!C107="Parcial","~","")) -> ~ | M56: =IF(OR(XM!C109="Sí",XM!C109="Si"),"✓",IF(XM!C109="Parcial","~","")) -> ~ | N56: =IF(OR(MEDICARTE!C110="Sí",MEDICARTE!C110="Si"),"✓",IF(MEDICARTE!C110="Parcial","~","")) | O56: =COUNTIF(C56:N56,"✓")+0.5*COUNTIF(C56:N56,"~") -> 4.5
B57: D11 | C57: =IF(OR('SURA Cotizadores'!C109="Sí",'SURA Cotizadores'!C109="Si"),"✓",IF('SURA Cotizadores'!C109="Parcial","~","")) -> ~ | D57: =IF(OR('SURA Digital Venta'!C110="Sí",'SURA Digital Venta'!C110="Si"),"✓",IF('SURA Digital Venta'!C110="Parcial","~","")) -> ~ | E57: =IF(OR('SURA Automatizacion'!C110="Sí",'SURA Automatizacion'!C110="Si"),"✓",IF('SURA Automatizacion'!C110="Parcial","~","")) -> ~ | F57: =IF(OR('SURA Canales Masivos'!C110="Sí",'SURA Canales Masivos'!C110="Si"),"✓",IF('SURA Canales Masivos'!C110="Parcial","~","")) -> ~ | G57: =IF(OR('BCO COES Integracion'!C111="Sí",'BCO COES Integracion'!C111="Si"),"✓",IF('BCO COES Integracion'!C111="Parcial","~","")) | H57: =IF(OR('BCO COES Datos'!C111="Sí",'BCO COES Datos'!C111="Si"),"✓",IF('BCO COES Datos'!C111="Parcial","~","")) | I57: =IF(OR('BCO Soporte'!C112="Sí",'BCO Soporte'!C112="Si"),"✓",IF('BCO Soporte'!C112="Parcial","~","")) -> ~ | J57: =IF(OR('BCO COES Emma'!C111="Sí",'BCO COES Emma'!C111="Si"),"✓",IF('BCO COES Emma'!C111="Parcial","~","")) | K57: =IF(OR('BCO Emma Iseries'!C111="Sí",'BCO Emma Iseries'!C111="Si"),"✓",IF('BCO Emma Iseries'!C111="Parcial","~","")) | L57: =IF(OR(AES!C108="Sí",AES!C108="Si"),"✓",IF(AES!C108="Parcial","~","")) -> ✓ | M57: =IF(OR(XM!C110="Sí",XM!C110="Si"),"✓",IF(XM!C110="Parcial","~","")) -> ✓ | N57: =IF(OR(MEDICARTE!C111="Sí",MEDICARTE!C111="Si"),"✓",IF(MEDICARTE!C111="Parcial","~","")) | O57: =COUNTIF(C57:N57,"✓")+0.5*COUNTIF(C57:N57,"~") -> 4.5
B58: D12 | C58: =IF(OR('SURA Cotizadores'!C110="Sí",'SURA Cotizadores'!C110="Si"),"✓",IF('SURA Cotizadores'!C110="Parcial","~","")) -> ~ | D58: =IF(OR('SURA Digital Venta'!C111="Sí",'SURA Digital Venta'!C111="Si"),"✓",IF('SURA Digital Venta'!C111="Parcial","~","")) -> ~ | E58: =IF(OR('SURA Automatizacion'!C111="Sí",'SURA Automatizacion'!C111="Si"),"✓",IF('SURA Automatizacion'!C111="Parcial","~","")) -> ~ | F58: =IF(OR('SURA Canales Masivos'!C111="Sí",'SURA Canales Masivos'!C111="Si"),"✓",IF('SURA Canales Masivos'!C111="Parcial","~","")) -> ~ | G58: =IF(OR('BCO COES Integracion'!C112="Sí",'BCO COES Integracion'!C112="Si"),"✓",IF('BCO COES Integracion'!C112="Parcial","~","")) -> ~ | H58: =IF(OR('BCO COES Datos'!C112="Sí",'BCO COES Datos'!C112="Si"),"✓",IF('BCO COES Datos'!C112="Parcial","~","")) -> ~ | I58: =IF(OR('BCO Soporte'!C113="Sí",'BCO Soporte'!C113="Si"),"✓",IF('BCO Soporte'!C113="Parcial","~","")) -> ~ | J58: =IF(OR('BCO COES Emma'!C112="Sí",'BCO COES Emma'!C112="Si"),"✓",IF('BCO COES Emma'!C112="Parcial","~","")) -> ~ | K58: =IF(OR('BCO Emma Iseries'!C112="Sí",'BCO Emma Iseries'!C112="Si"),"✓",IF('BCO Emma Iseries'!C112="Parcial","~","")) | L58: =IF(OR(AES!C109="Sí",AES!C109="Si"),"✓",IF(AES!C109="Parcial","~","")) -> ~ | M58: =IF(OR(XM!C111="Sí",XM!C111="Si"),"✓",IF(XM!C111="Parcial","~","")) -> ✓ | N58: =IF(OR(MEDICARTE!C112="Sí",MEDICARTE!C112="Si"),"✓",IF(MEDICARTE!C112="Parcial","~","")) | O58: =COUNTIF(C58:N58,"✓")+0.5*COUNTIF(C58:N58,"~") -> 5.5
... B64: D18 | C64: =IF(OR('SURA Cotizadores'!C116="Sí",'SURA Cotizadores'!C116="Si"),"✓",IF('SURA Cotizadores'!C116="Parcial","~","")) -> ~ | D64: =IF(OR('SURA Digital Venta'!C117="Sí",'SURA Digital Venta'!C117="Si"),"✓",IF('SURA Digital Venta'!C117="Parcial","~","")) -> ~ | E64: =IF(OR('SURA Automatizacion'!C117="Sí",'SURA Automatizacion'!C117="Si"),"✓",IF('SURA Automatizacion'!C117="Parcial","~","")) -> ~ | F64: =IF(OR('SURA Canales Masivos'!C117="Sí",'SURA Canales Masivos'!C117="Si"),"✓",IF('SURA Canales Masivos'!C117="Parcial","~","")) -> ~ | G64: =IF(OR('BCO COES Integracion'!C118="Sí",'BCO COES Integracion'!C118="Si"),"✓",IF('BCO COES Integracion'!C118="Parcial","~","")) -> ~ | H64: =IF(OR('BCO COES Datos'!C118="Sí",'BCO COES Datos'!C118="Si"),"✓",IF('BCO COES Datos'!C118="Parcial","~","")) -> ~ | I64: =IF(OR('BCO Soporte'!C119="Sí",'BCO Soporte'!C119="Si"),"✓",IF('BCO Soporte'!C119="Parcial","~","")) -> ✓ | J64: =IF(OR('BCO COES Emma'!C118="Sí",'BCO COES Emma'!C118="Si"),"✓",IF('BCO COES Emma'!C118="Parcial","~","")) -> ~ | K64: =IF(OR('BCO Emma Iseries'!C118="Sí",'BCO Emma Iseries'!C118="Si"),"✓",IF('BCO Emma Iseries'!C118="Parcial","~","")) | L64: =IF(OR(AES!C115="Sí",AES!C115="Si"),"✓",IF(AES!C115="Parcial","~","")) | M64: =IF(OR(XM!C117="Sí",XM!C117="Si"),"✓",IF(XM!C117="Parcial","~","")) -> ✓ | N64: =IF(OR(MEDICARTE!C118="Sí",MEDICARTE!C118="Si"),"✓",IF(MEDICARTE!C118="Parcial","~","")) | O64: =COUNTIF(C64:N64,"✓")+0.5*COUNTIF(C64:N64,"~") -> 5.5
B65: D19 | C65: =IF(OR('SURA Cotizadores'!C117="Sí",'SURA Cotizadores'!C117="Si"),"✓",IF('SURA Cotizadores'!C117="Parcial","~","")) -> ✓ | O65: =COUNTIF(C65:N65,"✓")+0.5*COUNTIF(C65:N65,"~") -> 1
B66: D20 | C66: =IF(OR('SURA Cotizadores'!C118="Sí",'SURA Cotizadores'!C118="Si"),"✓",IF('SURA Cotizadores'!C118="Parcial","~","")) -> ✓ | D66: =IF(OR('SURA Digital Venta'!C118="Sí",'SURA Digital Venta'!C118="Si"),"✓",IF('SURA Digital Venta'!C118="Parcial","~","")) -> ✓ | E66: =IF(OR('SURA Automatizacion'!C118="Sí",'SURA Automatizacion'!C118="Si"),"✓",IF('SURA Automatizacion'!C118="Parcial","~","")) -> ✓ | F66: =IF(OR('SURA Canales Masivos'!C118="Sí",'SURA Canales Masivos'!C118="Si"),"✓",IF('SURA Canales Masivos'!C118="Parcial","~","")) -> ✓ | G66: =IF(OR('BCO COES Integracion'!C119="Sí",'BCO COES Integracion'!C119="Si"),"✓",IF('BCO COES Integracion'!C119="Parcial","~","")) -> ✓ | H66: =IF(OR('BCO COES Datos'!C119="Sí",'BCO COES Datos'!C119="Si"),"✓",IF('BCO COES Datos'!C119="Parcial","~","")) -> ✓ | I66: =IF(OR('BCO Soporte'!C120="Sí",'BCO Soporte'!C120="Si"),"✓",IF('BCO Soporte'!C120="Parcial","~","")) -> ~ | J66: =IF(OR('BCO COES Emma'!C119="Sí",'BCO COES Emma'!C119="Si"),"✓",IF('BCO COES Emma'!C119="Parcial","~","")) -> ✓ | K66: =IF(OR('BCO Emma Iseries'!C119="Sí",'BCO Emma Iseries'!C119="Si"),"✓",IF('BCO Emma Iseries'!C119="Parcial","~","")) -> ✓ | L66: =IF(OR(AES!C116="Sí",AES!C116="Si"),"✓",IF(AES!C116="Parcial","~","")) -> ✓ | M66: =IF(OR(XM!C118="Sí",XM!C118="Si"),"✓",IF(XM!C118="Parcial","~","")) -> ✓ | N66: =IF(OR(MEDICARTE!C119="Sí",MEDICARTE!C119="Si"),"✓",IF(MEDICARTE!C119="Parcial","~","")) -> ✓ | O66: =COUNTIF(C66:N66,"✓")+0.5*COUNTIF(C66:N66,"~") -> 11.5
B67: D21 | C67: =IF(OR('SURA Cotizadores'!C119="Sí",'SURA Cotizadores'!C119="Si"),"✓",IF('SURA Cotizadores'!C119="Parcial","~","")) | D67: =IF(OR('SURA Digital Venta'!C119="Sí",'SURA Digital Venta'!C119="Si"),"✓",IF('SURA Digital Venta'!C119="Parcial","~","")) | E67: =IF(OR('SURA Automatizacion'!C119="Sí",'SURA Automatizacion'!C119="Si"),"✓",IF('SURA Automatizacion'!C119="Parcial","~","")) | F67: =IF(OR('SURA Canales Masivos'!C119="Sí",'SURA Canales Masivos'!C119="Si"),"✓",IF('SURA Canales Masivos'!C119="Parcial","~","")) | G67: =IF(OR('BCO COES Integracion'!C120="Sí",'BCO COES Integracion'!C120="Si"),"✓",IF('BCO COES Integracion'!C120="Parcial","~","")) -> ~ | H67: =IF(OR('BCO COES Datos'!C120="Sí",'BCO COES Datos'!C120="Si"),"✓",IF('BCO COES Datos'!C120="Parcial","~","")) -> ~ | I67: =IF(OR('BCO Soporte'!C121="Sí",'BCO Soporte'!C121="Si"),"✓",IF('BCO Soporte'!C121="Parcial","~","")) -> ~ | J67: =IF(OR('BCO COES Emma'!C120="Sí",'BCO COES Emma'!C120="Si"),"✓",IF('BCO COES Emma'!C120="Parcial","~","")) -> ~ | K67: =IF(OR('BCO Emma Iseries'!C120="Sí",'BCO Emma Iseries'!C120="Si"),"✓",IF('BCO Emma Iseries'!C120="Parcial","~","")) | L67: =IF(OR(AES!C117="Sí",AES!C117="Si"),"✓",IF(AES!C117="Parcial","~","")) | M67: =IF(OR(XM!C119="Sí",XM!C119="Si"),"✓",IF(XM!C119="Parcial","~","")) -> ✓ | N67: =IF(OR(MEDICARTE!C120="Sí",MEDICARTE!C120="Si"),"✓",IF(MEDICARTE!C120="Parcial","~","")) | O67: =COUNTIF(C67:N67,"✓")+0.5*COUNTIF(C67:N67,"~") -> 3
B68: D22 | C68: =IF(OR('SURA Cotizadores'!C120="Sí",'SURA Cotizadores'!C120="Si"),"✓",IF('SURA Cotizadores'!C120="Parcial","~","")) | D68: =IF(OR('SURA Digital Venta'!C120="Sí",'SURA Digital Venta'!C120="Si"),"✓",IF('SURA Digital Venta'!C120="Parcial","~","")) | E68: =IF(OR('SURA Automatizacion'!C120="Sí",'SURA Automatizacion'!C120="Si"),"✓",IF('SURA Automatizacion'!C120="Parcial","~","")) | F68: =IF(OR('SURA Canales Masivos'!C120="Sí",'SURA Canales Masivos'!C120="Si"),"✓",IF('SURA Canales Masivos'!C120="Parcial","~","")) | G68: =IF(OR('BCO COES Integracion'!C121="Sí",'BCO COES Integracion'!C121="Si"),"✓",IF('BCO COES Integracion'!C121="Parcial","~","")) -> ~ | H68: =IF(OR('BCO COES Datos'!C121="Sí",'BCO COES Datos'!C121="Si"),"✓",IF('BCO COES Datos'!C121="Parcial","~","")) -> ~ | J68: =IF(OR('BCO COES Emma'!C121="Sí",'BCO COES Emma'!C121="Si"),"✓",IF('BCO COES Emma'!C121="Parcial","~","")) -> ~ | K68: =IF(OR('BCO Emma Iseries'!C121="Sí",'BCO Emma Iseries'!C121="Si"),"✓",IF('BCO Emma Iseries'!C121="Parcial","~","")) | L68: =IF(OR(AES!C118="Sí",AES!C118="Si"),"✓",IF(AES!C118="Parcial","~","")) | M68: =IF(OR(XM!C120="Sí",XM!C120="Si"),"✓",IF(XM!C120="Parcial","~","")) -> ✓ | N68: =IF(OR(MEDICARTE!C121="Sí",MEDICARTE!C121="Si"),"✓",IF(MEDICARTE!C121="Parcial","~","")) | O68: =COUNTIF(C68:N68,"✓")+0.5*COUNTIF(C68:N68,"~") -> 2.5
B69: D23 | C69: =IF(OR('SURA Cotizadores'!C121="Sí",'SURA Cotizadores'!C121="Si"),"✓",IF('SURA Cotizadores'!C121="Parcial","~","")) | D69: =IF(OR('SURA Digital Venta'!C121="Sí",'SURA Digital Venta'!C121="Si"),"✓",IF('SURA Digital Venta'!C121="Parcial","~","")) | E69: =IF(OR('SURA Automatizacion'!C121="Sí",'SURA Automatizacion'!C121="Si"),"✓",IF('SURA Automatizacion'!C121="Parcial","~","")) | F69: =IF(OR('SURA Canales Masivos'!C121="Sí",'SURA Canales Masivos'!C121="Si"),"✓",IF('SURA Canales Masivos'!C121="Parcial","~","")) | G69: =IF(OR('BCO COES Integracion'!C122="Sí",'BCO COES Integracion'!C122="Si"),"✓",IF('BCO COES Integracion'!C122="Parcial","~","")) -> ✓ | H69: =IF(OR('BCO COES Datos'!C122="Sí",'BCO COES Datos'!C122="Si"),"✓",IF('BCO COES Datos'!C122="Parcial","~","")) -> ✓ | I69: =IF(OR('BCO Soporte'!C123="Sí",'BCO Soporte'!C123="Si"),"✓",IF('BCO Soporte'!C123="Parcial","~","")) -> ✓ | J69: =IF(OR('BCO COES Emma'!C122="Sí",'BCO COES Emma'!C122="Si"),"✓",IF('BCO COES Emma'!C122="Parcial","~","")) -> ✓ | K69: =IF(OR('BCO Emma Iseries'!C122="Sí",'BCO Emma Iseries'!C122="Si"),"✓",IF('BCO Emma Iseries'!C122="Parcial","~","")) -> ✓ | L69: =IF(OR(AES!C119="Sí",AES!C119="Si"),"✓",IF(AES!C119="Parcial","~","")) | M69: =IF(OR(XM!C121="Sí",XM!C121="Si"),"✓",IF(XM!C121="Parcial","~","")) -> ~ | N69: =IF(OR(MEDICARTE!C122="Sí",MEDICARTE!C122="Si"),"✓",IF(MEDICARTE!C122="Parcial","~","")) | O69: =COUNTIF(C69:N69,"✓")+0.5*COUNTIF(C69:N69,"~") -> 5.5
B115: COBERTURA PROMEDIO POR DIMENSIÓN

Sheet Graficas
E2: ANÁLISIS VISUAL— MESA DE SERVICIOS DE NUEVA GENERACIÓN | N2: Fecha: 2026/07/03 Clasificación: Interna
E3: Dashboard de madurez · prácticas · dolores · industria vs benchmark · Gen Next
E5: Versión: 1.0
B7: GRÁFICAS POR BLOQUE DE EVALUACIÓN — 11 DIMENSIONES + ④b

Sheet ChartData
A1: TABLA 1 — MADUREZ NUMÉRICA (N0-N5) | K1: HELPERS PARA GRÁFICAS | X1: ① Identificación general — completitud | AA1: ② Nivel de madurez actual | AE1: ③ Prácticas ITIL — score global | AH1: ④ Volumetría y KPIs — FCR/SLA | AM1: ④b Incidentes por categoría — tickets/mes | AP1: ⑤ XLA / DEX — NPS | AS1: ⑥ Dolores críticos — total activo D1–D23 | AV1: ⑦ Rotación y talento — completitud | AY1: ⑧ Tecnología y herramientas — herramientas registradas | BB1: ⑨ Modelo económico — completitud | BE1: ⑩ Visión nuevo servicio — completitud | BH1: ⑪ Casos de éxito — completitud | BK1: RESUMEN PROMEDIO POR DIMENSIÓN | BO1: DOLORES CONSOLIDADOS D1–D23
A2: Mesa | B2: Nivel Madurez (texto) | C2: Madurez Numérica (0-5) | D2: Meta (N3) | K2: Mesa | L2: Madurez | M2: Meta | X2: Mesa | Y2: Completitud | AA2: Mesa | AB2: Madurez | AC2: Meta N3 | AE2: Mesa | AF2: Score ITIL | AH2: Mesa | AI2: FCR | AJ2: SLA | AM2: Mesa | AN2: Tickets categorizados | AP2: Mesa | AQ2: NPS | AS2: Mesa | AT2: Dolores activos D1–D23 | AV2: Mesa | AW2: Completitud | AY2: Mesa | AZ2: Herramientas registradas | BB2: Mesa | BC2: Completitud | BE2: Mesa | BF2: Completitud | BH2: Mesa | BI2: Completitud | BK2: Dimensión | BL2: Promedio | BM2: Meta | BO2: Dolor | BP2: Total ponderado
A3: SURA Cotizadores | B3: ='SURA Cotizadores'!C12 -> N2 | C3: =IFERROR(VALUE(SUBSTITUTE(B3,"N","")),0) -> 2 | D3: 3 | K3: =A3 -> SURA Cotizadores | L3: =C3 -> 2 | M3: 3 | X3: =A3 -> SURA Cotizadores | Y3: =IFERROR(COUNTA('SURA Cotizadores'!C5:C24)/15,0) -> 1.2666667 | AA3: =A3 -> SURA Cotizadores | AB3: =C3 -> 2 | AC3: 3 | AE3: SURA Cotizadores | AF3: =IFERROR('SURA Cotizadores'!E56,0) -> 0.52941176 | AH3: =A3 -> SURA Cotizadores | AI3: =IFERROR('SURA Cotizadores'!C66,0) -> N/D | AJ3: =IFERROR('SURA Cotizadores'!C68,0) -> 0.7 | AM3: =A3 -> SURA Cotizadores | AN3: =IFERROR('SURA Cotizadores'!C82,0) -> 0 | AP3: =A3 -> SURA Cotizadores | AQ3: =IFERROR('SURA Cotizadores'!C89,0) -> 0 | AS3: =A3 -> SURA Cotizadores | AT3: =IF(OR('SURA Cotizadores'!C99="Sí",'SURA Cotizadores'!C99="Si"),1,IF('SURA Cotizadores'!C99="Parcial",0.5,0))+IF(OR('SURA Cotizadores'!C100="Sí",'SURA Cotizadores'!C100="Si"),1,IF('SURA Cotizadores'!C100="Parcial",0.5,0))+IF(OR('SURA Cotizadores'!C101="Sí",'SURA Cotizadores'!C101="Si"),1,IF('SURA Cotizadores'!C101="Parcial",0.5,0))+IF(OR('SURA Cotizadores'!C102="Sí",'SURA Cotizadores'!C102="Si"),1,IF('SURA Cotizadores'!C102="Parcial",0.5,0))+IF(OR('SURA Cotizadores'!C103="Sí",'SURA Cotizadores'!C103="Si"),1,IF('SURA Cotizadores'!C103="Parcial",0.5,0))+IF(OR('SURA Cotizadores'!C104="Sí",'SURA Cotizadores'!C104="Si"),1,IF('SURA Cotizadores'!C104="Parcial",0.5,0))+IF(OR('SURA Cotizadores'!C105="Sí",'SURA Cotizadores'!C105="Si"),1,IF('SURA Cotizadores'!C105="Parcial",0.5,0))+IF(OR('SURA Cotizadores'!C106="Sí",'SURA Cotizadores'!C106="Si"),1,IF('SURA Cotizadores'!C106="Parcial",0.5,0))+IF(OR('SURA Cotizadores'!C107="Sí",'SURA Cotizadores'!C107="Si"),1,IF('SURA Cotizadores'!C107="Parcial",0.5,0))+IF(OR('SURA Cotizadores'!C108="Sí",'SURA Cotizadores'!C108="Si"),1,IF('SURA Cotizadores'!C108="Parcial",0.5,0))+IF(OR('SURA Cotizadores'!C109="Sí",'SURA Cotizadores'!C109="Si"),1,IF('SURA Cotizadores'!C109="Parcial",0.5,0))+IF(OR('SURA Cotizadores'!C110="Sí",'SURA Cotizadores'!C110="Si"),1,IF('SURA Cotizadores'!C110="Parcial",0.5,0))+IF(OR('SURA Cotizadores'!C111="Sí",'SURA Cotizadores'!C111="Si"),1,IF('SURA Cotizadores'!C111="Parcial",0.5,0))+IF(OR('SURA Cotizadores'!C112="Sí",'SURA Cotizadores'!C112="Si"),1,IF('SURA Cotizadores'!C112="Parcial",0.5,0))+IF(OR('SURA Cotizadores'!C113="Sí",'SURA Cotizadores'!C113="Si"),1,IF('SURA Cotizadores'!C113="Parcial",0.5,0))+IF(OR('SURA Cotizadores'!C114="Sí",'SURA Cotizadores'!C114="Si"),1,IF('SURA Cotizadores'!C114="Parcial",0.5,0))+IF(OR('SURA Cotizadores'!C115="Sí",'SURA Cotizadores'!C115="Si"),1,IF('SURA Cotizadores'!C115="Parcial",0.5,0))+IF(OR('SURA Cotizadores'!C116="Sí",'SURA Cotizadores'!C116="Si"),1,IF('SURA Cotizadores'!C116="Parcial",0.5,0))+IF(OR('SURA Cotizadores'!C117="Sí",'SURA Cotizadores'!C117="Si"),1,IF('SURA Cotizadores'!C117="Parcial",0.5,0))+IF(OR('SURA Cotizadores'!C118="Sí",'SURA Cotizadores'!C118="Si"),1,IF('SURA Cotizadores'!C118="Parcial",0.5,0))+IF(OR('SURA Cotizadores'!C119="Sí",'SURA Cotizadores'!C119="Si"),1,IF('SURA Cotizadores'!C119="Parcial",0.5,0))+IF(OR('SURA Cotizadores'!C120="Sí",'SURA Cotizadores'!C120="Si"),1,IF('SURA Cotizadores'!C120="Parcial",0.5,0))+IF(OR('SURA Cotizadores'!C121="Sí",'SURA Cotizadores'!C121="Si"),1,IF('SURA Cotizadores'!C121="Parcial",0.5,0)) -> 13 | AV3: =A3 -> SURA Cotizadores | AW3: =IFERROR(COUNTA('SURA Cotizadores'!C126:C133)/8,0) -> 0.375 | AY3: =A3 -> SURA Cotizadores | AZ3: =IFERROR(COUNTA('SURA Cotizadores'!C137:C146),0) -> 3 | BB3: =A3 -> SURA Cotizadores | BC3: =IFERROR(COUNTA('SURA Cotizadores'!C150:C156)/7,0) -> 0.85714286 | BE3: =A3 -> SURA Cotizadores | BF3: =IFERROR(COUNTA('SURA Cotizadores'!C160:C168)/9,0) -> 0.88888889 | BH3: =A3 -> SURA Cotizadores | BI3: =IFERROR(COUNTA('SURA Cotizadores'!C172:C182)/10,0) -> 0.1 | BK3: ① Identificación general | BL3: =AVERAGE(Y3:Y13) -> 1.1454545 | BM3: =100% -> 1 | BO3: D1 | BP3: =Dashboard!O47 -> 4
A4: SURA Digital Venta | B4: ='SURA Digital Venta'!C13 -> N2 | C4: =IFERROR(VALUE(SUBSTITUTE(B4,"N","")),0) -> 2 | D4: 3 | K4: =A4 -> SURA Digital Venta | L4: =C4 -> 2 | M4: 3 | X4: =A4 -> SURA Digital Venta | Y4: =IFERROR(COUNTA('SURA Digital Venta'!C5:C24)/15,0) -> 1.2 | AA4: =A4 -> SURA Digital Venta | AB4: =C4 -> 2 | AC4: 3 | AE4: SURA Digital Venta | AF4: =IFERROR('SURA Digital Venta'!E57,0) -> 0.55882353 | AH4: =A4 -> SURA Digital Venta | AI4: =IFERROR('SURA Digital Venta'!C67,0) -> N/D | AJ4: =IFERROR('SURA Digital Venta'!C69,0) -> 0.74 | AM4: =A4 -> SURA Digital Venta | AN4: =IFERROR('SURA Digital Venta'!C82,0) -> 0 | AP4: =A4 -> SURA Digital Venta | AQ4: =IFERROR('SURA Digital Venta'!C89,0) -> Valor Actual | AS4: =A4 -> SURA Digital Venta | AT4: =IF(OR('SURA Digital Venta'!C100="Sí",'SURA Digital Venta'!C100="Si"),1,IF('SURA Digital Venta'!C100="Parcial",0.5,0))+IF(OR('SURA Digital Venta'!C101="Sí",'SURA Digital Venta'!C101="Si"),1,IF('SURA Digital Venta'!C101="Parcial",0.5,0))+IF(OR('SURA Digital Venta'!C102="Sí",'SURA Digital Venta'!C102="Si"),1,IF('SURA Digital Venta'!C102="Parcial",0.5,0))+IF(OR('SURA Digital Venta'!C103="Sí",'SURA Digital Venta'!C103="Si"),1,IF('SURA Digital Venta'!C103="Parcial",0.5,0))+IF(OR('SURA Digital Venta'!C104="Sí",'SURA Digital Venta'!C104="Si"),1,IF('SURA Digital Venta'!C104="Parcial",0.5,0))+IF(OR('SURA Digital Venta'!C105="Sí",'SURA Digital Venta'!C105="Si"),1,IF('SURA Digital Venta'!C105="Parcial",0.5,0))+IF(OR('SURA Digital Venta'!C106="Sí",'SURA Digital Venta'!C106="Si"),1,IF('SURA Digital Venta'!C106="Parcial",0.5,0))+IF(OR('SURA Digital Venta'!C107="Sí",'SURA Digital Venta'!C107="Si"),1,IF('SURA Digital Venta'!C107="Parcial",0.5,0))+IF(OR('SURA Digital Venta'!C108="Sí",'SURA Digital Venta'!C108="Si"),1,IF('SURA Digital Venta'!C108="Parcial",0.5,0))+IF(OR('SURA Digital Venta'!C109="Sí",'SURA Digital Venta'!C109="Si"),1,IF('SURA Digital Venta'!C109="Parcial",0.5,0))+IF(OR('SURA Digital Venta'!C110="Sí",'SURA Digital Venta'!C110="Si"),1,IF('SURA Digital Venta'!C110="Parcial",0.5,0))+IF(OR('SURA Digital Venta'!C111="Sí",'SURA Digital Venta'!C111="Si"),1,IF('SURA Digital Venta'!C111="Parcial",0.5,0))+IF(OR('SURA Digital Venta'!C112="Sí",'SURA Digital Venta'!C112="Si"),1,IF('SURA Digital Venta'!C112="Parcial",0.5,0))+IF(OR('SURA Digital Venta'!C113="Sí",'SURA Digital Venta'!C113="Si"),1,IF('SURA Digital Venta'!C113="Parcial",0.5,0))+IF(OR('SURA Digital Venta'!C114="Sí",'SURA Digital Venta'!C114="Si"),1,IF('SURA Digital Venta'!C114="Parcial",0.5,0))+IF(OR('SURA Digital Venta'!C115="Sí",'SURA Digital Venta'!C115="Si"),1,IF('SURA Digital Venta'!C115="Parcial",0.5,0))+IF(OR('SURA Digital Venta'!C116="Sí",'SURA Digital Venta'!C116="Si"),1,IF('SURA Digital Venta'!C116="Parcial",0.5,0))+IF(OR('SURA Digital Venta'!C117="Sí",'SURA Digital Venta'!C117="Si"),1,IF('SURA Digital Venta'!C117="Parcial",0.5,0))+IF(OR('SURA Digital Venta'!C118="Sí",'SURA Digital Venta'!C118="Si"),1,IF('SURA Digital Venta'!C118="Parcial",0.5,0))+IF(OR('SURA Digital Venta'!C119="Sí",'SURA Digital Venta'!C119="Si"),1,IF('SURA Digital Venta'!C119="Parcial",0.5,0))+IF(OR('SURA Digital Venta'!C120="Sí",'SURA Digital Venta'!C120="Si"),1,IF('SURA Digital Venta'!C120="Parcial",0.5,0))+IF(OR('SURA Digital Venta'!C121="Sí",'SURA Digital Venta'!C121="Si"),1,IF('SURA Digital Venta'!C121="Parcial",0.5,0)) -> 12.5 | AV4: =A4 -> SURA Digital Venta | AW4: =IFERROR(COUNTA('SURA Digital Venta'!C126:C133)/8,0) -> 0.375 | AY4: =A4 -> SURA Digital Venta | AZ4: =IFERROR(COUNTA('SURA Digital Venta'!C137:C146),0) -> 3 | BB4: =A4 -> SURA Digital Venta | BC4: =IFERROR(COUNTA('SURA Digital Venta'!C150:C156)/7,0) -> 0.85714286 | BE4: =A4 -> SURA Digital Venta | BF4: =IFERROR(COUNTA('SURA Digital Venta'!C160:C168)/9,0) -> 0.88888889 | BH4: =A4 -> SURA Digital Venta | BI4: =IFERROR(COUNTA('SURA Digital Venta'!C172:C182)/10,0) -> 0.1 | BK4: ② Madurez (normalizada) | BL4: =AVERAGE(AB3:AB13)/5 -> 0.27272727 | BM4: =60% -> 0.6 | BO4: D2 | BP4: =Dashboard!O48 -> 3.5
A5: SURA Automatizacion | B5: ='SURA Automatizacion'!C13 -> N2 | C5: =IFERROR(VALUE(SUBSTITUTE(B5,"N","")),0) -> 2 | D5: 3 | K5: =A5 -> SURA Automatizacion | L5: =C5 -> 2 | M5: 3 | X5: =A5 -> SURA Automatizacion | Y5: =IFERROR(COUNTA('SURA Automatizacion'!C5:C24)/15,0) -> 1.2 | AA5: =A5 -> SURA Automatizacion | AB5: =C5 -> 2 | AC5: 3 | AE5: SURA Automatizacion | AF5: =IFERROR('SURA Automatizacion'!E57,0) -> 0.61764706 | AH5: =A5 -> SURA Automatizacion | AI5: =IFERROR('SURA Automatizacion'!C67,0) -> N/D | AJ5: =IFERROR('SURA Automatizacion'!C69,0) -> 0.98 | AM5: =A5 -> SURA Automatizacion | AN5: =IFERROR('SURA Automatizacion'!C82,0) -> 0 | AP5: =A5 -> SURA Automatizacion | AQ5: =IFERROR('SURA Automatizacion'!C89,0) -> Valor Actual | AS5: =A5 -> SURA Automatizacion | AT5: =IF(OR('SURA Automatizacion'!C100="Sí",'SURA Automatizacion'!C100="Si"),1,IF('SURA Automatizacion'!C100="Parcial",0.5,0))+IF(OR('SURA Automatizacion'!C101="Sí",'SURA Automatizacion'!C101="Si"),1,IF('SURA Automatizacion'!C101="Parcial",0.5,0))+IF(OR('SURA Automatizacion'!C102="Sí",'SURA Automatizacion'!C102="Si"),1,IF('SURA Automatizacion'!C102="Parcial",0.5,0))+IF(OR('SURA Automatizacion'!C103="Sí",'SURA Automatizacion'!C103="Si"),1,IF('SURA Automatizacion'!C103="Parcial",0.5,0))+IF(OR('SURA Automatizacion'!C104="Sí",'SURA Automatizacion'!C104="Si"),1,IF('SURA Automatizacion'!C104="Parcial",0.5,0))+IF(OR('SURA Automatizacion'!C105="Sí",'SURA Automatizacion'!C105="Si"),1,IF('SURA Automatizacion'!C105="Parcial",0.5,0))+IF(OR('SURA Automatizacion'!C106="Sí",'SURA Automatizacion'!C106="Si"),1,IF('SURA Automatizacion'!C106="Parcial",0.5,0))+IF(OR('SURA Automatizacion'!C107="Sí",'SURA Automatizacion'!C107="Si"),1,IF('SURA Automatizacion'!C107="Parcial",0.5,0))+IF(OR('SURA Automatizacion'!C108="Sí",'SURA Automatizacion'!C108="Si"),1,IF('SURA Automatizacion'!C108="Parcial",0.5,0))+IF(OR('SURA Automatizacion'!C109="Sí",'SURA Automatizacion'!C109="Si"),1,IF('SURA Automatizacion'!C109="Parcial",0.5,0))+IF(OR('SURA Automatizacion'!C110="Sí",'SURA Automatizacion'!C110="Si"),1,IF('SURA Automatizacion'!C110="Parcial",0.5,0))+IF(OR('SURA Automatizacion'!C111="Sí",'SURA Automatizacion'!C111="Si"),1,IF('SURA Automatizacion'!C111="Parcial",0.5,0))+IF(OR('SURA Automatizacion'!C112="Sí",'SURA Automatizacion'!C112="Si"),1,IF('SURA Automatizacion'!C112="Parcial",0.5,0))+IF(OR('SURA Automatizacion'!C113="Sí",'SURA Automatizacion'!C113="Si"),1,IF('SURA Automatizacion'!C113="Parcial",0.5,0))+IF(OR('SURA Automatizacion'!C114="Sí",'SURA Automatizacion'!C114="Si"),1,IF('SURA Automatizacion'!C114="Parcial",0.5,0))+IF(OR('SURA Automatizacion'!C115="Sí",'SURA Automatizacion'!C115="Si"),1,IF('SURA Automatizacion'!C115="Parcial",0.5,0))+IF(OR('SURA Automatizacion'!C116="Sí",'SURA Automatizacion'!C116="Si"),1,IF('SURA Automatizacion'!C116="Parcial",0.5,0))+IF(OR('SURA Automatizacion'!C117="Sí",'SURA Automatizacion'!C117="Si"),1,IF('SURA Automatizacion'!C117="Parcial",0.5,0))+IF(OR('SURA Automatizacion'!C118="Sí",'SURA Automatizacion'!C118="Si"),1,IF('SURA Automatizacion'!C118="Parcial",0.5,0))+IF(OR('SURA Automatizacion'!C119="Sí",'SURA Automatizacion'!C119="Si"),1,IF('SURA Automatizacion'!C119="Parcial",0.5,0))+IF(OR('SURA Automatizacion'!C120="Sí",'SURA Automatizacion'!C120="Si"),1,IF('SURA Automatizacion'!C120="Parcial",0.5,0))+IF(OR('SURA Automatizacion'!C121="Sí",'SURA Automatizacion'!C121="Si"),1,IF('SURA Automatizacion'!C121="Parcial",0.5,0)) -> 11 | AV5: =A5 -> SURA Automatizacion | AW5: =IFERROR(COUNTA('SURA Automatizacion'!C126:C133)/8,0) -> 0.375 | AY5: =A5 -> SURA Automatizacion | AZ5: =IFERROR(COUNTA('SURA Automatizacion'!C137:C146),0) -> 5 | BB5: =A5 -> SURA Automatizacion | BC5: =IFERROR(COUNTA('SURA Automatizacion'!C150:C156)/7,0) -> 0.85714286 | BE5: =A5 -> SURA Automatizacion | BF5: =IFERROR(COUNTA('SURA Automatizacion'!C160:C168)/9,0) -> 0.88888889 | BH5: =A5 -> SURA Automatizacion | BI5: =IFERROR(COUNTA('SURA Automatizacion'!C172:C182)/10,0) -> 0.1 | BK5: ③ ITIL | BL5: =AVERAGE(AF3:AF13) -> 0.61497326 | BM5: =70% -> 0.7 | BO5: D3 | BP5: =Dashboard!O49 -> 6.5
A6: SURA Canales Masivos | B6: ='SURA Canales Masivos'!C13 -> N2 | C6: =IFERROR(VALUE(SUBSTITUTE(B6,"N","")),0) -> 2 | D6: 3 | K6: =A6 -> SURA Canales Masivos | L6: =C6 -> 2 | M6: 3 | X6: =A6 -> SURA Canales Masivos | Y6: =IFERROR(COUNTA('SURA Canales Masivos'!C5:C24)/15,0) -> 1.2 | AA6: =A6 -> SURA Canales Masivos | AB6: =C6 -> 2 | AC6: 3 | AE6: SURA Canales Masivos | AF6: =IFERROR('SURA Canales Masivos'!E57,0) -> 0.58823529 | AH6: =A6 -> SURA Canales Masivos | AI6: =IFERROR('SURA Canales Masivos'!C67,0) -> 0 | AJ6: =IFERROR('SURA Canales Masivos'!C69,0) -> 0.72 | AM6: =A6 -> SURA Canales Masivos | AN6: =IFERROR('SURA Canales Masivos'!C82,0) -> 0 | AP6: =A6 -> SURA Canales Masivos | AQ6: =IFERROR('SURA Canales Masivos'!C89,0) -> Valor Actual | AS6: =A6 -> SURA Canales Masivos | AT6: =IF(OR('SURA Canales Masivos'!C100="Sí",'SURA Canales Masivos'!C100="Si"),1,IF('SURA Canales Masivos'!C100="Parcial",0.5,0))+IF(OR('SURA Canales Masivos'!C101="Sí",'SURA Canales Masivos'!C101="Si"),1,IF('SURA Canales Masivos'!C101="Parcial",0.5,0))+IF(OR('SURA Canales Masivos'!C102="Sí",'SURA Canales Masivos'!C102="Si"),1,IF('SURA Canales Masivos'!C102="Parcial",0.5,0))+IF(OR('SURA Canales Masivos'!C103="Sí",'SURA Canales Masivos'!C103="Si"),1,IF('SURA Canales Masivos'!C103="Parcial",0.5,0))+IF(OR('SURA Canales Masivos'!C104="Sí",'SURA Canales Masivos'!C104="Si"),1,IF('SURA Canales Masivos'!C104="Parcial",0.5,0))+IF(OR('SURA Canales Masivos'!C105="Sí",'SURA Canales Masivos'!C105="Si"),1,IF('SURA Canales Masivos'!C105="Parcial",0.5,0))+IF(OR('SURA Canales Masivos'!C106="Sí",'SURA Canales Masivos'!C106="Si"),1,IF('SURA Canales Masivos'!C106="Parcial",0.5,0))+IF(OR('SURA Canales Masivos'!C107="Sí",'SURA Canales Masivos'!C107="Si"),1,IF('SURA Canales Masivos'!C107="Parcial",0.5,0))+IF(OR('SURA Canales Masivos'!C108="Sí",'SURA Canales Masivos'!C108="Si"),1,IF('SURA Canales Masivos'!C108="Parcial",0.5,0))+IF(OR('SURA Canales Masivos'!C109="Sí",'SURA Canales Masivos'!C109="Si"),1,IF('SURA Canales Masivos'!C109="Parcial",0.5,0))+IF(OR('SURA Canales Masivos'!C110="Sí",'SURA Canales Masivos'!C110="Si"),1,IF('SURA Canales Masivos'!C110="Parcial",0.5,0))+IF(OR('SURA Canales Masivos'!C111="Sí",'SURA Canales Masivos'!C111="Si"),1,IF('SURA Canales Masivos'!C111="Parcial",0.5,0))+IF(OR('SURA Canales Masivos'!C112="Sí",'SURA Canales Masivos'!C112="Si"),1,IF('SURA Canales Masivos'!C112="Parcial",0.5,0))+IF(OR('SURA Canales Masivos'!C113="Sí",'SURA Canales Masivos'!C113="Si"),1,IF('SURA Canales Masivos'!C113="Parcial",0.5,0))+IF(OR('SURA Canales Masivos'!C114="Sí",'SURA Canales Masivos'!C114="Si"),1,IF('SURA Canales Masivos'!C114="Parcial",0.5,0))+IF(OR('SURA Canales Masivos'!C115="Sí",'SURA Canales Masivos'!C115="Si"),1,IF('SURA Canales Masivos'!C115="Parcial",0.5,0))+IF(OR('SURA Canales Masivos'!C116="Sí",'SURA Canales Masivos'!C116="Si"),1,IF('SURA Canales Masivos'!C116="Parcial",0.5,0))+IF(OR('SURA Canales Masivos'!C117="Sí",'SURA Canales Masivos'!C117="Si"),1,IF('SURA Canales Masivos'!C117="Parcial",0.5,0))+IF(OR('SURA Canales Masivos'!C118="Sí",'SURA Canales Masivos'!C118="Si"),1,IF('SURA Canales Masivos'!C118="Parcial",0.5,0))+IF(OR('SURA Canales Masivos'!C119="Sí",'SURA Canales Masivos'!C119="Si"),1,IF('SURA Canales Masivos'!C119="Parcial",0.5,0))+IF(OR('SURA Canales Masivos'!C120="Sí",'SURA Canales Masivos'!C120="Si"),1,IF('SURA Canales Masivos'!C120="Parcial",0.5,0))+IF(OR('SURA Canales Masivos'!C121="Sí",'SURA Canales Masivos'!C121="Si"),1,IF('SURA Canales Masivos'!C121="Parcial",0.5,0)) -> 13 | AV6: =A6 -> SURA Canales Masivos | AW6: =IFERROR(COUNTA('SURA Canales Masivos'!C126:C133)/8,0) -> 0.375 | AY6: =A6 -> SURA Canales Masivos | AZ6: =IFERROR(COUNTA('SURA Canales Masivos'!C137:C146),0) -> 4 | BB6: =A6 -> SURA Canales Masivos | BC6: =IFERROR(COUNTA('SURA Canales Masivos'!C150:C156)/7,0) -> 0.85714286 | BE6: =A6 -> SURA Canales Masivos | BF6: =IFERROR(COUNTA('SURA Canales Masivos'!C160:C168)/9,0) -> 0.88888889 | BH6: =A6 -> SURA Canales Masivos | BI6: =IFERROR(COUNTA('SURA Canales Masivos'!C172:C182)/10,0) -> 0.1 | BK6: ④ KPIs FCR/SLA | BL6: =AVERAGE(AI3:AJ13) -> 0.28545455 | BM6: =85% -> 0.85 | BO6: D4 | BP6: =Dashboard!O50 -> 3
A7: BCO COES Integracion | B7: ='BCO COES Integracion'!C13 -> N1 | C7: =IFERROR(VALUE(SUBSTITUTE(B7,"N","")),0) -> 1 | D7: 3 | K7: =A7 -> BCO COES Integracion | L7: =C7 -> 1 | M7: 3 | X7: =A7 -> BCO COES Integracion | Y7: =IFERROR(COUNTA('BCO COES Integracion'!C5:C23)/15,0) -> 1 | AA7: =A7 -> BCO COES Integracion | AB7: =C7 -> 1 | AC7: 3 | AE7: =A7 -> BCO COES Integracion | AF7: =IFERROR('BCO COES Integracion'!E58,0) -> 0.73529412 | AH7: =A7 -> BCO COES Integracion | AI7: =IFERROR('BCO COES Integracion'!C68,0) -> Pendiente revisar líderes técnicos | AJ7: =IFERROR('BCO COES Integracion'!C70,0) -> No aplica SLA- ANS del Banco y de COES | AM7: =A7 -> BCO COES Integracion | AN7: =IFERROR('BCO COES Integracion'!C82,0) -> 700 a 3.000 | AP7: =A7 -> BCO COES Integracion | AQ7: =IFERROR('BCO COES Integracion'!C91,0) -> 0 | AS7: =A7 -> BCO COES Integracion | AT7: =IF(OR('BCO COES Integracion'!C101="Sí",'BCO COES Integracion'!C101="Si"),1,IF('BCO COES Integracion'!C101="Parcial",0.5,0))+IF(OR('BCO COES Integracion'!C102="Sí",'BCO COES Integracion'!C102="Si"),1,IF('BCO COES Integracion'!C102="Parcial",0.5,0))+IF(OR('BCO COES Integracion'!C103="Sí",'BCO COES Integracion'!C103="Si"),1,IF('BCO COES Integracion'!C103="Parcial",0.5,0))+IF(OR('BCO COES Integracion'!C104="Sí",'BCO COES Integracion'!C104="Si"),1,IF('BCO COES Integracion'!C104="Parcial",0.5,0))+IF(OR('BCO COES Integracion'!C105="Sí",'BCO COES Integracion'!C105="Si"),1,IF('BCO COES Integracion'!C105="Parcial",0.5,0))+IF(OR('BCO COES Integracion'!C106="Sí",'BCO COES Integracion'!C106="Si"),1,IF('BCO COES Integracion'!C106="Parcial",0.5,0))+IF(OR('BCO COES Integracion'!C107="Sí",'BCO COES Integracion'!C107="Si"),1,IF('BCO COES Integracion'!C107="Parcial",0.5,0))+IF(OR('BCO COES Integracion'!C108="Sí",'BCO COES Integracion'!C108="Si"),1,IF('BCO COES Integracion'!C108="Parcial",0.5,0))+IF(OR('BCO COES Integracion'!C109="Sí",'BCO COES Integracion'!C109="Si"),1,IF('BCO COES Integracion'!C109="Parcial",0.5,0))+IF(OR('BCO COES Integracion'!C110="Sí",'BCO COES Integracion'!C110="Si"),1,IF('BCO COES Integracion'!C110="Parcial",0.5,0))+IF(OR('BCO COES Integracion'!C111="Sí",'BCO COES Integracion'!C111="Si"),1,IF('BCO COES Integracion'!C111="Parcial",0.5,0))+IF(OR('BCO COES Integracion'!C112="Sí",'BCO COES Integracion'!C112="Si"),1,IF('BCO COES Integracion'!C112="Parcial",0.5,0))+IF(OR('BCO COES Integracion'!C113="Sí",'BCO COES Integracion'!C113="Si"),1,IF('BCO COES Integracion'!C113="Parcial",0.5,0))+IF(OR('BCO COES Integracion'!C114="Sí",'BCO COES Integracion'!C114="Si"),1,IF('BCO COES Integracion'!C114="Parcial",0.5,0))+IF(OR('BCO COES Integracion'!C115="Sí",'BCO COES Integracion'!C115="Si"),1,IF('BCO COES Integracion'!C115="Parcial",0.5,0))+IF(OR('BCO COES Integracion'!C116="Sí",'BCO COES Integracion'!C116="Si"),1,IF('BCO COES Integracion'!C116="Parcial",0.5,0))+IF(OR('BCO COES Integracion'!C117="Sí",'BCO COES Integracion'!C117="Si"),1,IF('BCO COES Integracion'!C117="Parcial",0.5,0))+IF(OR('BCO COES Integracion'!C118="Sí",'BCO COES Integracion'!C118="Si"),1,IF('BCO COES Integracion'!C118="Parcial",0.5,0))+IF(OR('BCO COES Integracion'!C119="Sí",'BCO COES Integracion'!C119="Si"),1,IF('BCO COES Integracion'!C119="Parcial",0.5,0))+IF(OR('BCO COES Integracion'!C120="Sí",'BCO COES Integracion'!C120="Si"),1,IF('BCO COES Integracion'!C120="Parcial",0.5,0))+IF(OR('BCO COES Integracion'!C121="Sí",'BCO COES Integracion'!C121="Si"),1,IF('BCO COES Integracion'!C121="Parcial",0.5,0))+IF(OR('BCO COES Integracion'!C122="Sí",'BCO COES Integracion'!C122="Si"),1,IF('BCO COES Integracion'!C122="Parcial",0.5,0)) -> 9.5 | AV7: =A7 -> BCO COES Integracion | AW7: =IFERROR(COUNTA('BCO COES Integracion'!C126:C133)/8,0) -> 0.625 | AY7: =A7 -> BCO COES Integracion | AZ7: =IFERROR(COUNTA('BCO COES Integracion'!C137:C146),0) -> 3 | BB7: =A7 -> BCO COES Integracion | BC7: =IFERROR(COUNTA('BCO COES Integracion'!C150:C156)/7,0) -> 0.42857143 | BE7: =A7 -> BCO COES Integracion | BF7: =IFERROR(COUNTA('BCO COES Integracion'!C160:C168)/9,0) -> 1 | BH7: =A7 -> BCO COES Integracion | BI7: =IFERROR(COUNTA('BCO COES Integracion'!C172:C182)/10,0) -> 0.1 | BK7: ④b Incidentes categorizados | BL7: =IFERROR(AVERAGE(AN3:AN13),0) -> 0 | BM7: =0 -> 0 | BO7: D5 | BP7: =Dashboard!O51 -> 0
A8: BCO COES Datos | B8: ='BCO COES Datos'!#REF! -> #REF! | C8: =IFERROR(VALUE(SUBSTITUTE(B8,"N","")),0) -> 0 | D8: 3 | K8: =A8 -> BCO COES Datos | L8: =C8 -> 0 | M8: 3 | X8: =A8 -> BCO COES Datos | Y8: =IFERROR(COUNTA('BCO COES Datos'!C5:C24)/15,0) -> 1 | AA8: =A8 -> BCO COES Datos | AB8: =C8 -> 0 | AC8: 3 | AE8: =A8 -> BCO COES Datos | AF8: =IFERROR('BCO COES Datos'!E58,0) -> 0.73529412 | AH8: =A8 -> BCO COES Datos | AI8: =IFERROR('BCO COES Datos'!C68,0) -> Pendiente revisar líderes técnicos | AJ8: =IFERROR('BCO COES Datos'!C70,0) -> No aplica SLA- ANS del Banco y de COES | AM8: =A8 -> BCO COES Datos | AN8: =IFERROR('BCO COES Datos'!C82,0) -> 700 a 3.000 | AP8: =A8 -> BCO COES Datos | AQ8: =IFERROR('BCO COES Datos'!C91,0) -> 0 | AS8: =A8 -> BCO COES Datos | AT8: =IF(OR('BCO COES Datos'!C101="Sí",'BCO COES Datos'!C101="Si"),1,IF('BCO COES Datos'!C101="Parcial",0.5,0))+IF(OR('BCO COES Datos'!C102="Sí",'BCO COES Datos'!C102="Si"),1,IF('BCO COES Datos'!C102="Parcial",0.5,0))+IF(OR('BCO COES Datos'!C103="Sí",'BCO COES Datos'!C103="Si"),1,IF('BCO COES Datos'!C103="Parcial",0.5,0))+IF(OR('BCO COES Datos'!C104="Sí",'BCO COES Datos'!C104="Si"),1,IF('BCO COES Datos'!C104="Parcial",0.5,0))+IF(OR('BCO COES Datos'!C105="Sí",'BCO COES Datos'!C105="Si"),1,IF('BCO COES Datos'!C105="Parcial",0.5,0))+IF(OR('BCO COES Datos'!C106="Sí",'BCO COES Datos'!C106="Si"),1,IF('BCO COES Datos'!C106="Parcial",0.5,0))+IF(OR('BCO COES Datos'!C107="Sí",'BCO COES Datos'!C107="Si"),1,IF('BCO COES Datos'!C107="Parcial",0.5,0))+IF(OR('BCO COES Datos'!C108="Sí",'BCO COES Datos'!C108="Si"),1,IF('BCO COES Datos'!C108="Parcial",0.5,0))+IF(OR('BCO COES Datos'!C109="Sí",'BCO COES Datos'!C109="Si"),1,IF('BCO COES Datos'!C109="Parcial",0.5,0))+IF(OR('BCO COES Datos'!C110="Sí",'BCO COES Datos'!C110="Si"),1,IF('BCO COES Datos'!C110="Parcial",0.5,0))+IF(OR('BCO COES Datos'!C111="Sí",'BCO COES Datos'!C111="Si"),1,IF('BCO COES Datos'!C111="Parcial",0.5,0))+IF(OR('BCO COES Datos'!C112="Sí",'BCO COES Datos'!C112="Si"),1,IF('BCO COES Datos'!C112="Parcial",0.5,0))+IF(OR('BCO COES Datos'!C113="Sí",'BCO COES Datos'!C113="Si"),1,IF('BCO COES Datos'!C113="Parcial",0.5,0))+IF(OR('BCO COES Datos'!C114="Sí",'BCO COES Datos'!C114="Si"),1,IF('BCO COES Datos'!C114="Parcial",0.5,0))+IF(OR('BCO COES Datos'!C115="Sí",'BCO COES Datos'!C115="Si"),1,IF('BCO COES Datos'!C115="Parcial",0.5,0))+IF(OR('BCO COES Datos'!C116="Sí",'BCO COES Datos'!C116="Si"),1,IF('BCO COES Datos'!C116="Parcial",0.5,0))+IF(OR('BCO COES Datos'!C117="Sí",'BCO COES Datos'!C117="Si"),1,IF('BCO COES Datos'!C117="Parcial",0.5,0))+IF(OR('BCO COES Datos'!C118="Sí",'BCO COES Datos'!C118="Si"),1,IF('BCO COES Datos'!C118="Parcial",0.5,0))+IF(OR('BCO COES Datos'!C119="Sí",'BCO COES Datos'!C119="Si"),1,IF('BCO COES Datos'!C119="Parcial",0.5,0))+IF(OR('BCO COES Datos'!C120="Sí",'BCO COES Datos'!C120="Si"),1,IF('BCO COES Datos'!C120="Parcial",0.5,0))+IF(OR('BCO COES Datos'!C121="Sí",'BCO COES Datos'!C121="Si"),1,IF('BCO COES Datos'!C121="Parcial",0.5,0))+IF(OR('BCO COES Datos'!C122="Sí",'BCO COES Datos'!C122="Si"),1,IF('BCO COES Datos'!C122="Parcial",0.5,0)) -> 9.5 | AV8: =A8 -> BCO COES Datos | AW8: =IFERROR(COUNTA('BCO COES Datos'!C126:C133)/8,0) -> 0.75 | AY8: =A8 -> BCO COES Datos | AZ8: =IFERROR(COUNTA('BCO COES Datos'!C137:C146),0) -> 3 | BB8: =A8 -> BCO COES Datos | BC8: =IFERROR(COUNTA('BCO COES Datos'!C150:C156)/7,0) -> 1 | BE8: =A8 -> BCO COES Datos | BF8: =IFERROR(COUNTA('BCO COES Datos'!C160:C168)/9,0) -> 1 | BH8: =A8 -> BCO COES Datos | BI8: =IFERROR(COUNTA('BCO COES Datos'!C172:C182)/10,0) -> 0.1 | BK8: ⑤ XLA/DEX NPS | BL8: =IFERROR(AVERAGE(AQ3:AQ13)/100,0) -> 0 | BM8: =65% -> 0.65 | BO8: D6 | BP8: =Dashboard!O52 -> 3
A9: BCO Soporte | B9: ='BCO Soporte'!C13 -> N1 | C9: =IFERROR(VALUE(SUBSTITUTE(B9,"N","")),0) -> 1 | D9: 3 | K9: =A9 -> BCO Soporte | L9: =C9 -> 1 | M9: 3 | X9: =A9 -> BCO Soporte | Y9: =IFERROR(COUNTA('BCO Soporte'!C5:C24)/15,0) -> 1.0666667 | AA9: =A9 -> BCO Soporte | AB9: =C9 -> 1 | AC9: 3 | AE9: =A9 -> BCO Soporte | AF9: =IFERROR('BCO Soporte'!E58,0) -> 0.73529412 | AH9: =A9 -> BCO Soporte | AI9: =IFERROR('BCO Soporte'!C68,0) -> Pendiente revisar líderes técnicos | AJ9: =IFERROR('BCO Soporte'!C70,0) -> No aplica SLA- ANS del Banco y de COES | AM9: =A9 -> BCO Soporte | AN9: =IFERROR('BCO Soporte'!C82,0) -> 700 a 3.000 | AP9: =A9 -> BCO Soporte | AQ9: =IFERROR('BCO Soporte'!C91,0) -> 0 | AS9: =A9 -> BCO Soporte | AT9: =IF(OR('BCO Soporte'!C102="Sí",'BCO Soporte'!C102="Si"),1,IF('BCO Soporte'!C102="Parcial",0.5,0))+IF(OR('BCO Soporte'!C103="Sí",'BCO Soporte'!C103="Si"),1,IF('BCO Soporte'!C103="Parcial",0.5,0))+IF(OR('BCO Soporte'!C104="Sí",'BCO Soporte'!C104="Si"),1,IF('BCO Soporte'!C104="Parcial",0.5,0))+IF(OR('BCO Soporte'!C105="Sí",'BCO Soporte'!C105="Si"),1,IF('BCO Soporte'!C105="Parcial",0.5,0))+IF(OR('BCO Soporte'!C106="Sí",'BCO Soporte'!C106="Si"),1,IF('BCO Soporte'!C106="Parcial",0.5,0))+IF(OR('BCO Soporte'!C107="Sí",'BCO Soporte'!C107="Si"),1,IF('BCO Soporte'!C107="Parcial",0.5,0))+IF(OR('BCO Soporte'!C108="Sí",'BCO Soporte'!C108="Si"),1,IF('BCO Soporte'!C108="Parcial",0.5,0))+IF(OR('BCO Soporte'!C109="Sí",'BCO Soporte'!C109="Si"),1,IF('BCO Soporte'!C109="Parcial",0.5,0))+IF(OR('BCO Soporte'!C110="Sí",'BCO Soporte'!C110="Si"),1,IF('BCO Soporte'!C110="Parcial",0.5,0))+IF(OR('BCO Soporte'!C111="Sí",'BCO Soporte'!C111="Si"),1,IF('BCO Soporte'!C111="Parcial",0.5,0))+IF(OR('BCO Soporte'!C112="Sí",'BCO Soporte'!C112="Si"),1,IF('BCO Soporte'!C112="Parcial",0.5,0))+IF(OR('BCO Soporte'!C113="Sí",'BCO Soporte'!C113="Si"),1,IF('BCO Soporte'!C113="Parcial",0.5,0))+IF(OR('BCO Soporte'!C114="Sí",'BCO Soporte'!C114="Si"),1,IF('BCO Soporte'!C114="Parcial",0.5,0))+IF(OR('BCO Soporte'!C115="Sí",'BCO Soporte'!C115="Si"),1,IF('BCO Soporte'!C115="Parcial",0.5,0))+IF(OR('BCO Soporte'!C116="Sí",'BCO Soporte'!C116="Si"),1,IF('BCO Soporte'!C116="Parcial",0.5,0))+IF(OR('BCO Soporte'!C117="Sí",'BCO Soporte'!C117="Si"),1,IF('BCO Soporte'!C117="Parcial",0.5,0))+IF(OR('BCO Soporte'!C118="Sí",'BCO Soporte'!C118="Si"),1,IF('BCO Soporte'!C118="Parcial",0.5,0))+IF(OR('BCO Soporte'!C119="Sí",'BCO Soporte'!C119="Si"),1,IF('BCO Soporte'!C119="Parcial",0.5,0))+IF(OR('BCO Soporte'!C120="Sí",'BCO Soporte'!C120="Si"),1,IF('BCO Soporte'!C120="Parcial",0.5,0))+IF(OR('BCO Soporte'!C121="Sí",'BCO Soporte'!C121="Si"),1,IF('BCO Soporte'!C121="Parcial",0.5,0))+IF(OR('BCO Soporte'!C123="Sí",'BCO Soporte'!C123="Si"),1,IF('BCO Soporte'!C123="Parcial",0.5,0)) -> 9 | AV9: =A9 -> BCO Soporte | AW9: =IFERROR(COUNTA('BCO Soporte'!C126:C133)/8,0) -> 0.75 | AY9: =A9 -> BCO Soporte | AZ9: =IFERROR(COUNTA('BCO Soporte'!C137:C146),0) -> 4 | BB9: =A9 -> BCO Soporte | BC9: =IFERROR(COUNTA('BCO Soporte'!C150:C156)/7,0) -> 1 | BE9: =A9 -> BCO Soporte | BF9: =IFERROR(COUNTA('BCO Soporte'!C160:C168)/9,0) -> 0.88888889 | BH9: =A9 -> BCO Soporte | BI9: =IFERROR(COUNTA('BCO Soporte'!C172:C182)/10,0) -> 0.1 | BK9: ⑥ Dolores activos | BL9: =IFERROR(AVERAGE(AT3:AT13)/7,0) -> 1.4545455 | BM9: =0 -> 0 | BO9: D7 | BP9: =Dashboard!O53 -> 4.5
A10: BCO COES Emma | B10: ='BCO COES Emma'!C13 -> N1 | C10: =IFERROR(VALUE(SUBSTITUTE(B10,"N","")),0) -> 1 | D10: 3 | K10: =A10 -> BCO COES Emma | L10: =C10 -> 1 | M10: 3 | X10: =A10 -> BCO COES Emma | Y10: =IFERROR(COUNTA('BCO COES Emma'!C5:C24)/15,0) -> 1 | AA10: =A10 -> BCO COES Emma | AB10: =C10 -> 1 | AC10: 3 | AE10: =A10 -> BCO COES Emma | AF10: =IFERROR('BCO COES Emma'!E58,0) -> 0.73529412 | AH10: =A10 -> BCO COES Emma | AI10: =IFERROR('BCO COES Emma'!C68,0) -> 0 | AJ10: =IFERROR('BCO COES Emma'!C70,0) -> No aplica SLA- ANS del Banco y de COES | AM10: =A10 -> BCO COES Emma | AN10: =IFERROR('BCO COES Emma'!C82,0) -> 700 a 3.000 | AP10: =A10 -> BCO COES Emma | AQ10: =IFERROR('BCO COES Emma'!C91,0) -> 0 | AS10: =A10 -> BCO COES Emma | AT10: =IF(OR('BCO COES Emma'!C101="Sí",'BCO COES Emma'!C101="Si"),1,IF('BCO COES Emma'!C101="Parcial",0.5,0))+IF(OR('BCO COES Emma'!C102="Sí",'BCO COES Emma'!C102="Si"),1,IF('BCO COES Emma'!C102="Parcial",0.5,0))+IF(OR('BCO COES Emma'!C103="Sí",'BCO COES Emma'!C103="Si"),1,IF('BCO COES Emma'!C103="Parcial",0.5,0))+IF(OR('BCO COES Emma'!C104="Sí",'BCO COES Emma'!C104="Si"),1,IF('BCO COES Emma'!C104="Parcial",0.5,0))+IF(OR('BCO COES Emma'!C105="Sí",'BCO COES Emma'!C105="Si"),1,IF('BCO COES Emma'!C105="Parcial",0.5,0))+IF(OR('BCO COES Emma'!C106="Sí",'BCO COES Emma'!C106="Si"),1,IF('BCO COES Emma'!C106="Parcial",0.5,0))+IF(OR('BCO COES Emma'!C107="Sí",'BCO COES Emma'!C107="Si"),1,IF('BCO COES Emma'!C107="Parcial",0.5,0))+IF(OR('BCO COES Emma'!C108="Sí",'BCO COES Emma'!C108="Si"),1,IF('BCO COES Emma'!C108="Parcial",0.5,0))+IF(OR('BCO COES Emma'!C109="Sí",'BCO COES Emma'!C109="Si"),1,IF('BCO COES Emma'!C109="Parcial",0.5,0))+IF(OR('BCO COES Emma'!C110="Sí",'BCO COES Emma'!C110="Si"),1,IF('BCO COES Emma'!C110="Parcial",0.5,0))+IF(OR('BCO COES Emma'!C111="Sí",'BCO COES Emma'!C111="Si"),1,IF('BCO COES Emma'!C111="Parcial",0.5,0))+IF(OR('BCO COES Emma'!C112="Sí",'BCO COES Emma'!C112="Si"),1,IF('BCO COES Emma'!C112="Parcial",0.5,0))+IF(OR('BCO COES Emma'!C113="Sí",'BCO COES Emma'!C113="Si"),1,IF('BCO COES Emma'!C113="Parcial",0.5,0))+IF(OR('BCO COES Emma'!C114="Sí",'BCO COES Emma'!C114="Si"),1,IF('BCO COES Emma'!C114="Parcial",0.5,0))+IF(OR('BCO COES Emma'!C115="Sí",'BCO COES Emma'!C115="Si"),1,IF('BCO COES Emma'!C115="Parcial",0.5,0))+IF(OR('BCO COES Emma'!C116="Sí",'BCO COES Emma'!C116="Si"),1,IF('BCO COES Emma'!C116="Parcial",0.5,0))+IF(OR('BCO COES Emma'!C117="Sí",'BCO COES Emma'!C117="Si"),1,IF('BCO COES Emma'!C117="Parcial",0.5,0))+IF(OR('BCO COES Emma'!C118="Sí",'BCO COES Emma'!C118="Si"),1,IF('BCO COES Emma'!C118="Parcial",0.5,0))+IF(OR('BCO COES Emma'!C119="Sí",'BCO COES Emma'!C119="Si"),1,IF('BCO COES Emma'!C119="Parcial",0.5,0))+IF(OR('BCO COES Emma'!C120="Sí",'BCO COES Emma'!C120="Si"),1,IF('BCO COES Emma'!C120="Parcial",0.5,0))+IF(OR('BCO COES Emma'!C121="Sí",'BCO COES Emma'!C121="Si"),1,IF('BCO COES Emma'!C121="Parcial",0.5,0))+IF(OR('BCO COES Emma'!C122="Sí",'BCO COES Emma'!C122="Si"),1,IF('BCO COES Emma'!C122="Parcial",0.5,0)) -> 9.5 | AV10: =A10 -> BCO COES Emma | AW10: =IFERROR(COUNTA('BCO COES Emma'!C126:C133)/8,0) -> 0.75 | AY10: =A10 -> BCO COES Emma | AZ10: =IFERROR(COUNTA('BCO COES Emma'!C137:C146),0) -> 3 | BB10: =A10 -> BCO COES Emma | BC10: =IFERROR(COUNTA('BCO COES Emma'!C150:C156)/7,0) -> 1 | BE10: =A10 -> BCO COES Emma | BF10: =IFERROR(COUNTA('BCO COES Emma'!C160:C168)/9,0) -> 1 | BH10: =A10 -> BCO COES Emma | BI10: =IFERROR(COUNTA('BCO COES Emma'!C172:C182)/10,0) -> 0.1 | BK10: ⑦ Talento | BL10: =AVERAGE(AW3:AW13) -> 0.45454545 | BM10: =100% -> 1 | BO10: D8 | BP10: =Dashboard!O54 -> 5
A11: BCO Emma Iseries | B11: ='BCO Emma Iseries'!C13 -> N1 | C11: =IFERROR(VALUE(SUBSTITUTE(B11,"N","")),0) -> 1 | D11: 3 | K11: =A11 -> BCO Emma Iseries | L11: =C11 -> 1 | M11: 3 | X11: =A11 -> BCO Emma Iseries | Y11: =IFERROR(COUNTA('BCO Emma Iseries'!C5:C24)/15,0) -> 1 | AA11: =A11 -> BCO Emma Iseries | AB11: =C11 -> 1 | AC11: 3 | AE11: =A11 -> BCO Emma Iseries | AF11: =IFERROR('BCO Emma Iseries'!E58,0) -> 0.73529412 | AH11: =A11 -> BCO Emma Iseries | AI11: =IFERROR('BCO Emma Iseries'!C68,0) -> 0 | AJ11: =IFERROR('BCO Emma Iseries'!C70,0) -> No aplica SLA- ANS del Banco y de COES | AM11: =A11 -> BCO Emma Iseries | AN11: =IFERROR('BCO Emma Iseries'!C82,0) -> 0 | AP11: =A11 -> BCO Emma Iseries | AQ11: =IFERROR('BCO Emma Iseries'!C91,0) -> 0 | AS11: =A11 -> BCO Emma Iseries | AT11: =IF(OR('BCO Emma Iseries'!C101="Sí",'BCO Emma Iseries'!C101="Si"),1,IF('BCO Emma Iseries'!C101="Parcial",0.5,0))+IF(OR('BCO Emma Iseries'!C102="Sí",'BCO Emma Iseries'!C102="Si"),1,IF('BCO Emma Iseries'!C102="Parcial",0.5,0))+IF(OR('BCO Emma Iseries'!C103="Sí",'BCO Emma Iseries'!C103="Si"),1,IF('BCO Emma Iseries'!C103="Parcial",0.5,0))+IF(OR('BCO Emma Iseries'!C104="Sí",'BCO Emma Iseries'!C104="Si"),1,IF('BCO Emma Iseries'!C104="Parcial",0.5,0))+IF(OR('BCO Emma Iseries'!C105="Sí",'BCO Emma Iseries'!C105="Si"),1,IF('BCO Emma Iseries'!C105="Parcial",0.5,0))+IF(OR('BCO Emma Iseries'!C106="Sí",'BCO Emma Iseries'!C106="Si"),1,IF('BCO Emma Iseries'!C106="Parcial",0.5,0))+IF(OR('BCO Emma Iseries'!C107="Sí",'BCO Emma Iseries'!C107="Si"),1,IF('BCO Emma Iseries'!C107="Parcial",0.5,0))+IF(OR('BCO Emma Iseries'!C108="Sí",'BCO Emma Iseries'!C108="Si"),1,IF('BCO Emma Iseries'!C108="Parcial",0.5,0))+IF(OR('BCO Emma Iseries'!C109="Sí",'BCO Emma Iseries'!C109="Si"),1,IF('BCO Emma Iseries'!C109="Parcial",0.5,0))+IF(OR('BCO Emma Iseries'!C110="Sí",'BCO Emma Iseries'!C110="Si"),1,IF('BCO Emma Iseries'!C110="Parcial",0.5,0))+IF(OR('BCO Emma Iseries'!C111="Sí",'BCO Emma Iseries'!C111="Si"),1,IF('BCO Emma Iseries'!C111="Parcial",0.5,0))+IF(OR('BCO Emma Iseries'!C112="Sí",'BCO Emma Iseries'!C112="Si"),1,IF('BCO Emma Iseries'!C112="Parcial",0.5,0))+IF(OR('BCO Emma Iseries'!C113="Sí",'BCO Emma Iseries'!C113="Si"),1,IF('BCO Emma Iseries'!C113="Parcial",0.5,0))+IF(OR('BCO Emma Iseries'!C114="Sí",'BCO Emma Iseries'!C114="Si"),1,IF('BCO Emma Iseries'!C114="Parcial",0.5,0))+IF(OR('BCO Emma Iseries'!C115="Sí",'BCO Emma Iseries'!C115="Si"),1,IF('BCO Emma Iseries'!C115="Parcial",0.5,0))+IF(OR('BCO Emma Iseries'!C116="Sí",'BCO Emma Iseries'!C116="Si"),1,IF('BCO Emma Iseries'!C116="Parcial",0.5,0))+IF(OR('BCO Emma Iseries'!C117="Sí",'BCO Emma Iseries'!C117="Si"),1,IF('BCO Emma Iseries'!C117="Parcial",0.5,0))+IF(OR('BCO Emma Iseries'!C118="Sí",'BCO Emma Iseries'!C118="Si"),1,IF('BCO Emma Iseries'!C118="Parcial",0.5,0))+IF(OR('BCO Emma Iseries'!C119="Sí",'BCO Emma Iseries'!C119="Si"),1,IF('BCO Emma Iseries'!C119="Parcial",0.5,0))+IF(OR('BCO Emma Iseries'!C120="Sí",'BCO Emma Iseries'!C120="Si"),1,IF('BCO Emma Iseries'!C120="Parcial",0.5,0))+IF(OR('BCO Emma Iseries'!C121="Sí",'BCO Emma Iseries'!C121="Si"),1,IF('BCO Emma Iseries'!C121="Parcial",0.5,0))+IF(OR('BCO Emma Iseries'!C122="Sí",'BCO Emma Iseries'!C122="Si"),1,IF('BCO Emma Iseries'!C122="Parcial",0.5,0)) -> 2 | AV11: =A11 -> BCO Emma Iseries | AW11: =IFERROR(COUNTA('BCO Emma Iseries'!C126:C133)/8,0) -> 0 | AY11: =A11 -> BCO Emma Iseries | AZ11: =IFERROR(COUNTA('BCO Emma Iseries'!C137:C146),0) -> 1 | BB11: =A11 -> BCO Emma Iseries | BC11: =IFERROR(COUNTA('BCO Emma Iseries'!C150:C156)/7,0) -> 0 | BE11: =A11 -> BCO Emma Iseries | BF11: =IFERROR(COUNTA('BCO Emma Iseries'!C160:C168)/9,0) -> 0.11111111 | BH11: =A11 -> BCO Emma Iseries | BI11: =IFERROR(COUNTA('BCO Emma Iseries'!C172:C182)/10,0) -> 0.1 | BK11: ⑧ Tecnología | BL11: =IFERROR(AVERAGE(AZ3:AZ13)/10,0) -> 0.34545455 | BM11: =100% -> 1 | BO11: D9 | BP11: =Dashboard!O55 -> 7
A12: AES | B12: =AES!C13 -> N1 | C12: =IFERROR(VALUE(SUBSTITUTE(B12,"N","")),0) -> 1 | D12: 3 | K12: =A12 -> AES | L12: =C12 -> 1 | M12: 3 | X12: =A12 -> AES | Y12: =IFERROR(COUNTA(AES!C5:C24)/15,0) -> 1.3333333 | AA12: =A12 -> AES | AB12: =C12 -> 1 | AC12: 3 | AE12: =A12 -> AES | AF12: =IFERROR(AES!E57,0) -> 0.29411765 | AH12: =A12 -> AES | AI12: =IFERROR(AES!C62,0) -> 0 | AJ12: =IFERROR(AES!C64,0) -> 0 | AM12: =A12 -> AES | AN12: =IFERROR(AES!C82,0) -> 0 | AP12: =A12 -> AES | AQ12: =IFERROR(AES!C85,0) -> 0 | AS12: =A12 -> AES | AT12: =IF(OR(AES!C98="Sí",AES!C98="Si"),1,IF(AES!C98="Parcial",0.5,0))+IF(OR(AES!C99="Sí",AES!C99="Si"),1,IF(AES!C99="Parcial",0.5,0))+IF(OR(AES!C100="Sí",AES!C100="Si"),1,IF(AES!C100="Parcial",0.5,0))+IF(OR(AES!C101="Sí",AES!C101="Si"),1,IF(AES!C101="Parcial",0.5,0))+IF(OR(AES!C102="Sí",AES!C102="Si"),1,IF(AES!C102="Parcial",0.5,0))+IF(OR(AES!C103="Sí",AES!C103="Si"),1,IF(AES!C103="Parcial",0.5,0))+IF(OR(AES!C104="Sí",AES!C104="Si"),1,IF(AES!C104="Parcial",0.5,0))+IF(OR(AES!C105="Sí",AES!C105="Si"),1,IF(AES!C105="Parcial",0.5,0))+IF(OR(AES!C106="Sí",AES!C106="Si"),1,IF(AES!C106="Parcial",0.5,0))+IF(OR(AES!C107="Sí",AES!C107="Si"),1,IF(AES!C107="Parcial",0.5,0))+IF(OR(AES!C108="Sí",AES!C108="Si"),1,IF(AES!C108="Parcial",0.5,0))+IF(OR(AES!C109="Sí",AES!C109="Si"),1,IF(AES!C109="Parcial",0.5,0))+IF(OR(AES!C110="Sí",AES!C110="Si"),1,IF(AES!C110="Parcial",0.5,0))+IF(OR(AES!C111="Sí",AES!C111="Si"),1,IF(AES!C111="Parcial",0.5,0))+IF(OR(AES!C112="Sí",AES!C112="Si"),1,IF(AES!C112="Parcial",0.5,0))+IF(OR(AES!C113="Sí",AES!C113="Si"),1,IF(AES!C113="Parcial",0.5,0))+IF(OR(AES!C114="Sí",AES!C114="Si"),1,IF(AES!C114="Parcial",0.5,0))+IF(OR(AES!C115="Sí",AES!C115="Si"),1,IF(AES!C115="Parcial",0.5,0))+IF(OR(AES!C116="Sí",AES!C116="Si"),1,IF(AES!C116="Parcial",0.5,0))+IF(OR(AES!C117="Sí",AES!C117="Si"),1,IF(AES!C117="Parcial",0.5,0))+IF(OR(AES!C118="Sí",AES!C118="Si"),1,IF(AES!C118="Parcial",0.5,0))+IF(OR(AES!C119="Sí",AES!C119="Si"),1,IF(AES!C119="Parcial",0.5,0)) -> 7 | AV12: =A12 -> AES | AW12: =IFERROR(COUNTA(AES!C126:C133)/8,0) -> 0.125 | AY12: =A12 -> AES | AZ12: =IFERROR(COUNTA(AES!C137:C146),0) -> 2 | BB12: =A12 -> AES | BC12: =IFERROR(COUNTA(AES!C150:C156)/7,0) -> 0.42857143 | BE12: =A12 -> AES | BF12: =IFERROR(COUNTA(AES!C160:C168)/9,0) -> 0.55555556 | BH12: =A12 -> AES | BI12: =IFERROR(COUNTA(AES!C172:C182)/10,0) -> 0.1 | BK12: ⑨ Económico | BL12: =AVERAGE(BC3:BC13) -> 0.7012987 | BM12: =100% -> 1 | BO12: D10 | BP12: =Dashboard!O56 -> 4.5
A13: XM | B13: =XM!C13 -> N2 | C13: =IFERROR(VALUE(SUBSTITUTE(B13,"N","")),0) -> 2 | D13: 3 | K13: =A13 -> XM | L13: =C13 -> 2 | M13: 3 | X13: =A13 -> XM | Y13: =IFERROR(COUNTA(XM!C5:C24)/15,0) -> 1.3333333 | AA13: =A13 -> XM | AB13: =C13 -> 2 | AC13: 3 | AE13: =A13 -> XM | AF13: =IFERROR(XM!E57,0) -> 0.5 | AH13: =A13 -> XM | AI13: =IFERROR(XM!C68,0) -> 0 | AJ13: =IFERROR(XM!C70,0) -> 0 | AM13: =A13 -> XM | AN13: =IFERROR(XM!C82,0) -> 0 | AP13: =A13 -> XM | AQ13: =IFERROR(XM!C91,0) -> 0 | AS13: =A13 -> XM | AT13: =IF(OR(XM!C100="Sí",XM!C100="Si"),1,IF(XM!C100="Parcial",0.5,0))+IF(OR(XM!C101="Sí",XM!C101="Si"),1,IF(XM!C101="Parcial",0.5,0))+IF(OR(XM!C102="Sí",XM!C102="Si"),1,IF(XM!C102="Parcial",0.5,0))+IF(OR(XM!C103="Sí",XM!C103="Si"),1,IF(XM!C103="Parcial",0.5,0))+IF(OR(XM!C104="Sí",XM!C104="Si"),1,IF(XM!C104="Parcial",0.5,0))+IF(OR(XM!C105="Sí",XM!C105="Si"),1,IF(XM!C105="Parcial",0.5,0))+IF(OR(XM!C106="Sí",XM!C106="Si"),1,IF(XM!C106="Parcial",0.5,0))+IF(OR(XM!C107="Sí",XM!C107="Si"),1,IF(XM!C107="Parcial",0.5,0))+IF(OR(XM!C108="Sí",XM!C108="Si"),1,IF(XM!C108="Parcial",0.5,0))+IF(OR(XM!C109="Sí",XM!C109="Si"),1,IF(XM!C109="Parcial",0.5,0))+IF(OR(XM!C110="Sí",XM!C110="Si"),1,IF(XM!C110="Parcial",0.5,0))+IF(OR(XM!C111="Sí",XM!C111="Si"),1,IF(XM!C111="Parcial",0.5,0))+IF(OR(XM!C112="Sí",XM!C112="Si"),1,IF(XM!C112="Parcial",0.5,0))+IF(OR(XM!C113="Sí",XM!C113="Si"),1,IF(XM!C113="Parcial",0.5,0))+IF(OR(XM!C114="Sí",XM!C114="Si"),1,IF(XM!C114="Parcial",0.5,0))+IF(OR(XM!C115="Sí",XM!C115="Si"),1,IF(XM!C115="Parcial",0.5,0))+IF(OR(XM!C116="Sí",XM!C116="Si"),1,IF(XM!C116="Parcial",0.5,0))+IF(OR(XM!C117="Sí",XM!C117="Si"),1,IF(XM!C117="Parcial",0.5,0))+IF(OR(XM!C118="Sí",XM!C118="Si"),1,IF(XM!C118="Parcial",0.5,0))+IF(OR(XM!C119="Sí",XM!C119="Si"),1,IF(XM!C119="Parcial",0.5,0))+IF(OR(XM!C120="Sí",XM!C120="Si"),1,IF(XM!C120="Parcial",0.5,0))+IF(OR(XM!C121="Sí",XM!C121="Si"),1,IF(XM!C121="Parcial",0.5,0)) -> 16 | AV13: =A13 -> XM | AW13: =IFERROR(COUNTA(XM!C126:C133)/8,0) -> 0.5 | AY13: =A13 -> XM | AZ13: =IFERROR(COUNTA(XM!C136:C145),0) -> 7 | BB13: =A13 -> XM | BC13: =IFERROR(COUNTA(XM!C150:C156)/7,0) -> 0.42857143 | BE13: =A13 -> XM | BF13: =IFERROR(COUNTA(XM!C160:C168)/9,0) -> 0.88888889 | BH13: =A13 -> XM | BI13: =IFERROR(COUNTA(XM!C172:C182)/10,0) -> 0.1 | BK13: ⑩ Visión | BL13: =AVERAGE(BF3:BF13) -> 0.81818182 | BM13: =100% -> 1 | BO13: D11 | BP13: =Dashboard!O57 -> 4.5
A14: MEDICARTE | B14: =MEDICARTE!C13 -> 0 | C14: =IFERROR(VALUE(SUBSTITUTE(B14,"N","")),0) -> 0 | D14: 3 | K14: =A14 -> MEDICARTE | L14: =C14 -> 0 | M14: 3 | X14: =A14 -> MEDICARTE | Y14: =IFERROR(COUNTA(MEDICARTE!C5:C24)/15,0) -> 0.33333333 | AA14: =A14 -> MEDICARTE | AB14: =C14 -> 0 | AC14: 3 | AE14: =A14 -> MEDICARTE | AF14: =IFERROR(MEDICARTE!E58,0) -> 0 | AH14: =A14 -> MEDICARTE | AI14: =IFERROR(MEDICARTE!C66,0) -> 0 | AJ14: =IFERROR(MEDICARTE!C68,0) -> 0.68 | AM14: =A14 -> MEDICARTE | AN14: =IFERROR(MEDICARTE!C82,0) -> 0 | AP14: =A14 -> MEDICARTE | AQ14: =IFERROR(MEDICARTE!C89,0) -> 0 | AS14: =A14 -> MEDICARTE | AT14: =IF(OR(MEDICARTE!C101="Sí",MEDICARTE!C101="Si"),1,IF(MEDICARTE!C101="Parcial",0.5,0))+IF(OR(MEDICARTE!C102="Sí",MEDICARTE!C102="Si"),1,IF(MEDICARTE!C102="Parcial",0.5,0))+IF(OR(MEDICARTE!C103="Sí",MEDICARTE!C103="Si"),1,IF(MEDICARTE!C103="Parcial",0.5,0))+IF(OR(MEDICARTE!C104="Sí",MEDICARTE!C104="Si"),1,IF(MEDICARTE!C104="Parcial",0.5,0))+IF(OR(MEDICARTE!C105="Sí",MEDICARTE!C105="Si"),1,IF(MEDICARTE!C105="Parcial",0.5,0))+IF(OR(MEDICARTE!C106="Sí",MEDICARTE!C106="Si"),1,IF(MEDICARTE!C106="Parcial",0.5,0))+IF(OR(MEDICARTE!C107="Sí",MEDICARTE!C107="Si"),1,IF(MEDICARTE!C107="Parcial",0.5,0))+IF(OR(MEDICARTE!C108="Sí",MEDICARTE!C108="Si"),1,IF(MEDICARTE!C108="Parcial",0.5,0))+IF(OR(MEDICARTE!C109="Sí",MEDICARTE!C109="Si"),1,IF(MEDICARTE!C109="Parcial",0.5,0))+IF(OR(MEDICARTE!C110="Sí",MEDICARTE!C110="Si"),1,IF(MEDICARTE!C110="Parcial",0.5,0))+IF(OR(MEDICARTE!C111="Sí",MEDICARTE!C111="Si"),1,IF(MEDICARTE!C111="Parcial",0.5,0))+IF(OR(MEDICARTE!C112="Sí",MEDICARTE!C112="Si"),1,IF(MEDICARTE!C112="Parcial",0.5,0))+IF(OR(MEDICARTE!C113="Sí",MEDICARTE!C113="Si"),1,IF(MEDICARTE!C113="Parcial",0.5,0))+IF(OR(MEDICARTE!C114="Sí",MEDICARTE!C114="Si"),1,IF(MEDICARTE!C114="Parcial",0.5,0))+IF(OR(MEDICARTE!C115="Sí",MEDICARTE!C115="Si"),1,IF(MEDICARTE!C115="Parcial",0.5,0))+IF(OR(MEDICARTE!C116="Sí",MEDICARTE!C116="Si"),1,IF(MEDICARTE!C116="Parcial",0.5,0))+IF(OR(MEDICARTE!C117="Sí",MEDICARTE!C117="Si"),1,IF(MEDICARTE!C117="Parcial",0.5,0))+IF(OR(MEDICARTE!C118="Sí",MEDICARTE!C118="Si"),1,IF(MEDICARTE!C118="Parcial",0.5,0))+IF(OR(MEDICARTE!C119="Sí",MEDICARTE!C119="Si"),1,IF(MEDICARTE!C119="Parcial",0.5,0))+IF(OR(MEDICARTE!C120="Sí",MEDICARTE!C120="Si"),1,IF(MEDICARTE!C120="Parcial",0.5,0))+IF(OR(MEDICARTE!C121="Sí",MEDICARTE!C121="Si"),1,IF(MEDICARTE!C121="Parcial",0.5,0))+IF(OR(MEDICARTE!C122="Sí",MEDICARTE!C122="Si"),1,IF(MEDICARTE!C122="Parcial",0.5,0)) -> 1 | AV14: =A14 -> MEDICARTE | AW14: =IFERROR(COUNTA(MEDICARTE!C126:C133)/8,0) -> 0 | AY14: =A14 -> MEDICARTE | AZ14: =IFERROR(COUNTA(MEDICARTE!C137:C146),0) -> 0 | BB14: =A14 -> MEDICARTE | BC14: =IFERROR(COUNTA(MEDICARTE!C150:C156)/7,0) -> 0 | BE14: =A14 -> MEDICARTE | BF14: =IFERROR(COUNTA(MEDICARTE!C160:C168)/9,0) -> 0.11111111 | BH14: =A14 -> MEDICARTE | BI14: =IFERROR(COUNTA(MEDICARTE!C172:C182)/10,0) -> 0.1 | BK14: ⑪ Casos éxito | BL14: =AVERAGE(BI3:BI13) -> 0.1 | BM14: =100% -> 1 | BO14: D12 | BP14: =Dashboard!O58 -> 5.5
A15: TABLA 2 — SCORE PRÁCTICAS POR DIMENSIÓN (%) | BO15: D13 | BP15: =Dashboard!O59 -> 7
A16: Mesa | B16: D1 Org/Personas | C16: D2 Info/Tecnología | D16: D3 Socios/Proveed. | E16: D4 Valor/Mejora | F16: Score Global | K16: Mesa | L16: D1 Org/Personas | N16: Mesa | O16: D2 Info/Tecnología | Q16: Mesa | R16: D3 Socios/Proveed. | T16: Mesa | U16: Score Global | BO16: D14 | BP16: =Dashboard!O60 -> 5
A17: SURA Cotizadores | B17: =IFERROR((COUNTIF('SURA Cotizadores'!D32:D36,"Sí")+COUNTIF('SURA Cotizadores'!D32:D36,"Si")+0.5*COUNTIF('SURA Cotizadores'!D32:D36,"Parcial"))/(COUNTIF('SURA Cotizadores'!D32:D36,"Sí")+COUNTIF('SURA Cotizadores'!D32:D36,"Si")+COUNTIF('SURA Cotizadores'!D32:D36,"Parcial")+COUNTIF('SURA Cotizadores'!D32:D36,"No")),0) -> 0.3 | C17: =IFERROR((COUNTIF('SURA Cotizadores'!D39:D45,"Sí")+COUNTIF('SURA Cotizadores'!D39:D45,"Si")+0.5*COUNTIF('SURA Cotizadores'!D39:D45,"Parcial"))/(COUNTIF('SURA Cotizadores'!D39:D45,"Sí")+COUNTIF('SURA Cotizadores'!D39:D45,"Si")+COUNTIF('SURA Cotizadores'!D39:D45,"Parcial")+COUNTIF('SURA Cotizadores'!D39:D45,"No")),0) -> 0.57142857 | D17: =IFERROR((COUNTIF('SURA Cotizadores'!D48:D50,"Sí")+COUNTIF('SURA Cotizadores'!D48:D50,"Si")+0.5*COUNTIF('SURA Cotizadores'!D48:D50,"Parcial"))/(COUNTIF('SURA Cotizadores'!D48:D50,"Sí")+COUNTIF('SURA Cotizadores'!D48:D50,"Si")+COUNTIF('SURA Cotizadores'!D48:D50,"Parcial")+COUNTIF('SURA Cotizadores'!D48:D50,"No")),0) -> 0.83333333 | E17: =IFERROR((COUNTIF('SURA Cotizadores'!D53:D54,"Sí")+COUNTIF('SURA Cotizadores'!D53:D54,"Si")+0.5*COUNTIF('SURA Cotizadores'!D53:D54,"Parcial"))/(COUNTIF('SURA Cotizadores'!D53:D54,"Sí")+COUNTIF('SURA Cotizadores'!D53:D54,"Si")+COUNTIF('SURA Cotizadores'!D53:D54,"Parcial")+COUNTIF('SURA Cotizadores'!D53:D54,"No")),0) -> 0.5 | F17: =IFERROR('SURA Cotizadores'!E56,0) -> 0.52941176 | K17: =A17 -> SURA Cotizadores | L17: =B17 -> 0.3 | N17: =A17 -> SURA Cotizadores | O17: =C17 -> 0.57142857 | Q17: =A17 -> SURA Cotizadores | R17: =D17 -> 0.83333333 | T17: =AE3 -> SURA Cotizadores | U17: =AF3 -> 0.52941176 | BO17: D15 | BP17: =Dashboard!O61 -> 5
A18: SURA Digital Venta | B18: =IFERROR((COUNTIF('SURA Digital Venta'!D33:D37,"Sí")+COUNTIF('SURA Digital Venta'!D33:D37,"Si")+0.5*COUNTIF('SURA Digital Venta'!D33:D37,"Parcial"))/(COUNTIF('SURA Digital Venta'!D33:D37,"Sí")+COUNTIF('SURA Digital Venta'!D33:D37,"Si")+COUNTIF('SURA Digital Venta'!D33:D37,"Parcial")+COUNTIF('SURA Digital Venta'!D33:D37,"No")),0) -> 0.4 | C18: =IFERROR((COUNTIF('SURA Digital Venta'!D40:D46,"Sí")+COUNTIF('SURA Digital Venta'!D40:D46,"Si")+0.5*COUNTIF('SURA Digital Venta'!D40:D46,"Parcial"))/(COUNTIF('SURA Digital Venta'!D40:D46,"Sí")+COUNTIF('SURA Digital Venta'!D40:D46,"Si")+COUNTIF('SURA Digital Venta'!D40:D46,"Parcial")+COUNTIF('SURA Digital Venta'!D40:D46,"No")),0) -> 0.57142857 | D18: =IFERROR((COUNTIF('SURA Digital Venta'!D49:D51,"Sí")+COUNTIF('SURA Digital Venta'!D49:D51,"Si")+0.5*COUNTIF('SURA Digital Venta'!D49:D51,"Parcial"))/(COUNTIF('SURA Digital Venta'!D49:D51,"Sí")+COUNTIF('SURA Digital Venta'!D49:D51,"Si")+COUNTIF('SURA Digital Venta'!D49:D51,"Parcial")+COUNTIF('SURA Digital Venta'!D49:D51,"No")),0) -> 0.83333333 | E18: =IFERROR((COUNTIF('SURA Digital Venta'!D54:D55,"Sí")+COUNTIF('SURA Digital Venta'!D54:D55,"Si")+0.5*COUNTIF('SURA Digital Venta'!D54:D55,"Parcial"))/(COUNTIF('SURA Digital Venta'!D54:D55,"Sí")+COUNTIF('SURA Digital Venta'!D54:D55,"Si")+COUNTIF('SURA Digital Venta'!D54:D55,"Parcial")+COUNTIF('SURA Digital Venta'!D54:D55,"No")),0) -> 0.5 | F18: =IFERROR('SURA Digital Venta'!E57,0) -> 0.55882353 | K18: =A18 -> SURA Digital Venta | L18: =B18 -> 0.4 | N18: =A18 -> SURA Digital Venta | O18: =C18 -> 0.57142857 | Q18: =A18 -> SURA Digital Venta | R18: =D18 -> 0.83333333 | T18: =AE4 -> SURA Digital Venta | U18: =AF4 -> 0.55882353 | BO18: D16 | BP18: =Dashboard!O62 -> 9.5
A19: SURA Automatizacion | B19: =IFERROR((COUNTIF('SURA Automatizacion'!D33:D37,"Sí")+COUNTIF('SURA Automatizacion'!D33:D37,"Si")+0.5*COUNTIF('SURA Automatizacion'!D33:D37,"Parcial"))/(COUNTIF('SURA Automatizacion'!D33:D37,"Sí")+COUNTIF('SURA Automatizacion'!D33:D37,"Si")+COUNTIF('SURA Automatizacion'!D33:D37,"Parcial")+COUNTIF('SURA Automatizacion'!D33:D37,"No")),0) -> 0.4 | C19: =IFERROR((COUNTIF('SURA Automatizacion'!D40:D46,"Sí")+COUNTIF('SURA Automatizacion'!D40:D46,"Si")+0.5*COUNTIF('SURA Automatizacion'!D40:D46,"Parcial"))/(COUNTIF('SURA Automatizacion'!D40:D46,"Sí")+COUNTIF('SURA Automatizacion'!D40:D46,"Si")+COUNTIF('SURA Automatizacion'!D40:D46,"Parcial")+COUNTIF('SURA Automatizacion'!D40:D46,"No")),0) -> 0.71428571 | D19: =IFERROR((COUNTIF('SURA Automatizacion'!D49:D51,"Sí")+COUNTIF('SURA Automatizacion'!D49:D51,"Si")+0.5*COUNTIF('SURA Automatizacion'!D49:D51,"Parcial"))/(COUNTIF('SURA Automatizacion'!D49:D51,"Sí")+COUNTIF('SURA Automatizacion'!D49:D51,"Si")+COUNTIF('SURA Automatizacion'!D49:D51,"Parcial")+COUNTIF('SURA Automatizacion'!D49:D51,"No")),0) -> 0.83333333 | E19: =IFERROR((COUNTIF('SURA Automatizacion'!D54:D55,"Sí")+COUNTIF('SURA Automatizacion'!D54:D55,"Si")+0.5*COUNTIF('SURA Automatizacion'!D54:D55,"Parcial"))/(COUNTIF('SURA Automatizacion'!D54:D55,"Sí")+COUNTIF('SURA Automatizacion'!D54:D55,"Si")+COUNTIF('SURA Automatizacion'!D54:D55,"Parcial")+COUNTIF('SURA Automatizacion'!D54:D55,"No")),0) -> 0.5 | F19: =IFERROR('SURA Automatizacion'!E57,0) -> 0.61764706 | K19: =A19 -> SURA Automatizacion | L19: =B19 -> 0.4 | N19: =A19 -> SURA Automatizacion | O19: =C19 -> 0.71428571 | Q19: =A19 -> SURA Automatizacion | R19: =D19 -> 0.83333333 | T19: =AE5 -> SURA Automatizacion | U19: =AF5 -> 0.61764706 | BO19: D17 | BP19: =Dashboard!O63 -> 6.5
A20: SURA Canales Masivos | B20: =IFERROR((COUNTIF('SURA Canales Masivos'!D33:D37,"Sí")+COUNTIF('SURA Canales Masivos'!D33:D37,"Si")+0.5*COUNTIF('SURA Canales Masivos'!D33:D37,"Parcial"))/(COUNTIF('SURA Canales Masivos'!D33:D37,"Sí")+COUNTIF('SURA Canales Masivos'!D33:D37,"Si")+COUNTIF('SURA Canales Masivos'!D33:D37,"Parcial")+COUNTIF('SURA Canales Masivos'!D33:D37,"No")),0) -> 0.4 | C20: =IFERROR((COUNTIF('SURA Canales Masivos'!D40:D46,"Sí")+COUNTIF('SURA Canales Masivos'!D40:D46,"Si")+0.5*COUNTIF('SURA Canales Masivos'!D40:D46,"Parcial"))/(COUNTIF('SURA Canales Masivos'!D40:D46,"Sí")+COUNTIF('SURA Canales Masivos'!D40:D46,"Si")+COUNTIF('SURA Canales Masivos'!D40:D46,"Parcial")+COUNTIF('SURA Canales Masivos'!D40:D46,"No")),0) -> 0.64285714 | D20: =IFERROR((COUNTIF('SURA Canales Masivos'!D49:D51,"Sí")+COUNTIF('SURA Canales Masivos'!D49:D51,"Si")+0.5*COUNTIF('SURA Canales Masivos'!D49:D51,"Parcial"))/(COUNTIF('SURA Canales Masivos'!D49:D51,"Sí")+COUNTIF('SURA Canales Masivos'!D49:D51,"Si")+COUNTIF('SURA Canales Masivos'!D49:D51,"Parcial")+COUNTIF('SURA Canales Masivos'!D49:D51,"No")),0) -> 0.83333333 | E20: =IFERROR((COUNTIF('SURA Canales Masivos'!D54:D55,"Sí")+COUNTIF('SURA Canales Masivos'!D54:D55,"Si")+0.5*COUNTIF('SURA Canales Masivos'!D54:D55,"Parcial"))/(COUNTIF('SURA Canales Masivos'!D54:D55,"Sí")+COUNTIF('SURA Canales Masivos'!D54:D55,"Si")+COUNTIF('SURA Canales Masivos'!D54:D55,"Parcial")+COUNTIF('SURA Canales Masivos'!D54:D55,"No")),0) -> 0.5 | F20: =IFERROR('SURA Canales Masivos'!E57,0) -> 0.58823529 | K20: =A20 -> SURA Canales Masivos | L20: =B20 -> 0.4 | N20: =A20 -> SURA Canales Masivos | O20: =C20 -> 0.64285714 | Q20: =A20 -> SURA Canales Masivos | R20: =D20 -> 0.83333333 | T20: =AE6 -> SURA Canales Masivos | U20: =AF6 -> 0.58823529 | BO20: D18 | BP20: =Dashboard!O64 -> 5.5
A21: BCO Gioti1 | B21: =IFERROR((COUNTIF('BCO COES Integracion'!D34:D38,"Sí")+COUNTIF('BCO COES Integracion'!D34:D38,"Si")+0.5*COUNTIF('BCO COES Integracion'!D34:D38,"Parcial"))/(COUNTIF('BCO COES Integracion'!D34:D38,"Sí")+COUNTIF('BCO COES Integracion'!D34:D38,"Si")+COUNTIF('BCO COES Integracion'!D34:D38,"Parcial")+COUNTIF('BCO COES Integracion'!D34:D38,"No")),0) -> 0.6 | C21: =IFERROR((COUNTIF('BCO COES Integracion'!D41:D47,"Sí")+COUNTIF('BCO COES Integracion'!D41:D47,"Si")+0.5*COUNTIF('BCO COES Integracion'!D41:D47,"Parcial"))/(COUNTIF('BCO COES Integracion'!D41:D47,"Sí")+COUNTIF('BCO COES Integracion'!D41:D47,"Si")+COUNTIF('BCO COES Integracion'!D41:D47,"Parcial")+COUNTIF('BCO COES Integracion'!D41:D47,"No")),0) -> 0.78571429 | D21: =IFERROR((COUNTIF('BCO COES Integracion'!D50:D52,"Sí")+COUNTIF('BCO COES Integracion'!D50:D52,"Si")+0.5*COUNTIF('BCO COES Integracion'!D50:D52,"Parcial"))/(COUNTIF('BCO COES Integracion'!D50:D52,"Sí")+COUNTIF('BCO COES Integracion'!D50:D52,"Si")+COUNTIF('BCO COES Integracion'!D50:D52,"Parcial")+COUNTIF('BCO COES Integracion'!D50:D52,"No")),0) -> 0.83333333 | E21: =IFERROR((COUNTIF('BCO COES Integracion'!D55:D56,"Sí")+COUNTIF('BCO COES Integracion'!D55:D56,"Si")+0.5*COUNTIF('BCO COES Integracion'!D55:D56,"Parcial"))/(COUNTIF('BCO COES Integracion'!D55:D56,"Sí")+COUNTIF('BCO COES Integracion'!D55:D56,"Si")+COUNTIF('BCO COES Integracion'!D55:D56,"Parcial")+COUNTIF('BCO COES Integracion'!D55:D56,"No")),0) -> 0.75 | F21: =IFERROR('BCO COES Integracion'!E58,0) -> 0.73529412 | K21: =A21 -> BCO Gioti1 | L21: =B21 -> 0.6 | N21: =A21 -> BCO Gioti1 | O21: =C21 -> 0.78571429 | Q21: =A21 -> BCO Gioti1 | R21: =D21 -> 0.83333333 | T21: =AE7 -> BCO COES Integracion | U21: =AF7 -> 0.73529412 | BO21: D19 | BP21: =Dashboard!O65 -> 1
A22: BCO Gioti2 | B22: =IFERROR((COUNTIF('BCO COES Datos'!D34:D38,"Sí")+COUNTIF('BCO COES Datos'!D34:D38,"Si")+0.5*COUNTIF('BCO COES Datos'!D34:D38,"Parcial"))/(COUNTIF('BCO COES Datos'!D34:D38,"Sí")+COUNTIF('BCO COES Datos'!D34:D38,"Si")+COUNTIF('BCO COES Datos'!D34:D38,"Parcial")+COUNTIF('BCO COES Datos'!D34:D38,"No")),0) -> 0.6 | C22: =IFERROR((COUNTIF('BCO COES Datos'!D41:D47,"Sí")+COUNTIF('BCO COES Datos'!D41:D47,"Si")+0.5*COUNTIF('BCO COES Datos'!D41:D47,"Parcial"))/(COUNTIF('BCO COES Datos'!D41:D47,"Sí")+COUNTIF('BCO COES Datos'!D41:D47,"Si")+COUNTIF('BCO COES Datos'!D41:D47,"Parcial")+COUNTIF('BCO COES Datos'!D41:D47,"No")),0) -> 0.78571429 | D22: =IFERROR((COUNTIF('BCO COES Datos'!D50:D52,"Sí")+COUNTIF('BCO COES Datos'!D50:D52,"Si")+0.5*COUNTIF('BCO COES Datos'!D50:D52,"Parcial"))/(COUNTIF('BCO COES Datos'!D50:D52,"Sí")+COUNTIF('BCO COES Datos'!D50:D52,"Si")+COUNTIF('BCO COES Datos'!D50:D52,"Parcial")+COUNTIF('BCO COES Datos'!D50:D52,"No")),0) -> 0.83333333 | E22: =IFERROR((COUNTIF('BCO COES Datos'!D55:D56,"Sí")+COUNTIF('BCO COES Datos'!D55:D56,"Si")+0.5*COUNTIF('BCO COES Datos'!D55:D56,"Parcial"))/(COUNTIF('BCO COES Datos'!D55:D56,"Sí")+COUNTIF('BCO COES Datos'!D55:D56,"Si")+COUNTIF('BCO COES Datos'!D55:D56,"Parcial")+COUNTIF('BCO COES Datos'!D55:D56,"No")),0) -> 0.75 | F22: =IFERROR('BCO COES Datos'!E58,0) -> 0.73529412 | K22: =A22 -> BCO Gioti2 | L22: =B22 -> 0.6 | N22: =A22 -> BCO Gioti2 | O22: =C22 -> 0.78571429 | Q22: =A22 -> BCO Gioti2 | R22: =D22 -> 0.83333333 | T22: =AE8 -> BCO COES Datos | U22: =AF8 -> 0.73529412 | BO22: D20 | BP22: =Dashboard!O66 -> 11.5
A23: BCO Gioti3 | B23: =IFERROR((COUNTIF('BCO Soporte'!D34:D38,"Sí")+COUNTIF('BCO Soporte'!D34:D38,"Si")+0.5*COUNTIF('BCO Soporte'!D34:D38,"Parcial"))/(COUNTIF('BCO Soporte'!D34:D38,"Sí")+COUNTIF('BCO Soporte'!D34:D38,"Si")+COUNTIF('BCO Soporte'!D34:D38,"Parcial")+COUNTIF('BCO Soporte'!D34:D38,"No")),0) -> 0.6 | C23: =IFERROR((COUNTIF('BCO Soporte'!D41:D47,"Sí")+COUNTIF('BCO Soporte'!D41:D47,"Si")+0.5*COUNTIF('BCO Soporte'!D41:D47,"Parcial"))/(COUNTIF('BCO Soporte'!D41:D47,"Sí")+COUNTIF('BCO Soporte'!D41:D47,"Si")+COUNTIF('BCO Soporte'!D41:D47,"Parcial")+COUNTIF('BCO Soporte'!D41:D47,"No")),0) -> 0.78571429 | D23: =IFERROR((COUNTIF('BCO Soporte'!D50:D52,"Sí")+COUNTIF('BCO Soporte'!D50:D52,"Si")+0.5*COUNTIF('BCO Soporte'!D50:D52,"Parcial"))/(COUNTIF('BCO Soporte'!D50:D52,"Sí")+COUNTIF('BCO Soporte'!D50:D52,"Si")+COUNTIF('BCO Soporte'!D50:D52,"Parcial")+COUNTIF('BCO Soporte'!D50:D52,"No")),0) -> 0.83333333 | E23: =IFERROR((COUNTIF('BCO Soporte'!D55:D56,"Sí")+COUNTIF('BCO Soporte'!D55:D56,"Si")+0.5*COUNTIF('BCO Soporte'!D55:D56,"Parcial"))/(COUNTIF('BCO Soporte'!D55:D56,"Sí")+COUNTIF('BCO Soporte'!D55:D56,"Si")+COUNTIF('BCO Soporte'!D55:D56,"Parcial")+COUNTIF('BCO Soporte'!D55:D56,"No")),0) -> 0.75 | F23: =IFERROR('BCO Soporte'!E58,0) -> 0.73529412 | K23: =A23 -> BCO Gioti3 | L23: =B23 -> 0.6 | N23: =A23 -> BCO Gioti3 | O23: =C23 -> 0.78571429 | Q23: =A23 -> BCO Gioti3 | R23: =D23 -> 0.83333333 | T23: =AE9 -> BCO Soporte | U23: =AF9 -> 0.73529412 | BO23: D21 | BP23: =Dashboard!O67 -> 3
A24: BCO Gioti4 | B24: =IFERROR((COUNTIF('BCO COES Emma'!D34:D38,"Sí")+COUNTIF('BCO COES Emma'!D34:D38,"Si")+0.5*COUNTIF('BCO COES Emma'!D34:D38,"Parcial"))/(COUNTIF('BCO COES Emma'!D34:D38,"Sí")+COUNTIF('BCO COES Emma'!D34:D38,"Si")+COUNTIF('BCO COES Emma'!D34:D38,"Parcial")+COUNTIF('BCO COES Emma'!D34:D38,"No")),0) -> 0.6 | C24: =IFERROR((COUNTIF('BCO COES Emma'!D41:D47,"Sí")+COUNTIF('BCO COES Emma'!D41:D47,"Si")+0.5*COUNTIF('BCO COES Emma'!D41:D47,"Parcial"))/(COUNTIF('BCO COES Emma'!D41:D47,"Sí")+COUNTIF('BCO COES Emma'!D41:D47,"Si")+COUNTIF('BCO COES Emma'!D41:D47,"Parcial")+COUNTIF('BCO COES Emma'!D41:D47,"No")),0) -> 0.78571429 | D24: =IFERROR((COUNTIF('BCO COES Emma'!D50:D52,"Sí")+COUNTIF('BCO COES Emma'!D50:D52,"Si")+0.5*COUNTIF('BCO COES Emma'!D50:D52,"Parcial"))/(COUNTIF('BCO COES Emma'!D50:D52,"Sí")+COUNTIF('BCO COES Emma'!D50:D52,"Si")+COUNTIF('BCO COES Emma'!D50:D52,"Parcial")+COUNTIF('BCO COES Emma'!D50:D52,"No")),0) -> 0.83333333 | E24: =IFERROR((COUNTIF('BCO COES Emma'!D55:D56,"Sí")+COUNTIF('BCO COES Emma'!D55:D56,"Si")+0.5*COUNTIF('BCO COES Emma'!D55:D56,"Parcial"))/(COUNTIF('BCO COES Emma'!D55:D56,"Sí")+COUNTIF('BCO COES Emma'!D55:D56,"Si")+COUNTIF('BCO COES Emma'!D55:D56,"Parcial")+COUNTIF('BCO COES Emma'!D55:D56,"No")),0) -> 0.75 | F24: =IFERROR('BCO COES Emma'!E58,0) -> 0.73529412 | K24: =A24 -> BCO Gioti4 | L24: =B24 -> 0.6 | N24: =A24 -> BCO Gioti4 | O24: =C24 -> 0.78571429 | Q24: =A24 -> BCO Gioti4 | R24: =D24 -> 0.83333333 | T24: =AE10 -> BCO COES Emma | U24: =AF10 -> 0.73529412 | BO24: D22 | BP24: =Dashboard!O68 -> 2.5
A25: AES | B25: =IFERROR((COUNTIF(AES!D33:D37,"Sí")+COUNTIF(AES!D33:D37,"Si")+0.5*COUNTIF(AES!D33:D37,"Parcial"))/(COUNTIF(AES!D33:D37,"Sí")+COUNTIF(AES!D33:D37,"Si")+COUNTIF(AES!D33:D37,"Parcial")+COUNTIF(AES!D33:D37,"No")),0) -> 0.4 | C25: =IFERROR((COUNTIF(AES!D40:D46,"Sí")+COUNTIF(AES!D40:D46,"Si")+0.5*COUNTIF(AES!D40:D46,"Parcial"))/(COUNTIF(AES!D40:D46,"Sí")+COUNTIF(AES!D40:D46,"Si")+COUNTIF(AES!D40:D46,"Parcial")+COUNTIF(AES!D40:D46,"No")),0) -> 0.42857143 | D25: =IFERROR((COUNTIF(AES!D49:D51,"Sí")+COUNTIF(AES!D49:D51,"Si")+0.5*COUNTIF(AES!D49:D51,"Parcial"))/(COUNTIF(AES!D49:D51,"Sí")+COUNTIF(AES!D49:D51,"Si")+COUNTIF(AES!D49:D51,"Parcial")+COUNTIF(AES!D49:D51,"No")),0) -> 0.16666667 | E25: =IFERROR((COUNTIF(AES!D54:D55,"Sí")+COUNTIF(AES!D54:D55,"Si")+0.5*COUNTIF(AES!D54:D55,"Parcial"))/(COUNTIF(AES!D54:D55,"Sí")+COUNTIF(AES!D54:D55,"Si")+COUNTIF(AES!D54:D55,"Parcial")+COUNTIF(AES!D54:D55,"No")),0) -> 0.25 | F25: =IFERROR(AES!E57,0) -> 0.29411765 | K25: =A25 -> AES | L25: =B25 -> 0.4 | N25: =A25 -> AES | O25: =C25 -> 0.42857143 | Q25: =A25 -> AES | R25: =D25 -> 0.16666667 | T25: =AE11 -> BCO Emma Iseries | U25: =AF11 -> 0.73529412 | BO25: D23 | BP25: =Dashboard!O69 -> 5.5
A26: XM | B26: =IFERROR((COUNTIF(XM!D33:D37,"Sí")+COUNTIF(XM!D33:D37,"Si")+0.5*COUNTIF(XM!D33:D37,"Parcial"))/(COUNTIF(XM!D33:D37,"Sí")+COUNTIF(XM!D33:D37,"Si")+COUNTIF(XM!D33:D37,"Parcial")+COUNTIF(XM!D33:D37,"No")),0) -> 0.4 | C26: =IFERROR((COUNTIF(XM!D40:D46,"Sí")+COUNTIF(XM!D40:D46,"Si")+0.5*COUNTIF(XM!D40:D46,"Parcial"))/(COUNTIF(XM!D40:D46,"Sí")+COUNTIF(XM!D40:D46,"Si")+COUNTIF(XM!D40:D46,"Parcial")+COUNTIF(XM!D40:D46,"No")),0) -> 0.5 | D26: =IFERROR((COUNTIF(XM!D49:D51,"Sí")+COUNTIF(XM!D49:D51,"Si")+0.5*COUNTIF(XM!D49:D51,"Parcial"))/(COUNTIF(XM!D49:D51,"Sí")+COUNTIF(XM!D49:D51,"Si")+COUNTIF(XM!D49:D51,"Parcial")+COUNTIF(XM!D49:D51,"No")),0) -> 0.66666667 | E26: =IFERROR((COUNTIF(XM!D54:D55,"Sí")+COUNTIF(XM!D54:D55,"Si")+0.5*COUNTIF(XM!D54:D55,"Parcial"))/(COUNTIF(XM!D54:D55,"Sí")+COUNTIF(XM!D54:D55,"Si")+COUNTIF(XM!D54:D55,"Parcial")+COUNTIF(XM!D54:D55,"No")),0) -> 0.5 | F26: =IFERROR(XM!E57,0) -> 0.5 | K26: =A26 -> XM | L26: =B26 -> 0.4 | N26: =A26 -> XM | O26: =C26 -> 0.5 | Q26: =A26 -> XM | R26: =D26 -> 0.66666667 | T26: =AE12 -> AES | U26: =AF12 -> 0.29411765
A27: MEDICARTE | B27: =IFERROR((COUNTIF(MEDICARTE!D34:D38,"Sí")+COUNTIF(MEDICARTE!D34:D38,"Si")+0.5*COUNTIF(MEDICARTE!D34:D38,"Parcial"))/(COUNTIF(MEDICARTE!D34:D38,"Sí")+COUNTIF(MEDICARTE!D34:D38,"Si")+COUNTIF(MEDICARTE!D34:D38,"Parcial")+COUNTIF(MEDICARTE!D34:D38,"No")),0) -> 0 | C27: =IFERROR((COUNTIF(MEDICARTE!D41:D47,"Sí")+COUNTIF(MEDICARTE!D41:D47,"Si")+0.5*COUNTIF(MEDICARTE!D41:D47,"Parcial"))/(COUNTIF(MEDICARTE!D41:D47,"Sí")+COUNTIF(MEDICARTE!D41:D47,"Si")+COUNTIF(MEDICARTE!D41:D47,"Parcial")+COUNTIF(MEDICARTE!D41:D47,"No")),0) -> 0 | D27: =IFERROR((COUNTIF(MEDICARTE!D50:D52,"Sí")+COUNTIF(MEDICARTE!D50:D52,"Si")+0.5*COUNTIF(MEDICARTE!D50:D52,"Parcial"))/(COUNTIF(MEDICARTE!D50:D52,"Sí")+COUNTIF(MEDICARTE!D50:D52,"Si")+COUNTIF(MEDICARTE!D50:D52,"Parcial")+COUNTIF(MEDICARTE!D50:D52,"No")),0) -> 0 | E27: =IFERROR((COUNTIF(MEDICARTE!D55:D56,"Sí")+COUNTIF(MEDICARTE!D55:D56,"Si")+0.5*COUNTIF(MEDICARTE!D55:D56,"Parcial"))/(COUNTIF(MEDICARTE!D55:D56,"Sí")+COUNTIF(MEDICARTE!D55:D56,"Si")+COUNTIF(MEDICARTE!D55:D56,"Parcial")+COUNTIF(MEDICARTE!D55:D56,"No")),0) -> 0 | F27: =IFERROR(MEDICARTE!E58,0) -> 0 | K27: =A27 -> MEDICARTE | L27: =B27 -> 0 | N27: =A27 -> MEDICARTE | O27: =C27 -> 0 | Q27: =A27 -> MEDICARTE | R27: =D27 -> 0 | T27: =AE13 -> XM | U27: =AF13 -> 0.5
T28: =AE14 -> MEDICARTE | U28: =AF14 -> 0
A29: TABLA 3 — DOLORES ACTIVOS POR MESA
A30: Mesa | B30: D1 Rotación | C30: D2 SLAs | D30: D3 Autoservicio | E30: D4 Herramientas | F30: D5 NPS bajo | G30: D6 Escalamientos | H30: D7 Sin dashboard | I30: Total dolores
A31: SURA Cotizadores | B31: =IF('SURA Cotizadores'!C99="Sí",1,IF('SURA Cotizadores'!C99="Si",1,IF('SURA Cotizadores'!C99="Parcial",0.5,IF('SURA Cotizadores'!C99="No",0,0)))) -> 0.5 | C31: =IF('SURA Cotizadores'!C100="Sí",1,IF('SURA Cotizadores'!C100="Si",1,IF('SURA Cotizadores'!C100="Parcial",0.5,IF('SURA Cotizadores'!C100="No",0,0)))) -> 1 | D31: =IF('SURA Cotizadores'!C101="Sí",1,IF('SURA Cotizadores'!C101="Si",1,IF('SURA Cotizadores'!C101="Parcial",0.5,IF('SURA Cotizadores'!C101="No",0,0)))) -> 1 | E31: =IF('SURA Cotizadores'!C102="Sí",1,IF('SURA Cotizadores'!C102="Si",1,IF('SURA Cotizadores'!C102="Parcial",0.5,IF('SURA Cotizadores'!C102="No",0,0)))) -> 0.5 | F31: =IF('SURA Cotizadores'!C103="Sí",1,IF('SURA Cotizadores'!C103="Si",1,IF('SURA Cotizadores'!C103="Parcial",0.5,IF('SURA Cotizadores'!C103="No",0,0)))) -> 0 | G31: =IF('SURA Cotizadores'!C104="Sí",1,IF('SURA Cotizadores'!C104="Si",1,IF('SURA Cotizadores'!C104="Parcial",0.5,IF('SURA Cotizadores'!C104="No",0,0)))) -> 0.5 | H31: =IF('SURA Cotizadores'!C105="Sí",1,IF('SURA Cotizadores'!C105="Si",1,IF('SURA Cotizadores'!C105="Parcial",0.5,IF('SURA Cotizadores'!C105="No",0,0)))) -> 0.5 | I31: =SUM(B31:H31) -> 4 | K31: Mesa | L31: D4 Valor/Mejora | N31: Mesa | O31: Total dolores D1-D23
A32: SURA Digital Venta | B32: =IF('SURA Digital Venta'!C100="Sí",1,IF('SURA Digital Venta'!C100="Si",1,IF('SURA Digital Venta'!C100="Parcial",0.5,IF('SURA Digital Venta'!C100="No",0,0)))) -> 0.5 | C32: =IF('SURA Digital Venta'!C101="Sí",1,IF('SURA Digital Venta'!C101="Si",1,IF('SURA Digital Venta'!C101="Parcial",0.5,IF('SURA Digital Venta'!C101="No",0,0)))) -> 1 | D32: =IF('SURA Digital Venta'!C102="Sí",1,IF('SURA Digital Venta'!C102="Si",1,IF('SURA Digital Venta'!C102="Parcial",0.5,IF('SURA Digital Venta'!C102="No",0,0)))) -> 1 | E32: =IF('SURA Digital Venta'!C103="Sí",1,IF('SURA Digital Venta'!C103="Si",1,IF('SURA Digital Venta'!C103="Parcial",0.5,IF('SURA Digital Venta'!C103="No",0,0)))) -> 0.5 | F32: =IF('SURA Digital Venta'!C104="Sí",1,IF('SURA Digital Venta'!C104="Si",1,IF('SURA Digital Venta'!C104="Parcial",0.5,IF('SURA Digital Venta'!C104="No",0,0)))) -> 0 | G32: =IF('SURA Digital Venta'!C105="Sí",1,IF('SURA Digital Venta'!C105="Si",1,IF('SURA Digital Venta'!C105="Parcial",0.5,IF('SURA Digital Venta'!C105="No",0,0)))) -> 0.5 | H32: =IF('SURA Digital Venta'!C106="Sí",1,IF('SURA Digital Venta'!C106="Si",1,IF('SURA Digital Venta'!C106="Parcial",0.5,IF('SURA Digital Venta'!C106="No",0,0)))) -> 1 | I32: =SUM(B32:H32) -> 4.5 | K32: =A17 -> SURA Cotizadores | L32: =E17 -> 0.5 | N32: =AS3 -> SURA Cotizadores | O32: =AT3 -> 13
A33: SURA Automatizacion | B33: =IF('SURA Automatizacion'!C100="Sí",1,IF('SURA Automatizacion'!C100="Si",1,IF('SURA Automatizacion'!C100="Parcial",0.5,IF('SURA Automatizacion'!C100="No",0,0)))) -> 0.5 | C33: =IF('SURA Automatizacion'!C101="Sí",1,IF('SURA Automatizacion'!C101="Si",1,IF('SURA Automatizacion'!C101="Parcial",0.5,IF('SURA Automatizacion'!C101="No",0,0)))) -> 0 | D33: =IF('SURA Automatizacion'!C102="Sí",1,IF('SURA Automatizacion'!C102="Si",1,IF('SURA Automatizacion'!C102="Parcial",0.5,IF('SURA Automatizacion'!C102="No",0,0)))) -> 1 | E33: =IF('SURA Automatizacion'!C103="Sí",1,IF('SURA Automatizacion'!C103="Si",1,IF('SURA Automatizacion'!C103="Parcial",0.5,IF('SURA Automatizacion'!C103="No",0,0)))) -> 0.5 | F33: =IF('SURA Automatizacion'!C104="Sí",1,IF('SURA Automatizacion'!C104="Si",1,IF('SURA Automatizacion'!C104="Parcial",0.5,IF('SURA Automatizacion'!C104="No",0,0)))) -> 0 | G33: =IF('SURA Automatizacion'!C105="Sí",1,IF('SURA Automatizacion'!C105="Si",1,IF('SURA Automatizacion'!C105="Parcial",0.5,IF('SURA Automatizacion'!C105="No",0,0)))) -> 0.5 | H33: =IF('SURA Automatizacion'!C106="Sí",1,IF('SURA Automatizacion'!C106="Si",1,IF('SURA Automatizacion'!C106="Parcial",0.5,IF('SURA Automatizacion'!C106="No",0,0)))) -> 1 | I33: =SUM(B33:H33) -> 3.5 | K33: =A18 -> SURA Digital Venta | L33: =E18 -> 0.5 | N33: =AS4 -> SURA Digital Venta | O33: =AT4 -> 12.5
A34: SURA Canales Masivos | B34: =IF('SURA Canales Masivos'!C100="Sí",1,IF('SURA Canales Masivos'!C100="Si",1,IF('SURA Canales Masivos'!C100="Parcial",0.5,IF('SURA Canales Masivos'!C100="No",0,0)))) -> 0.5 | C34: =IF('SURA Canales Masivos'!C101="Sí",1,IF('SURA Canales Masivos'!C101="Si",1,IF('SURA Canales Masivos'!C101="Parcial",0.5,IF('SURA Canales Masivos'!C101="No",0,0)))) -> 1 | D34: =IF('SURA Canales Masivos'!C102="Sí",1,IF('SURA Canales Masivos'!C102="Si",1,IF('SURA Canales Masivos'!C102="Parcial",0.5,IF('SURA Canales Masivos'!C102="No",0,0)))) -> 1 | E34: =IF('SURA Canales Masivos'!C103="Sí",1,IF('SURA Canales Masivos'!C103="Si",1,IF('SURA Canales Masivos'!C103="Parcial",0.5,IF('SURA Canales Masivos'!C103="No",0,0)))) -> 0.5 | F34: =IF('SURA Canales Masivos'!C104="Sí",1,IF('SURA Canales Masivos'!C104="Si",1,IF('SURA Canales Masivos'!C104="Parcial",0.5,IF('SURA Canales Masivos'!C104="No",0,0)))) -> 0 | G34: =IF('SURA Canales Masivos'!C105="Sí",1,IF('SURA Canales Masivos'!C105="Si",1,IF('SURA Canales Masivos'!C105="Parcial",0.5,IF('SURA Canales Masivos'!C105="No",0,0)))) -> 0.5 | H34: =IF('SURA Canales Masivos'!C106="Sí",1,IF('SURA Canales Masivos'!C106="Si",1,IF('SURA Canales Masivos'!C106="Parcial",0.5,IF('SURA Canales Masivos'!C106="No",0,0)))) -> 0.5 | I34: =SUM(B34:H34) -> 4 | K34: =A19 -> SURA Automatizacion | L34: =E19 -> 0.5 | N34: =AS5 -> SURA Automatizacion | O34: =AT5 -> 11
A35: BCO Gioti1 | B35: =IF('BCO COES Integracion'!C101="Sí",1,IF('BCO COES Integracion'!C101="Si",1,IF('BCO COES Integracion'!C101="Parcial",0.5,IF('BCO COES Integracion'!C101="No",0,0)))) -> 0.5 | C35: =IF('BCO COES Integracion'!C102="Sí",1,IF('BCO COES Integracion'!C102="Si",1,IF('BCO COES Integracion'!C102="Parcial",0.5,IF('BCO COES Integracion'!C102="No",0,0)))) -> 0 | D35: =IF('BCO COES Integracion'!C103="Sí",1,IF('BCO COES Integracion'!C103="Si",1,IF('BCO COES Integracion'!C103="Parcial",0.5,IF('BCO COES Integracion'!C103="No",0,0)))) -> 0.5 | E35: =IF('BCO COES Integracion'!C104="Sí",1,IF('BCO COES Integracion'!C104="Si",1,IF('BCO COES Integracion'!C104="Parcial",0.5,IF('BCO COES Integracion'!C104="No",0,0)))) -> 0 | F35: =IF('BCO COES Integracion'!C105="Sí",1,IF('BCO COES Integracion'!C105="Si",1,IF('BCO COES Integracion'!C105="Parcial",0.5,IF('BCO COES Integracion'!C105="No",0,0)))) -> 0 | G35: =IF('BCO COES Integracion'!C106="Sí",1,IF('BCO COES Integracion'!C106="Si",1,IF('BCO COES Integracion'!C106="Parcial",0.5,IF('BCO COES Integracion'!C106="No",0,0)))) -> 0 | H35: =IF('BCO COES Integracion'!C107="Sí",1,IF('BCO COES Integracion'!C107="Si",1,IF('BCO COES Integracion'!C107="Parcial",0.5,IF('BCO COES Integracion'!C107="No",0,0)))) -> 0 | I35: =SUM(B35:H35) -> 1 | K35: =A20 -> SURA Canales Masivos | L35: =E20 -> 0.5 | N35: =AS6 -> SURA Canales Masivos | O35: =AT6 -> 13
A36: BCO Gioti2 | B36: =IF('BCO COES Datos'!C101="Sí",1,IF('BCO COES Datos'!C101="Si",1,IF('BCO COES Datos'!C101="Parcial",0.5,IF('BCO COES Datos'!C101="No",0,0)))) -> 0.5 | C36: =IF('BCO COES Datos'!C102="Sí",1,IF('BCO COES Datos'!C102="Si",1,IF('BCO COES Datos'!C102="Parcial",0.5,IF('BCO COES Datos'!C102="No",0,0)))) -> 0 | D36: =IF('BCO COES Datos'!C103="Sí",1,IF('BCO COES Datos'!C103="Si",1,IF('BCO COES Datos'!C103="Parcial",0.5,IF('BCO COES Datos'!C103="No",0,0)))) -> 0.5 | E36: =IF('BCO COES Datos'!C104="Sí",1,IF('BCO COES Datos'!C104="Si",1,IF('BCO COES Datos'!C104="Parcial",0.5,IF('BCO COES Datos'!C104="No",0,0)))) -> 0 | F36: =IF('BCO COES Datos'!C105="Sí",1,IF('BCO COES Datos'!C105="Si",1,IF('BCO COES Datos'!C105="Parcial",0.5,IF('BCO COES Datos'!C105="No",0,0)))) -> 0 | G36: =IF('BCO COES Datos'!C106="Sí",1,IF('BCO COES Datos'!C106="Si",1,IF('BCO COES Datos'!C106="Parcial",0.5,IF('BCO COES Datos'!C106="No",0,0)))) -> 0 | H36: =IF('BCO COES Datos'!C107="Sí",1,IF('BCO COES Datos'!C107="Si",1,IF('BCO COES Datos'!C107="Parcial",0.5,IF('BCO COES Datos'!C107="No",0,0)))) -> 0 | I36: =SUM(B36:H36) -> 1 | K36: =A21 -> BCO Gioti1 | L36: =E21 -> 0.75 | N36: =AS7 -> BCO COES Integracion | O36: =AT7 -> 9.5
A37: BCO Gioti3 | B37: =IF('BCO Soporte'!C102="Sí",1,IF('BCO Soporte'!C102="Si",1,IF('BCO Soporte'!C102="Parcial",0.5,IF('BCO Soporte'!C102="No",0,0)))) -> 0 | C37: =IF('BCO Soporte'!C103="Sí",1,IF('BCO Soporte'!C103="Si",1,IF('BCO Soporte'!C103="Parcial",0.5,IF('BCO Soporte'!C103="No",0,0)))) -> 0.5 | D37: =IF('BCO Soporte'!C104="Sí",1,IF('BCO Soporte'!C104="Si",1,IF('BCO Soporte'!C104="Parcial",0.5,IF('BCO Soporte'!C104="No",0,0)))) -> 0 | E37: =IF('BCO Soporte'!C105="Sí",1,IF('BCO Soporte'!C105="Si",1,IF('BCO Soporte'!C105="Parcial",0.5,IF('BCO Soporte'!C105="No",0,0)))) -> 0 | F37: =IF('BCO Soporte'!C106="Sí",1,IF('BCO Soporte'!C106="Si",1,IF('BCO Soporte'!C106="Parcial",0.5,IF('BCO Soporte'!C106="No",0,0)))) -> 0 | G37: =IF('BCO Soporte'!C107="Sí",1,IF('BCO Soporte'!C107="Si",1,IF('BCO Soporte'!C107="Parcial",0.5,IF('BCO Soporte'!C107="No",0,0)))) -> 0 | H37: =IF('BCO Soporte'!C108="Sí",1,IF('BCO Soporte'!C108="Si",1,IF('BCO Soporte'!C108="Parcial",0.5,IF('BCO Soporte'!C108="No",0,0)))) -> 0.5 | I37: =SUM(B37:H37) -> 1 | K37: =A22 -> BCO Gioti2 | L37: =E22 -> 0.75 | N37: =AS8 -> BCO COES Datos | O37: =AT8 -> 9.5
A38: BCO Gioti4 | B38: =IF('BCO COES Emma'!C101="Sí",1,IF('BCO COES Emma'!C101="Si",1,IF('BCO COES Emma'!C101="Parcial",0.5,IF('BCO COES Emma'!C101="No",0,0)))) -> 0.5 | C38: =IF('BCO COES Emma'!C102="Sí",1,IF('BCO COES Emma'!C102="Si",1,IF('BCO COES Emma'!C102="Parcial",0.5,IF('BCO COES Emma'!C102="No",0,0)))) -> 0 | D38: =IF('BCO COES Emma'!C103="Sí",1,IF('BCO COES Emma'!C103="Si",1,IF('BCO COES Emma'!C103="Parcial",0.5,IF('BCO COES Emma'!C103="No",0,0)))) -> 0.5 | E38: =IF('BCO COES Emma'!C104="Sí",1,IF('BCO COES Emma'!C104="Si",1,IF('BCO COES Emma'!C104="Parcial",0.5,IF('BCO COES Emma'!C104="No",0,0)))) -> 0 | F38: =IF('BCO COES Emma'!C105="Sí",1,IF('BCO COES Emma'!C105="Si",1,IF('BCO COES Emma'!C105="Parcial",0.5,IF('BCO COES Emma'!C105="No",0,0)))) -> 0 | G38: =IF('BCO COES Emma'!C106="Sí",1,IF('BCO COES Emma'!C106="Si",1,IF('BCO COES Emma'!C106="Parcial",0.5,IF('BCO COES Emma'!C106="No",0,0)))) -> 0 | H38: =IF('BCO COES Emma'!C107="Sí",1,IF('BCO COES Emma'!C107="Si",1,IF('BCO COES Emma'!C107="Parcial",0.5,IF('BCO COES Emma'!C107="No",0,0)))) -> 0 | I38: =SUM(B38:H38) -> 1 | K38: =A23 -> BCO Gioti3 | L38: =E23 -> 0.75 | N38: =AS9 -> BCO Soporte | O38: =AT9 -> 9
A39: AES | B39: =IF(AES!C98="Sí",1,IF(AES!C98="Si",1,IF(AES!C98="Parcial",0.5,IF(AES!C98="No",0,0)))) -> 0 | C39: =IF(AES!C99="Sí",1,IF(AES!C99="Si",1,IF(AES!C99="Parcial",0.5,IF(AES!C99="No",0,0)))) -> 0 | D39: =IF(AES!C100="Sí",1,IF(AES!C100="Si",1,IF(AES!C100="Parcial",0.5,IF(AES!C100="No",0,0)))) -> 0 | E39: =IF(AES!C101="Sí",1,IF(AES!C101="Si",1,IF(AES!C101="Parcial",0.5,IF(AES!C101="No",0,0)))) -> 0.5 | F39: =IF(AES!C102="Sí",1,IF(AES!C102="Si",1,IF(AES!C102="Parcial",0.5,IF(AES!C102="No",0,0)))) -> 0 | G39: =IF(AES!C103="Sí",1,IF(AES!C103="Si",1,IF(AES!C103="Parcial",0.5,IF(AES!C103="No",0,0)))) -> 0.5 | H39: =IF(AES!C104="Sí",1,IF(AES!C104="Si",1,IF(AES!C104="Parcial",0.5,IF(AES!C104="No",0,0)))) -> 0 | I39: =SUM(B39:H39) -> 1 | K39: =A24 -> BCO Gioti4 | L39: =E24 -> 0.75 | N39: =AS10 -> BCO COES Emma | O39: =AT10 -> 9.5
A40: XM | B40: =IF(XM!C100="Sí",1,IF(XM!C100="Si",1,IF(XM!C100="Parcial",0.5,IF(XM!C100="No",0,0)))) -> 0.5 | C40: =IF(XM!C101="Sí",1,IF(XM!C101="Si",1,IF(XM!C101="Parcial",0.5,IF(XM!C101="No",0,0)))) -> 0 | D40: =IF(XM!C102="Sí",1,IF(XM!C102="Si",1,IF(XM!C102="Parcial",0.5,IF(XM!C102="No",0,0)))) -> 1 | E40: =IF(XM!C103="Sí",1,IF(XM!C103="Si",1,IF(XM!C103="Parcial",0.5,IF(XM!C103="No",0,0)))) -> 0.5 | F40: =IF(XM!C104="Sí",1,IF(XM!C104="Si",1,IF(XM!C104="Parcial",0.5,IF(XM!C104="No",0,0)))) -> 0 | G40: =IF(XM!C105="Sí",1,IF(XM!C105="Si",1,IF(XM!C105="Parcial",0.5,IF(XM!C105="No",0,0)))) -> 0.5 | H40: =IF(XM!C106="Sí",1,IF(XM!C106="Si",1,IF(XM!C106="Parcial",0.5,IF(XM!C106="No",0,0)))) -> 1 | I40: =SUM(B40:H40) -> 3.5 | K40: =A25 -> AES | L40: =E25 -> 0.25 | N40: =AS11 -> BCO Emma Iseries | O40: =AT11 -> 2
A41: MEDICARTE | B41: =IF(MEDICARTE!C101="Sí",1,IF(MEDICARTE!C101="Si",1,IF(MEDICARTE!C101="Parcial",0.5,IF(MEDICARTE!C101="No",0,0)))) -> 0 | C41: =IF(MEDICARTE!C102="Sí",1,IF(MEDICARTE!C102="Si",1,IF(MEDICARTE!C102="Parcial",0.5,IF(MEDICARTE!C102="No",0,0)))) -> 0 | D41: =IF(MEDICARTE!C103="Sí",1,IF(MEDICARTE!C103="Si",1,IF(MEDICARTE!C103="Parcial",0.5,IF(MEDICARTE!C103="No",0,0)))) -> 0 | E41: =IF(MEDICARTE!C104="Sí",1,IF(MEDICARTE!C104="Si",1,IF(MEDICARTE!C104="Parcial",0.5,IF(MEDICARTE!C104="No",0,0)))) -> 0 | F41: =IF(MEDICARTE!C105="Sí",1,IF(MEDICARTE!C105="Si",1,IF(MEDICARTE!C105="Parcial",0.5,IF(MEDICARTE!C105="No",0,0)))) -> 0 | G41: =IF(MEDICARTE!C106="Sí",1,IF(MEDICARTE!C106="Si",1,IF(MEDICARTE!C106="Parcial",0.5,IF(MEDICARTE!C106="No",0,0)))) -> 0 | H41: =IF(MEDICARTE!C107="Sí",1,IF(MEDICARTE!C107="Si",1,IF(MEDICARTE!C107="Parcial",0.5,IF(MEDICARTE!C107="No",0,0)))) -> 0 | I41: =SUM(B41:H41) -> 0 | K41: =A26 -> XM | L41: =E26 -> 0.5 | N41: =AS12 -> AES | O41: =AT12 -> 7
A42: Total por dolor (todas mesas) | B42: =SUM(B31:B41) -> 4 | C42: =SUM(C31:C41) -> 3.5 | D42: =SUM(D31:D41) -> 6.5 | E42: =SUM(E31:E41) -> 3 | F42: =SUM(F31:F41) -> 0 | G42: =SUM(G31:G41) -> 3 | H42: =SUM(H31:H41) -> 4.5 | I42: =SUM(I31:I41) -> 24.5 | K42: =A27 -> MEDICARTE | L42: =E27 -> 0 | N42: =AS13 -> XM | O42: =AT13 -> 16
N43: =AS14 -> MEDICARTE | O43: =AT14 -> 1
A44: TABLA 4 — PROMEDIO DIMENSIONES POR CLIENTE / GRUPO
A45: Dimensión | B45: SURA | C45: BCO | D45: AES | E45: XM | F45: MEDICARTE | G45: Meta (100%)
A46: D1 Org/Personas | B46: =IFERROR(AVERAGE(B17:B20),0) -> 0.375 | C46: =IFERROR(AVERAGE(B21:B24),0) -> 0.6 | D46: =B25 -> 0.4 | E46: =B26 -> 0.4 | F46: =B27 -> 0 | G46: =100% -> 1
A47: D2 Info/Tecnología | B47: =IFERROR(AVERAGE(C17:C20),0) -> 0.625 | C47: =IFERROR(AVERAGE(C21:C24),0) -> 0.78571429 | D47: =C25 -> 0.42857143 | E47: =C26 -> 0.5 | F47: =C27 -> 0 | G47: =100% -> 1
A48: D3 Socios/Proveed. | B48: =IFERROR(AVERAGE(D17:D20),0) -> 0.83333333 | C48: =IFERROR(AVERAGE(D21:D24),0) -> 0.83333333 | D48: =D25 -> 0.16666667 | E48: =D26 -> 0.66666667 | F48: =D27 -> 0 | G48: =100% -> 1
A49: D4 Valor/Mejora | B49: =IFERROR(AVERAGE(E17:E20),0) -> 0.5 | C49: =IFERROR(AVERAGE(E21:E24),0) -> 0.75 | D49: =E25 -> 0.25 | E49: =E26 -> 0.5 | F49: =E27 -> 0 | G49: =100% -> 1
A51: TABLA 5 — KPI BENCHMARK INDUSTRIA vs MESAS
A52: KPI | B52: Benchmark Industria | C52: Objetivo Gen Next | D52: Promedio Mesas Actuales
A53: FCR (%) | B53: =75% -> 0.75 | C53: =85% -> 0.85 | D53: =IFERROR(AVERAGE('SURA Cotizadores'!C66,'SURA Digital Venta'!C67,'SURA Automatizacion'!C67,'SURA Canales Masivos'!C67,'BCO COES Integracion'!C68,'BCO COES Datos'!C68,'BCO Soporte'!C68,'BCO COES Emma'!C68,AES!C65,XM!C67,MEDICARTE!C68),0) -> 0.68
A54: SLA Cumplimiento (%) | B54: =95% -> 0.95 | C54: =98% -> 0.98 | D54: =IFERROR(AVERAGE('SURA Cotizadores'!C68,'SURA Digital Venta'!C69,'SURA Automatizacion'!C69,'SURA Canales Masivos'!C69,'BCO COES Integracion'!C70,'BCO COES Datos'!C70,'BCO Soporte'!C70,'BCO COES Emma'!C70,AES!C67,XM!C69,MEDICARTE!C70),0) -> 0.806
A55: NPS | B55: =45 -> 45 | C55: =65 -> 65 | D55: =IFERROR(AVERAGE('SURA Cotizadores'!C89,'SURA Digital Venta'!C90,'SURA Automatizacion'!C90,'SURA Canales Masivos'!C90,'BCO COES Integracion'!C91,'BCO COES Datos'!C91,'BCO Soporte'!C91,'BCO COES Emma'!C91,AES!C88,XM!C90,MEDICARTE!C91),0) -> 0
A56: Rotación anual (%) | B56: =15% -> 0.15 | C56: =8% -> 0.08 | D56: =IFERROR(AVERAGE(IF('SURA Cotizadores'!C125>1,'SURA Cotizadores'!C125/100,'SURA Cotizadores'!C125),IF('SURA Digital Venta'!C125>1,'SURA Digital Venta'!C125/100,'SURA Digital Venta'!C125),IF('SURA Automatizacion'!C125>1,'SURA Automatizacion'!C125/100,'SURA Automatizacion'!C125),IF('SURA Canales Masivos'!C125>1,'SURA Canales Masivos'!C125/100,'SURA Canales Masivos'!C125),IF('BCO COES Integracion'!C126>1,'BCO COES Integracion'!C126/100,'BCO COES Integracion'!C126),IF('BCO COES Datos'!C126>1,'BCO COES Datos'!C126/100,'BCO COES Datos'!C126),IF('BCO Soporte'!C127>1,'BCO Soporte'!C127/100,'BCO Soporte'!C127),IF('BCO COES Emma'!C126>1,'BCO COES Emma'!C126/100,'BCO COES Emma'!C126),IF(AES!C123>1,AES!C123/100,AES!C123),IF(XM!C125>1,XM!C125/100,XM!C125),IF(MEDICARTE!C126>1,MEDICARTE!C126/100,MEDICARTE!C126)),0) -> 0
A57: % Autoservicio | B57: =20% -> 0.2 | C57: =40% -> 0.4 | D57: =IFERROR(AVERAGE(IF('SURA Cotizadores'!C73>1,'SURA Cotizadores'!C73/100,'SURA Cotizadores'!C73),IF('SURA Digital Venta'!C74>1,'SURA Digital Venta'!C74/100,'SURA Digital Venta'!C74),IF('SURA Automatizacion'!C74>1,'SURA Automatizacion'!C74/100,'SURA Automatizacion'!C74),IF('SURA Canales Masivos'!C74>1,'SURA Canales Masivos'!C74/100,'SURA Canales Masivos'!C74),IF('BCO COES Integracion'!C75>1,'BCO COES Integracion'!C75/100,'BCO COES Integracion'!C75),IF('BCO COES Datos'!C75>1,'BCO COES Datos'!C75/100,'BCO COES Datos'!C75),IF('BCO Soporte'!C75>1,'BCO Soporte'!C75/100,'BCO Soporte'!C75),IF('BCO COES Emma'!C75>1,'BCO COES Emma'!C75/100,'BCO COES Emma'!C75),IF(AES!C72>1,AES!C72/100,AES!C72),IF(XM!C74>1,XM!C74/100,XM!C74),IF(MEDICARTE!C75>1,MEDICARTE!C75/100,MEDICARTE!C75)),0) -> 0.013333333
A58: Costo/ticket (USD) | B58: =15 -> 15 | C58: =8 -> 8 | D58: =IFERROR(AVERAGE('SURA Cotizadores'!C71,'SURA Digital Venta'!C72,'SURA Automatizacion'!C72,'SURA Canales Masivos'!C72,'BCO COES Integracion'!C73,'BCO COES Datos'!C73,'BCO Soporte'!C73,'BCO COES Emma'!C73,AES!C70,XM!C72,MEDICARTE!C73),0) -> 0

Sheet Listas
B2: LISTAS DE VALIDACIÓN (no modificar)
B4: Respuestas Prácticas | D4: Nivel Madurez | F4: Criticidad Dolor | H4: Modelo Contrato | J4: Tipo Incidente | L4: Riesgo Churn | N4: Cliente | P4: Prioridad | R4: Integrado
B5: Sí | D5: N0 | F5: Alta | H5: FTE dedicado | J5: Incidente | L5: Alto | N5: SURA | P5: Alta | R5: Si
H6: Staffing
B7: Parcial | D7: N1 | F7: Media | H7: Capacidad | J7: Requerimiento | L7: Medio | N7: Bancolombia | P7: Media | R7: No
B8: No | D8: N2 | F8: Baja | H8: Bolsa de horas | J8: Cambio | L8: Bajo | N8: XM | P8: Baja | R8: En proceso
B9: N/A | D9: N3 | H9: Output/ticket | J9: Problema | N9: AES | P9: Sin prioridad
D10: N4 | H10: Mixto | J10: Consulta | N10: MEDICARTE
B11: Misión Principal | D11: N5
B12: Call Center ->Manejar grandes volúmenes de llamadas; filtrar y derivar
B13: Help Desk (Reactivo) -> Coordinación para la restauración del servicio. Infraestructura, herramientas de seguimiento, base de conocimiento
B14: Help Desk -> Service Desk (híbrido)
B15: Service Desk ->Servicio integral: incidentes, solicitudes, consultas, altas/bajas/cambios
B16: Service Desk + Problem Management
B17: Otro
B20: Herramientas ITSM | D20: Herramientas Monitoreo y observabilidad | F20: Herramientas de Chat / Bot de autoservicio | H20: Herramientas de Analítica / Dashboard / BI | J20: Herramientas de Colaboración (Teams, Slack, etc.) | L20: Herramientas de Gestión de identidades / IAM | N20: Herramientas de CMDB / Inventario de activos | P20: Herramientas de Base de conocimiento (KB)
B21: ServiceNow ITSM → Plataforma ITSM empresarial, muy personalizable. (24x7 o según SLA) | D21: AppDynamics → Monitoreo de rendimiento de aplicaciones (APM) y experiencia de usuario. | F21: Ada → Bot conversacional para atención al cliente y soporte automatizado. | H21: Azure Monitor Workbooks → Creación de dashboards y reportes para métricas en Azure. | J21: Asana → Gestión de tareas y proyectos con enfoque en equipos ágiles. | L21: AWS IAM → Gestión de identidades y accesos para servicios en AWS. | N21: BMC Atrium CMDB → Base de datos de configuración empresarial integrada con BMC Helix ITSM. | P21: BookStack → Plataforma open source para crear y organizar documentación en formato libro.
B22: Jira Service Management → Integración con desarrollo ágil y soporte TI. (8x5 o 24x7) | D22: AWS CloudWatch → Monitoreo, métricas y alertas para entornos AWS. | F22: Amelia → Asistente virtual con IA para soporte, RRHH y procesos empresariales. | H22: Datadog Dashboards → Visualización de métricas, logs y trazas en Datadog. | J22: ClickUp → Plataforma de productividad y gestión de proyectos todo-en-uno. | L22: Azure AD B2C → Gestión de identidades para aplicaciones orientadas a clientes en Azure. | N22: Device42 → Descubrimiento automático y gestión de activos de TI y dependencias. | P22: Confluence → Herramienta de documentación y colaboración de Atlassian, ideal para KB interna.
B23: BMC Helix ITSM → Gestión de servicios TI robusta, orientada a grandes organizaciones. (24x7 o 8x5) | D23: Azure Monitor → Observabilidad y métricas para entornos Microsoft Azure. | F23: Azure Bot Service → Plataforma de Microsoft para crear y desplegar bots en múltiples canales. | H23: Elastic Kibana → Visualización y análisis de datos de Elastic Stack. | J23: Confluence → Herramienta de documentación y colaboración en equipo de Atlassian. | L23: BeyondTrust → Gestión de accesos privilegiados (PAM) y control de sesiones. | N23: Freshservice Asset Management → Gestión de activos integrada en la plataforma Freshservice. | P23: Document360 → Plataforma de KB para clientes y equipos, con control de versiones.
B24: ManageEngine ServiceDesk Plus → ITSM con módulos de activos y CMDB. (8x5 o 24x7) | D24: Datadog → Monitoreo en la nube para infraestructura, logs, APM y seguridad. | F24: Botpress → Framework open source para desarrollar chatbots personalizados. | H24: Excel / Power Query → Análisis, transformación y modelado de datos en Microsoft Excel. | J24: Google Chat → Mensajería y colaboración integrada en Google Workspace. | L24: CyberArk → Plataforma líder en gestión de accesos privilegiados y credenciales. | N24: GLPI Assets → Módulo de gestión de activos e inventario de GLPI. | P24: Freshservice Knowledge Base → Módulo de KB integrado en Freshservice para autoservicio ITSM.
B25: Freshservice → ITSM en la nube, fácil de implementar. (8x5 o 24x7) | D25: Dynatrace → Observabilidad con IA para aplicaciones, microservicios y experiencia digital. | F25: ChatGPT / Copilot personalizado → Asistente conversacional con IA generativa y personalización de respuestas. | H25: Google Looker → Plataforma de BI y análisis de datos en la nube. | J25: Jira Software → Gestión de proyectos ágiles y seguimiento de incidencias. | L25: Duo Security → Autenticación multifactor (MFA) y verificación de identidad. | N25: iTop CMDB → Solución open source para CMDB y gestión de servicios. | P25: Google Sites → Creación sencilla de sitios web y KB internas en Google Workspace.
B26: Zendesk Support → Soporte multicanal, orientado a experiencia de cliente. (8x5 o 24x7) | D26: Elastic Observability → Monitoreo y análisis de logs con Elastic Stack (Elasticsearch, Kibana, Beats). | F26: Cognigy → Plataforma de automatización conversacional para empresas. | H26: Grafana → Visualización de métricas y datos en tiempo real desde múltiples fuentes. | J26: Microsoft Teams → Comunicación, videollamadas y colaboración empresarial. | L26: ForgeRock → Plataforma IAM para empresas con gestión de identidades y accesos. | N26: Ivanti Neurons for Discovery → Descubrimiento y mapeo automático de activos y dependencias. | P26: Guru → Plataforma de KB con enfoque en gestión del conocimiento en tiempo real.
B27: GLPI → Solución ITSM de código abierto, flexible y gratuita. (8x5 o 24x7) | D27: Google Cloud Operations → Observabilidad y monitoreo para entornos Google Cloud. | F27: Freshservice Freddy AI → Bot de soporte integrado en Freshservice para ITSM. | H27: Jira Dashboards → Paneles para seguimiento de proyectos, incidencias y métricas ágiles. | J27: Miro → Pizarra colaborativa online para trabajo visual en equipo. | L27: Google Cloud Identity → Gestión de usuarios, dispositivos y accesos en Google Cloud. | N27: Jira Assets / Insight → Gestión de activos y CMDB integrada en Jira Service Management. | P27: Helpjuice → KB para clientes y equipos, con analítica de uso.
B28: OTRS / Znuny → ITSM open source con alta capacidad de personalización. (8x5 o 24x7) | D28: Grafana / Prometheus → Recolección de métricas (Prometheus) y visualización en tiempo real (Grafana). | F28: Google Dialogflow → Creación de bots con procesamiento de lenguaje natural (NLP). | H28: Looker Studio → Creación de reportes y dashboards interactivos de Google. | J28: Monday.com → Gestión de proyectos y flujos de trabajo personalizables. | L28: IBM Security Verify → IAM con SSO, MFA y gestión de identidades en la nube. | N28: Lansweeper → Inventario y descubrimiento de hardware y software en red. | P28: Jira Service Management KB → Base de conocimiento integrada con el portal de soporte de Jira.
B29: Ivanti Neurons for ITSM → ITSM con automatización y gestión proactiva. (8x5 o 24x7) | D29: LogicMonitor → Monitoreo de infraestructura híbrida, nube y redes. | F29: IBM Watson Assistant → Asistente virtual con IA de IBM para soporte y autoservicio. | H29: ManageEngine Analytics Plus → BI y analítica para ITSM y operaciones. | J29: Notion → Documentación, bases de datos y colaboración en un solo espacio. | L29: Keycloak → Solución open source para SSO, autenticación y autorización. | N29: ManageEngine AssetExplorer → Gestión de activos de TI y ciclo de vida. | P29: MediaWiki → Plataforma wiki open source (usada por Wikipedia) para documentación colaborativa.
B30: Cherwell Service Management → Plataforma ITSM adaptable, orientada a medianas y grandes empresas. (8x5 o 24x7) | D30: Nagios → Monitoreo de red, servidores y servicios críticos. | F30: Intercom Fin → Bot de soporte y ventas con IA. | H30: MicroStrategy → Plataforma de BI empresarial con analítica avanzada. | J30: Planner → Planificación y seguimiento de tareas en Microsoft 365. | L30: ManageEngine ADManager Plus → Administración y reportes para Active Directory. | N30: Microsoft Intune → Gestión de dispositivos y aplicaciones en la nube. | P30: Microsoft Viva Topics → Organización automática de conocimiento en Microsoft 365.
B31: Aranda Service Management → ITSM popular en Latinoamérica, con módulos integrados. (8x5 o 24x7) | D31: New Relic → Observabilidad para aplicaciones, infraestructura y experiencia de usuario. | F31: Kore.ai → Plataforma de bots empresariales con IA conversacional. | H31: Power BI → BI y visualización de datos de Microsoft, con integración a múltiples fuentes. | J31: SharePoint → Gestión documental y colaboración en entornos Microsoft. | L31: Microsoft Entra ID → Plataforma de identidad de Microsoft (antes Azure AD) con SSO y MFA. | N31: OCS Inventory → Inventario de hardware y software open source. | P31: Notion → Herramienta de documentación, bases de datos y colaboración flexible.
... B35: Microsoft Dynamics 365 Customer Service → Soporte y atención al cliente integrado con CRM. (8x5 o 24x7) | D35: Zabbix → Monitoreo de red, servidores y aplicaciones con alertas configurables. | F35: Zendesk Answer Bot → Bot de soporte integrado en Zendesk para resolver tickets automáticamente. | H35: Tableau → Visualización y análisis de datos con enfoque en exploración interactiva. | J35: Zoom → Videoconferencias, webinars y colaboración remota. | L35: SailPoint → Gestión de identidades y gobierno de accesos (IGA). | N35: Snipe-IT → Gestión de activos de TI open source, ideal para control de inventario. | P35: Zendesk Guide → KB para autoservicio de clientes integrada con Zendesk Support.
B44: NPS (Net Promoter Score) | D44: CSAT (Satisfacción del cliente) — escala 1-5 | F44: CES (Customer Effort Score) | H44: Cantidad de Quejas escaladas / mes | J44: Tiempo promedio de espera en canal (minutos)
B45: No Aplica | D45: 5 Muy satisfecho - Experiencia excelente, superó expectativas. | F45: No Aplica | H45: 0-20 Bajo - Nivel de quejas controlado. | J45: 0-2 minutos → Excelente - Atención casi inmediata.
B46: 9-10 Promotor - Cliente muy satisfecho y leal. Recomienda activamente. | D46: 4 Satisfecho - Buena experiencia, cumplió expectativas. | F46: 7 Muy fácil - Casi sin esfuerzo para resolver la necesidad. | H46: 21-50 Medio - Atención necesaria para evitar aumento. | J46: 3-5 minutos → Bueno - Tiempo de espera aceptable.
B47: 7-8 Pasivo - Cliente satisfecho pero sin entusiasmo. | D47: 3 Neutral - Experiencia aceptable, sin destacar. | F47: 6 Fácil - Requirió poco esfuerzo. | H47: 51-100 Alto - Requiere acciones correctivas urgentes. | J47: 6-10 minutos → Regular - Puede generar ligera incomodidad.
B48: 0-6 Detractor - Cliente insatisfecho, riesgo de comentarios negativos. | D48: 2 Insatisfecho - Experiencia por debajo de lo esperado. | F48: 5 Algo fácil - Ligero esfuerzo, sin complicaciones. | H48: Más de 100 Crítico - Situación grave, intervención inmediata. | J48: 11-20 minutos → Malo - Riesgo de insatisfacción del cliente.
D49: 1 Muy insatisfecho - Experiencia muy negativa. | F49: 4 Neutral - Esfuerzo moderado. | J49: Más de 20 minutos → Crítico - Experiencia muy negativa, requiere acción urgente.
F50: 3 Algo difícil - Requirió atención y tiempo extra.
F51: 2 Difícil - Mucho esfuerzo para lograrlo.
B52: Disponibilidad | F52: 1 Muy difícil - Experiencia frustrante y complicada.
B53: 24x7 → 168 horas/semana
B54: 8x5 → 40 horas/semana
B55: 12x6 → 72 horas/semana
B56: 16x5 → 80 horas/semana
B57: 10x7 → 70 horas/semana
B58: Otra

Sheet Metricas bancolombia
A1: MÉTRICA | B1: Detalle | C1: Valor Actual
A2: Cantidad de Tickets / mes (total) | B2: Dependiendo la Coes apróximadamente entre 700 a 3,000 tickets | C2: No manejo esta información
A3: Cantidad de Incidentes / mes | B3: Entre 50 a 100 | C3: No manejo esta información
A4: Cantidad de Requerimientos / mes | B4: N.a | C4: No manejo esta información
A5: Cambios / mes | B5: N.a | C5: No manejo esta información
A6: First Call Resolution (FCR %) | B6: Pendiente revisar líderes técnicos | C6: No manejo esta información
A7: Mean Time to Resolve (MTTR horas) | B7: Entre 30 minutos a 3 horas (mesas)/ Dispos | C7: No manejo esta información
A8: SLA Cumplimiento (%) | B8: No aplica SLA- ANS del Banco y de COES | C8: No manejo esta información
A9: Backlog promedio (tickets abiertos) | B9: No manejamos Baclog- herramienta Helix (Bancolombia) si es un ticket del equipo no supera 12 horas abierto, si es un ticket con dependencia de otra área puede durar entre 8 o 15 días abierto | C9: No manejo esta información
A10: Tickets resueltos por agente/mes | B10: Promedio entre 80 a 250 casos (depende del equipo COES) | C10: No manejo esta información
A11: Costo estimado por ticket (USD) | B11: No manejo esa información | C11: No manejo esta información
A12: Agentes FTE totales | B12: "​ 32 colaboradores​​ Coes integración: 7 ​​+2 Coes Emma: 4​​ Emma Iseries: 1​​ Coes Soporte: 13​​ Coes Datos: 7" | C12: No manejo esta información
A13: % Tickets autoservicio / N0 | C13: No manejo esta información

Sheet Metricas Sura
A1: MÉTRICA | B1: Operacion Plataformas Suscripcion | C1: Operacion Canal Digital Venta | D1: Operacion Automatizacion | E1: Operacion Canales Masivos
A2: Cantidad de Tickets / mes (total) | B2: 668 | C2: 174 | D2: 512 | E2: 171
A3: Cantidad de Incidentes / mes | B3: 667 | C3: 174 | D3: 333 | E3: 163
A4: Cantidad de Requerimientos / mes | B4: 1 | C4: 0 | D4: 179 | E4: 8
A5: Cambios / mes | B5: N/A | C5: N/A | D5: N/A | E5: N/A
A6: First Call Resolution (FCR %) | B6: No se tiene dato | C6: No se tiene dato | D6: No se tiene dato | E6: No se tiene dato
A7: Mean Time to Resolve (MTTR horas) | B7: 24.58 | C7: 12.38 | D7: 2.98 | E7: 17.92
A8: Meta SLA | B8: 92% por categoria de criticidad ( alto y critico 9, Medio 12. bajo 18) | C8: 92% por categoria de criticidad ( alto y critico 9, Medio 12. bajo 18) | D8: 92% por categoria de criticidad ( alto y critico 9, Medio 12. bajo 18) | E8: 92% por categoria de criticidad ( alto y critico 9, Medio 12. bajo 18)
A9: SLA Cumplimiento (%) | B9: 0.7 | C9: 0.74 | D9: 0.98 | E9: 0.72
A10: Backlog promedio (tickets abiertos) | B10: 65 | C10: 12 | D10: 9 | E10: 11
A11: Tickets resueltos por agente/mes | B11: 150 | C11: 77 | D11: 80 | E11: 142
A12: Costo estimado por ticket (USD) | B12: N/D | C12: N/D | D12: N/D | E12: N/D
A13: Agentes FTE totales | B13: 8 | C13: 2 | D13: 6 | E13: 1
A14: % Tickets autoservicio / N0 | B14: 0 | C14: 0 | D14: 0 | E14: 0

Sheet Transcript Virginia & Lina
A1: Mesas Soporte-20260626_143756-Grabación de la reunión.mp4
A49: Virginia Durango Muriel
A50: 0 minutos 3 segundos0:03
A51: Virginia Durango Muriel 0 minutos 3 segundos
A52: Crecimiento precisamente de las mesas de Sura, donde precisamente alzamos las manos porque no teníamos como claridades en cosas de las que teníamos que empezar a determinar y al cliente si estábamos en capacidad o no de manejarle. Uno, el tema de los niveles listo. ¿Entonces, qué pasa con el tema de los niveles en las mesas de servicio? Normalmente se hablan nivel uno, nivel 2, nivel 3.
A53: Virginia Durango Muriel 0 minutos 26 segundos
A54: Cierto, o esas son por lo menos las que conocemos. Normalmente el nivel uno lo manejan directamente los clientes, porque nivel uno es muy focalizado como ese tema de las ayudas al negocio, mucho de regla de negocio funcional, mucho de que ay, venga, yo no sé cómo hacer la transacción, me explicas, entonces ellos van y ta ta ta.
A55: Virginia Durango Muriel 0 minutos 46 segundos
A56: Cierto, nivel 2, digamos que normalmente es un escalamiento que le hace el nivel uno, nivel 2, cuando posiblemente a nivel de proceso el proceso falla, pero el proceso hasta ahí no se sabe si ni siquiera hay que incluirle o inyectarle alguna mejora como tal desde la codificación, sino que seguramente hay que revisar un log.
A57: Virginia Durango Muriel 1 minuto 5 segundos
A58: Hay que hacer una un relanzamiento de algún proceso. Hay que entrar a la base de datos como para mirar de pronto información que en la visual no se ve, entonces para respuesta como ese tipo de cosas es las que nosotros normalmente atendemos. Listo, y el nivel 3 es cuando nosotros ya a nivel 2 esculcamos lo suficiente y decimos.
A59: Virginia Durango Muriel 1 minuto 24 segundos
... A247: Bueno, hasta luego, gracias.

Sheet Analisis de FTE, Tickets, MTTR
A1: ANÁLISIS FTE, TICKETS Y MTTR — MESAS ACTUALES (JULIO 2026)
A2: Costo/ticket USD = (FTE × 160 h/mes × $88.000 COP) ÷ tickets/mes ÷ TRM $4.200 · Réplica de la tabla de la PPT (Metodología de Cálculo) · Fuente: Levantamiento interno PS Julio 2026
A4: PARÁMETROS
A5: Horas/mes por FTE | B5: 160
A6: Costo hora FTE (COP) | B6: 88000
A7: TRM (COP/USD) | B7: 4200
A8: Benchmark industria N1-N2 (USD/ticket) | B8: 35
A9: Meta Gen Next N3 (USD/ticket) | B9: 15
A11: Mesa | B11: Cliente | C11: Nivel | D11: FTE | E11: Tickets/mes | F11: Tickets/FTE | G11: Capacidad h/mes | H11: MTTR (h) | I11: SLA % | J11: Costo mes (COP) | K11: Costo/ticket (COP) | L11: Costo/ticket (USD) | M11: vs Industria $35
A12: SURA Cotizadores | B12: SURA | C12: N2 | D12: ='Metricas Sura'!B13 -> 8 | E12: ='Metricas Sura'!B2 -> 668 | F12: =E12/D12 -> 83.5 | G12: =D12*$B$5 -> 1280 | H12: ='Metricas Sura'!B7 -> 24.58 | I12: ='Metricas Sura'!B9 -> 0.7 | J12: =D12*$B$5*$B$6 -> 112640000 | K12: =J12/E12 -> 168622.75 | L12: =K12/$B$7 -> 40.148275 | M12: =L12-$B$8 -> 5.1482749
A13: SURA Venta Digital | B13: SURA | C13: N2 | D13: ='Metricas Sura'!C13 -> 2 | E13: ='Metricas Sura'!C2 -> 174 | F13: =E13/D13 -> 87 | G13: =D13*$B$5 -> 320 | H13: ='Metricas Sura'!C7 -> 12.38 | I13: ='Metricas Sura'!C9 -> 0.74 | J13: =D13*$B$5*$B$6 -> 28160000 | K13: =J13/E13 -> 161839.08 | L13: =K13/$B$7 -> 38.533114 | M13: =L13-$B$8 -> 3.5331144
A14: SURA Automatización | B14: SURA | C14: N2 | D14: ='Metricas Sura'!D13 -> 6 | E14: ='Metricas Sura'!D2 -> 512 | F14: =E14/D14 -> 85.333333 | G14: =D14*$B$5 -> 960 | H14: ='Metricas Sura'!D7 -> 2.98 | I14: ='Metricas Sura'!D9 -> 0.98 | J14: =D14*$B$5*$B$6 -> 84480000 | K14: =J14/E14 -> 165000 | L14: =K14/$B$7 -> 39.285714 | M14: =L14-$B$8 -> 4.2857143
A15: SURA Canales Masivos | B15: SURA | C15: N2 | D15: ='Metricas Sura'!E13 -> 1 | E15: ='Metricas Sura'!E2 -> 171 | F15: =E15/D15 -> 171 | G15: =D15*$B$5 -> 160 | H15: ='Metricas Sura'!E7 -> 17.92 | I15: ='Metricas Sura'!E9 -> 0.72 | J15: =D15*$B$5*$B$6 -> 14080000 | K15: =J15/E15 -> 82339.181 | L15: =K15/$B$7 -> 19.604567 | M15: =L15-$B$8 -> -15.395433
A16: XM Apps Críticas | B16: XM | C16: N2-N3 | D16: 4 | E16: 90 | F16: =E16/D16 -> 22.5 | G16: =D16*$B$5 -> 640 | H16: N/D | I16: N/D | J16: =D16*$B$5*$B$6 -> 56320000 | K16: =J16/E16 -> 625777.78 | L16: =K16/$B$7 -> 148.99471 | M16: =L16-$B$8 -> 113.99471
A17: AES Soporte IT/OT | B17: AES | C17: N1 | D17: 4 | E17: N/D | F17: N/D | G17: =D17*$B$5 -> 640 | H17: N/D | I17: N/D | J17: =D17*$B$5*$B$6 -> 56320000 | K17: N/D | L17: N/D | M17: N/D
A18: BCO COES Integración | B18: Bancolombia | C18: N1 | D18: 7 | E18: 700–3.000* | F18: 80–250* | G18: =D18*$B$5 -> 1120 | H18: 0,5–3* | I18: ANS Banco | J18: =D18*$B$5*$B$6 -> 98560000 | K18: N/D | L18: N/D | M18: N/D
A19: BCO COES Datos | B19: Bancolombia | C19: N1 | D19: 7 | E19: 700–3.000* | F19: 80–250* | G19: =D19*$B$5 -> 1120 | H19: 0,5–3* | I19: ANS Banco | J19: =D19*$B$5*$B$6 -> 98560000 | K19: N/D | L19: N/D | M19: N/D
A20: BCO COES Soporte | B20: Bancolombia | C20: N1 | D20: 13 | E20: 700–3.000* | F20: 80–250* | G20: =D20*$B$5 -> 2080 | H20: 0,5–3* | I20: ANS Banco | J20: =D20*$B$5*$B$6 -> 183040000 | K20: N/D | L20: N/D | M20: N/D
A21: BCO COES Emma | B21: Bancolombia | C21: N1 | D21: 4 | E21: 700–3.000* | F21: 80–250* | G21: =D21*$B$5 -> 640 | H21: 0,5–3* | I21: ANS Banco | J21: =D21*$B$5*$B$6 -> 56320000 | K21: N/D | L21: N/D | M21: N/D
A22: BCO Emma iSeries | B22: Bancolombia | C22: N1 | D22: 1 | E22: 700–3.000* | F22: 80–250* | G22: =D22*$B$5 -> 160 | H22: 0,5–3* | I22: ANS Banco | J22: =D22*$B$5*$B$6 -> 14080000 | K22: N/D | L22: N/D | M22: N/D
A23: MEDICARTE (empalme)** | B23: Medicarte | C23: N1 | D23: 12 | E23: N/D | F23: N/D | G23: =D23*$B$5 -> 1920 | H23: 0.55 | I23: 0.89 | J23: =D23*$B$5*$B$6 -> 168960000 | K23: N/D | L23: N/D | M23: N/D
A25: TOTAL SURA (4 mesas) | B25: SURA | C25: N2 | D25: =SUM(D12:D15) -> 17 | E25: =SUM(E12:E15) -> 1525 | F25: =E25/D25 -> 89.705882 | G25: =D25*$B$5 -> 2720 | H25: =AVERAGE(H12:H15) -> 14.465 | I25: =AVERAGE(I12:I15) -> 0.785 | J25: =D25*$B$5*$B$6 -> 239360000 | K25: =J25/E25 -> 156957.38 | L25: =K25/$B$7 -> 37.370804 | M25: =L25-$B$8 -> 2.3708041
A26: TOTAL BANCOLOMBIA (5 COES) | B26: Bancolombia | C26: N1 | D26: =SUM(D18:D22) -> 32 | E26: 3.500–15.000* | F26: 80–250* | G26: =D26*$B$5 -> 5120 | H26: 0,5–3* | I26: ANS Banco | J26: =D26*$B$5*$B$6 -> 450560000 | K26: N/D | L26: N/D | M26: N/D
A27: TOTAL 11 MESAS EVALUADAS | B27: — | C27: — | D27: =SUM(D12:D22) -> 57 | E27: — | F27: — | G27: =D27*$B$5 -> 9120 | H27: — | I27: — | J27: =D27*$B$5*$B$6 -> 802560000 | K27: — | L27: — | M27: —
A29: * Bancolombia: rangos reportados por la líder (hoja "Metricas bancolombia"); sin registro exacto de tickets/MTTR por mesa — costo/ticket no calculable. Estimado global: $451M COP/mes ÷ 3.500–15.000 tix → USD $7–$31/ticket.
A30: ** MEDICARTE: datos preliminares (en empalme), no evaluada formalmente en Julio 2026. Valores SURA vinculados por fórmula a la hoja "Metricas Sura" (validación directa).
A33: MTTR VS BENCHMARKS (h) — datos de la gráfica | F33: TICKETS POR MESA — datos de la gráfica (BCO como rango)
A34: SURA Cotizadores | B34: =H12 -> 24.58 | C34: ← H12 de la tabla (='Metricas Sura'!B7) | F34: Mesa | G34: Registro | H34: Base rango | I34: Ancho rango
A35: SURA Canales Masivos | B35: =H15 -> 17.92 | C35: ← H15 de la tabla (='Metricas Sura'!E7) | F35: SURA Cotizadores | G35: =E12 -> 668
A36: SURA Venta Digital | B36: =H13 -> 12.38 | C36: ← H13 de la tabla (='Metricas Sura'!C7) | F36: SURA Venta Digital | G36: =E13 -> 174
A37: Industria promedio | B37: 8.85 | C37: Benchmark MetricNet/HDI | F37: SURA Automatización | G37: =E14 -> 512
A38: World-Class | B38: 4 | C38: Benchmark world-class MetricNet/HDI | F38: SURA Canales Masivos | G38: =E15 -> 171
A39: SURA Automatización | B39: =H14 -> 2.98 | C39: ← H14 de la tabla (='Metricas Sura'!D7) | F39: XM Apps Críticas | G39: =E16 -> 90
A40: BCO 5 COES (máx. rango) | B40: 3 | C40: Máximo del rango 0,5–3h reportado (hoja "Metricas bancolombia") | F40: BCO COES Integración | H40: 700 | I40: 2300
A41: MEDICARTE (preliminar) | B41: =H23 -> 0.55 | C41: ← H23 de la tabla (dato preliminar) | F41: BCO COES Datos | H41: 700 | I41: 2300
A42: Benchmarks: MetricNet/HDI (industria 8.85h · world-class <4h) · BCO: máximo del rango 0,5–3h | F42: BCO COES Soporte | H42: 700 | I42: 2300
F43: BCO COES Emma | H43: 700 | I43: 2300
F44: BCO Emma iSeries | H44: 700 | I44: 2300
A45: COSTO USD/TICKET — datos de la gráfica | F45: BCO: sin registro exacto por mesa; se grafica el rango 700–3.000 tickets/mesa/mes (hoja "Metricas bancolombia"). Barra = desde 700 hasta 3.000.
A46: XM Apps Críticas | B46: =L16 -> 148.99471 | C46: ← L16 de la tabla: (4 FTE×160h×$88.000)÷90 tix÷TRM
A47: SURA Cotizadores | B47: =L12 -> 40.148275 | C47: ← L12 de la tabla
A48: SURA Automatización | B48: =L14 -> 39.285714 | C48: ← L14 de la tabla
A49: SURA Venta Digital | B49: =L13 -> 38.533114 | C49: ← L13 de la tabla
A50: Industria N1-N2 | B50: =$B$8 -> 35 | C50: ← B8 (parámetro benchmark)
A51: SURA Canales Masivos | B51: =L15 -> 19.604567 | C51: ← L15 de la tabla
A52: Meta Gen Next N3 | B52: =$B$9 -> 15 | C52: ← B9 (parámetro meta N3)
A55: FTE POR CLIENTE — datos de la gráfica
A56: Bancolombia | B56: =SUM(D18:D22) -> 32 | C56: =SUM(D18:D22) de la tabla
A57: SURA | B57: =SUM(D12:D15) -> 17 | C57: =SUM(D12:D15) de la tabla
A58: XM | B58: =D16 -> 4 | C58: =D16 de la tabla
A59: AES | B59: =D17 -> 4 | C59: =D17 de la tabla
A62: MAPA DE DOLORES CRÍTICOS — MESAS AFECTADAS (11 mesas · ● confirmado · ◐ parcial)
A63: Conteo por dolor a partir del mapa de la PPT (slide "Mapa de Dolores Críticos"), agrupado por categoría.
A65: Categoría | B65: Dolor | C65: Etiqueta (gráfica) | D65: Confirmado (●) | E65: Parcial (◐) | F65: Total afectadas
A66: Gobierno | B66: Sin RACI ni roles definidos | C66: =A66&" — "&B66 -> Gobierno — Sin RACI ni roles definidos | D66: 11 | E66: 0 | F66: =D66+E66 -> 11
A67: Gobierno | B67: Sin gobierno — sin ANS formales | C67: =A67&" — "&B67 -> Gobierno — Sin gobierno — sin ANS formales | D67: 7 | E67: 4 | F67: =D67+E67 -> 11
A68: Gobierno | B68: Catálogo de servicios desactualizado | C68: =A68&" — "&B68 -> Gobierno — Catálogo de servicios desactualizado | D68: 0 | E68: 11 | F68: =D68+E68 -> 11
A69: Operación | B69: Postura 100% reactiva | C69: =A69&" — "&B69 -> Operación — Postura 100% reactiva | D69: 9 | E69: 2 | F69: =D69+E69 -> 11
A70: Operación | B70: Sin autoservicio — todo por call | C70: =A70&" — "&B70 -> Operación — Sin autoservicio — todo por call | D70: 11 | E70: 0 | F70: =D70+E70 -> 11
A71: Operación | B71: Scope creep — alcance no controlado | C71: =A71&" — "&B71 -> Operación — Scope creep — alcance no controlado | D71: 4 | E71: 7 | F71: =D71+E71 -> 11
A72: Operación | B72: SLAs incumplidos / penalizaciones | C72: =A72&" — "&B72 -> Operación — SLAs incumplidos / penalizaciones | D72: 3 | E72: 0 | F72: =D72+E72 -> 3
A73: Métricas | B73: Sin métricas ni KPIs | C73: =A73&" — "&B73 -> Métricas — Sin métricas ni KPIs | D73: 8 | E73: 3 | F73: =D73+E73 -> 11
A74: Métricas | B74: Sin dashboard ejecutivo | C74: =A74&" — "&B74 -> Métricas — Sin dashboard ejecutivo | D74: 3 | E74: 7 | F74: =D74+E74 -> 10
A75: Talento | B75: Rotación — pérdida de conocimiento | C75: =A75&" — "&B75 -> Talento — Rotación — pérdida de conocimiento | D75: 0 | E75: 11 | F75: =D75+E75 -> 11
A76: Talento | B76: Asignación sin modelo de demanda | C76: =A76&" — "&B76 -> Talento — Asignación sin modelo de demanda | D76: 11 | E76: 0 | F76: =D76+E76 -> 11
A77: Talento | B77: Penalización de la eficiencia | C77: =A77&" — "&B77 -> Talento — Penalización de la eficiencia | D77: 2 | E77: 8 | F77: =D77+E77 -> 10
... A80: Comercial | B80: Herramientas fragmentadas | C80: =A80&" — "&B80 -> Comercial — Herramientas fragmentadas | D80: 1 | E80: 10 | F80: =D80+E80 -> 11
A108: COSTO USD/TICKET — XM Y BANCOLOMBIA VS INDUSTRIA (réplica del slide nuevo de la PPT)
A109: Concepto | B109: USD/ticket | C109: Cálculo / origen
A110: XM Apps Críticas | B110: =L16 -> 148.99471 | C110: ← L16: (4 FTE × 160h × $88.000) ÷ 90 tickets ÷ TRM $4.200
A111: Industria N1-N2 (Benchmark) | B111: =$B$8 -> 35 | C111: ← B8 (benchmark Gartner/Giva/Freshservice)
A112: Bancolombia — estimado MÁXIMO | B112: =J26/(700*5)/$B$7 -> 30.65034 | C112: Costo mes BCO $450,6M (J26) ÷ 3.500 tix (700 × 5 COES, piso del rango) ÷ TRM
A113: Bancolombia — estimado MÍNIMO | B113: =J26/(3000*5)/$B$7 -> 7.151746 | C113: Costo mes BCO $450,6M (J26) ÷ 15.000 tix (3.000 × 5 COES, techo del rango) ÷ TRM
A114: Meta Gen Next N3 | B114: =$B$9 -> 15 | C114: ← B9 (parámetro meta N3)
A115: Bancolombia no reporta tickets formales por mesa; el estimado usa el rango 700–3.000 tickets/mesa/mes de la hoja "Metricas bancolombia". A más tickets reales, menor costo/ticket.
A118: ORIGEN DE DATOS DE CADA GRÁFICA
A119: Gráfica | B119: Rango de datos | C119: Cómo se calcula / de dónde sale
A120: FTE por Mesa | B120: D12:D22 | C120: SURA por fórmula desde 'Metricas Sura' fila 13 (8/2/6/1); XM, AES y BCO del levantamiento por mesa (4/4 y 7/7/13/4/1). Total 57 FTE.
A121: Tickets por Mesa al Mes | B121: F35:I44 | C121: Bloque F34:I45: SURA/XM con registro (=E12:E16); BCO como rango flotante 700–3.000 (base 700 invisible + ancho 2.300).
A122: MTTR vs Benchmarks | B122: A34:B41 | C122: SURA = columna H de la tabla ← 'Metricas Sura' fila 7; Industria 8,85h y World-Class 4h (MetricNet/HDI); BCO = máximo del rango 0,5–3h; MEDICARTE 0,55h preliminar.
A123: Costo USD por Ticket | B123: A46:B52 | C123: Columna L de la tabla: (FTE × B5 × B6) ÷ tickets ÷ B7; Industria = B8; Meta N3 = B9.
A124: FTE por Cliente (pie) | B124: A56:B59 | C124: Sumas de la columna D: BCO =SUM(D18:D22)=32, SURA =SUM(D12:D15)=17, XM =D16=4, AES =D17=4.
A125: XM y Bancolombia vs Industria | B125: A110:B114 | C125: XM = L16; BCO estimado = J26 ÷ (3.500 a 15.000 tickets) ÷ TRM → $7–$31; Industria/Meta = B8/B9.
A126: Mapa de Dolores | B126: C66:E80 | C126: Conteo de ● (confirmado) y ◐ (parcial) por dolor sobre las 11 mesas del mapa de la PPT, agrupado por categoría.

Sheet Automatizaciones
A1: Framework de mesas de servicio | C1: Carga administrativa*
A2: Lider: Ivan Oralndo Riveros Gomez
A3: Process automation, donde estan las mesas de servicios (procesos más operativos). Camilo Osorio y Steve Cardenas
A4: Cliente | B4: Herramientas | C4: Piloto / Oportunidad de automatizar | D4: Medir
A5: Un ejercicio con NEQUI | B5: N8N | C5: Proxima semana 14 de Junio 2026 | D5: Tiempos de resolucion de los casos, mejorar el triach* | E5: Dashboard. En un solo panel ver el estado delosproyectos, projects manager, esrvices managers. Estados de los flujos operacionales
A6: SURA (Con sura somos N2) | C6: Generación de PDFs | E6: Identificar que otros procesos se pueden optimizar, los procesos de la mesa y procesos administrativos.
C7: Para el registro de recargos y horas extras
A8: SURA — Cotizadores | C8: Autoservicio/portal N0 para incidentes recurrentes (hoy todo entra por call) y dashboard de SLA/backlog
A9: SURA — Venta Digital | C9: Dashboard ejecutivo automatizado y monitoreo proactivo del portal de venta
A10: SURA — Automatización | C10: Deflection N0 y clasificación/triaje automático de tickets (base Power Automate/PowerApps ya operando)
A11: SURA — Canales Masivos | C11: Automatizar campañas de renovaciones/cancelaciones masivas y alertas de backlog (contingencia: 1 solo FTE)
A12: XM | C12: Registro automático de recargos y horas extras · tableros en tiempo real · observabilidad/AIOps de los 14 componentes
A13: AES | C13: Implementar ITSM con métricas y reportes automáticos (hoy sin KPIs, sin SLA documentado)
A14: Bancolombia — 5 COES | C14: Automatizar recargos y horas extras, informes mensuales y tableros ejecutivos (identificado en levantamiento COES)
A15: Bancolombia | C15: Replicar el "Top tendencia" (predicción de comportamiento inusual) hacia las demás mesas de PS
A16: Todas las mesas | C16: KEDB / gestión de conocimiento asistida por IA y reportería consolidada para la operación de PersonalSoft

Sheet AES
B2: LEVANTAMIENTO DE MESA DE SERVICIOS — AES
I3: ESCALA DE MADUREZ — N0 a N5
B4: ① IDENTIFICACIÓN GENERAL DE LA MESA | I4: NIVEL | J4: NOMBRE | K4: DESCRIPCIÓN
B5: Cliente: | C5: AES | I5: N0 | J5: Reactivo / Sin estructura | K5: No existe proceso formal. Todo es manual y reactivo. Sin CMDB ni catálogo.
B6: Negocio del cliente: | C6: Empresa de energia. Central hidroelectrica | I6: N1 | J6: Inicial / Ad hoc/ Operación reactiva | K6: Procesos básicos documentados. Herramientas mínimas. Cumplimiento inconsistente.
B7: Nombre de la Mesa: | C7: Soporte IT/OT | I7: N2 | J7: Definido / Organización funcional | K7: Procesos ITIL definidos y seguidos. Métricas básicas (SLA (Service Level Agreement), FCR (Fondo de Capital Riesgo)). Equipo estable.
B8: Líder / Coordinador: | C8: Michael Arevalo Luna | I8: N3 | J8: Gestionado / Gestión por servicios | K8: Métricas avanzadas. Automatización parcial. Gestión proactiva de problemas.
B9: Fecha del Levantamiento: | C9: 46210 | I9: N4 | J9: Optimizado / Gestión integrada | K9: Autoservicio maduro. IA/ML básico. XLA (Experience Level Agreement) medidos. Mejora continua activa.
B10: Ubicación / Modalidad: | C10: Virtual
B11: N° de Agentes (FTE) (cantidad de personas): | C11: 4 | I11: Función | J11: Misión Principal | K11: Alcance
B12: Modelo de Contrato: | C12: Staffing | I12: Call Center | J12: Manejar grandes volúmenes de llamadas; filtrar y derivar | K12: Punto de contacto y distribución estructurada
B13: Nivel Madurez Actual: | C13: N1 | D13: (N0 Reactivo → N5 Innovador) | I13: Help Desk | J13: Coordinación para la restauración del servicio; "arreglar cosas" | K13: Infraestructura, herramientas de seguimiento, base de conocimiento
B14: Modelo de Operación | C14: Help Desk / soporte IT-OT e infraestructura: coordinación para restauración del servicio; atención de tareas y servicios derivados desde ServiceNow/ARUS. | I14: Service Desk | J14: Servicio integral: incidentes, solicitudes, consultas, altas/bajas/cambios | K14: Alcance configurable; representa al usuario dentro de TI
B15: (Tercero) Empresa de soporte al cliente | C15: ARUS; tickets
B16: En que otro Niveles tenemos presencia: | C16: No Aplica
B17: En que paises tenemos presencia: | C17: Colombia
B18: Que hacemos en el cliente: | C18: Soporte IT/OT y maneja infraestructura, aunque, si bien a ellos les cargan los requerimientos por Service Now. Las asignaciones llegan por tareas (por ejemplo un punto de red, falla de equipos de equipos de comunicación, fallas de equipos de red) o por servicios. Hay 4 personas que atienden soporte en redes, networking, facilities y seguridad electrónica + cableado estructurado y enlaces de fibra. Hacen mantenimiento preventivo
B19: Tiempo de la Mesa de Servicio | C19: 3 años
B20: Finalización | C20: 12 de Agosto 2026; extesion 12 Noviembre
B21: Renovación: | C21: RFP pendiente de aprobación para renovar 3 años más. El contrato con más condiciones y mejoras
B22: Equipos de infraestructura: | C22: del cliente; PersonalSoft compra y re-cobra al cliente
B23: Video: | C23: https://personalsoftsas-my.sharepoint.com/personal/jorengifo_personalsoft_com/_layouts/15/stream.aspx?id=%2Fpersonal%2Fjorengifo%5Fpersonalsoft%5Fcom%2FDocuments%2FGrabaciones%2FHablemos%20Mesas%20AES%2D20260707%5F113150%2DGrabaci%C3%B3n%20de%20la%20reuni%C3%B3n%2Emp4&referrer=StreamWebApp%2EWeb&referrerScenario=AddressBarCopied%2Eview%2E8bb79edf%2Dcf18%2D4677%2D8d5a%2Dc46ddd3c2dad
B24: Transcript: | C24: Natalia Zartha Suarez empezó la transcripción Natalia Zartha Suarez 0 minutos 3 segundos0:03 Natalia Zartha Suarez 0 minutos 3 segundos Sí, dime tranquilo. Michael Arevalo Luna 0 minutos 4 segundos0:04 Michael Arevalo Luna 0 minutos 4 segundos Dale y yo ahorita les doy un contexto de del cliente, vale. Natalia Zartha Suarez 0 minutos 8 segundos0:08 Natalia Zartha Suarez 0 minutos 8 segundos Dale listo listo Claro que sí muchas gracias Bueno si quieres te cuento yo ingresé hace más de una semanita a la a la empresa estoy en el área de de servicios Muchas gracias estoy en el área de servicios de innovación y vamos a diseñar un nuevo servicio para mesa de de servicios entonces antes de arrancar con el diseño queremos levantar la información que tenemos de las mesas actuales las lecciones Michael Arevalo Luna 0 minutos 17 segundos0:17 Michael Arevalo Luna 0 minutos 17 segundos Bienvenida. Natalia Zartha Suarez 0 minutos 32 segundos0:32 Natalia Zartha Suarez 0 minutos 32 segundos aprendidas Cuál es de pronto el feedback tuyo qué podríamos mejorar en el en el servicio que se va a estandarizar y a venir cierto si quieres te comparto acá muy muy rapidito nosotros decimos como eso es como una guía para irte preguntando no es que no es ni una evaluación es Natalia Zartha Suarez 0 minutos 52 segundos es como una auditoría muy rigurosa si no se cumple no no pasa nada o sea la idea es que podamos obtener como la mayor información posible y de ahí ya partir con el diseño cierto Entonces más o menos lo que hemos identificado en las en la madurez de las mesas de servicio lo estamos catalogando en estos cinco niveles en nivel uno que es un nivel muy muy inicial Natalia Zartha Suarez 1 minuto 15 segundos muy reactivo entonces salen tickets y se responden en el volumen que va saliendo y tiene un factor de riesgo y es el conocimiento hacia las personas y si rota pues es es muy eh un un riesgo para la la empresa entonces a esto lo lo llamamos el reactivo y crecimiento automatizado Natalia Zartha Suarez 1 minuto 34 segundos que por hoy en día es como muy reactivo el nivel y todo es un nivel más administrado entonces son procesos por mesa herramientas tickets y es como lo mínimo que tiene una mesa de ayuda o un Help de que por el contexto que nos yo yo creo que es es el caso cierto eh después el nivel tres que es predictivo y evolutivo es donde queremos empezar a a Natalia Zartha Suarez 1 minuto 55 segundos ayudar las mesas un nivel cuatro que ya es más como cuantitativas métricas y el nivel 5 es el servicio que nosotros queremos diseñar algo muy autónomo muy estandarizado muy óptimo entonces tiene como Mostrar Aquí estos cinco niveles porque de ahí y y si quieres ya nos vas dando como el el contexto diseñamos esta planta Natalia Zartha Suarez 2 minutos 15 segundos ya o sea te la muestro Qué son los puntos que que queremos levantar información general tratar de identificar En qué nivel En qué nivel estamos en cada mesa eh unas preguntas a nivel de prácticas y de itil cierto volumetría kpis que de pronto tengas eh distribución de de incidentes por categoría si están Natalia Zartha Suarez 2 minutos 38 segundos tema de experiencia del usuario del usuario del cliente cierto algunos dolores nosotros identificamos 18 dólares pero pueden haber más entonces como que les duele a ustedes temas de inter rotación y talento herramientas tecnologías algo del modelo económico si se conoce y eso ya es como para el nuevo servicio entonces una visión para el nuevo servicio Natalia Zartha Suarez 2 minutos 59 segundos qué debería cambiar y si tenemos algún caso de éxito listo y entonces si quieres aquí ya te doy la palabra yo aquí he empezado a tomar apuntes con lo que ya me me me ha pasado cierto para que seamos más o menos que sé que es una empresa de energía sé que pues yo lo puse Aquí como un gel dex que es más como temas de infraestructura Natalia Zartha Suarez 3 minutos 19 segundos Cierto, como de soporte de infraestructura, pero si quieres, ahora sí te dejo hablar. Ándale, sí. Michael Arevalo Luna 3 minutos 23 segundos3:23 Michael Arevalo Luna 3 minutos 23 segundos Dale nada, primero bienvenidos, que pena ahí que de cierta manera y cuando Johanna ayer me hizo preguntas, estaba como ocupado y no le ha dado respuesta y no está esta mañana y nada lo que necesiten con gusto. De cierta manera, yo siento que dentro del me imagino que con los con los clientes o de lo que están sacando de lo que estás haciendo ahorita. Natalia Zartha Suarez 3 minutos 34 segundos3:34 Natalia Zartha Suarez 3 minutos 34 segundos No, tranquilo. Natalia Zartha Suarez 3 minutos 43 segundos Sí. Michael Arevalo Luna 3 minutos 44 segundos3:44 Michael Arevalo Luna 3 minutos 44 segundos No debería estar dentro de esas priorías iniciales y ya te cuento por qué. Natalia Zartha Suarez 3 minutos 47 segundos3:47 Natalia Zartha Suarez 3 minutos 47 segundos O K, de bueno, sí. Michael Arevalo Luna 3 minutos 49 segundos3:49 Michael Arevalo Luna 3 minutos 49 segundos En este momento nosotros teníamos un contrato vigente hasta el 12 de agosto. Sí, ajá, ya les voy a contar. Entonces, ¿qué pasa? En se generó un RFP para licitación y hacer una renovación. Nosotros entramos a participar junto con otras cuatro o 5 compañías. Ajá. Natalia Zartha Suarez 3 minutos 53 segundos3:53 Natalia Zartha Suarez 3 minutos 53 segundos Y se termina. Natalia Zartha Suarez 3 minutos 55 segundos bueno. Michael Arevalo Luna 4 minutos 7 segundos4:07 Michael Arevalo Luna 4 minutos 7 segundos Hola Fredy, buen día. F Fredy Alonso Pinilla Juez 4 minutos 9 segundos4:09 Fredy Alonso Pinilla Juez 4 minutos 9 segundos Buen día para todos. Natalia Zartha Suarez 4 minutos 11 segundos4:11 Natalia Zartha Suarez 4 minutos 11 segundos Buenos días, Fredy, un gusto. Michael Arevalo Luna 4 minutos 11 segundos4:11 Michael Arevalo Luna 4 minutos 11 segundos Les presento a Fredy. Fredy es el coordinador que nos ayuda. Bueno, de hecho Fredy tiene doble error en AES. Él nos ayuda directamente en la planta, ellos están ubicados en la planta. Entonces Fredy es el que coordina como todas las actividades y es dentro de lo que hace el gerente y las solicitudes que hace la gerencia de AES dentro de la planta, pues ahí está ahí como coordinando. Natalia Zartha Suarez 4 minutos 32 segundos4:32 Natalia Zartha Suarez 4 minutos 32 segundos Sí. Michael Arevalo Luna 4 minutos 33 segundos4:33 Michael Arevalo Luna 4 minutos 33 segundos Todo lo que se requiera. Natalia Zartha Suarez 4 minutos 35 segundos4:35 Natalia Zartha Suarez 4 minutos 35 segundos Un gusto. Michael Arevalo Luna 4 minutos 36 segundos4:36 Michael Arevalo Luna 4 minutos 36 segundos Vale, entonces la idea de que Fredy nos acompañe es de cierta manera. Yo sé que él nos puede ayudar a tener algún entendimiento en cosas que a mí se me se me pasen, pero pues como te decía, digamos que antes de llegar a ese punto, siento que con el tema del RFP. F Fredy Alonso Pinilla Juez 4 minutos 37 segundos4:37 Fredy Alonso Pinilla Juez 4 minutos 37 segundos Igualmente. Michael Arevalo Luna 4 minutos 56 segundos4:56 Michael Arevalo Luna 4 minutos 56 segundos y con lo que como está actualmente este servicio, como funciona actualmente, eso va a cambiar muchísimo. Sí, digamos que actualmente, pues nosotros ellos están bajo el modelo de staffing, pero entonces con el error FP nuevo, el tema va a cambiar al punto en que nosotros nos vamos a cargar de absolutamente toda la operación. Natalia Zartha Suarez 5 minutos 7 segundos5:07 Natalia Zartha Suarez 5 minutos 7 segundos Sing. Michael Arevalo Luna 28 minutos 1 segundo28:01 Michael Arevalo Luna 28 minutos 1 segundo No a ustedes lo que necesiten con mucho gusto igual. Joan Sebastian Rengifo Ocampo 28 minutos 1 segundo28:01 Joan Sebastian Rengifo Ocampo 28 minutos 1 segundo Listo, muchas gracias. F Fredy Alonso Pinilla Juez 28 minutos 2 segundos28:02 Fredy Alonso Pinilla Juez 28 minutos 2 segundos Vale. Fredy Alonso Pinilla Juez 28 minutos 3 segundos Con todo gusto y cualquier consulta, pues quedamos ahí pendientes. Natalia Zartha Suarez 28 minutos 6 segundos28:06 Natalia Zartha Suarez 28 minutos 6 segundos Es igualmente por acá, muchísimas gracias. Chaita, gracias, hasta luego, gracias. Joan Sebastian Rengifo Ocampo 28 minutos 9 segundos28:09 Joan Sebastian Rengifo Ocampo 28 minutos 9 segundos Bueno, hasta luego. Michael Arevalo Luna 28 minutos 9 segundos28:09 Michael Arevalo Luna 28 minutos 9 segundos Vale, que estén bien, chao. F Fredy Alonso Pinilla Juez 28 minutos 10 segundos28:10 Fredy Alonso Pinilla Juez 28 minutos 10 segundos No Natalia John. Fredy Alonso Pinilla Juez 28 minutos 12 segundos Better.  Natalia Zartha Su
B25: # Aplicaciones:
B26: Comercial | C26: *Michael Arevalo Luna
B27: Roles
B28: Automatizaciones:
B30: ③ EVALUACIÓN DE PRÁCTICAS ITIL v4 — 4 DIMENSIONES
B31: # | C31: PRÁCTICA | D31: ¿Se cumple? | E31: Observaciones / Evidencia | F31: Prioridad Mejora
B32: D1 — Organización y Personas
B33: 1.1 | C33: Gestión de la Fuerza Laboral: Headcount, perfiles, competencias | D33: Parcial | F33: Media
B34: 1.2 | C34: Gestión del Conocimiento: KB (Knowledge Base), documentación, onboarding | D34: Parcial | F34: Alta
B35: 1.3 | C35: Gestión del Talento: Rotación, desarrollo, retención | D35: No | F35: Media
B36: 1.4 | C36: Gestión del Desempeño: Metas individuales, feedback, KPIs de agente | D36: No | F36: Media
B37: 1.5 | C37: Cultura de Servicio: Orientación al usuario, empatía, NPS (Net Promoter Score) interno | D37: Sí | E37: Sí aplica: hay disposición de soporte y coordinación con planta; Fredy coordina actividades directamente en AES. | F37: Baja
B39: D2 — Información y Tecnología
B40: 2.1 | C40: Gestión de Incidentes: Proceso, tiempos, escalamiento | D40: Sí | E40: Sí aplica: se atienden tareas/servicios como puntos de red y fallas de equipos de comunicación/red. | F40: Media
B41: 2.2 | C41: Gestión de Requerimientos: Catálogo de servicios, flujos | D41: Sí | E41: Sí aplica: los requerimientos se cargan por ServiceNow y llegan como tareas o servicios. | F41: Media
B42: 2.3 | C42: Gestión de Problemas: RCA (Análisis de Causa Raíz ), errores conocidos, KEDB (Known Error Database) | D42: Parcial | E42: Parcial: se mencionan fallas recurrentes de red/equipos, pero no se evidencia RCA/KEDB formal. | F42: Alta
B43: 2.4 | C43: Gestión de Cambios: CAB (Change Advisory Board), RFC (Solicitud de Cambio), ventanas de mantenimiento | D43: No | F43: Media
B44: 2.5 | C44: Gestión de la Configuración: CMDB (Configuration Management Database), assets, CIs (Elementos de Configuración) | D44: Parcial | E44: Parcial: se mencionan equipos de infraestructura del cliente y recobro de compras por PersonalSoft; no se confirma CMDB formal. | F44: Alta
B45: 2.6 | C45: Monitoreo y Eventos: Alertas, observabilidad, integración | D45: No | F45: Alta
B46: 2.7 | C46: Mesa de Servicio (Service Desk): Canal único, autoservicio, chatbot | D46: No | F46: Alta
B48: D3 — Socios y Proveedores
B49: 3.1 | C49: Gestión de Proveedores: SLAs (Acuerdo de nivel de servicio) tercerizados, contratos, evaluación | D49: Parcial | E49: Parcial: existe tercero ARUS/tickets y RFP con 4–5 compañías; falta evaluación formal de proveedores y SLAs tercerizados. | F49: Alta
B50: 3.2 | C50: Gestión de Niveles de Servicio: SLA, OLA (Acuerdo de nivel de operación), XLA (Acuerdo de nivel de experiencia) definidos y medidos | D50: No | F50: Alta
B51: 3.3 | C51: Gestión de Capacidad y Disponibilidad: Picos, contingencia | D51: No | F51: Media
B53: D4 — Flujos de Valor y Mejora
B54: 4.1 | C54: Mejora Continua: Ciclos PDCA (Planificar, Hacer, Comprobar y Actuar), retros, backlogs de mejora | D54: Parcial | E54: Parcial: el nuevo RFP implica cambio de modelo y mejoras, pero no se evidencia ciclo formal de mejora continua. | F54: Alta
B55: 4.2 | C55: Medición y Reporte: Dashboards, informes ejecutivos, tendencias | D55: No | F55: Alta
B57: SCORE GENERAL DE PRÁCTICAS ITIL: | D57: 5 | E57: 0.29411765
B59: ④ VOLUMETRÍA Y KPIs OPERATIVOS
B60: MÉTRICA | C60: Valor Actual | D60: Meta / SLA | E60: Tendencia | F60: Comentario
B61: Cantidad de Tickets / mes (total) | D61: N/A | E61: N/D
B62: Cantidad de Incidentes / mes | D62: N/A | E62: N/D
B63: Cantidad de Requerimientos / mes | D63: N/A | E63: N/D
B64: Cantidad de Cambios / mes | D64: N/A | E64: N/D
B65: First Call Resolution (FCR %) | D65: N/A | E65: N/D
B66: Mean Time to Resolve (MTTR horas) | D66: N/A | E66: N/D
B67: SLA Cumplimiento (%) | D67: N/A | E67: N/D
B68: Backlog promedio (tickets abiertos) | D68: N/A | E68: N/D
B69: Tickets resueltos por agente/mes | D69: N/A | E69: N/D
B70: Costo estimado por ticket (USD) | D70: N/A | E70: N/D
B71: Agentes FTE totales | C71: 4 | D71: 8 | E71: 8 | F71: Se indica que 4 personas atienden soporte en redes, networking, facilities y seguridad electrónica.
B72: % Tickets autoservicio / N0 | D72: N/A | E72: N/D
B74: ④b DISTRIBUCIÓN DE INCIDENTES POR CATEGORÍA
B75: Si el service desk del cliente les permite cateogorizarse asi
B76: CATEGORÍA | C76: Tickets/mes | D76: % del Total | E76: Tiempo Prom. Resolución (h) | F76: Observaciones
B77: Accesos / Permisos
B78: Red / Conectividad | F78: Aplica: puntos de red, fallas de equipos de comunicación/red y enlaces de fibra.
B79: Aplicaciones de negocio
B80: Hardware / Equipos | F80: Aplica: fallas de equipos mencionadas.
B81: Correo / Office 365
B82: ERP / SAP
B83: Seguridad / Ciberseguridad | F83: Aplica parcialmente: seguridad electrónica dentro del alcance del equipo.
B84: Otra categoría | F84: Facilities, cableado estructurado y mantenimiento preventivo.
B86: ⑤ EXPERIENCIA DEL USUARIO — XLA / DEX
B87: INDICADOR XLA | C87: Valor Actual | D87: Meta | E87: Método de Medición | F87: Observaciones
B88: NPS (Net Promoter Score) de la mesa | D88: N/A | E88: N/D
B89: CSAT (Satisfacción del cliente) — escala 1-5 | D89: N/A | E89: N/D
B90: CES (Customer Effort Score) | D90: N/A | E90: N/D
B91: Encuestas post-ticket (tasa de respuesta %) | D91: N/A | E91: N/D
B92: Percepción de calidad (top 3 palabras del usuario) | D92: N/A | E92: N/D
B93: Cantidad de Quejas escaladas / mes | D93: N/A | E93: N/D
B94: Tiempo promedio de espera en canal (minutos) | D94: N/A | E94: N/D
B96: ⑥ DOLORES CRÍTICOS DE LA MESA (D1–D21)
B97: DOLOR | C97: ¿Existe? | D97: Descripción / Evidencia | E97: Impacto (1-5) | F97: Criticidad | G97: Iniciativa sugerida
B98: D1 | C98: No | D98: Rotación excesiva de personal: pérdida de conocimiento | E98: 2 | F98: Baja | G98: Levantar rotación y mapa de conocimiento crítico.
B99: D2 | C99: No | D99: SLAs incumplidos / penalizaciones contractuales | E99: 2 | F99: Baja | G99: Confirmar cláusulas SLA en contrato/RFP.
B100: D3 | C100: No | D100: Ausencia de autoservicio: todo llega por call/correo | E100: 3 | F100: Media | G100: Evaluar autoservicio si el volumen lo justifica.
B101: D4 | C101: Parcial | D101: Herramientas fragmentadas / sin integración | E101: 3 | F101: Media | G101: Mapear flujo ServiceNow–ARUS–equipo AES.
B102: D5 | C102: No | D102: Baja satisfacción del usuario (NPS < 30) | E102: 2 | F102: Baja | G102: Implementar encuesta post-ticket.
B103: D6 | C103: Parcial | D103: Escalamientos excesivos a N2/N3 | E103: 3 | F103: Media | G103: Definir matriz de escalamiento y cierre.
B104: D7 | C104: No | D104: Falta de visibilidad en tiempo real (sin dashboard) | E104: 3 | F104: Media | G104: Diseñar tablero operativo mínimo.
B105: D8 | C105: No | D105: Reportes manuales: no hay visibilidad ejecutiva en tiempo real | E105: 3 | F105: Media | G105: Validar cadencia de informes en RFP.
B106: D9 | C106: Parcial | D106: Expansión del alcance no controlado: solicitudes fuera del alcance de la mesa de servicio (no delimitado) | E106: 4 | F106: Alta | G106: Definir alcance, exclusiones y catálogo operativo.
B107: D10 | C107: Parcial | D107: Escalamiento inefiiente y cuellos de botella: El modelo de N1/N2/N3 genera rebotes de tickets aumentado el MTTR (tiempo medio de resolución | E107: 3 | F107: Media | G107: Documentar flujo end-to-end y responsables.
B108: D11 | C108: Sí | D108: Postura 100% reactiva | E108: 4 | F108: Alta | G108: Transitar a operación gestionada con métricas y mejora continua.
B109: D12 | C109: Parcial | D109: Falta de gobierno claro | E109: 4 | F109: Alta | G109: Definir comité, RACI, SLAs/OLAs y reportes.
... B115: D18 | C115: No | D115: Reskilling - Upskilling constante del staff | E115: 2 | F115: Baja | G115: Validar brechas técnicas IT/OT del equipo.
...

Sheet SURA Cotizadores
B1: LEVANTAMIENTO DE MESA DE SERVICIOS — SURA COTIZADORES
B2: ⚠ DATOS DE EJEMPLO — Diligenciar con información real de la mesa | I2: ESCALA DE MADUREZ — N0 a N5
B3: ① IDENTIFICACIÓN GENERAL DE LA MESA | I3: NIVEL | J3: NOMBRE | K3: DESCRIPCIÓN
B4: Cliente: | C4: SURA | I4: N0 | J4: Reactivo / Sin estructura | K4: No existe proceso formal. Todo es manual y reactivo. Sin CMDB ni catálogo.
B5: Negocio del cliente: | C5: Todo tipo de seguros (SOAT ,Vida, Autos, Polizas, ...) | I5: N1 | J5: Inicial / Ad hoc/ Operación reactiva | K5: Procesos básicos documentados. Herramientas mínimas. Cumplimiento inconsistente.
B6: Nombre de la Mesa: | C6: Cotizadores; Plataforma Suscripción | I6: N2 | J6: Definido / Organización funcional | K6: Procesos ITIL definidos y seguidos. Métricas básicas (SLA (Service Level Agreement), FCR (Fondo de Capital Riesgo)). Equipo estable.
B7: Líder / Coordinador: | C7: Elsy Yulieth Marin Serna | I7: N3 | J7: Gestionado / Gestión por servicios | K7: Métricas avanzadas. Automatización parcial. Gestión proactiva de problemas.
B8: Fecha del Levantamiento: | C8: 46211 | I8: N4 | J8: Optimizado / Gestión integrada | K8: Autoservicio maduro. IA/ML básico. XLA (Experience Level Agreement) medidos. Mejora continua activa.
B9: Ubicación / Modalidad: | C9: Virtual
B10: N° de Agentes (FTE) (cantidad de personas): | C10: 8 | I10: Función | J10: Misión Principal | K10: Alcance
