Workbook

Sheet Control de Cambios
D3: LEVANTAMIENTO DE MESA DE SERVICIOS
D5: Caracterización y Diagnóstico de Mesas de Servicio Operación Actual | G5: Fecha: 2026/07/03
D6: Versión: | E6: 1.0 | G6: Clasificación: Interna
B9: Elaboró | D9: Revisó | F9: Aprobó
B10: Natalia Zartha Junior Architect
B11: Fecha | D11: Fecha | F11: Fecha
B12: 46206
B14: Fecha | C14: Versión | D14: Descripción
B15: 2026/07/03 | C15: 1 | D15: Versión inicial; levantamiento de información actual de las mesas de servicio
C16: 2
C17: 3
C18: 4
C19: 5

Sheet Instrucciones
D2: LECCIONES APRENDIDAS — MESA DE SERVICIOS DE NUEVA GENERACIÓN
D4: Esta herramienta permite caracterizar la mesa de servicios actual en todas sus dimensiones para diseñar el futuro servicio Gen Next | F4: Fecha: 2026/07/03
D5: Versión: 1.0 | F5: Clasificación: Interna
B8: AGENDA DE LA SESIÓN DE LECCIONES APRENDIDAS (~60 minutos)
B9: # | C9: BLOQUE | D9: TIEMPO | E9: DESCRIPCIÓN
B10: ① | C10: INFORMACIÓN GENERAL | D10: 5 min | E10: Registrar datos básicos de la mesa: cliente, nombre del servicio, líder, ubicación, modalidad, contrato, herramientas y participantes.
B11: ② | C11: IDENTIFICAR NIVEL DE MADUREZ ACTUAL | D11: 5 min | E11: Identificar el nivel de madurez actual de la mesa de servicio de TI en una escala N0–N5, identificando el punto de partida operativo.
B12: ③ | C12: 17 PRÁCTICAS ITIL v4 + DIMENSIONES | D12: 5 min | E12: Revisar el cumplimiento de las prácticas ITIL v4 por las 4 dimensiones: organización/personas, información/tecnología, socios/proveedores y valor/mejora.
B13: ④ | C13: VOLUMETRÍA Y KPIs OPERATIVOS | D13: 5 min | E13: Levantar métricas operativas clave: volumen de tickets, FCR, SLA, backlog, tiempos de atención, escalamiento y desempeño general.
B14: ④b | C14: ④b DISTRIBUCIÓN DE INCIDENTES POR CATEGORÍA | D14: 5 min | E14: Analizar la distribución de incidentes por categoría para identificar patrones, servicios críticos, causas recurrentes y oportunidades de mejora.
B15: ⑤ | C15: EXPERIENCIA DEL USUARIO — XLA / DEX | D15: 5 min | E15: Evaluar la experiencia del usuario final mediante indicadores XLA/DEX, satisfacción, percepción del servicio, puntos de dolor y canales de atención.
B16: ⑥ | C16: DOLORES CRÍTICOS DE LA MESA (D1–D18) | D16: 5 min | E16: Identificar y priorizar los dolores críticos de la mesa, su impacto operativo, evidencias disponibles y nivel de urgencia para intervención.
B17: ⑦ | C17: ROTACIÓN Y TALENTO | D17: 5 min | E17: Revisar rotación, perfiles críticos, capacidades del equipo, clima laboral, brechas de conocimiento y necesidades de formación.
B18: ⑧ | C18: TECNOLOGÍA Y HERRAMIENTAS | D18: 5 min | E18: Evaluar herramientas tecnológicas actuales: ITSM, monitoreo, autoservicio, base de conocimiento, automatización, integraciones y reportes.
B19: ⑨ | C19: MODELO ECONÓMICO ACTUAL | D19: 5 min | E19: Analizar el modelo económico actual: FTEs, costos, esquema contractual, capacidad instalada, eficiencia operativa y posibles oportunidades de optimización.
B20: ⑩ | C20: VISIÓN PARA EL NUEVO SERVICIO — ¿QUÉ DEBERÍA CAMBIAR? | D20: 5 min | E20: Definir la visión objetivo del nuevo servicio: cambios esperados, capacidades Gen Next, automatización, experiencia deseada y prioridades de transformación.
B21: ⑪ | C21: CASOS DE EXITO | D21: 5 min | E21: Documentar casos de éxito, buenas prácticas, aprendizajes reutilizables y elementos que deben conservarse o escalarse en el nuevo modelo.
B23: ESCALA DE MADUREZ — N0 a N5
B24: NIVEL | C24: NOMBRE | D24: DESCRIPCIÓN
B25: N0 | C25: Reactivo / Sin estructura | D25: No existe proceso formal. Todo es manual y reactivo. Sin CMDB ni catálogo.
B26: N1 | C26: Inicial / Ad hoc/ Operación reactiva | D26: Procesos básicos documentados. Herramientas mínimas. Cumplimiento inconsistente.
B27: N2 | C27: Definido / Organización funcional | D27: Procesos ITIL definidos y seguidos. Métricas básicas (SLA (Service Level Agreement), FCR (Fondo de Capital Riesgo)). Equipo estable.
B28: N3 | C28: Gestionado / Gestión por servicios | D28: Métricas avanzadas. Automatización parcial. Gestión proactiva de problemas.
B29: N4 | C29: Optimizado / Gestión integrada | D29: Autoservicio maduro. IA/ML básico. XLA (Experience Level Agreement) medidos. Mejora continua activa.
B30: N5 | C30: Innovador / Diferenciador | D30: IA generativa, predicción, hiper-automatización. Referente del sector.
B32: LEYENDA DE RESPUESTAS — PRÁCTICAS ITIL
B33: RESPUESTA | C33: SIGNIFICADO | D33: COLOR | E33: PUNTAJE
B34: Sí | C34: Cumplimiento completo y documentado | D34: 1F7A4D | E34: 1.0
B35: Parcial | C35: Cumplimiento parcial o en proceso | D35: E07B26 | E35: 0.5
B36: No | C36: No existe o no se cumple | D36: C0392B | E36: 0.0
B37: N/A | C37: No aplica a esta mesa | D37: D9D9D9 | E37: —

Sheet Dashboard
C2: DASHBOARD — MESA DE SERVICIOS DE NUEVA GENERACIÓN | I2: Fecha: 2026/07/03 Clasificación: Interna
C3: Resumen consolidado · Julio 2026 · PersonalSoft
C5: Versión: 1.0
B7: RESUMEN POR MESA DE SERVICIOS — 11 MESAS
B8: MESA | C8: Nivel Madurez | D8: Score Prácticas | E8: FCR (%) | F8: SLA (%) | G8: NPS | H8: FTEs | I8: Dolores Activos | J8: Prioridad Global | K8: Estado
B9: SURA Cotizadores | C9: ='SURA Cotizadores'!C12 -> N2 | D9: =IFERROR('SURA Cotizadores'!E54,0) -> 0.52941176 | E9: =IFERROR('SURA Cotizadores'!C62,0) -> N/D | F9: =IFERROR('SURA Cotizadores'!C64,0) -> 0.7 | G9: =IFERROR('SURA Cotizadores'!C85,0) -> 0 | H9: =IFERROR('SURA Cotizadores'!C68,0) -> 8 | I9: =COUNTIF('SURA Cotizadores'!C95:C112,"Sí")+COUNTIF('SURA Cotizadores'!C95:C112,"Si")+0.5*COUNTIF('SURA Cotizadores'!C95:C112,"Parcial") -> 11 | J9: =IF(D9<30%,"Alta",IF(D9<60%,"Media","Baja")) -> Media | K9: =IF(D9=0,"Pendiente",IF(D9>=70%,"Fuerte",IF(D9>=40%,"En desarrollo","Crítica"))) -> En desarrollo
B10: SURA Digital Venta | C10: =IF('SURA Digital Venta'!C13="","0",'SURA Digital Venta'!C13) -> N2 | D10: =IFERROR('SURA Digital Venta'!E55,0) -> 0.55882353 | E10: =IFERROR('SURA Digital Venta'!C63,0) -> N/D | F10: =IFERROR('SURA Digital Venta'!C65,0) -> 0.74 | G10: =IFERROR('SURA Digital Venta'!C86,0) -> 0 | H10: =IFERROR('SURA Digital Venta'!C69,0) -> 2 | I10: =COUNTIF('SURA Digital Venta'!C95:C112,"Sí")+COUNTIF('SURA Digital Venta'!C95:C112,"Si")+0.5*COUNTIF('SURA Digital Venta'!C95:C112,"Parcial") -> 11 | J10: =IF(D10<30%,"Alta",IF(D10<60%,"Media","Baja")) -> Media | K10: =IF(D10=0,"Pendiente",IF(D10>=70%,"Fuerte",IF(D10>=40%,"En desarrollo","Crítica"))) -> En desarrollo
B11: SURA Automatizacion | C11: =IF('SURA Automatizacion'!C13="","0",'SURA Automatizacion'!C13) -> N2 | D11: =IFERROR('SURA Automatizacion'!E55,0) -> 0.61764706 | E11: =IFERROR('SURA Automatizacion'!C63,0) -> N/D | F11: =IFERROR('SURA Automatizacion'!C65,0) -> 0.98 | G11: =IFERROR('SURA Automatizacion'!C86,0) -> 0 | H11: =IFERROR('SURA Automatizacion'!C69,0) -> 6 | I11: =COUNTIF('SURA Automatizacion'!C95:C112,"Sí")+COUNTIF('SURA Automatizacion'!C95:C112,"Si")+0.5*COUNTIF('SURA Automatizacion'!C95:C112,"Parcial") -> 9.5 | J11: =IF(D11<30%,"Alta",IF(D11<60%,"Media","Baja")) -> Baja | K11: =IF(D11=0,"Pendiente",IF(D11>=70%,"Fuerte",IF(D11>=40%,"En desarrollo","Crítica"))) -> En desarrollo
B12: SURA Canales Masivos | C12: =IF('SURA Canales Masivos'!C13="","0",'SURA Canales Masivos'!C13) -> N2 | D12: =IFERROR('SURA Canales Masivos'!E55,0) -> 0.58823529 | E12: =IFERROR('SURA Canales Masivos'!C63,0) -> N/D | F12: =IFERROR('SURA Canales Masivos'!C65,0) -> 0.72 | G12: =IFERROR('SURA Canales Masivos'!C86,0) -> 0 | H12: =IFERROR('SURA Canales Masivos'!C69,0) -> 1 | I12: =COUNTIF('SURA Canales Masivos'!C95:C112,"Sí")+COUNTIF('SURA Canales Masivos'!C95:C112,"Si")+0.5*COUNTIF('SURA Canales Masivos'!C95:C112,"Parcial") -> 11.5 | J12: =IF(D12<30%,"Alta",IF(D12<60%,"Media","Baja")) -> Media | K12: =IF(D12=0,"Pendiente",IF(D12>=70%,"Fuerte",IF(D12>=40%,"En desarrollo","Crítica"))) -> En desarrollo
B13: BCO Gioti 1 | C13: =IF('BCO Gioti 1'!C14="","0",'BCO Gioti 1'!C14) -> N1 | D13: =IFERROR('BCO Gioti 1'!E56,0) -> 0.79411765 | E13: =IFERROR('BCO Gioti 1'!C64,0) -> 0.68 | F13: =IFERROR('BCO Gioti 1'!C66,0) -> 0.89 | G13: =IFERROR('BCO Gioti 1'!C87,0) -> 0 | H13: =IFERROR('BCO Gioti 1'!C70,0) -> 12 | I13: =COUNTIF('BCO Gioti 1'!C96:C113,"Sí")+COUNTIF('BCO Gioti 1'!C96:C113,"Si")+0.5*COUNTIF('BCO Gioti 1'!C96:C113,"Parcial") -> 1 | J13: =IF(D13<30%,"Alta",IF(D13<60%,"Media","Baja")) -> Baja | K13: =IF(D13=0,"Pendiente",IF(D13>=70%,"Fuerte",IF(D13>=40%,"En desarrollo","Crítica"))) -> Fuerte
B14: BCO Gioti 2 | C14: =IF('BCO Gioti 2'!C14="","0",'BCO Gioti 2'!C14) -> N1 | D14: =IFERROR('BCO Gioti 2'!E56,0) -> 0 | E14: =IFERROR('BCO Gioti 2'!C64,0) -> 0.68 | F14: =IFERROR('BCO Gioti 2'!C66,0) -> 0.89 | G14: =IFERROR('BCO Gioti 2'!C87,0) -> 0 | H14: =IFERROR('BCO Gioti 2'!C70,0) -> 12 | I14: =COUNTIF('BCO Gioti 2'!C96:C113,"Sí")+COUNTIF('BCO Gioti 2'!C96:C113,"Si")+0.5*COUNTIF('BCO Gioti 2'!C96:C113,"Parcial") -> 1 | J14: =IF(D14<30%,"Alta",IF(D14<60%,"Media","Baja")) -> Alta | K14: =IF(D14=0,"Pendiente",IF(D14>=70%,"Fuerte",IF(D14>=40%,"En desarrollo","Crítica"))) -> Pendiente
B15: BCO Gioti 3 | C15: =IF('BCO Gioti 3'!C14="","0",'BCO Gioti 3'!C14) -> N1 | D15: =IFERROR('BCO Gioti 3'!E56,0) -> 0 | E15: =IFERROR('BCO Gioti 3'!C64,0) -> 0.68 | F15: =IFERROR('BCO Gioti 3'!C66,0) -> 0.89 | G15: =IFERROR('BCO Gioti 3'!C87,0) -> 0 | H15: =IFERROR('BCO Gioti 3'!C70,0) -> 12 | I15: =COUNTIF('BCO Gioti 3'!C97:C114,"Sí")+COUNTIF('BCO Gioti 3'!C97:C114,"Si")+0.5*COUNTIF('BCO Gioti 3'!C97:C114,"Parcial") -> 0 | J15: =IF(D15<30%,"Alta",IF(D15<60%,"Media","Baja")) -> Alta | K15: =IF(D15=0,"Pendiente",IF(D15>=70%,"Fuerte",IF(D15>=40%,"En desarrollo","Crítica"))) -> Pendiente
B16: BCO Gioti 4 | C16: =IF('BCO Gioti 4'!C14="","0",'BCO Gioti 4'!C14) -> N1 | D16: =IFERROR('BCO Gioti 4'!E56,0) -> 0 | E16: =IFERROR('BCO Gioti 4'!C64,0) -> 0.68 | F16: =IFERROR('BCO Gioti 4'!C66,0) -> 0.89 | G16: =IFERROR('BCO Gioti 4'!C87,0) -> 0 | H16: =IFERROR('BCO Gioti 4'!C70,0) -> 12 | I16: =COUNTIF('BCO Gioti 4'!C96:C113,"Sí")+COUNTIF('BCO Gioti 4'!C96:C113,"Si")+0.5*COUNTIF('BCO Gioti 4'!C96:C113,"Parcial") -> 0 | J16: =IF(D16<30%,"Alta",IF(D16<60%,"Media","Baja")) -> Alta | K16: =IF(D16=0,"Pendiente",IF(D16>=70%,"Fuerte",IF(D16>=40%,"En desarrollo","Crítica"))) -> Pendiente
B17: AES | C17: =IF(AES!C13="","0",AES!C13) -> N1 | D17: =IFERROR(AES!E54,0) -> 0.29411765 | E17: =IFERROR(AES!C62,0) -> 0 | F17: =IFERROR(AES!C64,0) -> 0 | G17: =IFERROR(AES!C85,0) -> 0 | H17: =IFERROR(AES!C68,0) -> 4 | I17: =COUNTIF(AES!C94:C111,"Sí")+COUNTIF(AES!C94:C111,"Si")+0.5*COUNTIF(AES!C94:C111,"Parcial") -> 6 | J17: =IF(D17<30%,"Alta",IF(D17<60%,"Media","Baja")) -> Alta | K17: =IF(D17=0,"Pendiente",IF(D17>=70%,"Fuerte",IF(D17>=40%,"En desarrollo","Crítica"))) -> Crítica
B18: XM | C18: =IF(XM!C14="","0",XM!C14) -> N1 | D18: =IFERROR(XM!E56,0) -> 0 | E18: =IFERROR(XM!C64,0) -> 0 | F18: =IFERROR(XM!C66,0) -> 0 | G18: =IFERROR(XM!C87,0) -> 0 | H18: =IFERROR(XM!C70,0) -> 0 | I18: =COUNTIF(XM!C96:C113,"Sí")+COUNTIF(XM!C96:C113,"Si")+0.5*COUNTIF(XM!C96:C113,"Parcial") -> 0 | J18: =IF(D18<30%,"Alta",IF(D18<60%,"Media","Baja")) -> Alta | K18: =IF(D18=0,"Pendiente",IF(D18>=70%,"Fuerte",IF(D18>=40%,"En desarrollo","Crítica"))) -> Pendiente
B19: MEDICARTE | C19: =IF(MEDICARTE!C14="","0",MEDICARTE!C14) -> N1 | D19: =IFERROR(MEDICARTE!E56,0) -> 0 | E19: =IFERROR(MEDICARTE!C64,0) -> 0.68 | F19: =IFERROR(MEDICARTE!C66,0) -> 0.89 | G19: =IFERROR(MEDICARTE!C87,0) -> 0 | H19: =IFERROR(MEDICARTE!C70,0) -> 12 | I19: =COUNTIF(MEDICARTE!C96:C113,"Sí")+COUNTIF(MEDICARTE!C96:C113,"Si")+0.5*COUNTIF(MEDICARTE!C96:C113,"Parcial") -> 0 | J19: =IF(D19<30%,"Alta",IF(D19<60%,"Media","Baja")) -> Alta | K19: =IF(D19=0,"Pendiente",IF(D19>=70%,"Fuerte",IF(D19>=40%,"En desarrollo","Crítica"))) -> Pendiente
B22: ESTADÍSTICAS DE CONSOLIDADO
B23: Promedio Score Prácticas ITIL: | E23: =AVERAGE(D9:D19) -> 0.30748663
B24: Score Mínimo: | E24: =MIN(D9:D19) -> 0
B25: Score Máximo: | E25: =MAX(D9:D19) -> 0.79411765
B26: Total FTEs evaluados: | E26: =SUM(H9:H19) -> 81
B27: Mesas evaluadas: | E27: =COUNTA(B9:B19) -> 11
B28: Mesas pendientes / sin datos: | E28: =COUNTIF(K9:K19,"Pendiente") -> 5
B31: SEMÁFORO DE MADUREZ — ESTADO POR MESA
B32: MESA | C32: Nivel | D32: Descripción del Nivel | E32: Score Prácticas | F32: Fortaleza Identificada | G32: Brecha Principal | H32: Acción Recomendada Mesas de Nueva Generación
B33: =B9 -> SURA Cotizadores | C33: =C9 -> N2 | D33: {=_xlfn.SWITCH(C33,"N0","Reactivo / Sin estructura","N1","Inicial / Ad hoc","N2","Definido","N3","Gestionado","N4","Optimizado","N5","Innovador / Diferenciador","— Por definir")} -> Definido | E33: =D9 -> 0.52941176 | F33: =IF(E33>=70%,"Buenas prácticas ITIL consolidadas",IF(E33>=40%,"Base operativa existente","Información o práctica incompleta")) -> Base operativa existente | G33: =IF(E33<40%,"Bajo cumplimiento / datos pendientes",IF(E33<70%,"Estandarización y medición","Escalamiento a automatización")) -> Estandarización y medición | H33: =IF(E33<40%,"Completar levantamiento y priorizar quick wins",IF(E33<70%,"Formalizar procesos, métricas y gobierno","Escalar autoservicio, analítica e IA")) -> Formalizar procesos, métricas y gobierno
B34: =B10 -> SURA Digital Venta | C34: =C10 -> N2 | D34: {=_xlfn.SWITCH(C34,"N0","Reactivo / Sin estructura","N1","Inicial / Ad hoc","N2","Definido","N3","Gestionado","N4","Optimizado","N5","Innovador / Diferenciador","— Por definir")} -> Definido | E34: =D10 -> 0.55882353 | F34: =IF(E34>=70%,"Buenas prácticas ITIL consolidadas",IF(E34>=40%,"Base operativa existente","Información o práctica incompleta")) -> Base operativa existente | G34: =IF(E34<40%,"Bajo cumplimiento / datos pendientes",IF(E34<70%,"Estandarización y medición","Escalamiento a automatización")) -> Estandarización y medición | H34: =IF(E34<40%,"Completar levantamiento y priorizar quick wins",IF(E34<70%,"Formalizar procesos, métricas y gobierno","Escalar autoservicio, analítica e IA")) -> Formalizar procesos, métricas y gobierno
B35: =B11 -> SURA Automatizacion | C35: =C11 -> N2 | D35: {=_xlfn.SWITCH(C35,"N0","Reactivo / Sin estructura","N1","Inicial / Ad hoc","N2","Definido","N3","Gestionado","N4","Optimizado","N5","Innovador / Diferenciador","— Por definir")} -> Definido | E35: =D11 -> 0.61764706 | F35: =IF(E35>=70%,"Buenas prácticas ITIL consolidadas",IF(E35>=40%,"Base operativa existente","Información o práctica incompleta")) -> Base operativa existente | G35: =IF(E35<40%,"Bajo cumplimiento / datos pendientes",IF(E35<70%,"Estandarización y medición","Escalamiento a automatización")) -> Estandarización y medición | H35: =IF(E35<40%,"Completar levantamiento y priorizar quick wins",IF(E35<70%,"Formalizar procesos, métricas y gobierno","Escalar autoservicio, analítica e IA")) -> Formalizar procesos, métricas y gobierno
B36: =B12 -> SURA Canales Masivos | C36: =C12 -> N2 | D36: {=_xlfn.SWITCH(C36,"N0","Reactivo / Sin estructura","N1","Inicial / Ad hoc","N2","Definido","N3","Gestionado","N4","Optimizado","N5","Innovador / Diferenciador","— Por definir")} -> Definido | E36: =D12 -> 0.58823529 | F36: =IF(E36>=70%,"Buenas prácticas ITIL consolidadas",IF(E36>=40%,"Base operativa existente","Información o práctica incompleta")) -> Base operativa existente | G36: =IF(E36<40%,"Bajo cumplimiento / datos pendientes",IF(E36<70%,"Estandarización y medición","Escalamiento a automatización")) -> Estandarización y medición | H36: =IF(E36<40%,"Completar levantamiento y priorizar quick wins",IF(E36<70%,"Formalizar procesos, métricas y gobierno","Escalar autoservicio, analítica e IA")) -> Formalizar procesos, métricas y gobierno
B37: =B13 -> BCO Gioti 1 | C37: =C13 -> N1 | D37: {=_xlfn.SWITCH(C37,"N0","Reactivo / Sin estructura","N1","Inicial / Ad hoc","N2","Definido","N3","Gestionado","N4","Optimizado","N5","Innovador / Diferenciador","— Por definir")} -> Inicial / Ad hoc | E37: =D13 -> 0.79411765 | F37: =IF(E37>=70%,"Buenas prácticas ITIL consolidadas",IF(E37>=40%,"Base operativa existente","Información o práctica incompleta")) -> Buenas prácticas ITIL consolidadas | G37: =IF(E37<40%,"Bajo cumplimiento / datos pendientes",IF(E37<70%,"Estandarización y medición","Escalamiento a automatización")) -> Escalamiento a automatización | H37: =IF(E37<40%,"Completar levantamiento y priorizar quick wins",IF(E37<70%,"Formalizar procesos, métricas y gobierno","Escalar autoservicio, analítica e IA")) -> Escalar autoservicio, analítica e IA
B38: =B14 -> BCO Gioti 2 | C38: =C14 -> N1 | D38: {=_xlfn.SWITCH(C38,"N0","Reactivo / Sin estructura","N1","Inicial / Ad hoc","N2","Definido","N3","Gestionado","N4","Optimizado","N5","Innovador / Diferenciador","— Por definir")} -> Inicial / Ad hoc | E38: =D14 -> 0 | F38: =IF(E38>=70%,"Buenas prácticas ITIL consolidadas",IF(E38>=40%,"Base operativa existente","Información o práctica incompleta")) -> Información o práctica incompleta | G38: =IF(E38<40%,"Bajo cumplimiento / datos pendientes",IF(E38<70%,"Estandarización y medición","Escalamiento a automatización")) -> Bajo cumplimiento / datos pendientes | H38: =IF(E38<40%,"Completar levantamiento y priorizar quick wins",IF(E38<70%,"Formalizar procesos, métricas y gobierno","Escalar autoservicio, analítica e IA")) -> Completar levantamiento y priorizar quick wins
B39: =B15 -> BCO Gioti 3 | C39: =C15 -> N1 | D39: {=_xlfn.SWITCH(C39,"N0","Reactivo / Sin estructura","N1","Inicial / Ad hoc","N2","Definido","N3","Gestionado","N4","Optimizado","N5","Innovador / Diferenciador","— Por definir")} -> Inicial / Ad hoc | E39: =D15 -> 0 | F39: =IF(E39>=70%,"Buenas prácticas ITIL consolidadas",IF(E39>=40%,"Base operativa existente","Información o práctica incompleta")) -> Información o práctica incompleta | G39: =IF(E39<40%,"Bajo cumplimiento / datos pendientes",IF(E39<70%,"Estandarización y medición","Escalamiento a automatización")) -> Bajo cumplimiento / datos pendientes | H39: =IF(E39<40%,"Completar levantamiento y priorizar quick wins",IF(E39<70%,"Formalizar procesos, métricas y gobierno","Escalar autoservicio, analítica e IA")) -> Completar levantamiento y priorizar quick wins
B40: =B16 -> BCO Gioti 4 | C40: =C16 -> N1 | D40: {=_xlfn.SWITCH(C40,"N0","Reactivo / Sin estructura","N1","Inicial / Ad hoc","N2","Definido","N3","Gestionado","N4","Optimizado","N5","Innovador / Diferenciador","— Por definir")} -> Inicial / Ad hoc | E40: =D16 -> 0 | F40: =IF(E40>=70%,"Buenas prácticas ITIL consolidadas",IF(E40>=40%,"Base operativa existente","Información o práctica incompleta")) -> Información o práctica incompleta | G40: =IF(E40<40%,"Bajo cumplimiento / datos pendientes",IF(E40<70%,"Estandarización y medición","Escalamiento a automatización")) -> Bajo cumplimiento / datos pendientes | H40: =IF(E40<40%,"Completar levantamiento y priorizar quick wins",IF(E40<70%,"Formalizar procesos, métricas y gobierno","Escalar autoservicio, analítica e IA")) -> Completar levantamiento y priorizar quick wins
B41: =B17 -> AES | C41: =C17 -> N1 | D41: {=_xlfn.SWITCH(C41,"N0","Reactivo / Sin estructura","N1","Inicial / Ad hoc","N2","Definido","N3","Gestionado","N4","Optimizado","N5","Innovador / Diferenciador","— Por definir")} -> Inicial / Ad hoc | E41: =D17 -> 0.29411765 | F41: =IF(E41>=70%,"Buenas prácticas ITIL consolidadas",IF(E41>=40%,"Base operativa existente","Información o práctica incompleta")) -> Información o práctica incompleta | G41: =IF(E41<40%,"Bajo cumplimiento / datos pendientes",IF(E41<70%,"Estandarización y medición","Escalamiento a automatización")) -> Bajo cumplimiento / datos pendientes | H41: =IF(E41<40%,"Completar levantamiento y priorizar quick wins",IF(E41<70%,"Formalizar procesos, métricas y gobierno","Escalar autoservicio, analítica e IA")) -> Completar levantamiento y priorizar quick wins
B42: =B18 -> XM | C42: =C18 -> N1 | D42: {=_xlfn.SWITCH(C42,"N0","Reactivo / Sin estructura","N1","Inicial / Ad hoc","N2","Definido","N3","Gestionado","N4","Optimizado","N5","Innovador / Diferenciador","— Por definir")} -> Inicial / Ad hoc | E42: =D18 -> 0 | F42: =IF(E42>=70%,"Buenas prácticas ITIL consolidadas",IF(E42>=40%,"Base operativa existente","Información o práctica incompleta")) -> Información o práctica incompleta | G42: =IF(E42<40%,"Bajo cumplimiento / datos pendientes",IF(E42<70%,"Estandarización y medición","Escalamiento a automatización")) -> Bajo cumplimiento / datos pendientes | H42: =IF(E42<40%,"Completar levantamiento y priorizar quick wins",IF(E42<70%,"Formalizar procesos, métricas y gobierno","Escalar autoservicio, analítica e IA")) -> Completar levantamiento y priorizar quick wins
B43: =B19 -> MEDICARTE | C43: =C19 -> N1 | D43: {=_xlfn.SWITCH(C43,"N0","Reactivo / Sin estructura","N1","Inicial / Ad hoc","N2","Definido","N3","Gestionado","N4","Optimizado","N5","Innovador / Diferenciador","— Por definir")} -> Inicial / Ad hoc | E43: =D19 -> 0 | F43: =IF(E43>=70%,"Buenas prácticas ITIL consolidadas",IF(E43>=40%,"Base operativa existente","Información o práctica incompleta")) -> Información o práctica incompleta | G43: =IF(E43<40%,"Bajo cumplimiento / datos pendientes",IF(E43<70%,"Estandarización y medición","Escalamiento a automatización")) -> Bajo cumplimiento / datos pendientes | H43: =IF(E43<40%,"Completar levantamiento y priorizar quick wins",IF(E43<70%,"Formalizar procesos, métricas y gobierno","Escalar autoservicio, analítica e IA")) -> Completar levantamiento y priorizar quick wins
B45: DOLORES ACTIVOS POR MESA — D1–D18 (✓=Sí · ~=Parcial)
B46: DOLOR | C46: SURA Cotiz. | D46: SURA Venta D. | E46: SURA Torre | F46: SURA Mesa 4 | G46: BCO Gioti 1 | H46: BCO Gioti 2 | I46: BCO Gioti 3 | J46: BCO Gioti 4 | K46: AES | L46: XM | M46: MEDICARTE | N46: TOTAL
B47: D1: Sí | C47: =IF(OR('SURA Cotizadores'!C95="Sí",'SURA Cotizadores'!C95="Si"),"✓",IF('SURA Cotizadores'!C95="Parcial","~","")) -> ~ | D47: =IF(OR('SURA Digital Venta'!C95="Sí",'SURA Digital Venta'!C95="Si"),"✓",IF('SURA Digital Venta'!C95="Parcial","~","")) | E47: =IF(OR('SURA Automatizacion'!C95="Sí",'SURA Automatizacion'!C95="Si"),"✓",IF('SURA Automatizacion'!C95="Parcial","~","")) | F47: =IF(OR('SURA Canales Masivos'!C95="Sí",'SURA Canales Masivos'!C95="Si"),"✓",IF('SURA Canales Masivos'!C95="Parcial","~","")) | G47: =IF(OR('BCO Gioti 1'!C96="Sí",'BCO Gioti 1'!C96="Si"),"✓",IF('BCO Gioti 1'!C96="Parcial","~","")) | H47: =IF(OR('BCO Gioti 2'!C96="Sí",'BCO Gioti 2'!C96="Si"),"✓",IF('BCO Gioti 2'!C96="Parcial","~","")) | I47: =IF(OR('BCO Gioti 3'!C97="Sí",'BCO Gioti 3'!C97="Si"),"✓",IF('BCO Gioti 3'!C97="Parcial","~","")) | J47: =IF(OR('BCO Gioti 4'!C96="Sí",'BCO Gioti 4'!C96="Si"),"✓",IF('BCO Gioti 4'!C96="Parcial","~","")) | K47: =IF(OR(AES!C94="Sí",AES!C94="Si"),"✓",IF(AES!C94="Parcial","~","")) | L47: =IF(OR(XM!C96="Sí",XM!C96="Si"),"✓",IF(XM!C96="Parcial","~","")) | M47: =IF(OR(MEDICARTE!C96="Sí",MEDICARTE!C96="Si"),"✓",IF(MEDICARTE!C96="Parcial","~","")) | N47: =COUNTIF(C47:M47,"✓")+0.5*COUNTIF(C47:M47,"~") -> 0.5
B48: D2: Parcial | C48: =IF(OR('SURA Cotizadores'!C96="Sí",'SURA Cotizadores'!C96="Si"),"✓",IF('SURA Cotizadores'!C96="Parcial","~","")) -> ✓ | D48: =IF(OR('SURA Digital Venta'!C96="Sí",'SURA Digital Venta'!C96="Si"),"✓",IF('SURA Digital Venta'!C96="Parcial","~","")) -> ~ | E48: =IF(OR('SURA Automatizacion'!C96="Sí",'SURA Automatizacion'!C96="Si"),"✓",IF('SURA Automatizacion'!C96="Parcial","~","")) -> ~ | F48: =IF(OR('SURA Canales Masivos'!C96="Sí",'SURA Canales Masivos'!C96="Si"),"✓",IF('SURA Canales Masivos'!C96="Parcial","~","")) -> ~ | G48: =IF(OR('BCO Gioti 1'!C97="Sí",'BCO Gioti 1'!C97="Si"),"✓",IF('BCO Gioti 1'!C97="Parcial","~","")) -> ~ | H48: =IF(OR('BCO Gioti 2'!C97="Sí",'BCO Gioti 2'!C97="Si"),"✓",IF('BCO Gioti 2'!C97="Parcial","~","")) | I48: =IF(OR('BCO Gioti 3'!C98="Sí",'BCO Gioti 3'!C98="Si"),"✓",IF('BCO Gioti 3'!C98="Parcial","~","")) | J48: =IF(OR('BCO Gioti 4'!C97="Sí",'BCO Gioti 4'!C97="Si"),"✓",IF('BCO Gioti 4'!C97="Parcial","~","")) | K48: =IF(OR(AES!C95="Sí",AES!C95="Si"),"✓",IF(AES!C95="Parcial","~","")) | L48: =IF(OR(XM!C97="Sí",XM!C97="Si"),"✓",IF(XM!C97="Parcial","~","")) | M48: =IF(OR(MEDICARTE!C97="Sí",MEDICARTE!C97="Si"),"✓",IF(MEDICARTE!C97="Parcial","~","")) | N48: =COUNTIF(C48:M48,"✓")+0.5*COUNTIF(C48:M48,"~") -> 3
B49: D3: Sí | C49: =IF(OR('SURA Cotizadores'!C97="Sí",'SURA Cotizadores'!C97="Si"),"✓",IF('SURA Cotizadores'!C97="Parcial","~","")) -> ✓ | D49: =IF(OR('SURA Digital Venta'!C97="Sí",'SURA Digital Venta'!C97="Si"),"✓",IF('SURA Digital Venta'!C97="Parcial","~","")) -> ✓ | E49: =IF(OR('SURA Automatizacion'!C97="Sí",'SURA Automatizacion'!C97="Si"),"✓",IF('SURA Automatizacion'!C97="Parcial","~","")) | F49: =IF(OR('SURA Canales Masivos'!C97="Sí",'SURA Canales Masivos'!C97="Si"),"✓",IF('SURA Canales Masivos'!C97="Parcial","~","")) -> ✓ | G49: =IF(OR('BCO Gioti 1'!C98="Sí",'BCO Gioti 1'!C98="Si"),"✓",IF('BCO Gioti 1'!C98="Parcial","~","")) | H49: =IF(OR('BCO Gioti 2'!C98="Sí",'BCO Gioti 2'!C98="Si"),"✓",IF('BCO Gioti 2'!C98="Parcial","~","")) | I49: =IF(OR('BCO Gioti 3'!C99="Sí",'BCO Gioti 3'!C99="Si"),"✓",IF('BCO Gioti 3'!C99="Parcial","~","")) | J49: =IF(OR('BCO Gioti 4'!C98="Sí",'BCO Gioti 4'!C98="Si"),"✓",IF('BCO Gioti 4'!C98="Parcial","~","")) | K49: =IF(OR(AES!C96="Sí",AES!C96="Si"),"✓",IF(AES!C96="Parcial","~","")) | L49: =IF(OR(XM!C98="Sí",XM!C98="Si"),"✓",IF(XM!C98="Parcial","~","")) | M49: =IF(OR(MEDICARTE!C98="Sí",MEDICARTE!C98="Si"),"✓",IF(MEDICARTE!C98="Parcial","~","")) | N49: =COUNTIF(C49:M49,"✓")+0.5*COUNTIF(C49:M49,"~") -> 3
B50: D4: Sí | C50: =IF(OR('SURA Cotizadores'!C98="Sí",'SURA Cotizadores'!C98="Si"),"✓",IF('SURA Cotizadores'!C98="Parcial","~","")) -> ~ | D50: =IF(OR('SURA Digital Venta'!C98="Sí",'SURA Digital Venta'!C98="Si"),"✓",IF('SURA Digital Venta'!C98="Parcial","~","")) -> ✓ | E50: =IF(OR('SURA Automatizacion'!C98="Sí",'SURA Automatizacion'!C98="Si"),"✓",IF('SURA Automatizacion'!C98="Parcial","~","")) -> ✓ | F50: =IF(OR('SURA Canales Masivos'!C98="Sí",'SURA Canales Masivos'!C98="Si"),"✓",IF('SURA Canales Masivos'!C98="Parcial","~","")) -> ✓ | G50: =IF(OR('BCO Gioti 1'!C99="Sí",'BCO Gioti 1'!C99="Si"),"✓",IF('BCO Gioti 1'!C99="Parcial","~","")) -> ~ | H50: =IF(OR('BCO Gioti 2'!C99="Sí",'BCO Gioti 2'!C99="Si"),"✓",IF('BCO Gioti 2'!C99="Parcial","~","")) | I50: =IF(OR('BCO Gioti 3'!C100="Sí",'BCO Gioti 3'!C100="Si"),"✓",IF('BCO Gioti 3'!C100="Parcial","~","")) | J50: =IF(OR('BCO Gioti 4'!C99="Sí",'BCO Gioti 4'!C99="Si"),"✓",IF('BCO Gioti 4'!C99="Parcial","~","")) | K50: =IF(OR(AES!C97="Sí",AES!C97="Si"),"✓",IF(AES!C97="Parcial","~","")) | L50: =IF(OR(XM!C99="Sí",XM!C99="Si"),"✓",IF(XM!C99="Parcial","~","")) | M50: =IF(OR(MEDICARTE!C99="Sí",MEDICARTE!C99="Si"),"✓",IF(MEDICARTE!C99="Parcial","~","")) | N50: =COUNTIF(C50:M50,"✓")+0.5*COUNTIF(C50:M50,"~") -> 4
B51: D5: Sí | C51: =IF(OR('SURA Cotizadores'!C99="Sí",'SURA Cotizadores'!C99="Si"),"✓",IF('SURA Cotizadores'!C99="Parcial","~","")) | D51: =IF(OR('SURA Digital Venta'!C99="Sí",'SURA Digital Venta'!C99="Si"),"✓",IF('SURA Digital Venta'!C99="Parcial","~","")) -> ~ | E51: =IF(OR('SURA Automatizacion'!C99="Sí",'SURA Automatizacion'!C99="Si"),"✓",IF('SURA Automatizacion'!C99="Parcial","~","")) -> ~ | F51: =IF(OR('SURA Canales Masivos'!C99="Sí",'SURA Canales Masivos'!C99="Si"),"✓",IF('SURA Canales Masivos'!C99="Parcial","~","")) -> ~ | G51: =IF(OR('BCO Gioti 1'!C100="Sí",'BCO Gioti 1'!C100="Si"),"✓",IF('BCO Gioti 1'!C100="Parcial","~","")) | H51: =IF(OR('BCO Gioti 2'!C100="Sí",'BCO Gioti 2'!C100="Si"),"✓",IF('BCO Gioti 2'!C100="Parcial","~","")) | I51: =IF(OR('BCO Gioti 3'!C101="Sí",'BCO Gioti 3'!C101="Si"),"✓",IF('BCO Gioti 3'!C101="Parcial","~","")) | J51: =IF(OR('BCO Gioti 4'!C100="Sí",'BCO Gioti 4'!C100="Si"),"✓",IF('BCO Gioti 4'!C100="Parcial","~","")) | K51: =IF(OR(AES!C98="Sí",AES!C98="Si"),"✓",IF(AES!C98="Parcial","~","")) -> ~ | L51: =IF(OR(XM!C100="Sí",XM!C100="Si"),"✓",IF(XM!C100="Parcial","~","")) | M51: =IF(OR(MEDICARTE!C100="Sí",MEDICARTE!C100="Si"),"✓",IF(MEDICARTE!C100="Parcial","~","")) | N51: =COUNTIF(C51:M51,"✓")+0.5*COUNTIF(C51:M51,"~") -> 2
B52: D6: Parcial | C52: =IF(OR('SURA Cotizadores'!C100="Sí",'SURA Cotizadores'!C100="Si"),"✓",IF('SURA Cotizadores'!C100="Parcial","~","")) -> ~ | D52: =IF(OR('SURA Digital Venta'!C100="Sí",'SURA Digital Venta'!C100="Si"),"✓",IF('SURA Digital Venta'!C100="Parcial","~","")) | E52: =IF(OR('SURA Automatizacion'!C100="Sí",'SURA Automatizacion'!C100="Si"),"✓",IF('SURA Automatizacion'!C100="Parcial","~","")) | F52: =IF(OR('SURA Canales Masivos'!C100="Sí",'SURA Canales Masivos'!C100="Si"),"✓",IF('SURA Canales Masivos'!C100="Parcial","~","")) | G52: =IF(OR('BCO Gioti 1'!C101="Sí",'BCO Gioti 1'!C101="Si"),"✓",IF('BCO Gioti 1'!C101="Parcial","~","")) | H52: =IF(OR('BCO Gioti 2'!C101="Sí",'BCO Gioti 2'!C101="Si"),"✓",IF('BCO Gioti 2'!C101="Parcial","~","")) | I52: =IF(OR('BCO Gioti 3'!C102="Sí",'BCO Gioti 3'!C102="Si"),"✓",IF('BCO Gioti 3'!C102="Parcial","~","")) | J52: =IF(OR('BCO Gioti 4'!C101="Sí",'BCO Gioti 4'!C101="Si"),"✓",IF('BCO Gioti 4'!C101="Parcial","~","")) | K52: =IF(OR(AES!C99="Sí",AES!C99="Si"),"✓",IF(AES!C99="Parcial","~","")) | L52: =IF(OR(XM!C101="Sí",XM!C101="Si"),"✓",IF(XM!C101="Parcial","~","")) | M52: =IF(OR(MEDICARTE!C101="Sí",MEDICARTE!C101="Si"),"✓",IF(MEDICARTE!C101="Parcial","~","")) | N52: =COUNTIF(C52:M52,"✓")+0.5*COUNTIF(C52:M52,"~") -> 0.5
B53: D7: No | C53: =IF(OR('SURA Cotizadores'!C101="Sí",'SURA Cotizadores'!C101="Si"),"✓",IF('SURA Cotizadores'!C101="Parcial","~","")) -> ~ | D53: =IF(OR('SURA Digital Venta'!C101="Sí",'SURA Digital Venta'!C101="Si"),"✓",IF('SURA Digital Venta'!C101="Parcial","~","")) -> ~ | E53: =IF(OR('SURA Automatizacion'!C101="Sí",'SURA Automatizacion'!C101="Si"),"✓",IF('SURA Automatizacion'!C101="Parcial","~","")) -> ~ | F53: =IF(OR('SURA Canales Masivos'!C101="Sí",'SURA Canales Masivos'!C101="Si"),"✓",IF('SURA Canales Masivos'!C101="Parcial","~","")) -> ~ | G53: =IF(OR('BCO Gioti 1'!C102="Sí",'BCO Gioti 1'!C102="Si"),"✓",IF('BCO Gioti 1'!C102="Parcial","~","")) | H53: =IF(OR('BCO Gioti 2'!C102="Sí",'BCO Gioti 2'!C102="Si"),"✓",IF('BCO Gioti 2'!C102="Parcial","~","")) | I53: =IF(OR('BCO Gioti 3'!C103="Sí",'BCO Gioti 3'!C103="Si"),"✓",IF('BCO Gioti 3'!C103="Parcial","~","")) | J53: =IF(OR('BCO Gioti 4'!C102="Sí",'BCO Gioti 4'!C102="Si"),"✓",IF('BCO Gioti 4'!C102="Parcial","~","")) | K53: =IF(OR(AES!C100="Sí",AES!C100="Si"),"✓",IF(AES!C100="Parcial","~","")) -> ~ | L53: =IF(OR(XM!C102="Sí",XM!C102="Si"),"✓",IF(XM!C102="Parcial","~","")) | M53: =IF(OR(MEDICARTE!C102="Sí",MEDICARTE!C102="Si"),"✓",IF(MEDICARTE!C102="Parcial","~","")) | N53: =COUNTIF(C53:M53,"✓")+0.5*COUNTIF(C53:M53,"~") -> 2.5
B54: D8: | C54: =IF(OR('SURA Cotizadores'!C102="Sí",'SURA Cotizadores'!C102="Si"),"✓",IF('SURA Cotizadores'!C102="Parcial","~","")) -> ~ | D54: =IF(OR('SURA Digital Venta'!C102="Sí",'SURA Digital Venta'!C102="Si"),"✓",IF('SURA Digital Venta'!C102="Parcial","~","")) -> ✓ | E54: =IF(OR('SURA Automatizacion'!C102="Sí",'SURA Automatizacion'!C102="Si"),"✓",IF('SURA Automatizacion'!C102="Parcial","~","")) -> ✓ | F54: =IF(OR('SURA Canales Masivos'!C102="Sí",'SURA Canales Masivos'!C102="Si"),"✓",IF('SURA Canales Masivos'!C102="Parcial","~","")) -> ~ | G54: =IF(OR('BCO Gioti 1'!C103="Sí",'BCO Gioti 1'!C103="Si"),"✓",IF('BCO Gioti 1'!C103="Parcial","~","")) | H54: =IF(OR('BCO Gioti 2'!C103="Sí",'BCO Gioti 2'!C103="Si"),"✓",IF('BCO Gioti 2'!C103="Parcial","~","")) | I54: =IF(OR('BCO Gioti 3'!C104="Sí",'BCO Gioti 3'!C104="Si"),"✓",IF('BCO Gioti 3'!C104="Parcial","~","")) | J54: =IF(OR('BCO Gioti 4'!C103="Sí",'BCO Gioti 4'!C103="Si"),"✓",IF('BCO Gioti 4'!C103="Parcial","~","")) | K54: =IF(OR(AES!C101="Sí",AES!C101="Si"),"✓",IF(AES!C101="Parcial","~","")) | L54: =IF(OR(XM!C103="Sí",XM!C103="Si"),"✓",IF(XM!C103="Parcial","~","")) | M54: =IF(OR(MEDICARTE!C103="Sí",MEDICARTE!C103="Si"),"✓",IF(MEDICARTE!C103="Parcial","~","")) | N54: =COUNTIF(C54:M54,"✓")+0.5*COUNTIF(C54:M54,"~") -> 3
B55: D9: | C55: =IF(OR('SURA Cotizadores'!C103="Sí",'SURA Cotizadores'!C103="Si"),"✓",IF('SURA Cotizadores'!C103="Parcial","~","")) -> ✓ | D55: =IF(OR('SURA Digital Venta'!C103="Sí",'SURA Digital Venta'!C103="Si"),"✓",IF('SURA Digital Venta'!C103="Parcial","~","")) -> ~ | E55: =IF(OR('SURA Automatizacion'!C103="Sí",'SURA Automatizacion'!C103="Si"),"✓",IF('SURA Automatizacion'!C103="Parcial","~","")) -> ~ | F55: =IF(OR('SURA Canales Masivos'!C103="Sí",'SURA Canales Masivos'!C103="Si"),"✓",IF('SURA Canales Masivos'!C103="Parcial","~","")) -> ~ | G55: =IF(OR('BCO Gioti 1'!C104="Sí",'BCO Gioti 1'!C104="Si"),"✓",IF('BCO Gioti 1'!C104="Parcial","~","")) | H55: =IF(OR('BCO Gioti 2'!C104="Sí",'BCO Gioti 2'!C104="Si"),"✓",IF('BCO Gioti 2'!C104="Parcial","~","")) | I55: =IF(OR('BCO Gioti 3'!C105="Sí",'BCO Gioti 3'!C105="Si"),"✓",IF('BCO Gioti 3'!C105="Parcial","~","")) | J55: =IF(OR('BCO Gioti 4'!C104="Sí",'BCO Gioti 4'!C104="Si"),"✓",IF('BCO Gioti 4'!C104="Parcial","~","")) | K55: =IF(OR(AES!C102="Sí",AES!C102="Si"),"✓",IF(AES!C102="Parcial","~","")) | L55: =IF(OR(XM!C104="Sí",XM!C104="Si"),"✓",IF(XM!C104="Parcial","~","")) | M55: =IF(OR(MEDICARTE!C104="Sí",MEDICARTE!C104="Si"),"✓",IF(MEDICARTE!C104="Parcial","~","")) | N55: =COUNTIF(C55:M55,"✓")+0.5*COUNTIF(C55:M55,"~") -> 2.5
B56: D10: Sí | C56: =IF(OR('SURA Cotizadores'!C104="Sí",'SURA Cotizadores'!C104="Si"),"✓",IF('SURA Cotizadores'!C104="Parcial","~","")) -> ~ | D56: =IF(OR('SURA Digital Venta'!C104="Sí",'SURA Digital Venta'!C104="Si"),"✓",IF('SURA Digital Venta'!C104="Parcial","~","")) -> ✓ | E56: =IF(OR('SURA Automatizacion'!C104="Sí",'SURA Automatizacion'!C104="Si"),"✓",IF('SURA Automatizacion'!C104="Parcial","~","")) -> ✓ | F56: =IF(OR('SURA Canales Masivos'!C104="Sí",'SURA Canales Masivos'!C104="Si"),"✓",IF('SURA Canales Masivos'!C104="Parcial","~","")) -> ✓ | G56: =IF(OR('BCO Gioti 1'!C105="Sí",'BCO Gioti 1'!C105="Si"),"✓",IF('BCO Gioti 1'!C105="Parcial","~","")) | H56: =IF(OR('BCO Gioti 2'!C105="Sí",'BCO Gioti 2'!C105="Si"),"✓",IF('BCO Gioti 2'!C105="Parcial","~","")) | I56: =IF(OR('BCO Gioti 3'!C106="Sí",'BCO Gioti 3'!C106="Si"),"✓",IF('BCO Gioti 3'!C106="Parcial","~","")) | J56: =IF(OR('BCO Gioti 4'!C105="Sí",'BCO Gioti 4'!C105="Si"),"✓",IF('BCO Gioti 4'!C105="Parcial","~","")) | K56: =IF(OR(AES!C103="Sí",AES!C103="Si"),"✓",IF(AES!C103="Parcial","~","")) -> ~ | L56: =IF(OR(XM!C105="Sí",XM!C105="Si"),"✓",IF(XM!C105="Parcial","~","")) | M56: =IF(OR(MEDICARTE!C105="Sí",MEDICARTE!C105="Si"),"✓",IF(MEDICARTE!C105="Parcial","~","")) | N56: =COUNTIF(C56:M56,"✓")+0.5*COUNTIF(C56:M56,"~") -> 4
B57: D11: | C57: =IF(OR('SURA Cotizadores'!C105="Sí",'SURA Cotizadores'!C105="Si"),"✓",IF('SURA Cotizadores'!C105="Parcial","~","")) -> ~ | D57: =IF(OR('SURA Digital Venta'!C105="Sí",'SURA Digital Venta'!C105="Si"),"✓",IF('SURA Digital Venta'!C105="Parcial","~","")) -> ~ | E57: =IF(OR('SURA Automatizacion'!C105="Sí",'SURA Automatizacion'!C105="Si"),"✓",IF('SURA Automatizacion'!C105="Parcial","~","")) -> ~ | F57: =IF(OR('SURA Canales Masivos'!C105="Sí",'SURA Canales Masivos'!C105="Si"),"✓",IF('SURA Canales Masivos'!C105="Parcial","~","")) -> ~ | G57: =IF(OR('BCO Gioti 1'!C106="Sí",'BCO Gioti 1'!C106="Si"),"✓",IF('BCO Gioti 1'!C106="Parcial","~","")) | H57: =IF(OR('BCO Gioti 2'!C106="Sí",'BCO Gioti 2'!C106="Si"),"✓",IF('BCO Gioti 2'!C106="Parcial","~","")) | I57: =IF(OR('BCO Gioti 3'!C107="Sí",'BCO Gioti 3'!C107="Si"),"✓",IF('BCO Gioti 3'!C107="Parcial","~","")) | J57: =IF(OR('BCO Gioti 4'!C106="Sí",'BCO Gioti 4'!C106="Si"),"✓",IF('BCO Gioti 4'!C106="Parcial","~","")) | K57: =IF(OR(AES!C104="Sí",AES!C104="Si"),"✓",IF(AES!C104="Parcial","~","")) -> ~ | L57: =IF(OR(XM!C106="Sí",XM!C106="Si"),"✓",IF(XM!C106="Parcial","~","")) | M57: =IF(OR(MEDICARTE!C106="Sí",MEDICARTE!C106="Si"),"✓",IF(MEDICARTE!C106="Parcial","~","")) | N57: =COUNTIF(C57:M57,"✓")+0.5*COUNTIF(C57:M57,"~") -> 2.5
B58: D12: | C58: =IF(OR('SURA Cotizadores'!C106="Sí",'SURA Cotizadores'!C106="Si"),"✓",IF('SURA Cotizadores'!C106="Parcial","~","")) -> ~ | D58: =IF(OR('SURA Digital Venta'!C106="Sí",'SURA Digital Venta'!C106="Si"),"✓",IF('SURA Digital Venta'!C106="Parcial","~","")) -> ~ | E58: =IF(OR('SURA Automatizacion'!C106="Sí",'SURA Automatizacion'!C106="Si"),"✓",IF('SURA Automatizacion'!C106="Parcial","~","")) -> ~ | F58: =IF(OR('SURA Canales Masivos'!C106="Sí",'SURA Canales Masivos'!C106="Si"),"✓",IF('SURA Canales Masivos'!C106="Parcial","~","")) -> ~ | G58: =IF(OR('BCO Gioti 1'!C107="Sí",'BCO Gioti 1'!C107="Si"),"✓",IF('BCO Gioti 1'!C107="Parcial","~","")) | H58: =IF(OR('BCO Gioti 2'!C107="Sí",'BCO Gioti 2'!C107="Si"),"✓",IF('BCO Gioti 2'!C107="Parcial","~","")) | I58: =IF(OR('BCO Gioti 3'!C108="Sí",'BCO Gioti 3'!C108="Si"),"✓",IF('BCO Gioti 3'!C108="Parcial","~","")) | J58: =IF(OR('BCO Gioti 4'!C107="Sí",'BCO Gioti 4'!C107="Si"),"✓",IF('BCO Gioti 4'!C107="Parcial","~","")) | K58: =IF(OR(AES!C105="Sí",AES!C105="Si"),"✓",IF(AES!C105="Parcial","~","")) -> ✓ | L58: =IF(OR(XM!C107="Sí",XM!C107="Si"),"✓",IF(XM!C107="Parcial","~","")) | M58: =IF(OR(MEDICARTE!C107="Sí",MEDICARTE!C107="Si"),"✓",IF(MEDICARTE!C107="Parcial","~","")) | N58: =COUNTIF(C58:M58,"✓")+0.5*COUNTIF(C58:M58,"~") -> 3
... B64: D18: Sí | C64: =IF(OR('SURA Cotizadores'!C112="Sí",'SURA Cotizadores'!C112="Si"),"✓",IF('SURA Cotizadores'!C112="Parcial","~","")) -> ~ | D64: =IF(OR('SURA Digital Venta'!C112="Sí",'SURA Digital Venta'!C112="Si"),"✓",IF('SURA Digital Venta'!C112="Parcial","~","")) -> ~ | E64: =IF(OR('SURA Automatizacion'!C112="Sí",'SURA Automatizacion'!C112="Si"),"✓",IF('SURA Automatizacion'!C112="Parcial","~","")) -> ~ | F64: =IF(OR('SURA Canales Masivos'!C112="Sí",'SURA Canales Masivos'!C112="Si"),"✓",IF('SURA Canales Masivos'!C112="Parcial","~","")) -> ✓ | G64: =IF(OR('BCO Gioti 1'!C113="Sí",'BCO Gioti 1'!C113="Si"),"✓",IF('BCO Gioti 1'!C113="Parcial","~","")) | H64: =IF(OR('BCO Gioti 2'!C113="Sí",'BCO Gioti 2'!C113="Si"),"✓",IF('BCO Gioti 2'!C113="Parcial","~","")) | I64: =IF(OR('BCO Gioti 3'!C114="Sí",'BCO Gioti 3'!C114="Si"),"✓",IF('BCO Gioti 3'!C114="Parcial","~","")) | J64: =IF(OR('BCO Gioti 4'!C113="Sí",'BCO Gioti 4'!C113="Si"),"✓",IF('BCO Gioti 4'!C113="Parcial","~","")) | K64: =IF(OR(AES!C111="Sí",AES!C111="Si"),"✓",IF(AES!C111="Parcial","~","")) -> ✓ | L64: =IF(OR(XM!C113="Sí",XM!C113="Si"),"✓",IF(XM!C113="Parcial","~","")) | M64: =IF(OR(MEDICARTE!C113="Sí",MEDICARTE!C113="Si"),"✓",IF(MEDICARTE!C113="Parcial","~","")) | N64: =COUNTIF(C64:M64,"✓")+0.5*COUNTIF(C64:M64,"~") -> 3.5
B111: COBERTURA PROMEDIO POR DIMENSIÓN

Sheet Graficas
E2: ANÁLISIS VISUAL— MESA DE SERVICIOS DE NUEVA GENERACIÓN | N2: Fecha: 2026/07/03 Clasificación: Interna
E3: Dashboard de madurez · prácticas · dolores · industria vs benchmark · Gen Next
E5: Versión: 1.0
B7: GRÁFICAS POR BLOQUE DE EVALUACIÓN — 11 DIMENSIONES + ④b

Sheet ChartData
A1: TABLA 1 — MADUREZ NUMÉRICA (N0-N5) | K1: HELPERS PARA GRÁFICAS | X1: ① Identificación general — completitud | AA1: ② Nivel de madurez actual | AE1: ③ Prácticas ITIL — score global | AH1: ④ Volumetría y KPIs — FCR/SLA | AM1: ④b Incidentes por categoría — tickets/mes | AP1: ⑤ XLA / DEX — NPS | AS1: ⑥ Dolores críticos — total activo D1–D18 | AV1: ⑦ Rotación y talento — completitud | AY1: ⑧ Tecnología y herramientas — herramientas registradas | BB1: ⑨ Modelo económico — completitud | BE1: ⑩ Visión nuevo servicio — completitud | BH1: ⑪ Casos de éxito — completitud | BK1: RESUMEN PROMEDIO POR DIMENSIÓN | BO1: DOLORES CONSOLIDADOS D1–D18
A2: Mesa | B2: Nivel Madurez (texto) | C2: Madurez Numérica (0-5) | D2: Meta (N3) | K2: Mesa | L2: Madurez | M2: Meta | X2: Mesa | Y2: Completitud | AA2: Mesa | AB2: Madurez | AC2: Meta N3 | AE2: Mesa | AF2: Score ITIL | AH2: Mesa | AI2: FCR | AJ2: SLA | AM2: Mesa | AN2: Tickets categorizados | AP2: Mesa | AQ2: NPS | AS2: Mesa | AT2: Dolores activos D1–D18 | AV2: Mesa | AW2: Completitud | AY2: Mesa | AZ2: Herramientas registradas | BB2: Mesa | BC2: Completitud | BE2: Mesa | BF2: Completitud | BH2: Mesa | BI2: Completitud | BK2: Dimensión | BL2: Promedio | BM2: Meta | BO2: Dolor | BP2: Total ponderado
A3: SURA Cotizadores | B3: ='SURA Cotizadores'!C12 -> N2 | C3: =VALUE(SUBSTITUTE(B3,"N","")) -> 2 | D3: 3 | K3: SURA Cotizadores | L3: =C3 -> 2 | M3: =D3 -> 3 | X3: SURA Cotizadores | Y3: =IFERROR(COUNTA('SURA Cotizadores'!C4:C17)/15,0) -> 0.86666667 | AA3: SURA Cotizadores | AB3: =C3 -> 2 | AC3: =3 -> 3 | AE3: SURA Cotizadores | AF3: =IFERROR((COUNTIF('SURA Cotizadores'!D30:D52,"Sí")+COUNTIF('SURA Cotizadores'!D30:D52,"Si")+0.5*COUNTIF('SURA Cotizadores'!D30:D52,"Parcial"))/(COUNTIF('SURA Cotizadores'!D30:D52,"Sí")+COUNTIF('SURA Cotizadores'!D30:D52,"Si")+COUNTIF('SURA Cotizadores'!D30:D52,"Parcial")+COUNTIF('SURA Cotizadores'!D30:D52,"No")),0) -> 0.52941176 | AH3: SURA Cotizadores | AI3: =IFERROR('SURA Cotizadores'!C62,0) -> N/D | AJ3: =IFERROR('SURA Cotizadores'!C64,0) -> 0.7 | AM3: SURA Cotizadores | AN3: =IFERROR(SUM('SURA Cotizadores'!C73:C81),0) -> 668 | AP3: SURA Cotizadores | AQ3: =IFERROR('SURA Cotizadores'!C85,0) -> 0 | AS3: SURA Cotizadores | AT3: =COUNTIF('SURA Cotizadores'!C95:C112,"Sí")+COUNTIF('SURA Cotizadores'!C95:C112,"Si")+0.5*COUNTIF('SURA Cotizadores'!C95:C112,"Parcial") -> 11 | AV3: SURA Cotizadores | AW3: =IFERROR(COUNTA('SURA Cotizadores'!C119:C126)/8,0) -> 0.5 | AY3: SURA Cotizadores | AZ3: =IFERROR(COUNTA('SURA Cotizadores'!C130:C139),0) -> 4 | BB3: SURA Cotizadores | BC3: =IFERROR(COUNTA('SURA Cotizadores'!C143:C149)/7,0) -> 1 | BE3: SURA Cotizadores | BF3: =IFERROR(COUNTA('SURA Cotizadores'!C153:C161)/9,0) -> 1 | BH3: SURA Cotizadores | BI3: =IFERROR(COUNTA('SURA Cotizadores'!C165:G175)/20,0) -> 0.35 | BK3: ① Identificación general | BL3: =AVERAGE(Y3:Y13) -> 0.64242424 | BM3: =100% -> 1 | BO3: D1: Sí | BP3: =Dashboard!N47 -> 0.5
A4: SURA Digital Venta | B4: =IF('SURA Digital Venta'!C13="","0",'SURA Digital Venta'!C13) -> N2 | C4: =IFERROR(VALUE(RIGHT(B4,1)),0) -> 2 | D4: 3 | K4: SURA Digital Venta | L4: =C4 -> 2 | M4: =D4 -> 3 | X4: SURA Digital Venta | Y4: =IFERROR(COUNTA('SURA Digital Venta'!C4:C18)/15,0) -> 0.86666667 | AA4: SURA Digital Venta | AB4: =IFERROR(VALUE(RIGHT('SURA Digital Venta'!C13,1)),0) -> 2 | AC4: =3 -> 3 | AE4: SURA Digital Venta | AF4: =IFERROR((COUNTIF('SURA Digital Venta'!D31:D53,"Sí")+COUNTIF('SURA Digital Venta'!D31:D53,"Si")+0.5*COUNTIF('SURA Digital Venta'!D31:D53,"Parcial"))/(COUNTIF('SURA Digital Venta'!D31:D53,"Sí")+COUNTIF('SURA Digital Venta'!D31:D53,"Si")+COUNTIF('SURA Digital Venta'!D31:D53,"Parcial")+COUNTIF('SURA Digital Venta'!D31:D53,"No")),0) -> 0.55882353 | AH4: SURA Digital Venta | AI4: =IFERROR('SURA Digital Venta'!C63,0) -> N/D | AJ4: =IFERROR('SURA Digital Venta'!C65,0) -> 0.74 | AM4: SURA Digital Venta | AN4: =IFERROR(SUM('SURA Digital Venta'!C74:C82),0) -> 174 | AP4: SURA Digital Venta | AQ4: =IFERROR('SURA Digital Venta'!C86,0) -> 0 | AS4: SURA Digital Venta | AT4: =COUNTIF('SURA Digital Venta'!C95:C112,"Sí")+COUNTIF('SURA Digital Venta'!C95:C112,"Si")+0.5*COUNTIF('SURA Digital Venta'!C95:C112,"Parcial") -> 11 | AV4: SURA Digital Venta | AW4: =IFERROR(COUNTA('SURA Digital Venta'!C119:C126)/8,0) -> 0.5 | AY4: SURA Digital Venta | AZ4: =IFERROR(COUNTA('SURA Digital Venta'!C130:C139),0) -> 4 | BB4: SURA Digital Venta | BC4: =IFERROR(COUNTA('SURA Digital Venta'!C143:C149)/7,0) -> 1 | BE4: SURA Digital Venta | BF4: =IFERROR(COUNTA('SURA Digital Venta'!C153:C161)/9,0) -> 1 | BH4: SURA Digital Venta | BI4: =IFERROR(COUNTA('SURA Digital Venta'!C165:G175)/20,0) -> 0.35 | BK4: ② Madurez (normalizada) | BL4: =AVERAGE(AB3:AB13)/5 -> 0.27272727 | BM4: =60% -> 0.6 | BO4: D2: Parcial | BP4: =Dashboard!N48 -> 3
A5: SURA Automatizacion | B5: =IF('SURA Automatizacion'!C13="","0",'SURA Automatizacion'!C13) -> N2 | C5: =IFERROR(VALUE(RIGHT(B5,1)),0) -> 2 | D5: 3 | K5: SURA Automatizacion | L5: =C5 -> 2 | M5: =D5 -> 3 | X5: SURA Automatizacion | Y5: =IFERROR(COUNTA('SURA Automatizacion'!C4:C18)/15,0) -> 0.86666667 | AA5: SURA Automatizacion | AB5: =IFERROR(VALUE(RIGHT('SURA Automatizacion'!C13,1)),0) -> 2 | AC5: =3 -> 3 | AE5: SURA Automatizacion | AF5: =IFERROR((COUNTIF('SURA Automatizacion'!D31:D53,"Sí")+COUNTIF('SURA Automatizacion'!D31:D53,"Si")+0.5*COUNTIF('SURA Automatizacion'!D31:D53,"Parcial"))/(COUNTIF('SURA Automatizacion'!D31:D53,"Sí")+COUNTIF('SURA Automatizacion'!D31:D53,"Si")+COUNTIF('SURA Automatizacion'!D31:D53,"Parcial")+COUNTIF('SURA Automatizacion'!D31:D53,"No")),0) -> 0.61764706 | AH5: SURA Automatizacion | AI5: =IFERROR('SURA Automatizacion'!C63,0) -> N/D | AJ5: =IFERROR('SURA Automatizacion'!C65,0) -> 0.98 | AM5: SURA Automatizacion | AN5: =IFERROR(SUM('SURA Automatizacion'!C74:C82),0) -> 512 | AP5: SURA Automatizacion | AQ5: =IFERROR('SURA Automatizacion'!C86,0) -> 0 | AS5: SURA Automatizacion | AT5: =COUNTIF('SURA Automatizacion'!C95:C112,"Sí")+COUNTIF('SURA Automatizacion'!C95:C112,"Si")+0.5*COUNTIF('SURA Automatizacion'!C95:C112,"Parcial") -> 9.5 | AV5: SURA Automatizacion | AW5: =IFERROR(COUNTA('SURA Automatizacion'!C119:C126)/8,0) -> 0.5 | AY5: SURA Automatizacion | AZ5: =IFERROR(COUNTA('SURA Automatizacion'!C130:C139),0) -> 6 | BB5: SURA Automatizacion | BC5: =IFERROR(COUNTA('SURA Automatizacion'!C143:C149)/7,0) -> 1 | BE5: SURA Automatizacion | BF5: =IFERROR(COUNTA('SURA Automatizacion'!C153:C161)/9,0) -> 1 | BH5: SURA Automatizacion | BI5: =IFERROR(COUNTA('SURA Automatizacion'!C165:G175)/20,0) -> 0.35 | BK5: ③ ITIL | BL5: =AVERAGE(AF3:AF13) -> 0.31283422 | BM5: =70% -> 0.7 | BO5: D3: Sí | BP5: =Dashboard!N49 -> 3
A6: SURA Canales Masivos | B6: =IF('SURA Canales Masivos'!C13="","0",'SURA Canales Masivos'!C13) -> N2 | C6: =IFERROR(VALUE(RIGHT(B6,1)),0) -> 2 | D6: 3 | K6: SURA Canales Masivos | L6: =C6 -> 2 | M6: =D6 -> 3 | X6: SURA Canales Masivos | Y6: =IFERROR(COUNTA('SURA Canales Masivos'!C4:C18)/15,0) -> 0.86666667 | AA6: SURA Canales Masivos | AB6: =IFERROR(VALUE(RIGHT('SURA Canales Masivos'!C13,1)),0) -> 2 | AC6: =3 -> 3 | AE6: SURA Canales Masivos | AF6: =IFERROR((COUNTIF('SURA Canales Masivos'!D31:D53,"Sí")+COUNTIF('SURA Canales Masivos'!D31:D53,"Si")+0.5*COUNTIF('SURA Canales Masivos'!D31:D53,"Parcial"))/(COUNTIF('SURA Canales Masivos'!D31:D53,"Sí")+COUNTIF('SURA Canales Masivos'!D31:D53,"Si")+COUNTIF('SURA Canales Masivos'!D31:D53,"Parcial")+COUNTIF('SURA Canales Masivos'!D31:D53,"No")),0) -> 0.58823529 | AH6: SURA Canales Masivos | AI6: =IFERROR('SURA Canales Masivos'!C63,0) -> N/D | AJ6: =IFERROR('SURA Canales Masivos'!C65,0) -> 0.72 | AM6: SURA Canales Masivos | AN6: =IFERROR(SUM('SURA Canales Masivos'!C74:C82),0) -> 171 | AP6: SURA Canales Masivos | AQ6: =IFERROR('SURA Canales Masivos'!C86,0) -> 0 | AS6: SURA Canales Masivos | AT6: =COUNTIF('SURA Canales Masivos'!C95:C112,"Sí")+COUNTIF('SURA Canales Masivos'!C95:C112,"Si")+0.5*COUNTIF('SURA Canales Masivos'!C95:C112,"Parcial") -> 11.5 | AV6: SURA Canales Masivos | AW6: =IFERROR(COUNTA('SURA Canales Masivos'!C119:C126)/8,0) -> 0.5 | AY6: SURA Canales Masivos | AZ6: =IFERROR(COUNTA('SURA Canales Masivos'!C130:C139),0) -> 5 | BB6: SURA Canales Masivos | BC6: =IFERROR(COUNTA('SURA Canales Masivos'!C143:C149)/7,0) -> 1 | BE6: SURA Canales Masivos | BF6: =IFERROR(COUNTA('SURA Canales Masivos'!C153:C161)/9,0) -> 1 | BH6: SURA Canales Masivos | BI6: =IFERROR(COUNTA('SURA Canales Masivos'!C165:G175)/20,0) -> 0.35 | BK6: ④ KPIs FCR/SLA | BL6: =AVERAGE(AI3:AJ13) -> 0.61055556 | BM6: =85% -> 0.85 | BO6: D4: Sí | BP6: =Dashboard!N50 -> 4
A7: BCO Gioti1 | B7: =IF('BCO Gioti 1'!C14="","0",'BCO Gioti 1'!C14) -> N1 | C7: =IFERROR(VALUE(RIGHT(B7,1)),0) -> 1 | D7: 3 | K7: =A7 -> BCO Gioti1 | L7: =C7 -> 1 | M7: =D7 -> 3 | X7: BCO Gioti1 | Y7: =IFERROR(COUNTA('BCO Gioti 1'!C4:C19)/15,0) -> 0.46666667 | AA7: BCO Gioti1 | AB7: =IFERROR(VALUE(RIGHT('BCO Gioti 1'!C14,1)),0) -> 1 | AC7: =3 -> 3 | AE7: BCO Gioti1 | AF7: =IFERROR((COUNTIF('BCO Gioti 1'!D32:D54,"Sí")+COUNTIF('BCO Gioti 1'!D32:D54,"Si")+0.5*COUNTIF('BCO Gioti 1'!D32:D54,"Parcial"))/(COUNTIF('BCO Gioti 1'!D32:D54,"Sí")+COUNTIF('BCO Gioti 1'!D32:D54,"Si")+COUNTIF('BCO Gioti 1'!D32:D54,"Parcial")+COUNTIF('BCO Gioti 1'!D32:D54,"No")),0) -> 0.79411765 | AH7: BCO Gioti1 | AI7: =IFERROR('BCO Gioti 1'!C64,0) -> 0.68 | AJ7: =IFERROR('BCO Gioti 1'!C66,0) -> 0.89 | AM7: BCO Gioti1 | AN7: =IFERROR(SUM('BCO Gioti 1'!C75:C83),0) -> 0 | AP7: BCO Gioti1 | AQ7: =IFERROR('BCO Gioti 1'!C87,0) -> 0 | AS7: BCO Gioti1 | AT7: =COUNTIF('BCO Gioti 1'!C96:C113,"Sí")+COUNTIF('BCO Gioti 1'!C96:C113,"Si")+0.5*COUNTIF('BCO Gioti 1'!C96:C113,"Parcial") -> 1 | AV7: BCO Gioti1 | AW7: =IFERROR(COUNTA('BCO Gioti 1'!C120:C127)/8,0) -> 0 | AY7: BCO Gioti1 | AZ7: =IFERROR(COUNTA('BCO Gioti 1'!C131:C140),0) -> 0 | BB7: BCO Gioti1 | BC7: =IFERROR(COUNTA('BCO Gioti 1'!C144:C150)/7,0) -> 0 | BE7: BCO Gioti1 | BF7: =IFERROR(COUNTA('BCO Gioti 1'!C154:C162)/9,0) -> 0.11111111 | BH7: BCO Gioti1 | BI7: =IFERROR(COUNTA('BCO Gioti 1'!C166:G176)/20,0) -> 0.35 | BK7: ④b Incidentes categorizados | BL7: =IFERROR(AVERAGE(AN3:AN13),0) -> 138.63636 | BM7: =0 -> 0 | BO7: D5: Sí | BP7: =Dashboard!N51 -> 2
A8: BCO Gioti2 | B8: =IF('BCO Gioti 2'!C14="","0",'BCO Gioti 2'!C14) -> N1 | C8: =IFERROR(VALUE(RIGHT(B8,1)),0) -> 1 | D8: 3 | K8: =A8 -> BCO Gioti2 | L8: =C8 -> 1 | M8: =D8 -> 3 | X8: BCO Gioti2 | Y8: =IFERROR(COUNTA('BCO Gioti 2'!C4:C19)/15,0) -> 0.46666667 | AA8: BCO Gioti2 | AB8: =IFERROR(VALUE(RIGHT('BCO Gioti 2'!C14,1)),0) -> 1 | AC8: =3 -> 3 | AE8: BCO Gioti2 | AF8: =IFERROR((COUNTIF('BCO Gioti 2'!D32:D54,"Sí")+COUNTIF('BCO Gioti 2'!D32:D54,"Si")+0.5*COUNTIF('BCO Gioti 2'!D32:D54,"Parcial"))/(COUNTIF('BCO Gioti 2'!D32:D54,"Sí")+COUNTIF('BCO Gioti 2'!D32:D54,"Si")+COUNTIF('BCO Gioti 2'!D32:D54,"Parcial")+COUNTIF('BCO Gioti 2'!D32:D54,"No")),0) -> 0 | AH8: BCO Gioti2 | AI8: =IFERROR('BCO Gioti 2'!C64,0) -> 0.68 | AJ8: =IFERROR('BCO Gioti 2'!C66,0) -> 0.89 | AM8: BCO Gioti2 | AN8: =IFERROR(SUM('BCO Gioti 2'!C75:C83),0) -> 0 | AP8: BCO Gioti2 | AQ8: =IFERROR('BCO Gioti 2'!C87,0) -> 0 | AS8: BCO Gioti2 | AT8: =COUNTIF('BCO Gioti 2'!C96:C113,"Sí")+COUNTIF('BCO Gioti 2'!C96:C113,"Si")+0.5*COUNTIF('BCO Gioti 2'!C96:C113,"Parcial") -> 1 | AV8: BCO Gioti2 | AW8: =IFERROR(COUNTA('BCO Gioti 2'!C120:C127)/8,0) -> 0 | AY8: BCO Gioti2 | AZ8: =IFERROR(COUNTA('BCO Gioti 2'!C131:C140),0) -> 0 | BB8: BCO Gioti2 | BC8: =IFERROR(COUNTA('BCO Gioti 2'!C144:C150)/7,0) -> 0 | BE8: BCO Gioti2 | BF8: =IFERROR(COUNTA('BCO Gioti 2'!C154:C162)/9,0) -> 0.11111111 | BH8: BCO Gioti2 | BI8: =IFERROR(COUNTA('BCO Gioti 2'!C166:G176)/20,0) -> 0.35 | BK8: ⑤ XLA/DEX NPS | BL8: =IFERROR(AVERAGE(AQ3:AQ13)/100,0) -> 0 | BM8: =65% -> 0.65 | BO8: D6: Parcial | BP8: =Dashboard!N52 -> 0.5
A9: BCO Gioti3 | B9: =IF('BCO Gioti 3'!C14="","0",'BCO Gioti 3'!C14) -> N1 | C9: =IFERROR(VALUE(RIGHT(B9,1)),0) -> 1 | D9: 3 | K9: =A9 -> BCO Gioti3 | L9: =C9 -> 1 | M9: =D9 -> 3 | X9: BCO Gioti3 | Y9: =IFERROR(COUNTA('BCO Gioti 3'!C4:C19)/15,0) -> 0.46666667 | AA9: BCO Gioti3 | AB9: =IFERROR(VALUE(RIGHT('BCO Gioti 3'!C14,1)),0) -> 1 | AC9: =3 -> 3 | AE9: BCO Gioti3 | AF9: =IFERROR((COUNTIF('BCO Gioti 3'!D32:D54,"Sí")+COUNTIF('BCO Gioti 3'!D32:D54,"Si")+0.5*COUNTIF('BCO Gioti 3'!D32:D54,"Parcial"))/(COUNTIF('BCO Gioti 3'!D32:D54,"Sí")+COUNTIF('BCO Gioti 3'!D32:D54,"Si")+COUNTIF('BCO Gioti 3'!D32:D54,"Parcial")+COUNTIF('BCO Gioti 3'!D32:D54,"No")),0) -> 0 | AH9: BCO Gioti3 | AI9: =IFERROR('BCO Gioti 3'!C64,0) -> 0.68 | AJ9: =IFERROR('BCO Gioti 3'!C66,0) -> 0.89 | AM9: BCO Gioti3 | AN9: =IFERROR(SUM('BCO Gioti 3'!C75:C83),0) -> 0 | AP9: BCO Gioti3 | AQ9: =IFERROR('BCO Gioti 3'!C87,0) -> 0 | AS9: BCO Gioti3 | AT9: =COUNTIF('BCO Gioti 3'!C97:C114,"Sí")+COUNTIF('BCO Gioti 3'!C97:C114,"Si")+0.5*COUNTIF('BCO Gioti 3'!C97:C114,"Parcial") -> 0 | AV9: BCO Gioti3 | AW9: =IFERROR(COUNTA('BCO Gioti 3'!C121:C128)/8,0) -> 0 | AY9: BCO Gioti3 | AZ9: =IFERROR(COUNTA('BCO Gioti 3'!C132:C141),0) -> 0 | BB9: BCO Gioti3 | BC9: =IFERROR(COUNTA('BCO Gioti 3'!C145:C151)/7,0) -> 0 | BE9: BCO Gioti3 | BF9: =IFERROR(COUNTA('BCO Gioti 3'!C155:C163)/9,0) -> 0.11111111 | BH9: BCO Gioti3 | BI9: =IFERROR(COUNTA('BCO Gioti 3'!C167:G177)/20,0) -> 0.35 | BK9: ⑥ Dolores activos | BL9: =IFERROR(AVERAGE(AT3:AT13)/7,0) -> 0.66233766 | BM9: =0 -> 0 | BO9: D7: No | BP9: =Dashboard!N53 -> 2.5
A10: BCO Gioti4 | B10: =IF('BCO Gioti 4'!C14="","0",'BCO Gioti 4'!C14) -> N1 | C10: =IFERROR(VALUE(RIGHT(B10,1)),0) -> 1 | D10: 3 | K10: =A10 -> BCO Gioti4 | L10: =C10 -> 1 | M10: =D10 -> 3 | X10: BCO Gioti4 | Y10: =IFERROR(COUNTA('BCO Gioti 4'!C4:C19)/15,0) -> 0.46666667 | AA10: BCO Gioti4 | AB10: =IFERROR(VALUE(RIGHT('BCO Gioti 4'!C14,1)),0) -> 1 | AC10: =3 -> 3 | AE10: BCO Gioti4 | AF10: =IFERROR((COUNTIF('BCO Gioti 4'!D32:D54,"Sí")+COUNTIF('BCO Gioti 4'!D32:D54,"Si")+0.5*COUNTIF('BCO Gioti 4'!D32:D54,"Parcial"))/(COUNTIF('BCO Gioti 4'!D32:D54,"Sí")+COUNTIF('BCO Gioti 4'!D32:D54,"Si")+COUNTIF('BCO Gioti 4'!D32:D54,"Parcial")+COUNTIF('BCO Gioti 4'!D32:D54,"No")),0) -> 0 | AH10: BCO Gioti4 | AI10: =IFERROR('BCO Gioti 4'!C64,0) -> 0.68 | AJ10: =IFERROR('BCO Gioti 4'!C66,0) -> 0.89 | AM10: BCO Gioti4 | AN10: =IFERROR(SUM('BCO Gioti 4'!C75:C83),0) -> 0 | AP10: BCO Gioti4 | AQ10: =IFERROR('BCO Gioti 4'!C87,0) -> 0 | AS10: BCO Gioti4 | AT10: =COUNTIF('BCO Gioti 4'!C96:C113,"Sí")+COUNTIF('BCO Gioti 4'!C96:C113,"Si")+0.5*COUNTIF('BCO Gioti 4'!C96:C113,"Parcial") -> 0 | AV10: BCO Gioti4 | AW10: =IFERROR(COUNTA('BCO Gioti 4'!C120:C127)/8,0) -> 0 | AY10: BCO Gioti4 | AZ10: =IFERROR(COUNTA('BCO Gioti 4'!C131:C140),0) -> 0 | BB10: BCO Gioti4 | BC10: =IFERROR(COUNTA('BCO Gioti 4'!C144:C150)/7,0) -> 0 | BE10: BCO Gioti4 | BF10: =IFERROR(COUNTA('BCO Gioti 4'!C154:C162)/9,0) -> 0.11111111 | BH10: BCO Gioti4 | BI10: =IFERROR(COUNTA('BCO Gioti 4'!C166:G176)/20,0) -> 0.35 | BK10: ⑦ Talento | BL10: =AVERAGE(AW3:AW13) -> 0.19318182 | BM10: =100% -> 1 | BO10: D8: | BP10: =Dashboard!N54 -> 3
A11: AES | B11: =IF(AES!C13="","0",AES!C13) -> N1 | C11: =IFERROR(VALUE(RIGHT(B11,1)),0) -> 1 | D11: 3 | K11: =A11 -> AES | L11: =C11 -> 1 | M11: =D11 -> 3 | X11: AES | Y11: =IFERROR(COUNTA(AES!C4:C19)/15,0) -> 1 | AA11: AES | AB11: =IFERROR(VALUE(RIGHT(AES!C13,1)),0) -> 1 | AC11: =3 -> 3 | AE11: AES | AF11: =IFERROR((COUNTIF(AES!D30:D52,"Sí")+COUNTIF(AES!D30:D52,"Si")+0.5*COUNTIF(AES!D30:D52,"Parcial"))/(COUNTIF(AES!D30:D52,"Sí")+COUNTIF(AES!D30:D52,"Si")+COUNTIF(AES!D30:D52,"Parcial")+COUNTIF(AES!D30:D52,"No")),0) -> 0.35294118 | AH11: AES | AI11: =IFERROR(AES!C62,0) -> 0 | AJ11: =IFERROR(AES!C64,0) -> 0 | AM11: AES | AN11: =IFERROR(SUM(AES!C73:C81),0) -> 0 | AP11: AES | AQ11: =IFERROR(AES!C85,0) -> 0 | AS11: AES | AT11: =COUNTIF(AES!C94:C111,"Sí")+COUNTIF(AES!C94:C111,"Si")+0.5*COUNTIF(AES!C94:C111,"Parcial") -> 6 | AV11: AES | AW11: =IFERROR(COUNTA(AES!C118:C125)/8,0) -> 0.125 | AY11: AES | AZ11: =IFERROR(COUNTA(AES!C129:C138),0) -> 2 | BB11: AES | BC11: =IFERROR(COUNTA(AES!C142:C148)/7,0) -> 0.42857143 | BE11: AES | BF11: =IFERROR(COUNTA(AES!C152:C160)/9,0) -> 0.88888889 | BH11: AES | BI11: =IFERROR(COUNTA(AES!C164:G174)/20,0) -> 0.35 | BK11: ⑧ Tecnología | BL11: =IFERROR(AVERAGE(AZ3:AZ13)/10,0) -> 0.19090909 | BM11: =100% -> 1 | BO11: D9: | BP11: =Dashboard!N55 -> 2.5
A12: XM | B12: =IF(XM!C14="","0",XM!C14) -> N1 | C12: =IFERROR(VALUE(RIGHT(B12,1)),0) -> 1 | D12: 3 | K12: =A12 -> XM | L12: =C12 -> 1 | M12: =D12 -> 3 | X12: XM | Y12: =IFERROR(COUNTA(XM!C4:C19)/15,0) -> 0.4 | AA12: XM | AB12: =IFERROR(VALUE(RIGHT(XM!C14,1)),0) -> 1 | AC12: =3 -> 3 | AE12: XM | AF12: =IFERROR((COUNTIF(XM!D32:D54,"Sí")+COUNTIF(XM!D32:D54,"Si")+0.5*COUNTIF(XM!D32:D54,"Parcial"))/(COUNTIF(XM!D32:D54,"Sí")+COUNTIF(XM!D32:D54,"Si")+COUNTIF(XM!D32:D54,"Parcial")+COUNTIF(XM!D32:D54,"No")),0) -> 0 | AH12: XM | AI12: =IFERROR(XM!C64,0) -> 0 | AJ12: =IFERROR(XM!C66,0) -> 0 | AM12: XM | AN12: =IFERROR(SUM(XM!C75:C83),0) -> 0 | AP12: XM | AQ12: =IFERROR(XM!C87,0) -> 0 | AS12: XM | AT12: =COUNTIF(XM!C96:C113,"Sí")+COUNTIF(XM!C96:C113,"Si")+0.5*COUNTIF(XM!C96:C113,"Parcial") -> 0 | AV12: XM | AW12: =IFERROR(COUNTA(XM!C120:C127)/8,0) -> 0 | AY12: XM | AZ12: =IFERROR(COUNTA(XM!C131:C140),0) -> 0 | BB12: XM | BC12: =IFERROR(COUNTA(XM!C144:C150)/7,0) -> 0 | BE12: XM | BF12: =IFERROR(COUNTA(XM!C154:C162)/9,0) -> 0.11111111 | BH12: XM | BI12: =IFERROR(COUNTA(XM!C166:G176)/20,0) -> 0.35 | BK12: ⑨ Económico | BL12: =AVERAGE(BC3:BC13) -> 0.4025974 | BM12: =100% -> 1 | BO12: D10: Sí | BP12: =Dashboard!N56 -> 4
A13: MEDICARTE | B13: =IF(MEDICARTE!C14="","0",MEDICARTE!C14) -> N1 | C13: =IFERROR(VALUE(RIGHT(B13,1)),0) -> 1 | D13: 3 | K13: =A13 -> MEDICARTE | L13: =C13 -> 1 | M13: =D13 -> 3 | X13: MEDICARTE | Y13: =IFERROR(COUNTA(MEDICARTE!C4:C19)/15,0) -> 0.33333333 | AA13: MEDICARTE | AB13: =IFERROR(VALUE(RIGHT(MEDICARTE!C14,1)),0) -> 1 | AC13: =3 -> 3 | AE13: MEDICARTE | AF13: =IFERROR((COUNTIF(MEDICARTE!D32:D54,"Sí")+COUNTIF(MEDICARTE!D32:D54,"Si")+0.5*COUNTIF(MEDICARTE!D32:D54,"Parcial"))/(COUNTIF(MEDICARTE!D32:D54,"Sí")+COUNTIF(MEDICARTE!D32:D54,"Si")+COUNTIF(MEDICARTE!D32:D54,"Parcial")+COUNTIF(MEDICARTE!D32:D54,"No")),0) -> 0 | AH13: MEDICARTE | AI13: =IFERROR(MEDICARTE!C64,0) -> 0.68 | AJ13: =IFERROR(MEDICARTE!C66,0) -> 0.89 | AM13: MEDICARTE | AN13: =IFERROR(SUM(MEDICARTE!C75:C83),0) -> 0 | AP13: MEDICARTE | AQ13: =IFERROR(MEDICARTE!C87,0) -> 0 | AS13: MEDICARTE | AT13: =COUNTIF(MEDICARTE!C96:C113,"Sí")+COUNTIF(MEDICARTE!C96:C113,"Si")+0.5*COUNTIF(MEDICARTE!C96:C113,"Parcial") -> 0 | AV13: MEDICARTE | AW13: =IFERROR(COUNTA(MEDICARTE!C120:C127)/8,0) -> 0 | AY13: MEDICARTE | AZ13: =IFERROR(COUNTA(MEDICARTE!C131:C140),0) -> 0 | BB13: MEDICARTE | BC13: =IFERROR(COUNTA(MEDICARTE!C144:C150)/7,0) -> 0 | BE13: MEDICARTE | BF13: =IFERROR(COUNTA(MEDICARTE!C154:C162)/9,0) -> 0.11111111 | BH13: MEDICARTE | BI13: =IFERROR(COUNTA(MEDICARTE!C166:G176)/20,0) -> 0.35 | BK13: ⑩ Visión | BL13: =AVERAGE(BF3:BF13) -> 0.50505051 | BM13: =100% -> 1 | BO13: D11: | BP13: =Dashboard!N57 -> 2.5
BK14: ⑪ Casos éxito | BL14: =AVERAGE(BI3:BI13) -> 0.35 | BM14: =100% -> 1 | BO14: D12: | BP14: =Dashboard!N58 -> 3
A15: TABLA 2 — SCORE PRÁCTICAS POR DIMENSIÓN (%) | BO15: D13: No | BP15: =Dashboard!N59 -> 3
A16: Mesa | B16: D1 Org/Personas | C16: D2 Info/Tecnología | D16: D3 Socios/Proveed. | E16: D4 Valor/Mejora | F16: Score Global | K16: Mesa | L16: D1 Org/Personas | N16: Mesa | O16: D2 Info/Tecnología | Q16: Mesa | R16: D3 Socios/Proveed. | T16: Mesa | U16: Score Global | BO16: D14: | BP16: =Dashboard!N60 -> 4
A17: SURA Cotizadores | B17: =IFERROR((COUNTIF('SURA Cotizadores'!D30:D34,"Sí")+COUNTIF('SURA Cotizadores'!D30:D34,"Si")+0.5*COUNTIF('SURA Cotizadores'!D30:D34,"Parcial"))/(COUNTIF('SURA Cotizadores'!D30:D34,"Sí")+COUNTIF('SURA Cotizadores'!D30:D34,"Si")+COUNTIF('SURA Cotizadores'!D30:D34,"Parcial")+COUNTIF('SURA Cotizadores'!D30:D34,"No")),0) -> 0.3 | C17: =IFERROR((COUNTIF('SURA Cotizadores'!D37:D43,"Sí")+COUNTIF('SURA Cotizadores'!D37:D43,"Si")+0.5*COUNTIF('SURA Cotizadores'!D37:D43,"Parcial"))/(COUNTIF('SURA Cotizadores'!D37:D43,"Sí")+COUNTIF('SURA Cotizadores'!D37:D43,"Si")+COUNTIF('SURA Cotizadores'!D37:D43,"Parcial")+COUNTIF('SURA Cotizadores'!D37:D43,"No")),0) -> 0.57142857 | D17: =IFERROR((COUNTIF('SURA Cotizadores'!D46:D48,"Sí")+COUNTIF('SURA Cotizadores'!D46:D48,"Si")+0.5*COUNTIF('SURA Cotizadores'!D46:D48,"Parcial"))/(COUNTIF('SURA Cotizadores'!D46:D48,"Sí")+COUNTIF('SURA Cotizadores'!D46:D48,"Si")+COUNTIF('SURA Cotizadores'!D46:D48,"Parcial")+COUNTIF('SURA Cotizadores'!D46:D48,"No")),0) -> 0.83333333 | E17: =IFERROR((COUNTIF('SURA Cotizadores'!D51:D52,"Sí")+COUNTIF('SURA Cotizadores'!D51:D52,"Si")+0.5*COUNTIF('SURA Cotizadores'!D51:D52,"Parcial"))/(COUNTIF('SURA Cotizadores'!D51:D52,"Sí")+COUNTIF('SURA Cotizadores'!D51:D52,"Si")+COUNTIF('SURA Cotizadores'!D51:D52,"Parcial")+COUNTIF('SURA Cotizadores'!D51:D52,"No")),0) -> 0.5 | F17: =IFERROR('SURA Cotizadores'!E54,0) -> 0.52941176 | K17: =A17 -> SURA Cotizadores | L17: =B17 -> 0.3 | N17: =A17 -> SURA Cotizadores | O17: =C17 -> 0.57142857 | Q17: =A17 -> SURA Cotizadores | R17: =D17 -> 0.83333333 | T17: =A17 -> SURA Cotizadores | U17: =F17 -> 0.52941176 | BO17: D15: No | BP17: =Dashboard!N61 -> 2
A18: SURA Digital Venta | B18: =IFERROR((COUNTIF('SURA Digital Venta'!D31:D35,"Sí")+COUNTIF('SURA Digital Venta'!D31:D35,"Si")+0.5*COUNTIF('SURA Digital Venta'!D31:D35,"Parcial"))/(COUNTIF('SURA Digital Venta'!D31:D35,"Sí")+COUNTIF('SURA Digital Venta'!D31:D35,"Si")+COUNTIF('SURA Digital Venta'!D31:D35,"Parcial")+COUNTIF('SURA Digital Venta'!D31:D35,"No")),0) -> 0.4 | C18: =IFERROR((COUNTIF('SURA Digital Venta'!D38:D44,"Sí")+COUNTIF('SURA Digital Venta'!D38:D44,"Si")+0.5*COUNTIF('SURA Digital Venta'!D38:D44,"Parcial"))/(COUNTIF('SURA Digital Venta'!D38:D44,"Sí")+COUNTIF('SURA Digital Venta'!D38:D44,"Si")+COUNTIF('SURA Digital Venta'!D38:D44,"Parcial")+COUNTIF('SURA Digital Venta'!D38:D44,"No")),0) -> 0.57142857 | D18: =IFERROR((COUNTIF('SURA Digital Venta'!D47:D49,"Sí")+COUNTIF('SURA Digital Venta'!D47:D49,"Si")+0.5*COUNTIF('SURA Digital Venta'!D47:D49,"Parcial"))/(COUNTIF('SURA Digital Venta'!D47:D49,"Sí")+COUNTIF('SURA Digital Venta'!D47:D49,"Si")+COUNTIF('SURA Digital Venta'!D47:D49,"Parcial")+COUNTIF('SURA Digital Venta'!D47:D49,"No")),0) -> 0.83333333 | E18: =IFERROR((COUNTIF('SURA Digital Venta'!D52:D53,"Sí")+COUNTIF('SURA Digital Venta'!D52:D53,"Si")+0.5*COUNTIF('SURA Digital Venta'!D52:D53,"Parcial"))/(COUNTIF('SURA Digital Venta'!D52:D53,"Sí")+COUNTIF('SURA Digital Venta'!D52:D53,"Si")+COUNTIF('SURA Digital Venta'!D52:D53,"Parcial")+COUNTIF('SURA Digital Venta'!D52:D53,"No")),0) -> 0.5 | F18: =IFERROR('SURA Digital Venta'!E55,0) -> 0.55882353 | K18: =A18 -> SURA Digital Venta | L18: =B18 -> 0.4 | N18: =A18 -> SURA Digital Venta | O18: =C18 -> 0.57142857 | Q18: =A18 -> SURA Digital Venta | R18: =D18 -> 0.83333333 | T18: =A18 -> SURA Digital Venta | U18: =F18 -> 0.55882353 | BO18: D16: | BP18: =Dashboard!N62 -> 2.5
A19: SURA Automatizacion | B19: =IFERROR((COUNTIF('SURA Automatizacion'!D31:D35,"Sí")+COUNTIF('SURA Automatizacion'!D31:D35,"Si")+0.5*COUNTIF('SURA Automatizacion'!D31:D35,"Parcial"))/(COUNTIF('SURA Automatizacion'!D31:D35,"Sí")+COUNTIF('SURA Automatizacion'!D31:D35,"Si")+COUNTIF('SURA Automatizacion'!D31:D35,"Parcial")+COUNTIF('SURA Automatizacion'!D31:D35,"No")),0) -> 0.4 | C19: =IFERROR((COUNTIF('SURA Automatizacion'!D38:D44,"Sí")+COUNTIF('SURA Automatizacion'!D38:D44,"Si")+0.5*COUNTIF('SURA Automatizacion'!D38:D44,"Parcial"))/(COUNTIF('SURA Automatizacion'!D38:D44,"Sí")+COUNTIF('SURA Automatizacion'!D38:D44,"Si")+COUNTIF('SURA Automatizacion'!D38:D44,"Parcial")+COUNTIF('SURA Automatizacion'!D38:D44,"No")),0) -> 0.71428571 | D19: =IFERROR((COUNTIF('SURA Automatizacion'!D47:D49,"Sí")+COUNTIF('SURA Automatizacion'!D47:D49,"Si")+0.5*COUNTIF('SURA Automatizacion'!D47:D49,"Parcial"))/(COUNTIF('SURA Automatizacion'!D47:D49,"Sí")+COUNTIF('SURA Automatizacion'!D47:D49,"Si")+COUNTIF('SURA Automatizacion'!D47:D49,"Parcial")+COUNTIF('SURA Automatizacion'!D47:D49,"No")),0) -> 0.83333333 | E19: =IFERROR((COUNTIF('SURA Automatizacion'!D52:D53,"Sí")+COUNTIF('SURA Automatizacion'!D52:D53,"Si")+0.5*COUNTIF('SURA Automatizacion'!D52:D53,"Parcial"))/(COUNTIF('SURA Automatizacion'!D52:D53,"Sí")+COUNTIF('SURA Automatizacion'!D52:D53,"Si")+COUNTIF('SURA Automatizacion'!D52:D53,"Parcial")+COUNTIF('SURA Automatizacion'!D52:D53,"No")),0) -> 0.5 | F19: =IFERROR('SURA Automatizacion'!E55,0) -> 0.61764706 | K19: =A19 -> SURA Automatizacion | L19: =B19 -> 0.4 | N19: =A19 -> SURA Automatizacion | O19: =C19 -> 0.71428571 | Q19: =A19 -> SURA Automatizacion | R19: =D19 -> 0.83333333 | T19: =A19 -> SURA Automatizacion | U19: =F19 -> 0.61764706 | BO19: D17: | BP19: =Dashboard!N63 -> 5.5
A20: SURA Canales Masivos | B20: =IFERROR((COUNTIF('SURA Canales Masivos'!D31:D35,"Sí")+COUNTIF('SURA Canales Masivos'!D31:D35,"Si")+0.5*COUNTIF('SURA Canales Masivos'!D31:D35,"Parcial"))/(COUNTIF('SURA Canales Masivos'!D31:D35,"Sí")+COUNTIF('SURA Canales Masivos'!D31:D35,"Si")+COUNTIF('SURA Canales Masivos'!D31:D35,"Parcial")+COUNTIF('SURA Canales Masivos'!D31:D35,"No")),0) -> 0.4 | C20: =IFERROR((COUNTIF('SURA Canales Masivos'!D38:D44,"Sí")+COUNTIF('SURA Canales Masivos'!D38:D44,"Si")+0.5*COUNTIF('SURA Canales Masivos'!D38:D44,"Parcial"))/(COUNTIF('SURA Canales Masivos'!D38:D44,"Sí")+COUNTIF('SURA Canales Masivos'!D38:D44,"Si")+COUNTIF('SURA Canales Masivos'!D38:D44,"Parcial")+COUNTIF('SURA Canales Masivos'!D38:D44,"No")),0) -> 0.64285714 | D20: =IFERROR((COUNTIF('SURA Canales Masivos'!D47:D49,"Sí")+COUNTIF('SURA Canales Masivos'!D47:D49,"Si")+0.5*COUNTIF('SURA Canales Masivos'!D47:D49,"Parcial"))/(COUNTIF('SURA Canales Masivos'!D47:D49,"Sí")+COUNTIF('SURA Canales Masivos'!D47:D49,"Si")+COUNTIF('SURA Canales Masivos'!D47:D49,"Parcial")+COUNTIF('SURA Canales Masivos'!D47:D49,"No")),0) -> 0.83333333 | E20: =IFERROR((COUNTIF('SURA Canales Masivos'!D52:D53,"Sí")+COUNTIF('SURA Canales Masivos'!D52:D53,"Si")+0.5*COUNTIF('SURA Canales Masivos'!D52:D53,"Parcial"))/(COUNTIF('SURA Canales Masivos'!D52:D53,"Sí")+COUNTIF('SURA Canales Masivos'!D52:D53,"Si")+COUNTIF('SURA Canales Masivos'!D52:D53,"Parcial")+COUNTIF('SURA Canales Masivos'!D52:D53,"No")),0) -> 0.5 | F20: =IFERROR('SURA Canales Masivos'!E55,0) -> 0.58823529 | K20: =A20 -> SURA Canales Masivos | L20: =B20 -> 0.4 | N20: =A20 -> SURA Canales Masivos | O20: =C20 -> 0.64285714 | Q20: =A20 -> SURA Canales Masivos | R20: =D20 -> 0.83333333 | T20: =A20 -> SURA Canales Masivos | U20: =F20 -> 0.58823529 | BO20: D18: Sí | BP20: =Dashboard!N64 -> 3.5
A21: BCO Gioti1 | B21: =IFERROR((COUNTIF('BCO Gioti 1'!D32:D36,"Sí")+COUNTIF('BCO Gioti 1'!D32:D36,"Si")+0.5*COUNTIF('BCO Gioti 1'!D32:D36,"Parcial"))/(COUNTIF('BCO Gioti 1'!D32:D36,"Sí")+COUNTIF('BCO Gioti 1'!D32:D36,"Si")+COUNTIF('BCO Gioti 1'!D32:D36,"Parcial")+COUNTIF('BCO Gioti 1'!D32:D36,"No")),0) -> 0.8 | C21: =IFERROR((COUNTIF('BCO Gioti 1'!D39:D45,"Sí")+COUNTIF('BCO Gioti 1'!D39:D45,"Si")+0.5*COUNTIF('BCO Gioti 1'!D39:D45,"Parcial"))/(COUNTIF('BCO Gioti 1'!D39:D45,"Sí")+COUNTIF('BCO Gioti 1'!D39:D45,"Si")+COUNTIF('BCO Gioti 1'!D39:D45,"Parcial")+COUNTIF('BCO Gioti 1'!D39:D45,"No")),0) -> 0.78571429 | D21: =IFERROR((COUNTIF('BCO Gioti 1'!D48:D50,"Sí")+COUNTIF('BCO Gioti 1'!D48:D50,"Si")+0.5*COUNTIF('BCO Gioti 1'!D48:D50,"Parcial"))/(COUNTIF('BCO Gioti 1'!D48:D50,"Sí")+COUNTIF('BCO Gioti 1'!D48:D50,"Si")+COUNTIF('BCO Gioti 1'!D48:D50,"Parcial")+COUNTIF('BCO Gioti 1'!D48:D50,"No")),0) -> 0.83333333 | E21: =IFERROR((COUNTIF('BCO Gioti 1'!D53:D54,"Sí")+COUNTIF('BCO Gioti 1'!D53:D54,"Si")+0.5*COUNTIF('BCO Gioti 1'!D53:D54,"Parcial"))/(COUNTIF('BCO Gioti 1'!D53:D54,"Sí")+COUNTIF('BCO Gioti 1'!D53:D54,"Si")+COUNTIF('BCO Gioti 1'!D53:D54,"Parcial")+COUNTIF('BCO Gioti 1'!D53:D54,"No")),0) -> 0.75 | F21: =IFERROR('BCO Gioti 1'!E56,0) -> 0.79411765 | K21: =A21 -> BCO Gioti1 | L21: =B21 -> 0.8 | N21: =A21 -> BCO Gioti1 | O21: =C21 -> 0.78571429 | Q21: =A21 -> BCO Gioti1 | R21: =D21 -> 0.83333333 | T21: =A21 -> BCO Gioti1 | U21: =F21 -> 0.79411765
A22: BCO Gioti2 | B22: =IFERROR((COUNTIF('BCO Gioti 2'!D32:D36,"Sí")+COUNTIF('BCO Gioti 2'!D32:D36,"Si")+0.5*COUNTIF('BCO Gioti 2'!D32:D36,"Parcial"))/(COUNTIF('BCO Gioti 2'!D32:D36,"Sí")+COUNTIF('BCO Gioti 2'!D32:D36,"Si")+COUNTIF('BCO Gioti 2'!D32:D36,"Parcial")+COUNTIF('BCO Gioti 2'!D32:D36,"No")),0) -> 0 | C22: =IFERROR((COUNTIF('BCO Gioti 2'!D39:D45,"Sí")+COUNTIF('BCO Gioti 2'!D39:D45,"Si")+0.5*COUNTIF('BCO Gioti 2'!D39:D45,"Parcial"))/(COUNTIF('BCO Gioti 2'!D39:D45,"Sí")+COUNTIF('BCO Gioti 2'!D39:D45,"Si")+COUNTIF('BCO Gioti 2'!D39:D45,"Parcial")+COUNTIF('BCO Gioti 2'!D39:D45,"No")),0) -> 0 | D22: =IFERROR((COUNTIF('BCO Gioti 2'!D48:D50,"Sí")+COUNTIF('BCO Gioti 2'!D48:D50,"Si")+0.5*COUNTIF('BCO Gioti 2'!D48:D50,"Parcial"))/(COUNTIF('BCO Gioti 2'!D48:D50,"Sí")+COUNTIF('BCO Gioti 2'!D48:D50,"Si")+COUNTIF('BCO Gioti 2'!D48:D50,"Parcial")+COUNTIF('BCO Gioti 2'!D48:D50,"No")),0) -> 0 | E22: =IFERROR((COUNTIF('BCO Gioti 2'!D53:D54,"Sí")+COUNTIF('BCO Gioti 2'!D53:D54,"Si")+0.5*COUNTIF('BCO Gioti 2'!D53:D54,"Parcial"))/(COUNTIF('BCO Gioti 2'!D53:D54,"Sí")+COUNTIF('BCO Gioti 2'!D53:D54,"Si")+COUNTIF('BCO Gioti 2'!D53:D54,"Parcial")+COUNTIF('BCO Gioti 2'!D53:D54,"No")),0) -> 0 | F22: =IFERROR('BCO Gioti 2'!E56,0) -> 0 | K22: =A22 -> BCO Gioti2 | L22: =B22 -> 0 | N22: =A22 -> BCO Gioti2 | O22: =C22 -> 0 | Q22: =A22 -> BCO Gioti2 | R22: =D22 -> 0 | T22: =A22 -> BCO Gioti2 | U22: =F22 -> 0
A23: BCO Gioti3 | B23: =IFERROR((COUNTIF('BCO Gioti 3'!D32:D36,"Sí")+COUNTIF('BCO Gioti 3'!D32:D36,"Si")+0.5*COUNTIF('BCO Gioti 3'!D32:D36,"Parcial"))/(COUNTIF('BCO Gioti 3'!D32:D36,"Sí")+COUNTIF('BCO Gioti 3'!D32:D36,"Si")+COUNTIF('BCO Gioti 3'!D32:D36,"Parcial")+COUNTIF('BCO Gioti 3'!D32:D36,"No")),0) -> 0 | C23: =IFERROR((COUNTIF('BCO Gioti 3'!D39:D45,"Sí")+COUNTIF('BCO Gioti 3'!D39:D45,"Si")+0.5*COUNTIF('BCO Gioti 3'!D39:D45,"Parcial"))/(COUNTIF('BCO Gioti 3'!D39:D45,"Sí")+COUNTIF('BCO Gioti 3'!D39:D45,"Si")+COUNTIF('BCO Gioti 3'!D39:D45,"Parcial")+COUNTIF('BCO Gioti 3'!D39:D45,"No")),0) -> 0 | D23: =IFERROR((COUNTIF('BCO Gioti 3'!D48:D50,"Sí")+COUNTIF('BCO Gioti 3'!D48:D50,"Si")+0.5*COUNTIF('BCO Gioti 3'!D48:D50,"Parcial"))/(COUNTIF('BCO Gioti 3'!D48:D50,"Sí")+COUNTIF('BCO Gioti 3'!D48:D50,"Si")+COUNTIF('BCO Gioti 3'!D48:D50,"Parcial")+COUNTIF('BCO Gioti 3'!D48:D50,"No")),0) -> 0 | E23: =IFERROR((COUNTIF('BCO Gioti 3'!D53:D54,"Sí")+COUNTIF('BCO Gioti 3'!D53:D54,"Si")+0.5*COUNTIF('BCO Gioti 3'!D53:D54,"Parcial"))/(COUNTIF('BCO Gioti 3'!D53:D54,"Sí")+COUNTIF('BCO Gioti 3'!D53:D54,"Si")+COUNTIF('BCO Gioti 3'!D53:D54,"Parcial")+COUNTIF('BCO Gioti 3'!D53:D54,"No")),0) -> 0 | F23: =IFERROR('BCO Gioti 3'!E56,0) -> 0 | K23: =A23 -> BCO Gioti3 | L23: =B23 -> 0 | N23: =A23 -> BCO Gioti3 | O23: =C23 -> 0 | Q23: =A23 -> BCO Gioti3 | R23: =D23 -> 0 | T23: =A23 -> BCO Gioti3 | U23: =F23 -> 0
A24: BCO Gioti4 | B24: =IFERROR((COUNTIF('BCO Gioti 4'!D32:D36,"Sí")+COUNTIF('BCO Gioti 4'!D32:D36,"Si")+0.5*COUNTIF('BCO Gioti 4'!D32:D36,"Parcial"))/(COUNTIF('BCO Gioti 4'!D32:D36,"Sí")+COUNTIF('BCO Gioti 4'!D32:D36,"Si")+COUNTIF('BCO Gioti 4'!D32:D36,"Parcial")+COUNTIF('BCO Gioti 4'!D32:D36,"No")),0) -> 0 | C24: =IFERROR((COUNTIF('BCO Gioti 4'!D39:D45,"Sí")+COUNTIF('BCO Gioti 4'!D39:D45,"Si")+0.5*COUNTIF('BCO Gioti 4'!D39:D45,"Parcial"))/(COUNTIF('BCO Gioti 4'!D39:D45,"Sí")+COUNTIF('BCO Gioti 4'!D39:D45,"Si")+COUNTIF('BCO Gioti 4'!D39:D45,"Parcial")+COUNTIF('BCO Gioti 4'!D39:D45,"No")),0) -> 0 | D24: =IFERROR((COUNTIF('BCO Gioti 4'!D48:D50,"Sí")+COUNTIF('BCO Gioti 4'!D48:D50,"Si")+0.5*COUNTIF('BCO Gioti 4'!D48:D50,"Parcial"))/(COUNTIF('BCO Gioti 4'!D48:D50,"Sí")+COUNTIF('BCO Gioti 4'!D48:D50,"Si")+COUNTIF('BCO Gioti 4'!D48:D50,"Parcial")+COUNTIF('BCO Gioti 4'!D48:D50,"No")),0) -> 0 | E24: =IFERROR((COUNTIF('BCO Gioti 4'!D53:D54,"Sí")+COUNTIF('BCO Gioti 4'!D53:D54,"Si")+0.5*COUNTIF('BCO Gioti 4'!D53:D54,"Parcial"))/(COUNTIF('BCO Gioti 4'!D53:D54,"Sí")+COUNTIF('BCO Gioti 4'!D53:D54,"Si")+COUNTIF('BCO Gioti 4'!D53:D54,"Parcial")+COUNTIF('BCO Gioti 4'!D53:D54,"No")),0) -> 0 | F24: =IFERROR('BCO Gioti 4'!E56,0) -> 0 | K24: =A24 -> BCO Gioti4 | L24: =B24 -> 0 | N24: =A24 -> BCO Gioti4 | O24: =C24 -> 0 | Q24: =A24 -> BCO Gioti4 | R24: =D24 -> 0 | T24: =A24 -> BCO Gioti4 | U24: =F24 -> 0
A25: AES | B25: =IFERROR((COUNTIF(AES!D30:D34,"Sí")+COUNTIF(AES!D30:D34,"Si")+0.5*COUNTIF(AES!D30:D34,"Parcial"))/(COUNTIF(AES!D30:D34,"Sí")+COUNTIF(AES!D30:D34,"Si")+COUNTIF(AES!D30:D34,"Parcial")+COUNTIF(AES!D30:D34,"No")),0) -> 0.4 | C25: =IFERROR((COUNTIF(AES!D37:D43,"Sí")+COUNTIF(AES!D37:D43,"Si")+0.5*COUNTIF(AES!D37:D43,"Parcial"))/(COUNTIF(AES!D37:D43,"Sí")+COUNTIF(AES!D37:D43,"Si")+COUNTIF(AES!D37:D43,"Parcial")+COUNTIF(AES!D37:D43,"No")),0) -> 0.42857143 | D25: =IFERROR((COUNTIF(AES!D46:D48,"Sí")+COUNTIF(AES!D46:D48,"Si")+0.5*COUNTIF(AES!D46:D48,"Parcial"))/(COUNTIF(AES!D46:D48,"Sí")+COUNTIF(AES!D46:D48,"Si")+COUNTIF(AES!D46:D48,"Parcial")+COUNTIF(AES!D46:D48,"No")),0) -> 0.16666667 | E25: =IFERROR((COUNTIF(AES!D51:D52,"Sí")+COUNTIF(AES!D51:D52,"Si")+0.5*COUNTIF(AES!D51:D52,"Parcial"))/(COUNTIF(AES!D51:D52,"Sí")+COUNTIF(AES!D51:D52,"Si")+COUNTIF(AES!D51:D52,"Parcial")+COUNTIF(AES!D51:D52,"No")),0) -> 0.25 | F25: =IFERROR(AES!E54,0) -> 0.29411765 | K25: =A25 -> AES | L25: =B25 -> 0.4 | N25: =A25 -> AES | O25: =C25 -> 0.42857143 | Q25: =A25 -> AES | R25: =D25 -> 0.16666667 | T25: =A25 -> AES | U25: =F25 -> 0.29411765
A26: XM | B26: =IFERROR((COUNTIF(XM!D32:D36,"Sí")+COUNTIF(XM!D32:D36,"Si")+0.5*COUNTIF(XM!D32:D36,"Parcial"))/(COUNTIF(XM!D32:D36,"Sí")+COUNTIF(XM!D32:D36,"Si")+COUNTIF(XM!D32:D36,"Parcial")+COUNTIF(XM!D32:D36,"No")),0) -> 0 | C26: =IFERROR((COUNTIF(XM!D39:D45,"Sí")+COUNTIF(XM!D39:D45,"Si")+0.5*COUNTIF(XM!D39:D45,"Parcial"))/(COUNTIF(XM!D39:D45,"Sí")+COUNTIF(XM!D39:D45,"Si")+COUNTIF(XM!D39:D45,"Parcial")+COUNTIF(XM!D39:D45,"No")),0) -> 0 | D26: =IFERROR((COUNTIF(XM!D48:D50,"Sí")+COUNTIF(XM!D48:D50,"Si")+0.5*COUNTIF(XM!D48:D50,"Parcial"))/(COUNTIF(XM!D48:D50,"Sí")+COUNTIF(XM!D48:D50,"Si")+COUNTIF(XM!D48:D50,"Parcial")+COUNTIF(XM!D48:D50,"No")),0) -> 0 | E26: =IFERROR((COUNTIF(XM!D53:D54,"Sí")+COUNTIF(XM!D53:D54,"Si")+0.5*COUNTIF(XM!D53:D54,"Parcial"))/(COUNTIF(XM!D53:D54,"Sí")+COUNTIF(XM!D53:D54,"Si")+COUNTIF(XM!D53:D54,"Parcial")+COUNTIF(XM!D53:D54,"No")),0) -> 0 | F26: =IFERROR(XM!E56,0) -> 0 | K26: =A26 -> XM | L26: =B26 -> 0 | N26: =A26 -> XM | O26: =C26 -> 0 | Q26: =A26 -> XM | R26: =D26 -> 0 | T26: =A26 -> XM | U26: =F26 -> 0
A27: MEDICARTE | B27: =IFERROR((COUNTIF(MEDICARTE!D32:D36,"Sí")+COUNTIF(MEDICARTE!D32:D36,"Si")+0.5*COUNTIF(MEDICARTE!D32:D36,"Parcial"))/(COUNTIF(MEDICARTE!D32:D36,"Sí")+COUNTIF(MEDICARTE!D32:D36,"Si")+COUNTIF(MEDICARTE!D32:D36,"Parcial")+COUNTIF(MEDICARTE!D32:D36,"No")),0) -> 0 | C27: =IFERROR((COUNTIF(MEDICARTE!D39:D45,"Sí")+COUNTIF(MEDICARTE!D39:D45,"Si")+0.5*COUNTIF(MEDICARTE!D39:D45,"Parcial"))/(COUNTIF(MEDICARTE!D39:D45,"Sí")+COUNTIF(MEDICARTE!D39:D45,"Si")+COUNTIF(MEDICARTE!D39:D45,"Parcial")+COUNTIF(MEDICARTE!D39:D45,"No")),0) -> 0 | D27: =IFERROR((COUNTIF(MEDICARTE!D48:D50,"Sí")+COUNTIF(MEDICARTE!D48:D50,"Si")+0.5*COUNTIF(MEDICARTE!D48:D50,"Parcial"))/(COUNTIF(MEDICARTE!D48:D50,"Sí")+COUNTIF(MEDICARTE!D48:D50,"Si")+COUNTIF(MEDICARTE!D48:D50,"Parcial")+COUNTIF(MEDICARTE!D48:D50,"No")),0) -> 0 | E27: =IFERROR((COUNTIF(MEDICARTE!D53:D54,"Sí")+COUNTIF(MEDICARTE!D53:D54,"Si")+0.5*COUNTIF(MEDICARTE!D53:D54,"Parcial"))/(COUNTIF(MEDICARTE!D53:D54,"Sí")+COUNTIF(MEDICARTE!D53:D54,"Si")+COUNTIF(MEDICARTE!D53:D54,"Parcial")+COUNTIF(MEDICARTE!D53:D54,"No")),0) -> 0 | F27: =IFERROR(MEDICARTE!E56,0) -> 0 | K27: =A27 -> MEDICARTE | L27: =B27 -> 0 | N27: =A27 -> MEDICARTE | O27: =C27 -> 0 | Q27: =A27 -> MEDICARTE | R27: =D27 -> 0 | T27: =A27 -> MEDICARTE | U27: =F27 -> 0
A29: TABLA 3 — DOLORES ACTIVOS POR MESA
A30: Mesa | B30: D1 Rotación | C30: D2 SLAs | D30: D3 Autoservicio | E30: D4 Herramientas | F30: D5 NPS bajo | G30: D6 Escalamientos | H30: D7 Sin dashboard | I30: Total dolores
A31: SURA Cotizadores | B31: =IF('SURA Cotizadores'!C95="Sí",1,IF('SURA Cotizadores'!C95="Si",1,IF('SURA Cotizadores'!C95="Parcial",0.5,IF('SURA Cotizadores'!C95="No",0,0)))) -> 0.5 | C31: =IF('SURA Cotizadores'!C96="Sí",1,IF('SURA Cotizadores'!C96="Si",1,IF('SURA Cotizadores'!C96="Parcial",0.5,IF('SURA Cotizadores'!C96="No",0,0)))) -> 1 | D31: =IF('SURA Cotizadores'!C97="Sí",1,IF('SURA Cotizadores'!C97="Si",1,IF('SURA Cotizadores'!C97="Parcial",0.5,IF('SURA Cotizadores'!C97="No",0,0)))) -> 1 | E31: =IF('SURA Cotizadores'!C98="Sí",1,IF('SURA Cotizadores'!C98="Si",1,IF('SURA Cotizadores'!C98="Parcial",0.5,IF('SURA Cotizadores'!C98="No",0,0)))) -> 0.5 | F31: =IF('SURA Cotizadores'!C99="Sí",1,IF('SURA Cotizadores'!C99="Si",1,IF('SURA Cotizadores'!C99="Parcial",0.5,IF('SURA Cotizadores'!C99="No",0,0)))) -> 0 | G31: =IF('SURA Cotizadores'!C100="Sí",1,IF('SURA Cotizadores'!C100="Si",1,IF('SURA Cotizadores'!C100="Parcial",0.5,IF('SURA Cotizadores'!C100="No",0,0)))) -> 0.5 | H31: =IF('SURA Cotizadores'!C101="Sí",1,IF('SURA Cotizadores'!C101="Si",1,IF('SURA Cotizadores'!C101="Parcial",0.5,IF('SURA Cotizadores'!C101="No",0,0)))) -> 0.5 | I31: =SUM(B31:H31) -> 4 | K31: Mesa | L31: D4 Valor/Mejora | N31: Mesa | O31: Total dolores
A32: SURA Digital Venta | B32: =IF('SURA Digital Venta'!C96="Sí",1,IF('SURA Digital Venta'!C96="Si",1,IF('SURA Digital Venta'!C96="Parcial",0.5,IF('SURA Digital Venta'!C96="No",0,0)))) -> 0.5 | C32: =IF('SURA Digital Venta'!C97="Sí",1,IF('SURA Digital Venta'!C97="Si",1,IF('SURA Digital Venta'!C97="Parcial",0.5,IF('SURA Digital Venta'!C97="No",0,0)))) -> 1 | D32: =IF('SURA Digital Venta'!C98="Sí",1,IF('SURA Digital Venta'!C98="Si",1,IF('SURA Digital Venta'!C98="Parcial",0.5,IF('SURA Digital Venta'!C98="No",0,0)))) -> 1 | E32: =IF('SURA Digital Venta'!C99="Sí",1,IF('SURA Digital Venta'!C99="Si",1,IF('SURA Digital Venta'!C99="Parcial",0.5,IF('SURA Digital Venta'!C99="No",0,0)))) -> 0.5 | F32: =IF('SURA Digital Venta'!C100="Sí",1,IF('SURA Digital Venta'!C100="Si",1,IF('SURA Digital Venta'!C100="Parcial",0.5,IF('SURA Digital Venta'!C100="No",0,0)))) -> 0 | G32: =IF('SURA Digital Venta'!C101="Sí",1,IF('SURA Digital Venta'!C101="Si",1,IF('SURA Digital Venta'!C101="Parcial",0.5,IF('SURA Digital Venta'!C101="No",0,0)))) -> 0.5 | H32: =IF('SURA Digital Venta'!C102="Sí",1,IF('SURA Digital Venta'!C102="Si",1,IF('SURA Digital Venta'!C102="Parcial",0.5,IF('SURA Digital Venta'!C102="No",0,0)))) -> 1 | I32: =SUM(B32:H32) -> 4.5 | K32: =A17 -> SURA Cotizadores | L32: =E17 -> 0.5 | N32: =A31 -> SURA Cotizadores | O32: =I31 -> 4
A33: SURA Automatizacion | B33: =IF('SURA Automatizacion'!C96="Sí",1,IF('SURA Automatizacion'!C96="Si",1,IF('SURA Automatizacion'!C96="Parcial",0.5,IF('SURA Automatizacion'!C96="No",0,0)))) -> 0.5 | C33: =IF('SURA Automatizacion'!C97="Sí",1,IF('SURA Automatizacion'!C97="Si",1,IF('SURA Automatizacion'!C97="Parcial",0.5,IF('SURA Automatizacion'!C97="No",0,0)))) -> 0 | D33: =IF('SURA Automatizacion'!C98="Sí",1,IF('SURA Automatizacion'!C98="Si",1,IF('SURA Automatizacion'!C98="Parcial",0.5,IF('SURA Automatizacion'!C98="No",0,0)))) -> 1 | E33: =IF('SURA Automatizacion'!C99="Sí",1,IF('SURA Automatizacion'!C99="Si",1,IF('SURA Automatizacion'!C99="Parcial",0.5,IF('SURA Automatizacion'!C99="No",0,0)))) -> 0.5 | F33: =IF('SURA Automatizacion'!C100="Sí",1,IF('SURA Automatizacion'!C100="Si",1,IF('SURA Automatizacion'!C100="Parcial",0.5,IF('SURA Automatizacion'!C100="No",0,0)))) -> 0 | G33: =IF('SURA Automatizacion'!C101="Sí",1,IF('SURA Automatizacion'!C101="Si",1,IF('SURA Automatizacion'!C101="Parcial",0.5,IF('SURA Automatizacion'!C101="No",0,0)))) -> 0.5 | H33: =IF('SURA Automatizacion'!C102="Sí",1,IF('SURA Automatizacion'!C102="Si",1,IF('SURA Automatizacion'!C102="Parcial",0.5,IF('SURA Automatizacion'!C102="No",0,0)))) -> 1 | I33: =SUM(B33:H33) -> 3.5 | K33: =A18 -> SURA Digital Venta | L33: =E18 -> 0.5 | N33: =A32 -> SURA Digital Venta | O33: =I32 -> 4.5
A34: SURA Canales Masivos | B34: =IF('SURA Canales Masivos'!C96="Sí",1,IF('SURA Canales Masivos'!C96="Si",1,IF('SURA Canales Masivos'!C96="Parcial",0.5,IF('SURA Canales Masivos'!C96="No",0,0)))) -> 0.5 | C34: =IF('SURA Canales Masivos'!C97="Sí",1,IF('SURA Canales Masivos'!C97="Si",1,IF('SURA Canales Masivos'!C97="Parcial",0.5,IF('SURA Canales Masivos'!C97="No",0,0)))) -> 1 | D34: =IF('SURA Canales Masivos'!C98="Sí",1,IF('SURA Canales Masivos'!C98="Si",1,IF('SURA Canales Masivos'!C98="Parcial",0.5,IF('SURA Canales Masivos'!C98="No",0,0)))) -> 1 | E34: =IF('SURA Canales Masivos'!C99="Sí",1,IF('SURA Canales Masivos'!C99="Si",1,IF('SURA Canales Masivos'!C99="Parcial",0.5,IF('SURA Canales Masivos'!C99="No",0,0)))) -> 0.5 | F34: =IF('SURA Canales Masivos'!C100="Sí",1,IF('SURA Canales Masivos'!C100="Si",1,IF('SURA Canales Masivos'!C100="Parcial",0.5,IF('SURA Canales Masivos'!C100="No",0,0)))) -> 0 | G34: =IF('SURA Canales Masivos'!C101="Sí",1,IF('SURA Canales Masivos'!C101="Si",1,IF('SURA Canales Masivos'!C101="Parcial",0.5,IF('SURA Canales Masivos'!C101="No",0,0)))) -> 0.5 | H34: =IF('SURA Canales Masivos'!C102="Sí",1,IF('SURA Canales Masivos'!C102="Si",1,IF('SURA Canales Masivos'!C102="Parcial",0.5,IF('SURA Canales Masivos'!C102="No",0,0)))) -> 0.5 | I34: =SUM(B34:H34) -> 4 | K34: =A19 -> SURA Automatizacion | L34: =E19 -> 0.5 | N34: =A33 -> SURA Automatizacion | O34: =I33 -> 3.5
A35: BCO Gioti1 | B35: =IF('BCO Gioti 1'!C97="Sí",1,IF('BCO Gioti 1'!C97="Si",1,IF('BCO Gioti 1'!C97="Parcial",0.5,IF('BCO Gioti 1'!C97="No",0,0)))) -> 0.5 | C35: =IF('BCO Gioti 1'!C98="Sí",1,IF('BCO Gioti 1'!C98="Si",1,IF('BCO Gioti 1'!C98="Parcial",0.5,IF('BCO Gioti 1'!C98="No",0,0)))) -> 0 | D35: =IF('BCO Gioti 1'!C99="Sí",1,IF('BCO Gioti 1'!C99="Si",1,IF('BCO Gioti 1'!C99="Parcial",0.5,IF('BCO Gioti 1'!C99="No",0,0)))) -> 0.5 | E35: =IF('BCO Gioti 1'!C100="Sí",1,IF('BCO Gioti 1'!C100="Si",1,IF('BCO Gioti 1'!C100="Parcial",0.5,IF('BCO Gioti 1'!C100="No",0,0)))) -> 0 | F35: =IF('BCO Gioti 1'!C101="Sí",1,IF('BCO Gioti 1'!C101="Si",1,IF('BCO Gioti 1'!C101="Parcial",0.5,IF('BCO Gioti 1'!C101="No",0,0)))) -> 0 | G35: =IF('BCO Gioti 1'!C102="Sí",1,IF('BCO Gioti 1'!C102="Si",1,IF('BCO Gioti 1'!C102="Parcial",0.5,IF('BCO Gioti 1'!C102="No",0,0)))) -> 0 | H35: =IF('BCO Gioti 1'!C103="Sí",1,IF('BCO Gioti 1'!C103="Si",1,IF('BCO Gioti 1'!C103="Parcial",0.5,IF('BCO Gioti 1'!C103="No",0,0)))) -> 0 | I35: =SUM(B35:H35) -> 1 | K35: =A20 -> SURA Canales Masivos | L35: =E20 -> 0.5 | N35: =A34 -> SURA Canales Masivos | O35: =I34 -> 4
A36: BCO Gioti2 | B36: =IF('BCO Gioti 2'!C97="Sí",1,IF('BCO Gioti 2'!C97="Si",1,IF('BCO Gioti 2'!C97="Parcial",0.5,IF('BCO Gioti 2'!C97="No",0,0)))) -> 0 | C36: =IF('BCO Gioti 2'!C98="Sí",1,IF('BCO Gioti 2'!C98="Si",1,IF('BCO Gioti 2'!C98="Parcial",0.5,IF('BCO Gioti 2'!C98="No",0,0)))) -> 0 | D36: =IF('BCO Gioti 2'!C99="Sí",1,IF('BCO Gioti 2'!C99="Si",1,IF('BCO Gioti 2'!C99="Parcial",0.5,IF('BCO Gioti 2'!C99="No",0,0)))) -> 0 | E36: =IF('BCO Gioti 2'!C100="Sí",1,IF('BCO Gioti 2'!C100="Si",1,IF('BCO Gioti 2'!C100="Parcial",0.5,IF('BCO Gioti 2'!C100="No",0,0)))) -> 0 | F36: =IF('BCO Gioti 2'!C101="Sí",1,IF('BCO Gioti 2'!C101="Si",1,IF('BCO Gioti 2'!C101="Parcial",0.5,IF('BCO Gioti 2'!C101="No",0,0)))) -> 0 | G36: =IF('BCO Gioti 2'!C102="Sí",1,IF('BCO Gioti 2'!C102="Si",1,IF('BCO Gioti 2'!C102="Parcial",0.5,IF('BCO Gioti 2'!C102="No",0,0)))) -> 0 | H36: =IF('BCO Gioti 2'!C103="Sí",1,IF('BCO Gioti 2'!C103="Si",1,IF('BCO Gioti 2'!C103="Parcial",0.5,IF('BCO Gioti 2'!C103="No",0,0)))) -> 0 | I36: =SUM(B36:H36) -> 0 | K36: =A21 -> BCO Gioti1 | L36: =E21 -> 0.75 | N36: =A35 -> BCO Gioti1 | O36: =I35 -> 1
A37: BCO Gioti3 | B37: =IF('BCO Gioti 3'!C98="Sí",1,IF('BCO Gioti 3'!C98="Si",1,IF('BCO Gioti 3'!C98="Parcial",0.5,IF('BCO Gioti 3'!C98="No",0,0)))) -> 0 | C37: =IF('BCO Gioti 3'!C99="Sí",1,IF('BCO Gioti 3'!C99="Si",1,IF('BCO Gioti 3'!C99="Parcial",0.5,IF('BCO Gioti 3'!C99="No",0,0)))) -> 0 | D37: =IF('BCO Gioti 3'!C100="Sí",1,IF('BCO Gioti 3'!C100="Si",1,IF('BCO Gioti 3'!C100="Parcial",0.5,IF('BCO Gioti 3'!C100="No",0,0)))) -> 0 | E37: =IF('BCO Gioti 3'!C101="Sí",1,IF('BCO Gioti 3'!C101="Si",1,IF('BCO Gioti 3'!C101="Parcial",0.5,IF('BCO Gioti 3'!C101="No",0,0)))) -> 0 | F37: =IF('BCO Gioti 3'!C102="Sí",1,IF('BCO Gioti 3'!C102="Si",1,IF('BCO Gioti 3'!C102="Parcial",0.5,IF('BCO Gioti 3'!C102="No",0,0)))) -> 0 | G37: =IF('BCO Gioti 3'!C103="Sí",1,IF('BCO Gioti 3'!C103="Si",1,IF('BCO Gioti 3'!C103="Parcial",0.5,IF('BCO Gioti 3'!C103="No",0,0)))) -> 0 | H37: =IF('BCO Gioti 3'!C104="Sí",1,IF('BCO Gioti 3'!C104="Si",1,IF('BCO Gioti 3'!C104="Parcial",0.5,IF('BCO Gioti 3'!C104="No",0,0)))) -> 0 | I37: =SUM(B37:H37) -> 0 | K37: =A22 -> BCO Gioti2 | L37: =E22 -> 0 | N37: =A36 -> BCO Gioti2 | O37: =I36 -> 0
A38: BCO Gioti4 | B38: =IF('BCO Gioti 4'!C97="Sí",1,IF('BCO Gioti 4'!C97="Si",1,IF('BCO Gioti 4'!C97="Parcial",0.5,IF('BCO Gioti 4'!C97="No",0,0)))) -> 0 | C38: =IF('BCO Gioti 4'!C98="Sí",1,IF('BCO Gioti 4'!C98="Si",1,IF('BCO Gioti 4'!C98="Parcial",0.5,IF('BCO Gioti 4'!C98="No",0,0)))) -> 0 | D38: =IF('BCO Gioti 4'!C99="Sí",1,IF('BCO Gioti 4'!C99="Si",1,IF('BCO Gioti 4'!C99="Parcial",0.5,IF('BCO Gioti 4'!C99="No",0,0)))) -> 0 | E38: =IF('BCO Gioti 4'!C100="Sí",1,IF('BCO Gioti 4'!C100="Si",1,IF('BCO Gioti 4'!C100="Parcial",0.5,IF('BCO Gioti 4'!C100="No",0,0)))) -> 0 | F38: =IF('BCO Gioti 4'!C101="Sí",1,IF('BCO Gioti 4'!C101="Si",1,IF('BCO Gioti 4'!C101="Parcial",0.5,IF('BCO Gioti 4'!C101="No",0,0)))) -> 0 | G38: =IF('BCO Gioti 4'!C102="Sí",1,IF('BCO Gioti 4'!C102="Si",1,IF('BCO Gioti 4'!C102="Parcial",0.5,IF('BCO Gioti 4'!C102="No",0,0)))) -> 0 | H38: =IF('BCO Gioti 4'!C103="Sí",1,IF('BCO Gioti 4'!C103="Si",1,IF('BCO Gioti 4'!C103="Parcial",0.5,IF('BCO Gioti 4'!C103="No",0,0)))) -> 0 | I38: =SUM(B38:H38) -> 0 | K38: =A23 -> BCO Gioti3 | L38: =E23 -> 0 | N38: =A37 -> BCO Gioti3 | O38: =I37 -> 0
A39: AES | B39: =IF(AES!C95="Sí",1,IF(AES!C95="Si",1,IF(AES!C95="Parcial",0.5,IF(AES!C95="No",0,0)))) -> 0 | C39: =IF(AES!C96="Sí",1,IF(AES!C96="Si",1,IF(AES!C96="Parcial",0.5,IF(AES!C96="No",0,0)))) -> 0 | D39: =IF(AES!C97="Sí",1,IF(AES!C97="Si",1,IF(AES!C97="Parcial",0.5,IF(AES!C97="No",0,0)))) -> 0 | E39: =IF(AES!C98="Sí",1,IF(AES!C98="Si",1,IF(AES!C98="Parcial",0.5,IF(AES!C98="No",0,0)))) -> 0.5 | F39: =IF(AES!C99="Sí",1,IF(AES!C99="Si",1,IF(AES!C99="Parcial",0.5,IF(AES!C99="No",0,0)))) -> 0 | G39: =IF(AES!C100="Sí",1,IF(AES!C100="Si",1,IF(AES!C100="Parcial",0.5,IF(AES!C100="No",0,0)))) -> 0.5 | H39: =IF(AES!C101="Sí",1,IF(AES!C101="Si",1,IF(AES!C101="Parcial",0.5,IF(AES!C101="No",0,0)))) -> 0 | I39: =SUM(B39:H39) -> 1 | K39: =A24 -> BCO Gioti4 | L39: =E24 -> 0 | N39: =A38 -> BCO Gioti4 | O39: =I38 -> 0
A40: XM | B40: =IF(XM!C97="Sí",1,IF(XM!C97="Si",1,IF(XM!C97="Parcial",0.5,IF(XM!C97="No",0,0)))) -> 0 | C40: =IF(XM!C98="Sí",1,IF(XM!C98="Si",1,IF(XM!C98="Parcial",0.5,IF(XM!C98="No",0,0)))) -> 0 | D40: =IF(XM!C99="Sí",1,IF(XM!C99="Si",1,IF(XM!C99="Parcial",0.5,IF(XM!C99="No",0,0)))) -> 0 | E40: =IF(XM!C100="Sí",1,IF(XM!C100="Si",1,IF(XM!C100="Parcial",0.5,IF(XM!C100="No",0,0)))) -> 0 | F40: =IF(XM!C101="Sí",1,IF(XM!C101="Si",1,IF(XM!C101="Parcial",0.5,IF(XM!C101="No",0,0)))) -> 0 | G40: =IF(XM!C102="Sí",1,IF(XM!C102="Si",1,IF(XM!C102="Parcial",0.5,IF(XM!C102="No",0,0)))) -> 0 | H40: =IF(XM!C103="Sí",1,IF(XM!C103="Si",1,IF(XM!C103="Parcial",0.5,IF(XM!C103="No",0,0)))) -> 0 | I40: =SUM(B40:H40) -> 0 | K40: =A25 -> AES | L40: =E25 -> 0.25 | N40: =A39 -> AES | O40: =I39 -> 1
A41: MEDICARTE | B41: =IF(MEDICARTE!C97="Sí",1,IF(MEDICARTE!C97="Si",1,IF(MEDICARTE!C97="Parcial",0.5,IF(MEDICARTE!C97="No",0,0)))) -> 0 | C41: =IF(MEDICARTE!C98="Sí",1,IF(MEDICARTE!C98="Si",1,IF(MEDICARTE!C98="Parcial",0.5,IF(MEDICARTE!C98="No",0,0)))) -> 0 | D41: =IF(MEDICARTE!C99="Sí",1,IF(MEDICARTE!C99="Si",1,IF(MEDICARTE!C99="Parcial",0.5,IF(MEDICARTE!C99="No",0,0)))) -> 0 | E41: =IF(MEDICARTE!C100="Sí",1,IF(MEDICARTE!C100="Si",1,IF(MEDICARTE!C100="Parcial",0.5,IF(MEDICARTE!C100="No",0,0)))) -> 0 | F41: =IF(MEDICARTE!C101="Sí",1,IF(MEDICARTE!C101="Si",1,IF(MEDICARTE!C101="Parcial",0.5,IF(MEDICARTE!C101="No",0,0)))) -> 0 | G41: =IF(MEDICARTE!C102="Sí",1,IF(MEDICARTE!C102="Si",1,IF(MEDICARTE!C102="Parcial",0.5,IF(MEDICARTE!C102="No",0,0)))) -> 0 | H41: =IF(MEDICARTE!C103="Sí",1,IF(MEDICARTE!C103="Si",1,IF(MEDICARTE!C103="Parcial",0.5,IF(MEDICARTE!C103="No",0,0)))) -> 0 | I41: =SUM(B41:H41) -> 0 | K41: =A26 -> XM | L41: =E26 -> 0 | N41: =A40 -> XM | O41: =I40 -> 0
A42: Total por dolor (todas mesas) | B42: =SUM(B31:B41) -> 2.5 | C42: =SUM(C31:C41) -> 3 | D42: =SUM(D31:D41) -> 4.5 | E42: =SUM(E31:E41) -> 2.5 | F42: =SUM(F31:F41) -> 0 | G42: =SUM(G31:G41) -> 2.5 | H42: =SUM(H31:H41) -> 3 | I42: =SUM(I31:I41) -> 18 | K42: =A27 -> MEDICARTE | L42: =E27 -> 0 | N42: =A41 -> MEDICARTE | O42: =I41 -> 0
A44: TABLA 4 — PROMEDIO DIMENSIONES POR CLIENTE / GRUPO
A45: Dimensión | B45: SURA | C45: BCO | D45: AES | E45: XM | F45: MEDICARTE | G45: Meta (100%)
A46: D1 Org/Personas | B46: =IFERROR(AVERAGE(B17:B20),0) -> 0.375 | C46: =IFERROR(AVERAGE(B21:B24),0) -> 0.2 | D46: =B25 -> 0.4 | E46: =B26 -> 0 | F46: =B27 -> 0 | G46: =100% -> 1
A47: D2 Info/Tecnología | B47: =IFERROR(AVERAGE(C17:C20),0) -> 0.625 | C47: =IFERROR(AVERAGE(C21:C24),0) -> 0.19642857 | D47: =C25 -> 0.42857143 | E47: =C26 -> 0 | F47: =C27 -> 0 | G47: =100% -> 1
A48: D3 Socios/Proveed. | B48: =IFERROR(AVERAGE(D17:D20),0) -> 0.83333333 | C48: =IFERROR(AVERAGE(D21:D24),0) -> 0.20833333 | D48: =D25 -> 0.16666667 | E48: =D26 -> 0 | F48: =D27 -> 0 | G48: =100% -> 1
A49: D4 Valor/Mejora | B49: =IFERROR(AVERAGE(E17:E20),0) -> 0.5 | C49: =IFERROR(AVERAGE(E21:E24),0) -> 0.1875 | D49: =E25 -> 0.25 | E49: =E26 -> 0 | F49: =E27 -> 0 | G49: =100% -> 1
A51: TABLA 5 — KPI BENCHMARK INDUSTRIA vs MESAS
A52: KPI | B52: Benchmark Industria | C52: Objetivo Gen Next | D52: Promedio Mesas Actuales
A53: FCR (%) | B53: =75% -> 0.75 | C53: =85% -> 0.85 | D53: =IFERROR(AVERAGE('SURA Cotizadores'!C62,'SURA Digital Venta'!C63,'SURA Automatizacion'!C63,'SURA Canales Masivos'!C63,'BCO Gioti 1'!C64,'BCO Gioti 2'!C64,'BCO Gioti 3'!C64,'BCO Gioti 4'!C64,AES!C62,XM!C64,MEDICARTE!C64),0) -> 0.68
A54: SLA Cumplimiento (%) | B54: =95% -> 0.95 | C54: =98% -> 0.98 | D54: =IFERROR(AVERAGE('SURA Cotizadores'!C64,'SURA Digital Venta'!C65,'SURA Automatizacion'!C65,'SURA Canales Masivos'!C65,'BCO Gioti 1'!C66,'BCO Gioti 2'!C66,'BCO Gioti 3'!C66,'BCO Gioti 4'!C66,AES!C64,XM!C66,MEDICARTE!C66),0) -> 0.84333333
A55: NPS | B55: =45 -> 45 | C55: =65 -> 65 | D55: =IFERROR(AVERAGE('SURA Cotizadores'!C85,'SURA Digital Venta'!C86,'SURA Automatizacion'!C86,'SURA Canales Masivos'!C86,'BCO Gioti 1'!C87,'BCO Gioti 2'!C87,'BCO Gioti 3'!C87,'BCO Gioti 4'!C87,AES!C85,XM!C87,MEDICARTE!C87),0) -> 0
A56: Rotación anual (%) | B56: =15% -> 0.15 | C56: =8% -> 0.08 | D56: =IFERROR(AVERAGE(IF('SURA Cotizadores'!C119>1,'SURA Cotizadores'!C119/100,'SURA Cotizadores'!C119),IF('SURA Digital Venta'!C119>1,'SURA Digital Venta'!C119/100,'SURA Digital Venta'!C119),IF('SURA Automatizacion'!C119>1,'SURA Automatizacion'!C119/100,'SURA Automatizacion'!C119),IF('SURA Canales Masivos'!C119>1,'SURA Canales Masivos'!C119/100,'SURA Canales Masivos'!C119),IF('BCO Gioti 1'!C120>1,'BCO Gioti 1'!C120/100,'BCO Gioti 1'!C120),IF('BCO Gioti 2'!C120>1,'BCO Gioti 2'!C120/100,'BCO Gioti 2'!C120),IF('BCO Gioti 3'!C121>1,'BCO Gioti 3'!C121/100,'BCO Gioti 3'!C121),IF('BCO Gioti 4'!C120>1,'BCO Gioti 4'!C120/100,'BCO Gioti 4'!C120),IF(AES!C118>1,AES!C118/100,AES!C118),IF(XM!C120>1,XM!C120/100,XM!C120),IF(MEDICARTE!C120>1,MEDICARTE!C120/100,MEDICARTE!C120)),0) -> 0
A57: % Autoservicio | B57: =20% -> 0.2 | C57: =40% -> 0.4 | D57: =IFERROR(AVERAGE(IF('SURA Cotizadores'!C69>1,'SURA Cotizadores'!C69/100,'SURA Cotizadores'!C69),IF('SURA Digital Venta'!C70>1,'SURA Digital Venta'!C70/100,'SURA Digital Venta'!C70),IF('SURA Automatizacion'!C70>1,'SURA Automatizacion'!C70/100,'SURA Automatizacion'!C70),IF('SURA Canales Masivos'!C70>1,'SURA Canales Masivos'!C70/100,'SURA Canales Masivos'!C70),IF('BCO Gioti 1'!C71>1,'BCO Gioti 1'!C71/100,'BCO Gioti 1'!C71),IF('BCO Gioti 2'!C71>1,'BCO Gioti 2'!C71/100,'BCO Gioti 2'!C71),IF('BCO Gioti 3'!C71>1,'BCO Gioti 3'!C71/100,'BCO Gioti 3'!C71),IF('BCO Gioti 4'!C71>1,'BCO Gioti 4'!C71/100,'BCO Gioti 4'!C71),IF(AES!C69>1,AES!C69/100,AES!C69),IF(XM!C71>1,XM!C71/100,XM!C71),IF(MEDICARTE!C71>1,MEDICARTE!C71/100,MEDICARTE!C71)),0) -> 0.044444444
A58: Costo/ticket (USD) | B58: =15 -> 15 | C58: =8 -> 8 | D58: =IFERROR(AVERAGE('SURA Cotizadores'!C67,'SURA Digital Venta'!C68,'SURA Automatizacion'!C68,'SURA Canales Masivos'!C68,'BCO Gioti 1'!C69,'BCO Gioti 2'!C69,'BCO Gioti 3'!C69,'BCO Gioti 4'!C69,AES!C67,XM!C69,MEDICARTE!C69),0) -> 0

Sheet Listas
B2: LISTAS DE VALIDACIÓN (no modificar)
B4: Respuestas Prácticas | D4: Nivel Madurez | F4: Criticidad Dolor | H4: Modelo Contrato | J4: Tipo Incidente | L4: Riesgo Churn | N4: Cliente | P4: Prioridad | R4: Integrado
B5: Sí | D5: N0 | F5: Alta | H5: FTE dedicado | J5: Incidente | L5: Alto | N5: SURA | P5: Alta | R5: Si
H6: Staffing
B7: Parcial | D7: N1 | F7: Media | H7: Capacidad | J7: Requerimiento | L7: Medio | N7: Bancolombia | P7: Media | R7: No
B8: No | D8: N2 | F8: Baja | H8: Bolsa de horas | J8: Cambio | L8: Bajo | N8: XM | P8: Baja | R8: En proceso
B9: N/A | D9: N3 | H9: Output/ticket | J9: Problema | N9: AES | P9: Sin prioridad
D10: N4 | H10: Mixto | J10: Consulta | N10: MEDICARTE
B11: Misión Principal | D11: N5
B12: Call Center ->Manejar grandes volúmenes de llamadas; filtrar y derivar
B13: Help Desk (Reactivo) -> Coordinación para la restauración del servicio. Infraestructura, herramientas de seguimiento, base de conocimiento
B14: Help Desk -> Service Desk (híbrido)
B15: Service Desk ->Servicio integral: incidentes, solicitudes, consultas, altas/bajas/cambios
B16: Service Desk + Problem Management
B17: Otro
B20: Herramientas ITSM | D20: Herramientas Monitoreo y observabilidad | F20: Herramientas de Chat / Bot de autoservicio | H20: Herramientas de Analítica / Dashboard / BI | J20: Herramientas de Colaboración (Teams, Slack, etc.) | L20: Herramientas de Gestión de identidades / IAM | N20: Herramientas de CMDB / Inventario de activos | P20: Herramientas de Base de conocimiento (KB)
B21: ServiceNow ITSM → Plataforma ITSM empresarial, muy personalizable. (24x7 o según SLA) | D21: AppDynamics → Monitoreo de rendimiento de aplicaciones (APM) y experiencia de usuario. | F21: Ada → Bot conversacional para atención al cliente y soporte automatizado. | H21: Azure Monitor Workbooks → Creación de dashboards y reportes para métricas en Azure. | J21: Asana → Gestión de tareas y proyectos con enfoque en equipos ágiles. | L21: AWS IAM → Gestión de identidades y accesos para servicios en AWS. | N21: BMC Atrium CMDB → Base de datos de configuración empresarial integrada con BMC Helix ITSM. | P21: BookStack → Plataforma open source para crear y organizar documentación en formato libro.
B22: Jira Service Management → Integración con desarrollo ágil y soporte TI. (8x5 o 24x7) | D22: AWS CloudWatch → Monitoreo, métricas y alertas para entornos AWS. | F22: Amelia → Asistente virtual con IA para soporte, RRHH y procesos empresariales. | H22: Datadog Dashboards → Visualización de métricas, logs y trazas en Datadog. | J22: ClickUp → Plataforma de productividad y gestión de proyectos todo-en-uno. | L22: Azure AD B2C → Gestión de identidades para aplicaciones orientadas a clientes en Azure. | N22: Device42 → Descubrimiento automático y gestión de activos de TI y dependencias. | P22: Confluence → Herramienta de documentación y colaboración de Atlassian, ideal para KB interna.
B23: BMC Helix ITSM → Gestión de servicios TI robusta, orientada a grandes organizaciones. (24x7 o 8x5) | D23: Azure Monitor → Observabilidad y métricas para entornos Microsoft Azure. | F23: Azure Bot Service → Plataforma de Microsoft para crear y desplegar bots en múltiples canales. | H23: Elastic Kibana → Visualización y análisis de datos de Elastic Stack. | J23: Confluence → Herramienta de documentación y colaboración en equipo de Atlassian. | L23: BeyondTrust → Gestión de accesos privilegiados (PAM) y control de sesiones. | N23: Freshservice Asset Management → Gestión de activos integrada en la plataforma Freshservice. | P23: Document360 → Plataforma de KB para clientes y equipos, con control de versiones.
B24: ManageEngine ServiceDesk Plus → ITSM con módulos de activos y CMDB. (8x5 o 24x7) | D24: Datadog → Monitoreo en la nube para infraestructura, logs, APM y seguridad. | F24: Botpress → Framework open source para desarrollar chatbots personalizados. | H24: Excel / Power Query → Análisis, transformación y modelado de datos en Microsoft Excel. | J24: Google Chat → Mensajería y colaboración integrada en Google Workspace. | L24: CyberArk → Plataforma líder en gestión de accesos privilegiados y credenciales. | N24: GLPI Assets → Módulo de gestión de activos e inventario de GLPI. | P24: Freshservice Knowledge Base → Módulo de KB integrado en Freshservice para autoservicio ITSM.
B25: Freshservice → ITSM en la nube, fácil de implementar. (8x5 o 24x7) | D25: Dynatrace → Observabilidad con IA para aplicaciones, microservicios y experiencia digital. | F25: ChatGPT / Copilot personalizado → Asistente conversacional con IA generativa y personalización de respuestas. | H25: Google Looker → Plataforma de BI y análisis de datos en la nube. | J25: Jira Software → Gestión de proyectos ágiles y seguimiento de incidencias. | L25: Duo Security → Autenticación multifactor (MFA) y verificación de identidad. | N25: iTop CMDB → Solución open source para CMDB y gestión de servicios. | P25: Google Sites → Creación sencilla de sitios web y KB internas en Google Workspace.
B26: Zendesk Support → Soporte multicanal, orientado a experiencia de cliente. (8x5 o 24x7) | D26: Elastic Observability → Monitoreo y análisis de logs con Elastic Stack (Elasticsearch, Kibana, Beats). | F26: Cognigy → Plataforma de automatización conversacional para empresas. | H26: Grafana → Visualización de métricas y datos en tiempo real desde múltiples fuentes. | J26: Microsoft Teams → Comunicación, videollamadas y colaboración empresarial. | L26: ForgeRock → Plataforma IAM para empresas con gestión de identidades y accesos. | N26: Ivanti Neurons for Discovery → Descubrimiento y mapeo automático de activos y dependencias. | P26: Guru → Plataforma de KB con enfoque en gestión del conocimiento en tiempo real.
B27: GLPI → Solución ITSM de código abierto, flexible y gratuita. (8x5 o 24x7) | D27: Google Cloud Operations → Observabilidad y monitoreo para entornos Google Cloud. | F27: Freshservice Freddy AI → Bot de soporte integrado en Freshservice para ITSM. | H27: Jira Dashboards → Paneles para seguimiento de proyectos, incidencias y métricas ágiles. | J27: Miro → Pizarra colaborativa online para trabajo visual en equipo. | L27: Google Cloud Identity → Gestión de usuarios, dispositivos y accesos en Google Cloud. | N27: Jira Assets / Insight → Gestión de activos y CMDB integrada en Jira Service Management. | P27: Helpjuice → KB para clientes y equipos, con analítica de uso.
B28: OTRS / Znuny → ITSM open source con alta capacidad de personalización. (8x5 o 24x7) | D28: Grafana / Prometheus → Recolección de métricas (Prometheus) y visualización en tiempo real (Grafana). | F28: Google Dialogflow → Creación de bots con procesamiento de lenguaje natural (NLP). | H28: Looker Studio → Creación de reportes y dashboards interactivos de Google. | J28: Monday.com → Gestión de proyectos y flujos de trabajo personalizables. | L28: IBM Security Verify → IAM con SSO, MFA y gestión de identidades en la nube. | N28: Lansweeper → Inventario y descubrimiento de hardware y software en red. | P28: Jira Service Management KB → Base de conocimiento integrada con el portal de soporte de Jira.
B29: Ivanti Neurons for ITSM → ITSM con automatización y gestión proactiva. (8x5 o 24x7) | D29: LogicMonitor → Monitoreo de infraestructura híbrida, nube y redes. | F29: IBM Watson Assistant → Asistente virtual con IA de IBM para soporte y autoservicio. | H29: ManageEngine Analytics Plus → BI y analítica para ITSM y operaciones. | J29: Notion → Documentación, bases de datos y colaboración en un solo espacio. | L29: Keycloak → Solución open source para SSO, autenticación y autorización. | N29: ManageEngine AssetExplorer → Gestión de activos de TI y ciclo de vida. | P29: MediaWiki → Plataforma wiki open source (usada por Wikipedia) para documentación colaborativa.
B30: Cherwell Service Management → Plataforma ITSM adaptable, orientada a medianas y grandes empresas. (8x5 o 24x7) | D30: Nagios → Monitoreo de red, servidores y servicios críticos. | F30: Intercom Fin → Bot de soporte y ventas con IA. | H30: MicroStrategy → Plataforma de BI empresarial con analítica avanzada. | J30: Planner → Planificación y seguimiento de tareas en Microsoft 365. | L30: ManageEngine ADManager Plus → Administración y reportes para Active Directory. | N30: Microsoft Intune → Gestión de dispositivos y aplicaciones en la nube. | P30: Microsoft Viva Topics → Organización automática de conocimiento en Microsoft 365.
B31: Aranda Service Management → ITSM popular en Latinoamérica, con módulos integrados. (8x5 o 24x7) | D31: New Relic → Observabilidad para aplicaciones, infraestructura y experiencia de usuario. | F31: Kore.ai → Plataforma de bots empresariales con IA conversacional. | H31: Power BI → BI y visualización de datos de Microsoft, con integración a múltiples fuentes. | J31: SharePoint → Gestión documental y colaboración en entornos Microsoft. | L31: Microsoft Entra ID → Plataforma de identidad de Microsoft (antes Azure AD) con SSO y MFA. | N31: OCS Inventory → Inventario de hardware y software open source. | P31: Notion → Herramienta de documentación, bases de datos y colaboración flexible.
... B35: Microsoft Dynamics 365 Customer Service → Soporte y atención al cliente integrado con CRM. (8x5 o 24x7) | D35: Zabbix → Monitoreo de red, servidores y aplicaciones con alertas configurables. | F35: Zendesk Answer Bot → Bot de soporte integrado en Zendesk para resolver tickets automáticamente. | H35: Tableau → Visualización y análisis de datos con enfoque en exploración interactiva. | J35: Zoom → Videoconferencias, webinars y colaboración remota. | L35: SailPoint → Gestión de identidades y gobierno de accesos (IGA). | N35: Snipe-IT → Gestión de activos de TI open source, ideal para control de inventario. | P35: Zendesk Guide → KB para autoservicio de clientes integrada con Zendesk Support.
B44: NPS (Net Promoter Score) | D44: CSAT (Satisfacción del cliente) — escala 1-5 | F44: CES (Customer Effort Score) | H44: Cantidad de Quejas escaladas / mes | J44: Tiempo promedio de espera en canal (minutos)
B45: No Aplica | D45: 5 Muy satisfecho - Experiencia excelente, superó expectativas. | F45: No Aplica | H45: 0-20 Bajo - Nivel de quejas controlado. | J45: 0-2 minutos → Excelente - Atención casi inmediata.
B46: 9-10 Promotor - Cliente muy satisfecho y leal. Recomienda activamente. | D46: 4 Satisfecho - Buena experiencia, cumplió expectativas. | F46: 7 Muy fácil - Casi sin esfuerzo para resolver la necesidad. | H46: 21-50 Medio - Atención necesaria para evitar aumento. | J46: 3-5 minutos → Bueno - Tiempo de espera aceptable.
B47: 7-8 Pasivo - Cliente satisfecho pero sin entusiasmo. | D47: 3 Neutral - Experiencia aceptable, sin destacar. | F47: 6 Fácil - Requirió poco esfuerzo. | H47: 51-100 Alto - Requiere acciones correctivas urgentes. | J47: 6-10 minutos → Regular - Puede generar ligera incomodidad.
B48: 0-6 Detractor - Cliente insatisfecho, riesgo de comentarios negativos. | D48: 2 Insatisfecho - Experiencia por debajo de lo esperado. | F48: 5 Algo fácil - Ligero esfuerzo, sin complicaciones. | H48: Más de 100 Crítico - Situación grave, intervención inmediata. | J48: 11-20 minutos → Malo - Riesgo de insatisfacción del cliente.
D49: 1 Muy insatisfecho - Experiencia muy negativa. | F49: 4 Neutral - Esfuerzo moderado. | J49: Más de 20 minutos → Crítico - Experiencia muy negativa, requiere acción urgente.
F50: 3 Algo difícil - Requirió atención y tiempo extra.
F51: 2 Difícil - Mucho esfuerzo para lograrlo.
B52: Disponibilidad | F52: 1 Muy difícil - Experiencia frustrante y complicada.
B53: 24x7 → 168 horas/semana
B54: 8x5 → 40 horas/semana
B55: 12x6 → 72 horas/semana
B56: 16x5 → 80 horas/semana
B57: 10x7 → 70 horas/semana
B58: Otra

Sheet Transcript Virginia & Lina
A1: Mesas Soporte-20260626_143756-Grabación de la reunión.mp4
A49: Virginia Durango Muriel
A50: 0 minutos 3 segundos0:03
A51: Virginia Durango Muriel 0 minutos 3 segundos
A52: Crecimiento precisamente de las mesas de Sura, donde precisamente alzamos las manos porque no teníamos como claridades en cosas de las que teníamos que empezar a determinar y al cliente si estábamos en capacidad o no de manejarle. Uno, el tema de los niveles listo. ¿Entonces, qué pasa con el tema de los niveles en las mesas de servicio? Normalmente se hablan nivel uno, nivel 2, nivel 3.
A53: Virginia Durango Muriel 0 minutos 26 segundos
A54: Cierto, o esas son por lo menos las que conocemos. Normalmente el nivel uno lo manejan directamente los clientes, porque nivel uno es muy focalizado como ese tema de las ayudas al negocio, mucho de regla de negocio funcional, mucho de que ay, venga, yo no sé cómo hacer la transacción, me explicas, entonces ellos van y ta ta ta.
A55: Virginia Durango Muriel 0 minutos 46 segundos
A56: Cierto, nivel 2, digamos que normalmente es un escalamiento que le hace el nivel uno, nivel 2, cuando posiblemente a nivel de proceso el proceso falla, pero el proceso hasta ahí no se sabe si ni siquiera hay que incluirle o inyectarle alguna mejora como tal desde la codificación, sino que seguramente hay que revisar un log.
A57: Virginia Durango Muriel 1 minuto 5 segundos
A58: Hay que hacer una un relanzamiento de algún proceso. Hay que entrar a la base de datos como para mirar de pronto información que en la visual no se ve, entonces para respuesta como ese tipo de cosas es las que nosotros normalmente atendemos. Listo, y el nivel 3 es cuando nosotros ya a nivel 2 esculcamos lo suficiente y decimos.
A59: Virginia Durango Muriel 1 minuto 24 segundos
... A247: Bueno, hasta luego, gracias.

Sheet AES
B2: LEVANTAMIENTO DE MESA DE SERVICIOS — AES
I3: ESCALA DE MADUREZ — N0 a N5
B4: ① IDENTIFICACIÓN GENERAL DE LA MESA | I4: NIVEL | J4: NOMBRE | K4: DESCRIPCIÓN
B5: Cliente: | C5: AES | I5: N0 | J5: Reactivo / Sin estructura | K5: No existe proceso formal. Todo es manual y reactivo. Sin CMDB ni catálogo.
B6: Negocio del cliente: | C6: Empresa de energia. Central hidroelectrica | I6: N1 | J6: Inicial / Ad hoc/ Operación reactiva | K6: Procesos básicos documentados. Herramientas mínimas. Cumplimiento inconsistente.
B7: Nombre de la Mesa: | C7: Soporte IT/OT | I7: N2 | J7: Definido / Organización funcional | K7: Procesos ITIL definidos y seguidos. Métricas básicas (SLA (Service Level Agreement), FCR (Fondo de Capital Riesgo)). Equipo estable.
B8: Líder / Coordinador: | C8: Michael Arevalo Luna | I8: N3 | J8: Gestionado / Gestión por servicios | K8: Métricas avanzadas. Automatización parcial. Gestión proactiva de problemas.
B9: Fecha del Levantamiento: | C9: 46210 | I9: N4 | J9: Optimizado / Gestión integrada | K9: Autoservicio maduro. IA/ML básico. XLA (Experience Level Agreement) medidos. Mejora continua activa.
B10: Ubicación / Modalidad: | C10: Virtual
B11: N° de Agentes (FTE) (cantidad de personas): | C11: 4 | I11: Función | J11: Misión Principal | K11: Alcance
B12: Modelo de Contrato: | C12: Staffing | I12: Call Center | J12: Manejar grandes volúmenes de llamadas; filtrar y derivar | K12: Punto de contacto y distribución estructurada
B13: Nivel Madurez Actual: | C13: N1 | D13: (N0 Reactivo → N5 Innovador) | I13: Help Desk | J13: Coordinación para la restauración del servicio; "arreglar cosas" | K13: Infraestructura, herramientas de seguimiento, base de conocimiento
B14: Modelo de Operación | C14: Help Desk / soporte IT-OT e infraestructura: coordinación para restauración del servicio; atención de tareas y servicios derivados desde ServiceNow/ARUS. | I14: Service Desk | J14: Servicio integral: incidentes, solicitudes, consultas, altas/bajas/cambios | K14: Alcance configurable; representa al usuario dentro de TI
B15: (Tercero) Empresa de soporte al cliente | C15: ARUS; tickets
B16: En que otro Niveles tenemos presencia: | C16: No Aplica
B17: En que paises tenemos presencia: | C17: Colombia
B18: Que hacemos en el cliente: | C18: Soporte IT/OT y maneja infraestructura, aunque, si bien a ellos les cargan los requerimientos por Service Now. Las asignaciones llegan por tareas (por ejemplo un punto de red, falla de equipos de equipos de comunicación, fallas de equipos de red) o por servicios. Hay 4 personas que atienden soporte en redes, networking, facilities y seguridad electrónica + cableado estructurado y enlaces de fibra. Hacen mantenimiento preventivo
B19: Tiempo de la Mesa de Servicio | C19: 3 años
B20: Finalización | C20: 12 de Agosto 2026; extesion 12 Noviembre
B21: Renovación: | C21: RFP pendiente de aprobación para renovar 3 años más. El contrato con más condiciones y mejoras
B22: Equipos de infraestructura: | C22: del cliente; PersonalSoft compra y re-cobra al cliente
B23: Video: | C23: https://personalsoftsas-my.sharepoint.com/personal/jorengifo_personalsoft_com/_layouts/15/stream.aspx?id=%2Fpersonal%2Fjorengifo%5Fpersonalsoft%5Fcom%2FDocuments%2FGrabaciones%2FHablemos%20Mesas%20AES%2D20260707%5F113150%2DGrabaci%C3%B3n%20de%20la%20reuni%C3%B3n%2Emp4&referrer=StreamWebApp%2EWeb&referrerScenario=AddressBarCopied%2Eview%2E8bb79edf%2Dcf18%2D4677%2D8d5a%2Dc46ddd3c2dad
B24: Transcript: | C24: Natalia Zartha Suarez empezó la transcripción Natalia Zartha Suarez 0 minutos 3 segundos0:03 Natalia Zartha Suarez 0 minutos 3 segundos Sí, dime tranquilo. Michael Arevalo Luna 0 minutos 4 segundos0:04 Michael Arevalo Luna 0 minutos 4 segundos Dale y yo ahorita les doy un contexto de del cliente, vale. Natalia Zartha Suarez 0 minutos 8 segundos0:08 Natalia Zartha Suarez 0 minutos 8 segundos Dale listo listo Claro que sí muchas gracias Bueno si quieres te cuento yo ingresé hace más de una semanita a la a la empresa estoy en el área de de servicios Muchas gracias estoy en el área de servicios de innovación y vamos a diseñar un nuevo servicio para mesa de de servicios entonces antes de arrancar con el diseño queremos levantar la información que tenemos de las mesas actuales las lecciones Michael Arevalo Luna 0 minutos 17 segundos0:17 Michael Arevalo Luna 0 minutos 17 segundos Bienvenida. Natalia Zartha Suarez 0 minutos 32 segundos0:32 Natalia Zartha Suarez 0 minutos 32 segundos aprendidas Cuál es de pronto el feedback tuyo qué podríamos mejorar en el en el servicio que se va a estandarizar y a venir cierto si quieres te comparto acá muy muy rapidito nosotros decimos como eso es como una guía para irte preguntando no es que no es ni una evaluación es Natalia Zartha Suarez 0 minutos 52 segundos es como una auditoría muy rigurosa si no se cumple no no pasa nada o sea la idea es que podamos obtener como la mayor información posible y de ahí ya partir con el diseño cierto Entonces más o menos lo que hemos identificado en las en la madurez de las mesas de servicio lo estamos catalogando en estos cinco niveles en nivel uno que es un nivel muy muy inicial Natalia Zartha Suarez 1 minuto 15 segundos muy reactivo entonces salen tickets y se responden en el volumen que va saliendo y tiene un factor de riesgo y es el conocimiento hacia las personas y si rota pues es es muy eh un un riesgo para la la empresa entonces a esto lo lo llamamos el reactivo y crecimiento automatizado Natalia Zartha Suarez 1 minuto 34 segundos que por hoy en día es como muy reactivo el nivel y todo es un nivel más administrado entonces son procesos por mesa herramientas tickets y es como lo mínimo que tiene una mesa de ayuda o un Help de que por el contexto que nos yo yo creo que es es el caso cierto eh después el nivel tres que es predictivo y evolutivo es donde queremos empezar a a Natalia Zartha Suarez 1 minuto 55 segundos ayudar las mesas un nivel cuatro que ya es más como cuantitativas métricas y el nivel 5 es el servicio que nosotros queremos diseñar algo muy autónomo muy estandarizado muy óptimo entonces tiene como Mostrar Aquí estos cinco niveles porque de ahí y y si quieres ya nos vas dando como el el contexto diseñamos esta planta Natalia Zartha Suarez 2 minutos 15 segundos ya o sea te la muestro Qué son los puntos que que queremos levantar información general tratar de identificar En qué nivel En qué nivel estamos en cada mesa eh unas preguntas a nivel de prácticas y de itil cierto volumetría kpis que de pronto tengas eh distribución de de incidentes por categoría si están Natalia Zartha Suarez 2 minutos 38 segundos tema de experiencia del usuario del usuario del cliente cierto algunos dolores nosotros identificamos 18 dólares pero pueden haber más entonces como que les duele a ustedes temas de inter rotación y talento herramientas tecnologías algo del modelo económico si se conoce y eso ya es como para el nuevo servicio entonces una visión para el nuevo servicio Natalia Zartha Suarez 2 minutos 59 segundos qué debería cambiar y si tenemos algún caso de éxito listo y entonces si quieres aquí ya te doy la palabra yo aquí he empezado a tomar apuntes con lo que ya me me me ha pasado cierto para que seamos más o menos que sé que es una empresa de energía sé que pues yo lo puse Aquí como un gel dex que es más como temas de infraestructura Natalia Zartha Suarez 3 minutos 19 segundos Cierto, como de soporte de infraestructura, pero si quieres, ahora sí te dejo hablar. Ándale, sí. Michael Arevalo Luna 3 minutos 23 segundos3:23 Michael Arevalo Luna 3 minutos 23 segundos Dale nada, primero bienvenidos, que pena ahí que de cierta manera y cuando Johanna ayer me hizo preguntas, estaba como ocupado y no le ha dado respuesta y no está esta mañana y nada lo que necesiten con gusto. De cierta manera, yo siento que dentro del me imagino que con los con los clientes o de lo que están sacando de lo que estás haciendo ahorita. Natalia Zartha Suarez 3 minutos 34 segundos3:34 Natalia Zartha Suarez 3 minutos 34 segundos No, tranquilo. Natalia Zartha Suarez 3 minutos 43 segundos Sí. Michael Arevalo Luna 3 minutos 44 segundos3:44 Michael Arevalo Luna 3 minutos 44 segundos No debería estar dentro de esas priorías iniciales y ya te cuento por qué. Natalia Zartha Suarez 3 minutos 47 segundos3:47 Natalia Zartha Suarez 3 minutos 47 segundos O K, de bueno, sí. Michael Arevalo Luna 3 minutos 49 segundos3:49 Michael Arevalo Luna 3 minutos 49 segundos En este momento nosotros teníamos un contrato vigente hasta el 12 de agosto. Sí, ajá, ya les voy a contar. Entonces, ¿qué pasa? En se generó un RFP para licitación y hacer una renovación. Nosotros entramos a participar junto con otras cuatro o 5 compañías. Ajá. Natalia Zartha Suarez 3 minutos 53 segundos3:53 Natalia Zartha Suarez 3 minutos 53 segundos Y se termina. Natalia Zartha Suarez 3 minutos 55 segundos bueno. Michael Arevalo Luna 4 minutos 7 segundos4:07 Michael Arevalo Luna 4 minutos 7 segundos Hola Fredy, buen día. F Fredy Alonso Pinilla Juez 4 minutos 9 segundos4:09 Fredy Alonso Pinilla Juez 4 minutos 9 segundos Buen día para todos. Natalia Zartha Suarez 4 minutos 11 segundos4:11 Natalia Zartha Suarez 4 minutos 11 segundos Buenos días, Fredy, un gusto. Michael Arevalo Luna 4 minutos 11 segundos4:11 Michael Arevalo Luna 4 minutos 11 segundos Les presento a Fredy. Fredy es el coordinador que nos ayuda. Bueno, de hecho Fredy tiene doble error en AES. Él nos ayuda directamente en la planta, ellos están ubicados en la planta. Entonces Fredy es el que coordina como todas las actividades y es dentro de lo que hace el gerente y las solicitudes que hace la gerencia de AES dentro de la planta, pues ahí está ahí como coordinando. Natalia Zartha Suarez 4 minutos 32 segundos4:32 Natalia Zartha Suarez 4 minutos 32 segundos Sí. Michael Arevalo Luna 4 minutos 33 segundos4:33 Michael Arevalo Luna 4 minutos 33 segundos Todo lo que se requiera. Natalia Zartha Suarez 4 minutos 35 segundos4:35 Natalia Zartha Suarez 4 minutos 35 segundos Un gusto. Michael Arevalo Luna 4 minutos 36 segundos4:36 Michael Arevalo Luna 4 minutos 36 segundos Vale, entonces la idea de que Fredy nos acompañe es de cierta manera. Yo sé que él nos puede ayudar a tener algún entendimiento en cosas que a mí se me se me pasen, pero pues como te decía, digamos que antes de llegar a ese punto, siento que con el tema del RFP. F Fredy Alonso Pinilla Juez 4 minutos 37 segundos4:37 Fredy Alonso Pinilla Juez 4 minutos 37 segundos Igualmente. Michael Arevalo Luna 4 minutos 56 segundos4:56 Michael Arevalo Luna 4 minutos 56 segundos y con lo que como está actualmente este servicio, como funciona actualmente, eso va a cambiar muchísimo. Sí, digamos que actualmente, pues nosotros ellos están bajo el modelo de staffing, pero entonces con el error FP nuevo, el tema va a cambiar al punto en que nosotros nos vamos a cargar de absolutamente toda la operación. Natalia Zartha Suarez 5 minutos 7 segundos5:07 Natalia Zartha Suarez 5 minutos 7 segundos Sing. Michael Arevalo Luna 28 minutos 1 segundo28:01 Michael Arevalo Luna 28 minutos 1 segundo No a ustedes lo que necesiten con mucho gusto igual. Joan Sebastian Rengifo Ocampo 28 minutos 1 segundo28:01 Joan Sebastian Rengifo Ocampo 28 minutos 1 segundo Listo, muchas gracias. F Fredy Alonso Pinilla Juez 28 minutos 2 segundos28:02 Fredy Alonso Pinilla Juez 28 minutos 2 segundos Vale. Fredy Alonso Pinilla Juez 28 minutos 3 segundos Con todo gusto y cualquier consulta, pues quedamos ahí pendientes. Natalia Zartha Suarez 28 minutos 6 segundos28:06 Natalia Zartha Suarez 28 minutos 6 segundos Es igualmente por acá, muchísimas gracias. Chaita, gracias, hasta luego, gracias. Joan Sebastian Rengifo Ocampo 28 minutos 9 segundos28:09 Joan Sebastian Rengifo Ocampo 28 minutos 9 segundos Bueno, hasta luego. Michael Arevalo Luna 28 minutos 9 segundos28:09 Michael Arevalo Luna 28 minutos 9 segundos Vale, que estén bien, chao. F Fredy Alonso Pinilla Juez 28 minutos 10 segundos28:10 Fredy Alonso Pinilla Juez 28 minutos 10 segundos No Natalia John. Fredy Alonso Pinilla Juez 28 minutos 12 segundos Better.  Natalia Zartha Su
B25: # Aplicaciones:
B27: ③ EVALUACIÓN DE PRÁCTICAS ITIL v4 — 4 DIMENSIONES
B28: # | C28: PRÁCTICA | D28: ¿Se cumple? | E28: Observaciones / Evidencia | F28: Prioridad Mejora
B29: D1 — Organización y Personas
B30: 1.1 | C30: Gestión de la Fuerza Laboral: Headcount, perfiles, competencias | D30: Parcial | F30: Media
B31: 1.2 | C31: Gestión del Conocimiento: KB (Knowledge Base), documentación, onboarding | D31: Parcial | F31: Alta
B32: 1.3 | C32: Gestión del Talento: Rotación, desarrollo, retención | D32: No | F32: Media
B33: 1.4 | C33: Gestión del Desempeño: Metas individuales, feedback, KPIs de agente | D33: No | F33: Media
B34: 1.5 | C34: Cultura de Servicio: Orientación al usuario, empatía, NPS (Net Promoter Score) interno | D34: Sí | E34: Sí aplica: hay disposición de soporte y coordinación con planta; Fredy coordina actividades directamente en AES. | F34: Baja
B36: D2 — Información y Tecnología
B37: 2.1 | C37: Gestión de Incidentes: Proceso, tiempos, escalamiento | D37: Sí | E37: Sí aplica: se atienden tareas/servicios como puntos de red y fallas de equipos de comunicación/red. | F37: Media
B38: 2.2 | C38: Gestión de Requerimientos: Catálogo de servicios, flujos | D38: Sí | E38: Sí aplica: los requerimientos se cargan por ServiceNow y llegan como tareas o servicios. | F38: Media
B39: 2.3 | C39: Gestión de Problemas: RCA (Análisis de Causa Raíz ), errores conocidos, KEDB (Known Error Database) | D39: Parcial | E39: Parcial: se mencionan fallas recurrentes de red/equipos, pero no se evidencia RCA/KEDB formal. | F39: Alta
B40: 2.4 | C40: Gestión de Cambios: CAB (Change Advisory Board), RFC (Solicitud de Cambio), ventanas de mantenimiento | D40: No | F40: Media
B41: 2.5 | C41: Gestión de la Configuración: CMDB (Configuration Management Database), assets, CIs (Elementos de Configuración) | D41: Parcial | E41: Parcial: se mencionan equipos de infraestructura del cliente y recobro de compras por PersonalSoft; no se confirma CMDB formal. | F41: Alta
B42: 2.6 | C42: Monitoreo y Eventos: Alertas, observabilidad, integración | D42: No | F42: Alta
B43: 2.7 | C43: Mesa de Servicio (Service Desk): Canal único, autoservicio, chatbot | D43: No | F43: Alta
B45: D3 — Socios y Proveedores
B46: 3.1 | C46: Gestión de Proveedores: SLAs (Acuerdo de nivel de servicio) tercerizados, contratos, evaluación | D46: Parcial | E46: Parcial: existe tercero ARUS/tickets y RFP con 4–5 compañías; falta evaluación formal de proveedores y SLAs tercerizados. | F46: Alta
B47: 3.2 | C47: Gestión de Niveles de Servicio: SLA, OLA (Acuerdo de nivel de operación), XLA (Acuerdo de nivel de experiencia) definidos y medidos | D47: No | F47: Alta
B48: 3.3 | C48: Gestión de Capacidad y Disponibilidad: Picos, contingencia | D48: No | F48: Media
B50: D4 — Flujos de Valor y Mejora
B51: 4.1 | C51: Mejora Continua: Ciclos PDCA (Planificar, Hacer, Comprobar y Actuar), retros, backlogs de mejora | D51: Parcial | E51: Parcial: el nuevo RFP implica cambio de modelo y mejoras, pero no se evidencia ciclo formal de mejora continua. | F51: Alta
B52: 4.2 | C52: Medición y Reporte: Dashboards, informes ejecutivos, tendencias | D52: No | F52: Alta
B54: SCORE GENERAL DE PRÁCTICAS ITIL: | D54: 5 | E54: 0.29411765
B56: ④ VOLUMETRÍA Y KPIs OPERATIVOS
B57: MÉTRICA | C57: Valor Actual | D57: Meta / SLA | E57: Tendencia | F57: Comentario
B58: Cantidad de Tickets / mes (total) | D58: N/A | E58: N/D
B59: Cantidad de Incidentes / mes | D59: N/A | E59: N/D
B60: Cantidad de Requerimientos / mes | D60: N/A | E60: N/D
B61: Cantidad de Cambios / mes | D61: N/A | E61: N/D
B62: First Call Resolution (FCR %) | D62: N/A | E62: N/D
B63: Mean Time to Resolve (MTTR horas) | D63: N/A | E63: N/D
B64: SLA Cumplimiento (%) | D64: N/A | E64: N/D
B65: Backlog promedio (tickets abiertos) | D65: N/A | E65: N/D
B66: Tickets resueltos por agente/mes | D66: N/A | E66: N/D
B67: Costo estimado por ticket (USD) | D67: N/A | E67: N/D
B68: Agentes FTE totales | C68: 4 | D68: 8 | E68: 8 | F68: Se indica que 4 personas atienden soporte en redes, networking, facilities y seguridad electrónica.
B69: % Tickets autoservicio / N0 | D69: N/A | E69: N/D
B71: ④b DISTRIBUCIÓN DE INCIDENTES POR CATEGORÍA
B72: Si el service desk del cliente les permite cateogorizarse asi
B73: CATEGORÍA | C73: Tickets/mes | D73: % del Total | E73: Tiempo Prom. Resolución (h) | F73: Observaciones
B74: Accesos / Permisos
B75: Red / Conectividad | F75: Aplica: puntos de red, fallas de equipos de comunicación/red y enlaces de fibra.
B76: Aplicaciones de negocio
B77: Hardware / Equipos | F77: Aplica: fallas de equipos mencionadas.
B78: Correo / Office 365
B79: ERP / SAP
B80: Seguridad / Ciberseguridad | F80: Aplica parcialmente: seguridad electrónica dentro del alcance del equipo.
B81: Otra categoría | F81: Facilities, cableado estructurado y mantenimiento preventivo.
B83: ⑤ EXPERIENCIA DEL USUARIO — XLA / DEX
B84: INDICADOR XLA | C84: Valor Actual | D84: Meta | E84: Método de Medición | F84: Observaciones
B85: NPS (Net Promoter Score) de la mesa | D85: N/A | E85: N/D
B86: CSAT (Satisfacción del cliente) — escala 1-5 | D86: N/A | E86: N/D
B87: CES (Customer Effort Score) | D87: N/A | E87: N/D
B88: Encuestas post-ticket (tasa de respuesta %) | D88: N/A | E88: N/D
B89: Percepción de calidad (top 3 palabras del usuario) | D89: N/A | E89: N/D
B90: Cantidad de Quejas escaladas / mes | D90: N/A | E90: N/D
B91: Tiempo promedio de espera en canal (minutos) | D91: N/A | E91: N/D
B93: ⑥ DOLORES CRÍTICOS DE LA MESA (D1–D21)
B94: DOLOR | C94: ¿Existe? | D94: Descripción / Evidencia | E94: Impacto (1-5) | F94: Criticidad | G94: Iniciativa sugerida
B95: D1 | C95: No | D95: Rotación excesiva de personal: pérdida de conocimiento | E95: 2 | F95: Baja | G95: Levantar rotación y mapa de conocimiento crítico.
B96: D2 | C96: No | D96: SLAs incumplidos / penalizaciones contractuales | E96: 2 | F96: Baja | G96: Confirmar cláusulas SLA en contrato/RFP.
B97: D3 | C97: No | D97: Ausencia de autoservicio: todo llega por call/correo | E97: 3 | F97: Media | G97: Evaluar autoservicio si el volumen lo justifica.
B98: D4 | C98: Parcial | D98: Herramientas fragmentadas / sin integración | E98: 3 | F98: Media | G98: Mapear flujo ServiceNow–ARUS–equipo AES.
B99: D5 | C99: No | D99: Baja satisfacción del usuario (NPS < 30) | E99: 2 | F99: Baja | G99: Implementar encuesta post-ticket.
B100: D6 | C100: Parcial | D100: Escalamientos excesivos a N2/N3 | E100: 3 | F100: Media | G100: Definir matriz de escalamiento y cierre.
B101: D7 | C101: No | D101: Falta de visibilidad en tiempo real (sin dashboard) | E101: 3 | F101: Media | G101: Diseñar tablero operativo mínimo.
B102: D8 | C102: No | D102: Reportes manuales: no hay visibilidad ejecutiva en tiempo real | E102: 3 | F102: Media | G102: Validar cadencia de informes en RFP.
B103: D9 | C103: Parcial | D103: Expansión del alcance no controlado: solicitudes fuera del alcance de la mesa de servicio (no delimitado) | E103: 4 | F103: Alta | G103: Definir alcance, exclusiones y catálogo operativo.
B104: D10 | C104: Parcial | D104: Escalamiento inefiiente y cuellos de botella: El modelo de N1/N2/N3 genera rebotes de tickets aumentado el MTTR (tiempo medio de resolución | E104: 3 | F104: Media | G104: Documentar flujo end-to-end y responsables.
B105: D11 | C105: Sí | D105: Postura 100% reactiva | E105: 4 | F105: Alta | G105: Transitar a operación gestionada con métricas y mejora continua.
B106: D12 | C106: Parcial | D106: Falta de gobierno claro | E106: 4 | F106: Alta | G106: Definir comité, RACI, SLAs/OLAs y reportes.
... B112: D18 | C112: No | D112: Reskilling - Upskilling constante del staff | E112: 2 | F112: Baja | G112: Validar brechas técnicas IT/OT del equipo.
B113: D20 | C113: Sí | D113: Asignación de personal a las mesas y Niveles basada en criterio experto, sin modelo de demanda. No hay como dimensionarlo | G113: Se hace a juicio de expero de la emrpesa
B114: D21
B116: ⑦ ROTACIÓN Y TALENTO
...

Sheet SURA Cotizadores
B1: LEVANTAMIENTO DE MESA DE SERVICIOS — SURA COTIZADORES
B2: ⚠ DATOS DE EJEMPLO — Diligenciar con información real de la mesa | I2: ESCALA DE MADUREZ — N0 a N5
B3: ① IDENTIFICACIÓN GENERAL DE LA MESA | I3: NIVEL | J3: NOMBRE | K3: DESCRIPCIÓN
B4: Cliente: | C4: SURA | I4: N0 | J4: Reactivo / Sin estructura | K4: No existe proceso formal. Todo es manual y reactivo. Sin CMDB ni catálogo.
B5: Negocio del cliente: | C5: Todo tipo de seguros (SOAT ,Vida, Autos, Polizas, ...) | I5: N1 | J5: Inicial / Ad hoc/ Operación reactiva | K5: Procesos básicos documentados. Herramientas mínimas. Cumplimiento inconsistente.
B6: Nombre de la Mesa: | C6: Cotizadores; Plataforma Suscripción | I6: N2 | J6: Definido / Organización funcional | K6: Procesos ITIL definidos y seguidos. Métricas básicas (SLA (Service Level Agreement), FCR (Fondo de Capital Riesgo)). Equipo estable.
B7: Líder / Coordinador: | C7: Elsy Yulieth Marin Serna | I7: N3 | J7: Gestionado / Gestión por servicios | K7: Métricas avanzadas. Automatización parcial. Gestión proactiva de problemas.
B8: Fecha del Levantamiento: | C8: 46211 | I8: N4 | J8: Optimizado / Gestión integrada | K8: Autoservicio maduro. IA/ML básico. XLA (Experience Level Agreement) medidos. Mejora continua activa.
B9: Ubicación / Modalidad: | C9: Virtual
B10: N° de Agentes (FTE) (cantidad de personas): | C10: 8 | I10: Función | J10: Misión Principal | K10: Alcance
B11: Modelo de Contrato: | C11: FTE dedicado | I11: Call Center | J11: Manejar grandes volúmenes de llamadas; filtrar y derivar | K11: Punto de contacto y distribución estructurada
B12: Nivel Madurez Actual: | C12: N2 | D12: (N0 Reactivo → N5 Innovador) | I12: Help Desk | J12: Coordinación para la restauración del servicio; "arreglar cosas" | K12: Infraestructura, herramientas de seguimiento, base de conocimiento
B13: Modelo de Operación | C13: Service Desk ->Servicio integral: incidentes, solicitudes, consultas, altas/bajas/cambios | I13: Service Desk | J13: Servicio integral: incidentes, solicitudes, consultas, altas/bajas/cambios | K13: Alcance configurable; representa al usuario dentro de TI
B14: (Tercero) Empresa de soporte al cliente de N1: | D14: (N0 Reactivo → N5 Innovador)
B15: En que otro Niveles tenemos presencia: | C15: N3 | D15: Raizales
B16: En que paises tenemos presencia: | C16: Colombia
B17: Que hacemos en el cliente: | C17: (Capacidad operativa) Operación de plataforma de suscripción/cotizadores para venta de seguros; atención principalmente de incidentes con bajo volumen de requerimientos. Soporte funcional/técnico de plataforma de suscripción y cotizadores; atención de incidentes y requerimientos por BMC.
B18: Tiempo de la Mesa de Servicio | C18: 3 años
B19: Finalización: | C19: Agosto con posible renovación hasta diciembre de 2026
B20: Renovación: | C20: Propuesta con mirada de optimización; Compañía de Conexión / negociación comercial para el 2027. Se debe competir con otros proveedores
B21: Equipos de infraestructura: | C21: N/A
B22: Video: | C22: Hablemos Mesas Sura-20260708_090044-Grabación de la reunión.mp4
B23: Transcript: | C23: Natalia Zartha Suarez 0 30:03 Natalia Zartha Suarez 0 minutos 3 segundos Esto es un gusto conocerte. E Elsy Yulieth Marin Serna 0 50:05 Elsy Yulieth Marin Serna 0 minutos 5 segundos Súper bien, gracias a Dios también un placer. Ya había escuchado tu nombre, pero no había visto tu rostro. Natalia Zartha Suarez 0 70:07 Natalia Zartha Suarez 0 minutos 7 segundos bueno. Natalia Zartha Suarez 0 minutos 11 segundos Ah, bueno, súper. Muchísimas gracias por este espacio. Si quieres arrancamos para aprovechar el tiempito. Joan y Joan están invitados, pero pues igual la idea es como que que conversemos. Yo en este momento, pues entré hace como dos semanitas en la compañía, estoy trabajando en el equipo de de Joan. E Elsy Yulieth Marin Serna 0 180:18 Elsy Yulieth Marin Serna 0 minutos 18 segundos De una. Elsy Yulieth Marin Serna 0 minutos 28 segundos And. Natalia Zartha Suarez 0 300:30 Natalia Zartha Suarez 0 minutos 30 segundos Y estoy comenzando con el diseño de las mesas de de servicio como un servicio estandarizado. Entonces estamos haciendo la la tarea de reunirnos con cada mesa. Joan me pues me me estaba colaborando con con la citación de estos para recoger como toda la información, todo el feedback, las lecciones aprendidas que ustedes tengan. O sea, cómo podemos mejorar esas mesas para que este servicio estandarizado. Pues. E Elsy Yulieth Marin Serna 0 360:36 Elsy Yulieth Marin Serna 0 minutos 36 segundos Okay. Elsy Yulieth Marin Serna 0 minutos 52 segundos Y. Natalia Zartha Suarez 0 minutos 55 segundos0:55 Natalia Zartha Suarez 0 minutos 55 segundos sea mejor cierto entonces creo que él dejó unas pregunticas por aquí en el chat igual si si tú las tienes bien sino también porque pues podemos hacerlas como como mirando listo Ah súper Natalia Zartha Suarez 58 minutos 22 segundos58:22 Natalia Zartha Suarez 58 minutos 22 segundos Sí. E Elsy Yulieth Marin Serna 58 minutos 25 segundos58:25 Elsy Yulieth Marin Serna 58 minutos 25 segundos que se tienen, se hacen este canal que se llama canales masivos. Acá hay muchas tareas automáticas porque como la volumetría es tan alta, pues hay muchos procesos automáticos que corren durante la semana, los fines de semana para renovar, para cancelar, pues todo eso es como muy automático por la volumetría propiamente según el cliente que tenemos. Elsy Yulieth Marin Serna 58 minutos 44 segundos Los clientes que manejamos y es un canal muy sensible, o sea, en serio Bancolombia dice, ay, esta póliza salió con un error y mejor dicho, hay que pagar todo lo que sea porque hay que revisar esa póliza de Bancolombia. Entonces es un canal muy demandante, más que en volumen de incidentes, en revisiones. Elsy Yulieth Marin Serna 59 minutos 4 segundos Ay, es que están diciendo que está saliendo este error, entonces el pelado se tiene que parar lo que sea para ir a hacer y acá supuestamente, según el cliente, una sola persona. Elsy Yulieth Marin Serna 59 minutos 14 segundos apalancado en el número de incidentes solamente nosotros ya en este tiempo que llevamos operando hemos visto no es que él no solo atiende incidentes en serio lo llaman demasiado para revisar un tema al otro le mandan correos que manda este informe que necesitamos cruzar esto que porque esto está pasando o sea es demandante en actividades adicionales un montón Elsy Yulieth Marin Serna 59 minutos 35 segundos que no quedan mapeadas siempre como en incidente Sí hemos tratado con él de venga acá que a usted le pidan algo que le Monten un incidente para que usted tenga un respaldo de qué es lo que está trabajando pero eh Este es el Pues los los clientes de este canal son los consentidos de su de hecho allá todo el mundo le dicen si usted va para canales masivos Natalia Zartha Suarez 59 minutos 38 segundos59:38 Natalia Zartha Suarez 59 minutos 38 segundos Mhm. E Elsy Yulieth Marin Serna 59 minutos 56 segundos59:56 Elsy Yulieth Marin Serna 59 minutos 56 segundos Mejor dicho, usted le dicen hola y ya usted allá sentado mirando que necesitan. Natalia Zartha Suarez 1 hora 2 segundos1:00:02 Natalia Zartha Suarez 1 hora 2 segundos O K, esa, el horario también es 7 normalito en los 17:30. E Elsy Yulieth Marin Serna 1 hora 3 segundos1:00:03 Elsy Yulieth Marin Serna 1 hora 3 segundos No. Elsy Yulieth Marin Serna 1 hora 7 segundos 7:30, 7:30, 5 y este digamos que por los cierres de mes tiene también una disponibilidad en el final de el último día del mes y el primer día del mes siguiente, independiente si son hábiles o no. Si el último día del mes del 31 cae un domingo, tenemos que tener disponibilidad. Si el primero es postivo, tenemos que tener disponibilidad. Natalia Zartha Suarez 1 hora 10 segundos1:00:10 Natalia Zartha Suarez 1 hora 10 segundos Okay. Natalia Zartha Suarez 1 hora 27 segundos Mhm. E Elsy Yulieth Marin Serna 1 hora 29 segundos1:00:29 Elsy Yulieth Marin Serna 1 hora 29 segundos Para todos los temas de cierre, pues garantizar que todo lo de cierre quede pues como el día. Natalia Zartha Suarez 1 hora 31 segundos1:00:31 Natalia Zartha Suarez 1 hora 31 segundos Ya. Natalia Zartha Suarez 1 hora 35 segundos Listo. E Elsy Yulieth Marin Serna 1 hora 35 segundos1:00:35 Elsy Yulieth Marin Serna 1 hora 35 segundos Eso es como el resumen rápido. Natalia Zartha Suarez 1 hora 38 segundos1:00:38 Natalia Zartha Suarez 1 hora 38 segundos No, muchísimas. Bueno, bueno, pero todo es un toda esa manera con la herramienta de BMX. ¿Cómo fue que dijiste la ticket? E Elsy Yulieth Marin Serna 1 hora 44 segundos1:00:44 Elsy Yulieth Marin Serna 1 hora 44 segundos Sí, BMC se llama. Natalia Zartha Suarez 1 hora 48 segundos1:00:48 Natalia Zartha Suarez 1 hora 48 segundos No creté, no, dale. Joan Sebastian Rengifo Ocampo 1 hora 48 segundos1:00:48 Joan Sebastian Rengifo Ocampo 1 hora 48 segundos Yo me debo de pasar a un espacio, pero te iba a comentar algo. el. E Elsy Yulieth Marin Serna 1 hora 53 segundos1:00:53 Elsy Yulieth Marin Serna 1 hora 53 segundos Mhm. Joan Sebastian Rengifo Ocampo 1 hora 56 segundos1:00:56 Joan Sebastian Rengifo Ocampo 1 hora 56 segundos De los agile que estábamos en Bancolombia, hay tres compañeras que están indisponibles o igual los agile que quedamos, por ejemplo, una luz es mi persona. Hemos acompañado a equipos de soporte, incluso una de las que está disponible acompañada del centro de excelencia donde está la Jioti, donde están muchos de los equipos de soporte. Joan Sebastian Rengifo Ocampo 1 hora 1 minuto 16 segundos Yo acompañaba, por ejemplo, a los equipos que soportaban todo el canal la sucursal virtual negocios. Entonces, si puedes hablar, por ejemplo, con Jenny que ella tiene mis tres compañeras disponibles, porque esto que va a construir Natalia es más como pensando en temas, clientes nuevos, mesas nuevas, pero por el momento el enfoque no va a ser tanto de venga como le solucionamos a ustedes la vida. Natalia Zartha Suarez 1 hora 1 minuto 34 segundos1:01:34 Natalia Zartha Suarez 1 hora 1 minuto 34 segundos Mhm, sí. Joan Sebastian Rengifo Ocampo 1 hora 1 minuto 40 segundos1:01:40 Joan Sebastian Rengifo Ocampo 1 hora 1 minuto 40 segundos inicialmente, pero esa asesoría que no les funcionó con esta chica que nos decías, podrían tener un espacio con las compañeras o con cualquiera de nosotros, porque a mí ahorita yo decía aquí le sirve un Kanban, allá automatizamos esto con un power app si nos sacaba tal información. E Elsy Yulieth Marin Serna 1 hora 1 minuto 40 segundos1:01:40 Elsy Yulieth Marin Serna 1 hora 1 minuto 40 segundos Mhm. Natalia Zartha Suarez 1 hora 1 minuto 43 segundos1:01:43 Natalia Zartha Suarez 1 hora 1 minuto 43 segundos sí. Joan Sebastian Rengifo Ocampo 1 hora 1 minuto 59 segundos1:01:59 Joan Sebastian Rengifo Ocampo 1 hora 1 minuto 59 segundos O sea, les pueden dar ciertas ideas de los equipos que acompañaban, qué hacían, cómo lo hacían y te puede dar ideas como para llevarlo a este proceso. Mientras pues te dejo ahí como esa inquietud para que de pronto hables con Jenny, porque ahí están disponibles y te pueden apoyar pues en esos temas. E Elsy Yulieth Marin Serna 1 hora 2 minutos 2 segundos1:02:02 Elsy Yulieth Marin Serna 1 hora 2 minutos 2 segundos Mhm, super. Natalia Zartha Suarez 1 hora 2 minutos 11 segundos1:02:11 Natalia Zartha Suarez 1 hora 2 minutos 11 segundos Mhm. E Elsy Yulieth Marin Serna 1 hora 2 minutos 11 segundos1:02:11 Elsy Yulieth Marin Serna 1 hora 2 minutos 11 segundos De una. Elsy Yulieth Marin Serna 1 hora 2 minutos 13 segundos Súper de una, yo 1000 gracias. Natalia Zartha Suarez 1 hora 2 minutos 19 segundos1:02:19 Natalia Zartha Suarez 1 hora 2 minutos 19 segundos Súper, muchas gracias. Listo Elsy, muchísimas gracias. Un gusto conocerte. De pronto te esté preguntando cositas puntuales mientras organizo como toda la información, pero muchísimas gracias por el espacio. Excelente. Nada, bye. Sí. E Elsy Yulieth Marin Serna 1 hora 2 minutos 19 segundos1:02:19 Elsy Yulieth Marin Serna 1 hora 2 minutos 19 segundos De una. Elsy Yulieth Marin Serna 1 hora 2 minutos 24 segundos Con gusto. Elsy Yulieth Marin Serna 1 hora 2 minutos 33 segundos Con gusto a ustedes, muchísimas gracias. Les voy a dejar esto aquí en el chat de esta reunioncita listo. Joan Sebastian Rengifo Ocampo 1 hora 2 minutos 35 segundos1:02:35 Joan Sebastian Rengifo Ocampo 1 hora 2 minutos 35 segundos Vale, gracias. Joan Sebastian Rengifo Ocampo 1 hora 2 minutos 38 segundos Listo, súper, gracias. Natalia Zartha Suarez 1 hora 2 minutos 38 segundos1:02:38 Natalia Zartha Suarez 1 hora 2 minutos 38 segundos Súper, dale, muchas gracias. Chaito, un gusto, chaito, gracias.
B24: # Applicaciones | C24: 24
B25: Comercial: | C25: Adriana Montez
B27: ③ EVALUACIÓN DE PRÁCTICAS ITIL v4 — 4 DIMENSIONES
B28: # | C28: PRÁCTICA | D28: ¿Se cumple? | E28: Observaciones / Evidencia | F28: Prioridad Mejora
B29: D1 — Organización y Personas
B30: 1.1 | C30: Gestión de la Fuerza Laboral: Headcount, perfiles, competencias | D30: Parcial | E30: Headcount identificado por operación y líder definida (Elsy). | F30: Media
B31: 1.2 | C31: Gestión del Conocimiento: KB (Knowledge Base), documentación, onboarding | D31: Parcial | E31: Existe operación en BMC, pero se requiere reforzar documentación, KB y transferencia de conocimiento por niveles. | F31: Alta
B32: 1.3 | C32: Gestión del Talento: Rotación, desarrollo, retención | D32: No | E32: Se requiere validar retención/rotación por operación; hay dependencia de conocimiento del equipo. | F32: Media
B33: 1.4 | C33: Gestión del Desempeño: Metas individuales, feedback, KPIs de agente | D33: Parcial | E33: Hay métricas operativas por mesa (tickets, SLA, MTTR, backlog), pero no se evidencian KPIs individuales por agente. | F33: Media
B34: 1.5 | C34: Cultura de Servicio: Orientación al usuario, empatía, NPS (Net Promoter Score) interno | D34: No | E34: Servicio sensible al usuario/negocio; falta medición formal de experiencia (NPS/CSAT). | F34: Media
B36: D2 — Información y Tecnología
B37: 2.1 | C37: Gestión de Incidentes: Proceso, tiempos, escalamiento | D37: Sí | E37: Gestión de incidentes en BMC con volumetría mensual disponible. | F37: Media
B38: 2.2 | C38: Gestión de Requerimientos: Catálogo de servicios, flujos | D38: Sí | E38: Gestión de requerimientos en BMC con volumetría mensual disponible. | F38: Media
B39: 2.3 | C39: Gestión de Problemas: RCA (Análisis de Causa Raíz ), errores conocidos, KEDB (Known Error Database) | D39: Sí | E39: Hay atención de causa raíz / nivel 3, pero se requiere formalizar RCA/KEDB y criterios de escalamiento. | F39: Alta
B40: 2.4 | C40: Gestión de Cambios: CAB (Change Advisory Board), RFC (Solicitud de Cambio), ventanas de mantenimiento | D40: Parcial | E40: Se observan procesos operativos y cierres, pero no se confirma gestión formal de cambios/CAB/RFC. | F40: Media
B41: 2.5 | C41: Gestión de la Configuración: CMDB (Configuration Management Database), assets, CIs (Elementos de Configuración) | D41: No | F41: Media
B42: 2.6 | C42: Monitoreo y Eventos: Alertas, observabilidad, integración | D42: No | F42: Media
B43: 2.7 | C43: Mesa de Servicio (Service Desk): Canal único, autoservicio, chatbot | D43: Parcial | E43: BMC centraliza ticketing, pero no se evidencia autoservicio/chatbot ni canal único maduro. | F43: Alta
B45: D3 — Socios y Proveedores
B46: 3.1 | C46: Gestión de Proveedores: SLAs (Acuerdo de nivel de servicio) tercerizados, contratos, evaluación | D46: Sí | E46: Proveedor/cliente gestionado mediante operación SURA y herramienta BMC. | F46: Media
B47: 3.2 | C47: Gestión de Niveles de Servicio: SLA, OLA (Acuerdo de nivel de operación), XLA (Acuerdo de nivel de experiencia) definidos y medidos | D47: Sí | E47: Hay meta SLA y medición de cumplimiento; no se evidencian OLA/XLA. | F47: Alta
B48: 3.3 | C48: Gestión de Capacidad y Disponibilidad: Picos, contingencia | D48: Parcial | E48: Hay métricas de volumen, backlog y FTE; se requiere capacidad formal por picos/cierres. | F48: Alta
B50: D4 — Flujos de Valor y Mejora
B51: 4.1 | C51: Mejora Continua: Ciclos PDCA (Planificar, Hacer, Comprobar y Actuar), retros, backlogs de mejora | D51: Parcial | E51: Se identifican oportunidades de mejora con Kanban/Power App y optimización del seguimiento. | F51: Alta
B52: 4.2 | C52: Medición y Reporte: Dashboards, informes ejecutivos, tendencias | D52: Parcial | E52: Existen métricas base; falta visibilidad ejecutiva/tablero consolidado y trazabilidad de tareas no registradas. | F52: Alta
B54: SCORE GENERAL DE PRÁCTICAS ITIL: | D54: =IF(D30="Sí",1,IF(D30="Parcial",0.5,0))+IF(D31="Sí",1,IF(D31="Parcial",0.5,0))+IF(D32="Sí",1,IF(D32="Parcial",0.5,0))+IF(D33="Sí",1,IF(D33="Parcial",0.5,0))+IF(D34="Sí",1,IF(D34="Parcial",0.5,0))+IF(D37="Sí",1,IF(D37="Parcial",0.5,0))+IF(D38="Sí",1,IF(D38="Parcial",0.5,0))+IF(D39="Sí",1,IF(D39="Parcial",0.5,0))+IF(D40="Sí",1,IF(D40="Parcial",0.5,0))+IF(D41="Sí",1,IF(D41="Parcial",0.5,0))+IF(D42="Sí",1,IF(D42="Parcial",0.5,0))+IF(D43="Sí",1,IF(D43="Parcial",0.5,0))+IF(D46="Sí",1,IF(D46="Parcial",0.5,0))+IF(D47="Sí",1,IF(D47="Parcial",0.5,0))+IF(D48="Sí",1,IF(D48="Parcial",0.5,0))+IF(D51="Sí",1,IF(D51="Parcial",0.5,0))+IF(D52="Sí",1,IF(D52="Parcial",0.5,0)) -> 9 | E54: =D54/17 -> 0.52941176
B56: ④ VOLUMETRÍA Y KPIs OPERATIVOS
B57: MÉTRICA | C57: Valor Actual | D57: Meta / SLA | E57: Tendencia | F57: Comentario
B58: Cantidad de Tickets / mes (total) | C58: 668 | E58: Volumen baja ene-jun; SLA promedio por debajo de meta.
B59: Cantidad de Incidentes / mes | C59: 667 | E59: Volumen baja ene-jun; SLA promedio por debajo de meta.
B60: Cantidad de Requerimientos / mes | C60: 1 | E60: Volumen baja ene-jun; SLA promedio por debajo de meta.
B61: Cantidad de Cambios / mes | C61: N/A | D61: N/A | E61: Volumen baja ene-jun; SLA promedio por debajo de meta.
B62: First Call Resolution (FCR %) | C62: N/D | D62: N/D | E62: Volumen baja ene-jun; SLA promedio por debajo de meta.
B63: Mean Time to Resolve (MTTR horas) | C63: 24.58 | D63: 92% por categoría de criticidad: alto/crítico 9h, medio 12h, bajo 18h | E63: Volumen baja ene-jun; SLA promedio por debajo de meta.
B64: SLA Cumplimiento (%) | C64: 0.7 | D64: 0.92 | E64: Volumen baja ene-jun; SLA promedio por debajo de meta.
B65: Backlog promedio (tickets abiertos) | C65: 65 | E65: Volumen baja ene-jun; SLA promedio por debajo de meta.
B66: Tickets resueltos por agente/mes | C66: 150 | E66: Volumen baja ene-jun; SLA promedio por debajo de meta.
B67: Costo estimado por ticket (USD) | C67: N/D | D67: N/D | E67: Volumen baja ene-jun; SLA promedio por debajo de meta.
B68: Agentes FTE totales | C68: 8 | E68: Volumen baja ene-jun; SLA promedio por debajo de meta.
B69: % Tickets autoservicio / N0 | C69: 0 | D69: 0 | E69: Volumen baja ene-jun; SLA promedio por debajo de meta.
B71: ④b DISTRIBUCIÓN DE INCIDENTES POR CATEGORÍA
B72: Si el service desk del cliente les permite cateogorizarse asi
B73: CATEGORÍA | C73: Tickets/mes | D73: % del Total | E73: Tiempo Prom. Resolución (h) | F73: Observaciones
B74: Accesos / Permisos
B75: Red / Conectividad
B76: Aplicaciones de negocio | C76: 668 | D76: 1 | E76: 24.58 | F76: Plataforma de suscripción/cotizadores; 668 tickets/mes promedio.
B77: Hardware / Equipos
B78: Correo / Office 365
B79: ERP / SAP
B80: Seguridad / Ciberseguridad
B81: Otra categoría
B83: ⑤ EXPERIENCIA DEL USUARIO — XLA / DEX
B84: INDICADOR XLA | C84: Valor Actual | D84: Meta | E84: Método de Medición | F84: Observaciones
B85: NPS (Net Promoter Score) de la mesa
B86: CSAT (Satisfacción del cliente) — escala 1-5
B87: CES (Customer Effort Score)
B88: Encuestas post-ticket (tasa de respuesta %)
B89: Percepción de calidad (top 3 palabras del usuario)
B90: Cantidad de Quejas escaladas / mes
B91: Tiempo promedio de espera en canal (minutos)
B93: ⑥ DOLORES CRÍTICOS DE LA MESA (D1–D21)
B94: DOLOR | C94: ¿Existe? | D94: Descripción / Evidencia | E94: Impacto (1-5) | F94: Criticidad | G94: Iniciativa sugerida
B95: D1 | C95: Parcial | D95: Rotación excesiva de personal: pérdida de conocimiento | E95: 3 | F95: Media | G95: Documentar conocimiento crítico y plan de respaldo por operación.
B96: D2 | C96: Sí | D96: SLAs incumplidos / penalizaciones contractuales | E96: 4 | F96: Alta | G96: Plan de mejora SLA por criticidad y seguimiento semanal.
B97: D3 | C97: Sí | D97: Ausencia de autoservicio: todo llega por call/correo | E97: 4 | F97: Alta | G97: Diseñar autoservicio/N0 para consultas repetitivas y solicitudes estándar.
B98: D4 | C98: Parcial | D98: Herramientas fragmentadas / sin integración | E98: 3 | F98: Media | G98: Integrar BMC con tablero/Kanban y trazabilidad operativa.
B99: D5 | C99: No | D99: Baja satisfacción del usuario (NPS < 30) | E99: 2 | F99: Baja | G99: Levantar NPS/CSAT para confirmar percepción del usuario.
B100: D6 | C100: Parcial | D100: Escalamientos excesivos a N2/N3 | E100: 3 | F100: Media | G100: Definir matriz clara N1/N2/N3 y criterios de raízal/desarrollo.
B101: D7 | C101: Parcial | D101: Alta carga de tareas repetitivas | E101: 3 | F101: Media | G101: Crear tablero de seguimiento operativo y visibilidad de backlog/SLA.
B102: D8 | C102: Parcial | D102: Reportes manuales: no hay visibilidad ejecutiva en tiempo real | E102: 3 | F102: Media | G102: Automatizar reportes con BMC/Power App/BI.
B103: D9 | C103: Sí | D103: Expansión del alcance no controlado: solicitudes fuera del alcance de la mesa de servicio (no delimitado) | E103: 3 | F103: Media | G103: Registrar solicitudes adicionales y delimitar alcance por canal/mesa.
B104: D10 | C104: Parcial | D104: Escalamiento ineficiente y cuellos de botella: El modelo de N1/N2/N3 genera rebotes de tickets aumentado el MTTR (tiempo medio de resolución | E104: 3 | F104: Media | G104: Estandarizar escalamiento y tiempos por nivel.
B105: D11 | C105: Parcial | D105: Postura 100% reactiva | E105: 3 | F105: Media | G105: Pasar de atención reactiva a gestión por métricas y mejora continua.
B106: D12 | C106: Parcial | D106: Falta de gobierno claro | E106: 3 | F106: Media | G106: Definir gobierno operativo, RACI, comités y responsables.
... B112: D18 | C112: Parcial | D112: Reskilling - Upskilling constante del staff | E112: 3 | F112: Media | G112: Plan de reskilling en BMC, operación por niveles, Power Apps/Kanban y automatización.
B113: D19 | C113: Sí | D113: Los roles se asignan por perfil individual, no por modelo estandarizado
B114: D20 | C114: Sí | D114: Asignación de personal a las mesas y Niveles basada en criterio experto, sin modelo de demanda. No hay como dimensionarlo | G114: Se hace a juicio de expero de la emrpesa
...

Sheet SURA Digital Venta
B2: LEVANTAMIENTO DE MESA DE SERVICIOS — SURA VENTA DIGITAL
B3: ⚠ DATOS DE EJEMPLO — Diligenciar con información real de la mesa | I3: ESCALA DE MADUREZ — N0 a N5
B4: ① IDENTIFICACIÓN GENERAL DE LA MESA | I4: NIVEL | J4: NOMBRE | K4: DESCRIPCIÓN
B5: Cliente: | C5: SURA | I5: N0 | J5: Reactivo / Sin estructura | K5: No existe proceso formal. Todo es manual y reactivo. Sin CMDB ni catálogo.
B6: Negocio del cliente: | C6: Soporte a canal digital de venta y análisis de causa raíz. | I6: N1 | J6: Inicial / Ad hoc/ Operación reactiva | K6: Procesos básicos documentados. Herramientas mínimas. Cumplimiento inconsistente.
B7: Nombre de la Mesa: | C7: Digital Venta | I7: N2 | J7: Definido / Organización funcional | K7: Procesos ITIL definidos y seguidos. Métricas básicas (SLA (Service Level Agreement), FCR (Fondo de Capital Riesgo)). Equipo estable.
B8: Líder / Coordinador: | C8: Elsy Yulieth Marin Serna | I8: N3 | J8: Gestionado / Gestión por servicios | K8: Métricas avanzadas. Automatización parcial. Gestión proactiva de problemas.
B9: Fecha del Levantamiento: | C9: 46211 | I9: N4 | J9: Optimizado / Gestión integrada | K9: Autoservicio maduro. IA/ML básico. XLA (Experience Level Agreement) medidos. Mejora continua activa.
B10: Ubicación / Modalidad: | C10: Virtual
B11: N° de Agentes (FTE) (cantidad de personas): | C11: 2 | I11: Función | J11: Misión Principal | K11: Alcance
B12: Modelo de Contrato: | C12: Staffing | I12: Call Center | J12: Manejar grandes volúmenes de llamadas; filtrar y derivar | K12: Punto de contacto y distribución estructurada
B13: Nivel Madurez Actual: | C13: N2 | D13: (N0 Reactivo → N5 Innovador) | I13: Help Desk | J13: Coordinación para la restauración del servicio; "arreglar cosas" | K13: Infraestructura, herramientas de seguimiento, base de conocimiento
B14: Modelo de Operación | C14: Service Desk + Problem Management | I14: Service Desk | J14: Servicio integral: incidentes, solicitudes, consultas, altas/bajas/cambios | K14: Alcance configurable; representa al usuario dentro de TI
B15: (Tercero) Empresa de soporte al cliente | D15: (N0 Reactivo → N5 Innovador)
B16: En que otro Niveles tenemos presencia: | C16: No Aplica
B17: En que paises tenemos presencia: | C17: Colombia y Panamá
B18: Que hacemos en el cliente: | C18: Atención de incidentes del canal digital de venta; operación con bajo FTE y métricas de SLA/MTTR en BMC.
B19: Tiempo de la Mesa de Servicio | C19: 7 meses
B20: Finalización: | C20: Agosto con posible renovación hasta diciembre
B21: Renovación: | C21: Propuesta con mirada de optimización; Compañía de Conexión / negociación comercial.
B22: Equipos de infraestructura:
B23: Video: | C23: Hablemos Mesas Sura-20260708_090044-Grabación de la reunión.mp4
B24: Transcript: | C24: Natalia Zartha Suarez 0 30:03 Natalia Zartha Suarez 0 minutos 3 segundos Esto es un gusto conocerte. E Elsy Yulieth Marin Serna 0 50:05 Elsy Yulieth Marin Serna 0 minutos 5 segundos Súper bien, gracias a Dios también un placer. Ya había escuchado tu nombre, pero no había visto tu rostro. Natalia Zartha Suarez 0 70:07 Natalia Zartha Suarez 0 minutos 7 segundos bueno. Natalia Zartha Suarez 0 minutos 11 segundos Ah, bueno, súper. Muchísimas gracias por este espacio. Si quieres arrancamos para aprovechar el tiempito. Joan y Joan están invitados, pero pues igual la idea es como que que conversemos. Yo en este momento, pues entré hace como dos semanitas en la compañía, estoy trabajando en el equipo de de Joan. E Elsy Yulieth Marin Serna 0 180:18 Elsy Yulieth Marin Serna 0 minutos 18 segundos De una. Elsy Yulieth Marin Serna 0 minutos 28 segundos And. Natalia Zartha Suarez 0 300:30 Natalia Zartha Suarez 0 minutos 30 segundos Y estoy comenzando con el diseño de las mesas de de servicio como un servicio estandarizado. Entonces estamos haciendo la la tarea de reunirnos con cada mesa. Joan me pues me me estaba colaborando con con la citación de estos para recoger como toda la información, todo el feedback, las lecciones aprendidas que ustedes tengan. O sea, cómo podemos mejorar esas mesas para que este servicio estandarizado. Pues. E Elsy Yulieth Marin Serna 0 360:36 Elsy Yulieth Marin Serna 0 minutos 36 segundos Okay. Elsy Yulieth Marin Serna 0 minutos 52 segundos Y. Natalia Zartha Suarez 0 minutos 55 segundos0:55 Natalia Zartha Suarez 0 minutos 55 segundos sea mejor cierto entonces creo que él dejó unas pregunticas por aquí en el chat igual si si tú las tienes bien sino también porque pues podemos hacerlas como como mirando listo Ah súper Natalia Zartha Suarez 58 minutos 22 segundos58:22 Natalia Zartha Suarez 58 minutos 22 segundos Sí. E Elsy Yulieth Marin Serna 58 minutos 25 segundos58:25 Elsy Yulieth Marin Serna 58 minutos 25 segundos que se tienen, se hacen este canal que se llama canales masivos. Acá hay muchas tareas automáticas porque como la volumetría es tan alta, pues hay muchos procesos automáticos que corren durante la semana, los fines de semana para renovar, para cancelar, pues todo eso es como muy automático por la volumetría propiamente según el cliente que tenemos. Elsy Yulieth Marin Serna 58 minutos 44 segundos Los clientes que manejamos y es un canal muy sensible, o sea, en serio Bancolombia dice, ay, esta póliza salió con un error y mejor dicho, hay que pagar todo lo que sea porque hay que revisar esa póliza de Bancolombia. Entonces es un canal muy demandante, más que en volumen de incidentes, en revisiones. Elsy Yulieth Marin Serna 59 minutos 4 segundos Ay, es que están diciendo que está saliendo este error, entonces el pelado se tiene que parar lo que sea para ir a hacer y acá supuestamente, según el cliente, una sola persona. Elsy Yulieth Marin Serna 59 minutos 14 segundos apalancado en el número de incidentes solamente nosotros ya en este tiempo que llevamos operando hemos visto no es que él no solo atiende incidentes en serio lo llaman demasiado para revisar un tema al otro le mandan correos que manda este informe que necesitamos cruzar esto que porque esto está pasando o sea es demandante en actividades adicionales un montón Elsy Yulieth Marin Serna 59 minutos 35 segundos que no quedan mapeadas siempre como en incidente Sí hemos tratado con él de venga acá que a usted le pidan algo que le Monten un incidente para que usted tenga un respaldo de qué es lo que está trabajando pero eh Este es el Pues los los clientes de este canal son los consentidos de su de hecho allá todo el mundo le dicen si usted va para canales masivos Natalia Zartha Suarez 59 minutos 38 segundos59:38 Natalia Zartha Suarez 59 minutos 38 segundos Mhm. E Elsy Yulieth Marin Serna 59 minutos 56 segundos59:56 Elsy Yulieth Marin Serna 59 minutos 56 segundos Mejor dicho, usted le dicen hola y ya usted allá sentado mirando que necesitan. Natalia Zartha Suarez 1 hora 2 segundos1:00:02 Natalia Zartha Suarez 1 hora 2 segundos O K, esa, el horario también es 7 normalito en los 17:30. E Elsy Yulieth Marin Serna 1 hora 3 segundos1:00:03 Elsy Yulieth Marin Serna 1 hora 3 segundos No. Elsy Yulieth Marin Serna 1 hora 7 segundos 7:30, 7:30, 5 y este digamos que por los cierres de mes tiene también una disponibilidad en el final de el último día del mes y el primer día del mes siguiente, independiente si son hábiles o no. Si el último día del mes del 31 cae un domingo, tenemos que tener disponibilidad. Si el primero es postivo, tenemos que tener disponibilidad. Natalia Zartha Suarez 1 hora 10 segundos1:00:10 Natalia Zartha Suarez 1 hora 10 segundos Okay. Natalia Zartha Suarez 1 hora 27 segundos Mhm. E Elsy Yulieth Marin Serna 1 hora 29 segundos1:00:29 Elsy Yulieth Marin Serna 1 hora 29 segundos Para todos los temas de cierre, pues garantizar que todo lo de cierre quede pues como el día. Natalia Zartha Suarez 1 hora 31 segundos1:00:31 Natalia Zartha Suarez 1 hora 31 segundos Ya. Natalia Zartha Suarez 1 hora 35 segundos Listo. E Elsy Yulieth Marin Serna 1 hora 35 segundos1:00:35 Elsy Yulieth Marin Serna 1 hora 35 segundos Eso es como el resumen rápido. Natalia Zartha Suarez 1 hora 38 segundos1:00:38 Natalia Zartha Suarez 1 hora 38 segundos No, muchísimas. Bueno, bueno, pero todo es un toda esa manera con la herramienta de BMX. ¿Cómo fue que dijiste la ticket? E Elsy Yulieth Marin Serna 1 hora 44 segundos1:00:44 Elsy Yulieth Marin Serna 1 hora 44 segundos Sí, BMC se llama. Natalia Zartha Suarez 1 hora 48 segundos1:00:48 Natalia Zartha Suarez 1 hora 48 segundos No creté, no, dale. Joan Sebastian Rengifo Ocampo 1 hora 48 segundos1:00:48 Joan Sebastian Rengifo Ocampo 1 hora 48 segundos Yo me debo de pasar a un espacio, pero te iba a comentar algo. el. E Elsy Yulieth Marin Serna 1 hora 53 segundos1:00:53 Elsy Yulieth Marin Serna 1 hora 53 segundos Mhm. Joan Sebastian Rengifo Ocampo 1 hora 56 segundos1:00:56 Joan Sebastian Rengifo Ocampo 1 hora 56 segundos De los agile que estábamos en Bancolombia, hay tres compañeras que están indisponibles o igual los agile que quedamos, por ejemplo, una luz es mi persona. Hemos acompañado a equipos de soporte, incluso una de las que está disponible acompañada del centro de excelencia donde está la Jioti, donde están muchos de los equipos de soporte. Joan Sebastian Rengifo Ocampo 1 hora 1 minuto 16 segundos Yo acompañaba, por ejemplo, a los equipos que soportaban todo el canal la sucursal virtual negocios. Entonces, si puedes hablar, por ejemplo, con Jenny que ella tiene mis tres compañeras disponibles, porque esto que va a construir Natalia es más como pensando en temas, clientes nuevos, mesas nuevas, pero por el momento el enfoque no va a ser tanto de venga como le solucionamos a ustedes la vida. Natalia Zartha Suarez 1 hora 1 minuto 34 segundos1:01:34 Natalia Zartha Suarez 1 hora 1 minuto 34 segundos Mhm, sí. Joan Sebastian Rengifo Ocampo 1 hora 1 minuto 40 segundos1:01:40 Joan Sebastian Rengifo Ocampo 1 hora 1 minuto 40 segundos inicialmente, pero esa asesoría que no les funcionó con esta chica que nos decías, podrían tener un espacio con las compañeras o con cualquiera de nosotros, porque a mí ahorita yo decía aquí le sirve un Kanban, allá automatizamos esto con un power app si nos sacaba tal información. E Elsy Yulieth Marin Serna 1 hora 1 minuto 40 segundos1:01:40 Elsy Yulieth Marin Serna 1 hora 1 minuto 40 segundos Mhm. Natalia Zartha Suarez 1 hora 1 minuto 43 segundos1:01:43 Natalia Zartha Suarez 1 hora 1 minuto 43 segundos sí. Joan Sebastian Rengifo Ocampo 1 hora 1 minuto 59 segundos1:01:59 Joan Sebastian Rengifo Ocampo 1 hora 1 minuto 59 segundos O sea, les pueden dar ciertas ideas de los equipos que acompañaban, qué hacían, cómo lo hacían y te puede dar ideas como para llevarlo a este proceso. Mientras pues te dejo ahí como esa inquietud para que de pronto hables con Jenny, porque ahí están disponibles y te pueden apoyar pues en esos temas. E Elsy Yulieth Marin Serna 1 hora 2 minutos 2 segundos1:02:02 Elsy Yulieth Marin Serna 1 hora 2 minutos 2 segundos Mhm, super. Natalia Zartha Suarez 1 hora 2 minutos 11 segundos1:02:11 Natalia Zartha Suarez 1 hora 2 minutos 11 segundos Mhm. E Elsy Yulieth Marin Serna 1 hora 2 minutos 11 segundos1:02:11 Elsy Yulieth Marin Serna 1 hora 2 minutos 11 segundos De una. Elsy Yulieth Marin Serna 1 hora 2 minutos 13 segundos Súper de una, yo 1000 gracias. Natalia Zartha Suarez 1 hora 2 minutos 19 segundos1:02:19 Natalia Zartha Suarez 1 hora 2 minutos 19 segundos Súper, muchas gracias. Listo Elsy, muchísimas gracias. Un gusto conocerte. De pronto te esté preguntando cositas puntuales mientras organizo como toda la información, pero muchísimas gracias por el espacio. Excelente. Nada, bye. Sí. E Elsy Yulieth Marin Serna 1 hora 2 minutos 19 segundos1:02:19 Elsy Yulieth Marin Serna 1 hora 2 minutos 19 segundos De una. Elsy Yulieth Marin Serna 1 hora 2 minutos 24 segundos Con gusto. Elsy Yulieth Marin Serna 1 hora 2 minutos 33 segundos Con gusto a ustedes, muchísimas gracias. Les voy a dejar esto aquí en el chat de esta reunioncita listo. Joan Sebastian Rengifo Ocampo 1 hora 2 minutos 35 segundos1:02:35 Joan Sebastian Rengifo Ocampo 1 hora 2 minutos 35 segundos Vale, gracias. Joan Sebastian Rengifo Ocampo 1 hora 2 minutos 38 segundos Listo, súper, gracias. Natalia Zartha Suarez 1 hora 2 minutos 38 segundos1:02:38 Natalia Zartha Suarez 1 hora 2 minutos 38 segundos Súper, dale, muchas gracias. Chaito, un gusto, chaito, gracias.
B25: # Applicaciones | C25: 3
B26: Comercial: | C26: Adriana Montez
B28: ③ EVALUACIÓN DE PRÁCTICAS ITIL v4 — 4 DIMENSIONES
B29: # | C29: PRÁCTICA | D29: ¿Se cumple? | E29: Observaciones / Evidencia | F29: Prioridad Mejora
B30: D1 — Organización y Personas
B31: 1.1 | C31: Gestión de la Fuerza Laboral: Headcount, perfiles, competencias | D31: Parcial | E31: Headcount identificado por operación y líder definida (Elsy). | F31: Media
B32: 1.2 | C32: Gestión del Conocimiento: KB (Knowledge Base), documentación, onboarding | D32: Parcial | E32: Existe operación en BMC, pero se requiere reforzar documentación, KB y transferencia de conocimiento por niveles. | F32: Alta
B33: 1.3 | C33: Gestión del Talento: Rotación, desarrollo, retención | D33: No | E33: Se requiere validar retención/rotación por operación; hay dependencia de conocimiento del equipo. | F33: Media
B34: 1.4 | C34: Gestión del Desempeño: Metas individuales, feedback, KPIs de agente | D34: Parcial | E34: Hay métricas operativas por mesa (tickets, SLA, MTTR, backlog), pero no se evidencian KPIs individuales por agente. | F34: Media
B35: 1.5 | C35: Cultura de Servicio: Orientación al usuario, empatía, NPS (Net Promoter Score) interno | D35: Parcial | E35: Servicio sensible al usuario/negocio; falta medición formal de experiencia (NPS/CSAT). | F35: Media
B37: D2 — Información y Tecnología
B38: 2.1 | C38: Gestión de Incidentes: Proceso, tiempos, escalamiento | D38: Sí | E38: Gestión de incidentes en BMC con volumetría mensual disponible. | F38: Media
B39: 2.2 | C39: Gestión de Requerimientos: Catálogo de servicios, flujos | D39: Sí | E39: Gestión de requerimientos en BMC con volumetría mensual disponible. | F39: Media
B40: 2.3 | C40: Gestión de Problemas: RCA (Análisis de Causa Raíz ), errores conocidos, KEDB (Known Error Database) | D40: Sí | E40: Hay atención de causa raíz / nivel 3, pero se requiere formalizar RCA/KEDB y criterios de escalamiento. | F40: Alta
B41: 2.4 | C41: Gestión de Cambios: CAB (Change Advisory Board), RFC (Solicitud de Cambio), ventanas de mantenimiento | D41: Parcial | E41: Se observan procesos operativos y cierres, pero no se confirma gestión formal de cambios/CAB/RFC. | F41: Media
B42: 2.5 | C42: Gestión de la Configuración: CMDB (Configuration Management Database), assets, CIs (Elementos de Configuración) | D42: No | F42: Media
B43: 2.6 | C43: Monitoreo y Eventos: Alertas, observabilidad, integración | D43: No | F43: Media
B44: 2.7 | C44: Mesa de Servicio (Service Desk): Canal único, autoservicio, chatbot | D44: Parcial | E44: BMC centraliza ticketing, pero no se evidencia autoservicio/chatbot ni canal único maduro. | F44: Alta
B46: D3 — Socios y Proveedores
B47: 3.1 | C47: Gestión de Proveedores: SLAs (Acuerdo de nivel de servicio) tercerizados, contratos, evaluación | D47: Sí | E47: Proveedor/cliente gestionado mediante operación SURA y herramienta BMC. | F47: Media
B48: 3.2 | C48: Gestión de Niveles de Servicio: SLA, OLA (Acuerdo de nivel de operación), XLA (Acuerdo de nivel de experiencia) definidos y medidos | D48: Sí | E48: Hay meta SLA y medición de cumplimiento; no se evidencian OLA/XLA. | F48: Alta
B49: 3.3 | C49: Gestión de Capacidad y Disponibilidad: Picos, contingencia | D49: Parcial | E49: Hay métricas de volumen, backlog y FTE; se requiere capacidad formal por picos/cierres. | F49: Alta
B51: D4 — Flujos de Valor y Mejora
B52: 4.1 | C52: Mejora Continua: Ciclos PDCA (Planificar, Hacer, Comprobar y Actuar), retros, backlogs de mejora | D52: Parcial | E52: Se identifican oportunidades de mejora con Kanban/Power App y optimización del seguimiento. | F52: Alta
B53: 4.2 | C53: Medición y Reporte: Dashboards, informes ejecutivos, tendencias | D53: Parcial | E53: Existen métricas base; falta visibilidad ejecutiva/tablero consolidado y trazabilidad de tareas no registradas. | F53: Alta
B55: SCORE GENERAL DE PRÁCTICAS ITIL: | D55: =IF(D31="Sí",1,IF(D31="Parcial",0.5,0))+IF(D32="Sí",1,IF(D32="Parcial",0.5,0))+IF(D33="Sí",1,IF(D33="Parcial",0.5,0))+IF(D34="Sí",1,IF(D34="Parcial",0.5,0))+IF(D35="Sí",1,IF(D35="Parcial",0.5,0))+IF(D38="Sí",1,IF(D38="Parcial",0.5,0))+IF(D39="Sí",1,IF(D39="Parcial",0.5,0))+IF(D40="Sí",1,IF(D40="Parcial",0.5,0))+IF(D41="Sí",1,IF(D41="Parcial",0.5,0))+IF(D42="Sí",1,IF(D42="Parcial",0.5,0))+IF(D43="Sí",1,IF(D43="Parcial",0.5,0))+IF(D44="Sí",1,IF(D44="Parcial",0.5,0))+IF(D47="Sí",1,IF(D47="Parcial",0.5,0))+IF(D48="Sí",1,IF(D48="Parcial",0.5,0))+IF(D49="Sí",1,IF(D49="Parcial",0.5,0))+IF(D52="Sí",1,IF(D52="Parcial",0.5,0))+IF(D53="Sí",1,IF(D53="Parcial",0.5,0)) -> 9.5 | E55: =D55/17 -> 0.55882353
B57: ④ VOLUMETRÍA Y KPIs OPERATIVOS
B58: MÉTRICA | C58: Valor Actual | D58: Meta / SLA | E58: Tendencia | F58: Comentario
B59: Cantidad de Tickets / mes (total) | C59: 174 | E59: Volumen variable; SLA mejora hacia junio, pero promedio bajo meta.
B60: Cantidad de Incidentes / mes | C60: 174 | E60: Volumen variable; SLA mejora hacia junio, pero promedio bajo meta.
B61: Cantidad de Requerimientos / mes | C61: 0 | E61: Volumen variable; SLA mejora hacia junio, pero promedio bajo meta.
B62: Cantidad de Cambios / mes | C62: N/A | D62: N/A | E62: Volumen variable; SLA mejora hacia junio, pero promedio bajo meta.
B63: First Call Resolution (FCR %) | C63: N/D | D63: N/D | E63: Volumen variable; SLA mejora hacia junio, pero promedio bajo meta.
B64: Mean Time to Resolve (MTTR horas) | C64: 12.38 | D64: 92% por categoría de criticidad: alto/crítico 9h, medio 12h, bajo 18h | E64: Volumen variable; SLA mejora hacia junio, pero promedio bajo meta.
B65: SLA Cumplimiento (%) | C65: 0.74 | D65: 0.92 | E65: Volumen variable; SLA mejora hacia junio, pero promedio bajo meta.
B66: Backlog promedio (tickets abiertos) | C66: 12 | E66: Volumen variable; SLA mejora hacia junio, pero promedio bajo meta.
B67: Tickets resueltos por agente/mes | C67: 77 | E67: Volumen variable; SLA mejora hacia junio, pero promedio bajo meta.
B68: Costo estimado por ticket (USD) | C68: N/D | D68: N/D | E68: Volumen variable; SLA mejora hacia junio, pero promedio bajo meta.
B69: Agentes FTE totales | C69: 2 | E69: Volumen variable; SLA mejora hacia junio, pero promedio bajo meta.
B70: % Tickets autoservicio / N0 | C70: 0 | D70: 0 | E70: Volumen variable; SLA mejora hacia junio, pero promedio bajo meta.
B72: ④b DISTRIBUCIÓN DE INCIDENTES POR CATEGORÍA
B73: Si el service desk del cliente les permite cateogorizarse asi
B74: CATEGORÍA | C74: Tickets/mes | D74: % del Total | E74: Tiempo Prom. Resolución (h) | F74: Observaciones
B75: Accesos / Permisos
B76: Red / Conectividad
B77: Aplicaciones de negocio | C77: 174 | D77: 1 | E77: 12.38 | F77: Canal digital de venta; 174 tickets/mes promedio.
B78: Hardware / Equipos
B79: Correo / Office 365
B80: ERP (Enterprise resource planning) / SAP (System Applications and Products in Data Processing)
B81: Seguridad / Ciberseguridad
B82: Otra categoría
B84: ⑤ EXPERIENCIA DEL USUARIO — XLA (Acuerdos de Nivel de Experiencia) / DEX (Experiencia Digital del Empleado)
B85: INDICADOR XLA | C85: Valor Actual | D85: Meta | E85: Método de Medición | F85: Observaciones
B86: NPS (Net Promoter Score) de la mesa
B87: CSAT (Satisfacción del cliente) — escala 1-5
B88: CES (Customer Effort Score)
B89: Encuestas post-ticket (tasa de respuesta %)
B90: Percepción de calidad (top 3 palabras del usuario)
B91: Cantidad de Quejas escaladas / mes
B92: Tiempo promedio de espera en canal (minutos)
B94: ⑥ DOLORES CRÍTICOS DE LA MESA (D1–D21)
B95: DOLOR | C95: ¿Existe? | D95: Descripción / Evidencia | E95: Impacto (1-5) | F95: Criticidad | G95: Iniciativa sugerida
B96: D1 | C96: Parcial | D96: Rotación excesiva de personal: pérdida de conocimiento | E96: 3 | F96: Media | G96: Documentar conocimiento crítico y plan de respaldo por operación.
B97: D2 | C97: Sí | D97: SLAs incumplidos / penalizaciones contractuales | E97: 4 | F97: Alta | G97: Plan de mejora SLA por criticidad y seguimiento semanal.
B98: D3 | C98: Sí | D98: Ausencia de autoservicio: todo llega por call/correo | E98: 4 | F98: Alta | G98: Diseñar autoservicio/N0 para consultas repetitivas y solicitudes estándar.
B99: D4 | C99: Parcial | D99: Herramientas fragmentadas / sin integración | E99: 3 | F99: Media | G99: Integrar BMC con tablero/Kanban y trazabilidad operativa.
B100: D5 | C100: No | D100: Baja satisfacción del usuario (NPS < 30) | E100: 2 | F100: Baja | G100: Levantar NPS/CSAT para confirmar percepción del usuario.
B101: D6 | C101: Parcial | D101: Escalamientos excesivos a N2/N3 | E101: 3 | F101: Media | G101: Definir matriz clara N1/N2/N3 y criterios de raízal/desarrollo.
B102: D7 | C102: Sí | D102: Falta de visibilidad en tiempo real (sin dashboard) | E102: 3 | F102: Media | G102: Crear tablero de seguimiento operativo y visibilidad de backlog/SLA.
B103: D8 | C103: Parcial | D103: Reportes manuales: no hay visibilidad ejecutiva en tiempo real | E103: 3 | F103: Media | G103: Automatizar reportes con BMC/Power App/BI.
B104: D9 | C104: Sí | D104: Expansión del alcance no controlado: solicitudes fuera del alcance de la mesa de servicio (no delimitado) | E104: 3 | F104: Media | G104: Registrar solicitudes adicionales y delimitar alcance por canal/mesa.
B105: D10 | C105: Parcial | D105: Escalamiento inefiiente y cuellos de botella: El modelo de N1/N2/N3 genera rebotes de tickets aumentado el MTTR (tiempo medio de resolución | E105: 3 | F105: Media | G105: Estandarizar escalamiento y tiempos por nivel.
B106: D11 | C106: Parcial | D106: Postura 100% reactiva | E106: 3 | F106: Media | G106: Pasar de atención reactiva a gestión por métricas y mejora continua.
B107: D12 | C107: Parcial | D107: Falta de gobierno claro | E107: 3 | F107: Media | G107: Definir gobierno operativo, RACI, comités y responsables.
... B113: D18 | C113: Parcial | D113: Reskilling - Upskilling constante del staff | E113: 3 | F113: Media | G113: Plan de reskilling en BMC, operación por niveles, Power Apps/Kanban y automatización.
B114: D20 | C114: Sí | D114: Asignación de personal a las mesas y Niveles basada en criterio experto, sin modelo de demanda. No hay como dimensionarlo | G114: Se hace a juicio de expero de la emrpesa
B115: D21
...

Sheet SURA Automatizacion
B2: LEVANTAMIENTO DE MESA DE SERVICIOS — SURA TORRE CONTROL
I3: ESCALA DE MADUREZ — N0 a N5
B4: ① IDENTIFICACIÓN GENERAL DE LA MESA | I4: NIVEL | J4: NOMBRE | K4: DESCRIPCIÓN
B5: Cliente: | C5: SURA | I5: N0 | J5: Reactivo / Sin estructura | K5: No existe proceso formal. Todo es manual y reactivo. Sin CMDB ni catálogo.
B6: Negocio del cliente: | C6: Soporte a Automate, PowerApps. Preventivo, Monitoreo | I6: N1 | J6: Inicial / Ad hoc/ Operación reactiva | K6: Procesos básicos documentados. Herramientas mínimas. Cumplimiento inconsistente.
B7: Nombre de la Mesa: | C7: Automatizacion | I7: N2 | J7: Definido / Organización funcional | K7: Procesos ITIL definidos y seguidos. Métricas básicas (SLA (Service Level Agreement), FCR (Fondo de Capital Riesgo)). Equipo estable.
B8: Líder / Coordinador: | C8: Elsy Yulieth Marin Serna | I8: N3 | J8: Gestionado / Gestión por servicios | K8: Métricas avanzadas. Automatización parcial. Gestión proactiva de problemas.
B9: Fecha del Levantamiento: | C9: 46211 | I9: N4 | J9: Optimizado / Gestión integrada | K9: Autoservicio maduro. IA/ML básico. XLA (Experience Level Agreement) medidos. Mejora continua activa.
B10: Ubicación / Modalidad: | C10: Virtual
B11: N° de Agentes (FTE) (cantidad de personas): | C11: 6 | I11: Función | J11: Misión Principal | K11: Alcance
B12: Modelo de Contrato: | C12: FTE dedicado | I12: Call Center | J12: Manejar grandes volúmenes de llamadas; filtrar y derivar | K12: Punto de contacto y distribución estructurada
B13: Nivel Madurez Actual: | C13: N2 | D13: (N0 Reactivo → N5 Innovador) | I13: Help Desk | J13: Coordinación para la restauración del servicio; "arreglar cosas" | K13: Infraestructura, herramientas de seguimiento, base de conocimiento
B14: Modelo de Operación | C14: Service Desk ->Servicio integral: incidentes, solicitudes, consultas, altas/bajas/cambios | I14: Service Desk | J14: Servicio integral: incidentes, solicitudes, consultas, altas/bajas/cambios | K14: Alcance configurable; representa al usuario dentro de TI
B15: (Tercero) Empresa de soporte al cliente | D15: (N0 Reactivo → N5 Innovador)
B16: En que otro Niveles tenemos presencia: | C16: No Aplica
B17: En que paises tenemos presencia: | C17: Colombia
B18: Que hacemos en el cliente: | C18: Soporte y operación de automatizaciones; combina incidentes y requerimientos con MTTR bajo y SLA sobre meta.
B19: Tiempo de la Mesa de Servicio | C19: Por confirmar
B20: Finalización: | C20: Agosto con posible renovación hasta diciembre
B21: Renovación: | C21: Propuesta con mirada de optimización; Compañía de Conexión / negociación comercial.
B22: Equipos de infraestructura:
B23: Video: | C23: Hablemos Mesas Sura-20260708_090044-Grabación de la reunión.mp4
B24: Transcript: | C24: Natalia Zartha Suarez 0 30:03 Natalia Zartha Suarez 0 minutos 3 segundos Esto es un gusto conocerte. E Elsy Yulieth Marin Serna 0 50:05 Elsy Yulieth Marin Serna 0 minutos 5 segundos Súper bien, gracias a Dios también un placer. Ya había escuchado tu nombre, pero no había visto tu rostro. Natalia Zartha Suarez 0 70:07 Natalia Zartha Suarez 0 minutos 7 segundos bueno. Natalia Zartha Suarez 0 minutos 11 segundos Ah, bueno, súper. Muchísimas gracias por este espacio. Si quieres arrancamos para aprovechar el tiempito. Joan y Joan están invitados, pero pues igual la idea es como que que conversemos. Yo en este momento, pues entré hace como dos semanitas en la compañía, estoy trabajando en el equipo de de Joan. E Elsy Yulieth Marin Serna 0 180:18 Elsy Yulieth Marin Serna 0 minutos 18 segundos De una. Elsy Yulieth Marin Serna 0 minutos 28 segundos And. Natalia Zartha Suarez 0 300:30 Natalia Zartha Suarez 0 minutos 30 segundos Y estoy comenzando con el diseño de las mesas de de servicio como un servicio estandarizado. Entonces estamos haciendo la la tarea de reunirnos con cada mesa. Joan me pues me me estaba colaborando con con la citación de estos para recoger como toda la información, todo el feedback, las lecciones aprendidas que ustedes tengan. O sea, cómo podemos mejorar esas mesas para que este servicio estandarizado. Pues. E Elsy Yulieth Marin Serna 0 360:36 Elsy Yulieth Marin Serna 0 minutos 36 segundos Okay. Elsy Yulieth Marin Serna 0 minutos 52 segundos Y. Natalia Zartha Suarez 0 minutos 55 segundos0:55 Natalia Zartha Suarez 0 minutos 55 segundos sea mejor cierto entonces creo que él dejó unas pregunticas por aquí en el chat igual si si tú las tienes bien sino también porque pues podemos hacerlas como como mirando listo Ah súper Natalia Zartha Suarez 58 minutos 22 segundos58:22 Natalia Zartha Suarez 58 minutos 22 segundos Sí. E Elsy Yulieth Marin Serna 58 minutos 25 segundos58:25 Elsy Yulieth Marin Serna 58 minutos 25 segundos que se tienen, se hacen este canal que se llama canales masivos. Acá hay muchas tareas automáticas porque como la volumetría es tan alta, pues hay muchos procesos automáticos que corren durante la semana, los fines de semana para renovar, para cancelar, pues todo eso es como muy automático por la volumetría propiamente según el cliente que tenemos. Elsy Yulieth Marin Serna 58 minutos 44 segundos Los clientes que manejamos y es un canal muy sensible, o sea, en serio Bancolombia dice, ay, esta póliza salió con un error y mejor dicho, hay que pagar todo lo que sea porque hay que revisar esa póliza de Bancolombia. Entonces es un canal muy demandante, más que en volumen de incidentes, en revisiones. Elsy Yulieth Marin Serna 59 minutos 4 segundos Ay, es que están diciendo que está saliendo este error, entonces el pelado se tiene que parar lo que sea para ir a hacer y acá supuestamente, según el cliente, una sola persona. Elsy Yulieth Marin Serna 59 minutos 14 segundos apalancado en el número de incidentes solamente nosotros ya en este tiempo que llevamos operando hemos visto no es que él no solo atiende incidentes en serio lo llaman demasiado para revisar un tema al otro le mandan correos que manda este informe que necesitamos cruzar esto que porque esto está pasando o sea es demandante en actividades adicionales un montón Elsy Yulieth Marin Serna 59 minutos 35 segundos que no quedan mapeadas siempre como en incidente Sí hemos tratado con él de venga acá que a usted le pidan algo que le Monten un incidente para que usted tenga un respaldo de qué es lo que está trabajando pero eh Este es el Pues los los clientes de este canal son los consentidos de su de hecho allá todo el mundo le dicen si usted va para canales masivos Natalia Zartha Suarez 59 minutos 38 segundos59:38 Natalia Zartha Suarez 59 minutos 38 segundos Mhm. E Elsy Yulieth Marin Serna 59 minutos 56 segundos59:56 Elsy Yulieth Marin Serna 59 minutos 56 segundos Mejor dicho, usted le dicen hola y ya usted allá sentado mirando que necesitan. Natalia Zartha Suarez 1 hora 2 segundos1:00:02 Natalia Zartha Suarez 1 hora 2 segundos O K, esa, el horario también es 7 normalito en los 17:30. E Elsy Yulieth Marin Serna 1 hora 3 segundos1:00:03 Elsy Yulieth Marin Serna 1 hora 3 segundos No. Elsy Yulieth Marin Serna 1 hora 7 segundos 7:30, 7:30, 5 y este digamos que por los cierres de mes tiene también una disponibilidad en el final de el último día del mes y el primer día del mes siguiente, independiente si son hábiles o no. Si el último día del mes del 31 cae un domingo, tenemos que tener disponibilidad. Si el primero es postivo, tenemos que tener disponibilidad. Natalia Zartha Suarez 1 hora 10 segundos1:00:10 Natalia Zartha Suarez 1 hora 10 segundos Okay. Natalia Zartha Suarez 1 hora 27 segundos Mhm. E Elsy Yulieth Marin Serna 1 hora 29 segundos1:00:29 Elsy Yulieth Marin Serna 1 hora 29 segundos Para todos los temas de cierre, pues garantizar que todo lo de cierre quede pues como el día. Natalia Zartha Suarez 1 hora 31 segundos1:00:31 Natalia Zartha Suarez 1 hora 31 segundos Ya. Natalia Zartha Suarez 1 hora 35 segundos Listo. E Elsy Yulieth Marin Serna 1 hora 35 segundos1:00:35 Elsy Yulieth Marin Serna 1 hora 35 segundos Eso es como el resumen rápido. Natalia Zartha Suarez 1 hora 38 segundos1:00:38 Natalia Zartha Suarez 1 hora 38 segundos No, muchísimas. Bueno, bueno, pero todo es un toda esa manera con la herramienta de BMX. ¿Cómo fue que dijiste la ticket? E Elsy Yulieth Marin Serna 1 hora 44 segundos1:00:44 Elsy Yulieth Marin Serna 1 hora 44 segundos Sí, BMC se llama. Natalia Zartha Suarez 1 hora 48 segundos1:00:48 Natalia Zartha Suarez 1 hora 48 segundos No creté, no, dale. Joan Sebastian Rengifo Ocampo 1 hora 48 segundos1:00:48 Joan Sebastian Rengifo Ocampo 1 hora 48 segundos Yo me debo de pasar a un espacio, pero te iba a comentar algo. el. E Elsy Yulieth Marin Serna 1 hora 53 segundos1:00:53 Elsy Yulieth Marin Serna 1 hora 53 segundos Mhm. Joan Sebastian Rengifo Ocampo 1 hora 56 segundos1:00:56 Joan Sebastian Rengifo Ocampo 1 hora 56 segundos De los agile que estábamos en Bancolombia, hay tres compañeras que están indisponibles o igual los agile que quedamos, por ejemplo, una luz es mi persona. Hemos acompañado a equipos de soporte, incluso una de las que está disponible acompañada del centro de excelencia donde está la Jioti, donde están muchos de los equipos de soporte. Joan Sebastian Rengifo Ocampo 1 hora 1 minuto 16 segundos Yo acompañaba, por ejemplo, a los equipos que soportaban todo el canal la sucursal virtual negocios. Entonces, si puedes hablar, por ejemplo, con Jenny que ella tiene mis tres compañeras disponibles, porque esto que va a construir Natalia es más como pensando en temas, clientes nuevos, mesas nuevas, pero por el momento el enfoque no va a ser tanto de venga como le solucionamos a ustedes la vida. Natalia Zartha Suarez 1 hora 1 minuto 34 segundos1:01:34 Natalia Zartha Suarez 1 hora 1 minuto 34 segundos Mhm, sí. Joan Sebastian Rengifo Ocampo 1 hora 1 minuto 40 segundos1:01:40 Joan Sebastian Rengifo Ocampo 1 hora 1 minuto 40 segundos inicialmente, pero esa asesoría que no les funcionó con esta chica que nos decías, podrían tener un espacio con las compañeras o con cualquiera de nosotros, porque a mí ahorita yo decía aquí le sirve un Kanban, allá automatizamos esto con un power app si nos sacaba tal información. E Elsy Yulieth Marin Serna 1 hora 1 minuto 40 segundos1:01:40 Elsy Yulieth Marin Serna 1 hora 1 minuto 40 segundos Mhm. Natalia Zartha Suarez 1 hora 1 minuto 43 segundos1:01:43 Natalia Zartha Suarez 1 hora 1 minuto 43 segundos sí. Joan Sebastian Rengifo Ocampo 1 hora 1 minuto 59 segundos1:01:59 Joan Sebastian Rengifo Ocampo 1 hora 1 minuto 59 segundos O sea, les pueden dar ciertas ideas de los equipos que acompañaban, qué hacían, cómo lo hacían y te puede dar ideas como para llevarlo a este proceso. Mientras pues te dejo ahí como esa inquietud para que de pronto hables con Jenny, porque ahí están disponibles y te pueden apoyar pues en esos temas. E Elsy Yulieth Marin Serna 1 hora 2 minutos 2 segundos1:02:02 Elsy Yulieth Marin Serna 1 hora 2 minutos 2 segundos Mhm, super. Natalia Zartha Suarez 1 hora 2 minutos 11 segundos1:02:11 Natalia Zartha Suarez 1 hora 2 minutos 11 segundos Mhm. E Elsy Yulieth Marin Serna 1 hora 2 minutos 11 segundos1:02:11 Elsy Yulieth Marin Serna 1 hora 2 minutos 11 segundos De una. Elsy Yulieth Marin Serna 1 hora 2 minutos 13 segundos Súper de una, yo 1000 gracias. Natalia Zartha Suarez 1 hora 2 minutos 19 segundos1:02:19 Natalia Zartha Suarez 1 hora 2 minutos 19 segundos Súper, muchas gracias. Listo Elsy, muchísimas gracias. Un gusto conocerte. De pronto te esté preguntando cositas puntuales mientras organizo como toda la información, pero muchísimas gracias por el espacio. Excelente. Nada, bye. Sí. E Elsy Yulieth Marin Serna 1 hora 2 minutos 19 segundos1:02:19 Elsy Yulieth Marin Serna 1 hora 2 minutos 19 segundos De una. Elsy Yulieth Marin Serna 1 hora 2 minutos 24 segundos Con gusto. Elsy Yulieth Marin Serna 1 hora 2 minutos 33 segundos Con gusto a ustedes, muchísimas gracias. Les voy a dejar esto aquí en el chat de esta reunioncita listo. Joan Sebastian Rengifo Ocampo 1 hora 2 minutos 35 segundos1:02:35 Joan Sebastian Rengifo Ocampo 1 hora 2 minutos 35 segundos Vale, gracias. Joan Sebastian Rengifo Ocampo 1 hora 2 minutos 38 segundos Listo, súper, gracias. Natalia Zartha Suarez 1 hora 2 minutos 38 segundos1:02:38 Natalia Zartha Suarez 1 hora 2 minutos 38 segundos Súper, dale, muchas gracias. Chaito, un gusto, chaito, gracias.
B25: # Applicaciones
B26: Comercial: | C26: Adriana Montez
B28: ③ EVALUACIÓN DE PRÁCTICAS ITIL v4 — 4 DIMENSIONES
B29: # | C29: PRÁCTICA | D29: ¿Se cumple? | E29: Observaciones / Evidencia | F29: Prioridad Mejora
B30: D1 — Organización y Personas
B31: 1.1 | C31: Gestión de la Fuerza Laboral: Headcount, perfiles, competencias | D31: Parcial | E31: Headcount identificado por operación y líder definida (Elsy). | F31: Media
B32: 1.2 | C32: Gestión del Conocimiento: KB (Knowledge Base), documentación, onboarding | D32: Parcial | E32: Existe operación en BMC, pero se requiere reforzar documentación, KB y transferencia de conocimiento por niveles. | F32: Alta
B33: 1.3 | C33: Gestión del Talento: Rotación, desarrollo, retención | D33: No | E33: Se requiere validar retención/rotación por operación; hay dependencia de conocimiento del equipo. | F33: Media
B34: 1.4 | C34: Gestión del Desempeño: Metas individuales, feedback, KPIs de agente | D34: Parcial | E34: Hay métricas operativas por mesa (tickets, SLA, MTTR, backlog), pero no se evidencian KPIs individuales por agente. | F34: Media
B35: 1.5 | C35: Cultura de Servicio: Orientación al usuario, empatía, NPS (Net Promoter Score) interno | D35: Parcial | E35: Servicio sensible al usuario/negocio; falta medición formal de experiencia (NPS/CSAT). | F35: Media
B37: D2 — Información y Tecnología
B38: 2.1 | C38: Gestión de Incidentes: Proceso, tiempos, escalamiento | D38: Sí | E38: Gestión de incidentes en BMC con volumetría mensual disponible. | F38: Media
B39: 2.2 | C39: Gestión de Requerimientos: Catálogo de servicios, flujos | D39: Sí | E39: Gestión de requerimientos en BMC con volumetría mensual disponible. | F39: Media
B40: 2.3 | C40: Gestión de Problemas: RCA (Análisis de Causa Raíz ), errores conocidos, KEDB (Known Error Database) | D40: Sí | E40: Hay atención de causa raíz / nivel 3, pero se requiere formalizar RCA/KEDB y criterios de escalamiento. | F40: Alta
B41: 2.4 | C41: Gestión de Cambios: CAB (Change Advisory Board), RFC (Solicitud de Cambio), ventanas de mantenimiento | D41: Parcial | E41: Se observan procesos operativos y cierres, pero no se confirma gestión formal de cambios/CAB/RFC. | F41: Media
B42: 2.5 | C42: Gestión de la Configuración: CMDB (Configuration Management Database), assets, CIs (Elementos de Configuración) | D42: No | F42: Media
B43: 2.6 | C43: Monitoreo y Eventos: Alertas, observabilidad, integración | D43: Sí | E43: Se menciona preventivo y monitoreo dentro del alcance de automatización. | F43: Media
B44: 2.7 | C44: Mesa de Servicio (Service Desk): Canal único, autoservicio, chatbot | D44: Parcial | E44: BMC centraliza ticketing, pero no se evidencia autoservicio/chatbot ni canal único maduro. | F44: Alta
B46: D3 — Socios y Proveedores
B47: 3.1 | C47: Gestión de Proveedores: SLAs (Acuerdo de nivel de servicio) tercerizados, contratos, evaluación | D47: Sí | E47: Proveedor/cliente gestionado mediante operación SURA y herramienta BMC. | F47: Media
B48: 3.2 | C48: Gestión de Niveles de Servicio: SLA, OLA (Acuerdo de nivel de operación), XLA (Acuerdo de nivel de experiencia) definidos y medidos | D48: Sí | E48: Hay meta SLA y medición de cumplimiento; no se evidencian OLA/XLA. | F48: Alta
B49: 3.3 | C49: Gestión de Capacidad y Disponibilidad: Picos, contingencia | D49: Parcial | E49: Hay métricas de volumen, backlog y FTE; se requiere capacidad formal por picos/cierres. | F49: Alta
B51: D4 — Flujos de Valor y Mejora
B52: 4.1 | C52: Mejora Continua: Ciclos PDCA (Planificar, Hacer, Comprobar y Actuar), retros, backlogs de mejora | D52: Parcial | E52: Se identifican oportunidades de mejora con Kanban/Power App y optimización del seguimiento. | F52: Alta
B53: 4.2 | C53: Medición y Reporte: Dashboards, informes ejecutivos, tendencias | D53: Parcial | E53: Existen métricas base; falta visibilidad ejecutiva/tablero consolidado y trazabilidad de tareas no registradas. | F53: Alta
B55: SCORE GENERAL DE PRÁCTICAS ITIL: | D55: =IF(D31="Sí",1,IF(D31="Parcial",0.5,0))+IF(D32="Sí",1,IF(D32="Parcial",0.5,0))+IF(D33="Sí",1,IF(D33="Parcial",0.5,0))+IF(D34="Sí",1,IF(D34="Parcial",0.5,0))+IF(D35="Sí",1,IF(D35="Parcial",0.5,0))+IF(D38="Sí",1,IF(D38="Parcial",0.5,0))+IF(D39="Sí",1,IF(D39="Parcial",0.5,0))+IF(D40="Sí",1,IF(D40="Parcial",0.5,0))+IF(D41="Sí",1,IF(D41="Parcial",0.5,0))+IF(D42="Sí",1,IF(D42="Parcial",0.5,0))+IF(D43="Sí",1,IF(D43="Parcial",0.5,0))+IF(D44="Sí",1,IF(D44="Parcial",0.5,0))+IF(D47="Sí",1,IF(D47="Parcial",0.5,0))+IF(D48="Sí",1,IF(D48="Parcial",0.5,0))+IF(D49="Sí",1,IF(D49="Parcial",0.5,0))+IF(D52="Sí",1,IF(D52="Parcial",0.5,0))+IF(D53="Sí",1,IF(D53="Parcial",0.5,0)) -> 10.5 | E55: =D55/17 -> 0.61764706
B57: ④ VOLUMETRÍA Y KPIs OPERATIVOS
B58: MÉTRICA | C58: Valor Actual | D58: Meta / SLA | E58: Tendencia | F58: Comentario
B59: Cantidad de Tickets / mes (total) | C59: 512 | E59: SLA estable y sobre meta; volumen alto con buen desempeño.
B60: Cantidad de Incidentes / mes | C60: 333 | E60: SLA estable y sobre meta; volumen alto con buen desempeño.
B61: Cantidad de Requerimientos / mes | C61: 179 | E61: SLA estable y sobre meta; volumen alto con buen desempeño.
B62: Cantidad de Cambios / mes | C62: N/A | D62: N/A | E62: SLA estable y sobre meta; volumen alto con buen desempeño.
B63: First Call Resolution (FCR %) | C63: N/D | D63: N/D | E63: SLA estable y sobre meta; volumen alto con buen desempeño.
B64: Mean Time to Resolve (MTTR horas) | C64: 2.98 | D64: 92% por categoría de criticidad: alto/crítico 9h, medio 12h, bajo 18h | E64: SLA estable y sobre meta; volumen alto con buen desempeño.
B65: SLA Cumplimiento (%) | C65: 0.98 | D65: 0.92 | E65: SLA estable y sobre meta; volumen alto con buen desempeño.
B66: Backlog promedio (tickets abiertos) | C66: 9 | E66: SLA estable y sobre meta; volumen alto con buen desempeño.
B67: Tickets resueltos por agente/mes | C67: 80 | E67: SLA estable y sobre meta; volumen alto con buen desempeño.
B68: Costo estimado por ticket (USD) | C68: N/D | D68: N/D | E68: SLA estable y sobre meta; volumen alto con buen desempeño.
B69: Agentes FTE totales | C69: 6 | E69: SLA estable y sobre meta; volumen alto con buen desempeño.
B70: % Tickets autoservicio / N0 | C70: 0 | D70: 0 | E70: SLA estable y sobre meta; volumen alto con buen desempeño.
B72: ④b DISTRIBUCIÓN DE INCIDENTES POR CATEGORÍA
B73: Si el service desk del cliente les permite cateogorizarse asi
B74: CATEGORÍA | C74: Tickets/mes | D74: % del Total | E74: Tiempo Prom. Resolución (h) | F74: Observaciones
B75: Accesos / Permisos
B76: Red / Conectividad
B77: Aplicaciones de negocio | C77: 512 | D77: 1 | E77: 2.98 | F77: Automatizaciones / PowerApps; 512 tickets/mes promedio.
B78: Hardware / Equipos
B79: Correo / Office 365
B80: ERP / SAP
B81: Seguridad / Ciberseguridad
B82: Otra categoría
B84: ⑤ EXPERIENCIA DEL USUARIO — XLA / DEX
B85: INDICADOR XLA | C85: Valor Actual | D85: Meta | E85: Método de Medición | F85: Observaciones
B86: NPS (Net Promoter Score) de la mesa
B87: CSAT (Satisfacción del cliente) — escala 1-5
B88: CES (Customer Effort Score)
B89: Encuestas post-ticket (tasa de respuesta %)
B90: Percepción de calidad (top 3 palabras del usuario)
B91: Cantidad de Quejas escaladas / mes
B92: Tiempo promedio de espera en canal (minutos)
B94: ⑥ DOLORES CRÍTICOS DE LA MESA (D1–D21)
B95: DOLOR | C95: ¿Existe? | D95: Descripción / Evidencia | E95: Impacto (1-5) | F95: Criticidad | G95: Iniciativa sugerida
B96: D1 | C96: Parcial | D96: Rotación excesiva de personal: pérdida de conocimiento | E96: 3 | F96: Media | G96: Documentar conocimiento crítico y plan de respaldo por operación.
B97: D2 | C97: No | D97: SLAs incumplidos / penalizaciones contractuales | E97: 2 | F97: Baja | G97: Plan de mejora SLA por criticidad y seguimiento semanal.
B98: D3 | C98: Sí | D98: Ausencia de autoservicio: todo llega por call/correo | E98: 4 | F98: Alta | G98: Diseñar autoservicio/N0 para consultas repetitivas y solicitudes estándar.
B99: D4 | C99: Parcial | D99: Herramientas fragmentadas / sin integración | E99: 3 | F99: Media | G99: Integrar BMC con tablero/Kanban y trazabilidad operativa.
B100: D5 | C100: No | D100: Baja satisfacción del usuario (NPS < 30) | E100: 2 | F100: Baja | G100: Levantar NPS/CSAT para confirmar percepción del usuario.
B101: D6 | C101: Parcial | D101: Escalamientos excesivos a N2/N3 | E101: 3 | F101: Media | G101: Definir matriz clara N1/N2/N3 y criterios de raízal/desarrollo.
B102: D7 | C102: Sí | D102: Falta de visibilidad en tiempo real (sin dashboard) | E102: 3 | F102: Media | G102: Crear tablero de seguimiento operativo y visibilidad de backlog/SLA.
B103: D8 | C103: Parcial | D103: Reportes manuales: no hay visibilidad ejecutiva en tiempo real | E103: 3 | F103: Media | G103: Automatizar reportes con BMC/Power App/BI.
B104: D9 | C104: Sí | D104: Expansión del alcance no controlado: solicitudes fuera del alcance de la mesa de servicio (no delimitado) | E104: 3 | F104: Media | G104: Registrar solicitudes adicionales y delimitar alcance por canal/mesa.
B105: D10 | C105: Parcial | D105: Escalamiento inefiiente y cuellos de botella: El modelo de N1/N2/N3 genera rebotes de tickets aumentado el MTTR (tiempo medio de resolución | E105: 3 | F105: Media | G105: Estandarizar escalamiento y tiempos por nivel.
B106: D11 | C106: Parcial | D106: Postura 100% reactiva | E106: 3 | F106: Media | G106: Pasar de atención reactiva a gestión por métricas y mejora continua.
B107: D12 | C107: Parcial | D107: Falta de gobierno claro | E107: 3 | F107: Media | G107: Definir gobierno operativo, RACI, comités y responsables.
... B113: D18 | C113: Parcial | D113: Reskilling - Upskilling constante del staff | E113: 3 | F113: Media | G113: Plan de reskilling en BMC, operación por niveles, Power Apps/Kanban y automatización.
B114: D20 | C114: Sí | D114: Asignación de personal a las mesas y Niveles basada en criterio experto, sin modelo de demanda. No hay como dimensionarlo | G114: Se hace a juicio de expero de la emrpesa
B115: D21
...

Sheet SURA Canales Masivos
B2: LEVANTAMIENTO DE MESA DE SERVICIOS — SURA MESA 4
I3: ESCALA DE MADUREZ — N0 a N5
B4: ① IDENTIFICACIÓN GENERAL DE LA MESA | I4: NIVEL | J4: NOMBRE | K4: DESCRIPCIÓN
B5: Cliente: | C5: SURA | I5: N0 | J5: Reactivo / Sin estructura | K5: No existe proceso formal. Todo es manual y reactivo. Sin CMDB ni catálogo.
B6: Negocio del cliente: | C6: Canales masivos de pólizas/operación de alto volumen y alta sensibilidad para clientes como Bancolombia. | I6: N1 | J6: Inicial / Ad hoc/ Operación reactiva | K6: Procesos básicos documentados. Herramientas mínimas. Cumplimiento inconsistente.
B7: Nombre de la Mesa: | C7: Canales masivos | I7: N2 | J7: Definido / Organización funcional | K7: Procesos ITIL definidos y seguidos. Métricas básicas (SLA (Service Level Agreement), FCR (Fondo de Capital Riesgo)). Equipo estable.
B8: Líder / Coordinador: | C8: Elsy Yulieth Marin Serna | I8: N3 | J8: Gestionado / Gestión por servicios | K8: Métricas avanzadas. Automatización parcial. Gestión proactiva de problemas.
B9: Fecha del Levantamiento: | C9: 46211 | I9: N4 | J9: Optimizado / Gestión integrada | K9: Autoservicio maduro. IA/ML básico. XLA (Experience Level Agreement) medidos. Mejora continua activa.
B10: Ubicación / Modalidad: | C10: Virtual
B11: N° de Agentes (FTE) (cantidad de personas): | C11: 1 | I11: Función | J11: Misión Principal | K11: Alcance
B12: Modelo de Contrato: | C12: FTE dedicado | I12: Call Center | J12: Manejar grandes volúmenes de llamadas; filtrar y derivar | K12: Punto de contacto y distribución estructurada
B13: Nivel Madurez Actual: | C13: N2 | D13: (N0 Reactivo → N5 Innovador) | I13: Help Desk | J13: Coordinación para la restauración del servicio; "arreglar cosas" | K13: Infraestructura, herramientas de seguimiento, base de conocimiento
B14: Modelo de Operación | C14: Help Desk -> Service Desk (híbrido) | I14: Service Desk | J14: Servicio integral: incidentes, solicitudes, consultas, altas/bajas/cambios | K14: Alcance configurable; representa al usuario dentro de TI
B15: (Tercero) Empresa de soporte al cliente | D15: (N0 Reactivo → N5 Innovador)
B16: En que otro Niveles tenemos presencia: | C16: No Aplica
B17: En que paises tenemos presencia: | C17: Colombia
B18: Que hacemos en el cliente: | C18: Operación de canales masivos: renovaciones/cancelaciones automáticas, revisiones de pólizas y atención de solicitudes adicionales por correo/informes. Soporte de canal masivo con revisiones críticas, cierres de mes y atención de solicitudes que no siempre quedan como incidente.
B19: Tiempo de la Mesa de Servicio | C19: Por confirmar
B20: Finalización | C20: Agosto con posible renovación hasta diciembre
B21: Renovación: | C21: Propuesta con mirada de optimización; Compañía de Conexión / negociación comercial.
B22: Equipos de infraestructura:
B23: Video: | C23: Hablemos Mesas Sura-20260708_090044-Grabación de la reunión.mp4
